Workbook

Sheet Country-regions
A1: Countries, per region, worked on by [Insert Program/Accelerator name]
A2: CGIAR regions and countries.xlsx | B2: <-- Spreadsheet showing the CGIAR regions and the countries that fall into these regions
A3: Program and Accelerator's Countries (2024).xlsx | B3: <-- Spreadsheet showing the countries that each Program/Accelerator is working on (as per what was submitted in 2024 for the original methodology).
A4: LAC | B4: CWANA | C4: WCA | D4: ESA | E4: SA | F4: SEA
A5: Guatemala | C5: Benin | D5: Ethiopia | E5: Bangladesh | F5: the Philippines
A6: Honduras | C6: Ghana | D6: Kenya | E6: India | F6: Vietnam
C7: Nigeria | D7: Malawi | E7: Sri Lanka
D8: Tanzania
D9: Uganda

Sheet HLOs
A2: VH | B2: 5
A3: H | B3: 4
A4: MH | B4: 3
A5: M | B5: 2
A6: L | B6: 1
C7: # | D7: HLO + concise description
A8: HLO count: | B8: =COUNTA(D8:D29) -> 22 | C8: 1 | D8: AoW1-Suite of solutions focused on consumers that promote consumption of sustainable heathy diets co-developed, tested, and scaled with technical support and country engagement
A9: Sets of 5: | B9: =_xlfn.FLOOR.MATH(B8/5) -> 4 | C9: 2 | D9: AoW1-Suite of solutions focused on vendors that promote employment opportunities and the sale of sustainable nutritious foods co-developed, tested, and scaled with technical support and country engagement
A10: Remainder: | B10: =MOD(B8,5) -> 2 | C10: 3 | D10: AoW1-Policy options and engagement that support effective management of national action plans and other policy processes, for food systems transformation in support of sustainable healthy diets
A11: Max score: | B11: =(B9*SUM($B$2:$B$6))+SUM(B2:INDEX(B:B, $B$10+1)) -> 69 | C11: 4 | D11: AoW2-Suite of Solutions to lower transaction costs
C12: 5 | D12: AoW2-Suite of Solutions to catalyze business growth
C13: 6 | D13: AoW2-Trade and Limiting UPC Consumption
C14: 7 | D14: AoW3-Suite of tested end-to-end solutions for health and agriculture extension agents, fruit and vegetable vendors/retailers, processors, traders and producers that promote healthy food choice behaviors of consumers, healthy food environments, food quality and safety, reduce food loss, and increase profits co-developed, tested, and scaled.
C15: 8 | D15: AoW3-Suite of end-to-end solutions for health and agriculture extension agents, aquatic food vendors/retailers processors, and traders that promote healthy food choice behaviors of consumers, healthy food environments, food quality and safety, reduce food loss, and increase profits co-developed, tested, and scaled.
C16: 9 | D16: AoW3-Suite of end-to-end solutions for health and agriculture extension agents, terrestrial animal-source vendors/retailers processors, and traders that promote healthy food choice behaviors of consumers, healthy food environments, food quality and safety, reduce food loss, and increase profits co-developed, tested, and scaled.
C17: 10 | D17: AoW3-Suite of integrated end-to-end solutions for health and agriculture extension agents, perishable nutrient-rich food vendors/retailers, processors, traders and producers that promote healthy food choice behaviors of consumers, healthy food environments, food quality and safety, reduce food loss,and increase profits co-developed, tested, and scaled.
C18: 11 | D18: AoW3-Policy options that address constraints to sustainable healthy diets
C19: 12 | D19: AoW4-Suite of solutions for producers and processors that address constraints to sustainable healthy diets co-developed, tested, and scaled with technical support and country engagement.
C20: 13 | D20: AoW4-Policy options and engagement that address constraints to sustainable healthy diets.
C21: 14 | D21: AoW4-Framework for embedding nutrition into breeding pipelines and processes.
C22: 15 | D22: AoW4-Suite of solutions for traders and vendors that address constraints to sustainable healthy diets co-developed, tested, and scaled with technical support and country engagement.
C23: 16 | D23: AoW4-Suite of solutions to support consumers awareness, preference, affordability, and utilization of biofortified and health-enhancing crops in their diets.
... C29: 22 | D29: AoW6-Task force that guides the CGIAR Portfolio along pathways that lead to credible impacts on nutrition, health, and food security

Sheet Indicators
A1: BASE Indicator database - (from 2024).xlsx | C1: <-- source of Baseline data
A2: Projected Benefits Data (Nov 2024) - With Analysis.xlsx | C2: <-- source of Projected data (with graphs)
A3: Impact Area | B3: Projected to 2040 (without CGIAR intervention) or baseline data? | C3: Indicator | D3: r_lac | E3: r_cwana | F3: r_wca | G3: r_esa | H3: r_sa | I3: r_sea
A5: Nutrition | B5: Baseline data | C5: Prevalence of stunting (height for age <-2 standard deviation from the median of the World Health Organization (WHO) Child Growth Standards) % children under 5 years of age | D5: 11.679145 | E5: 17.238147 | F5: 31.597628 | G5: 30.494793 | H5: 34.286344 | I5: 11.083749
A6: Nutrition | B6: Baseline data | C6: Prevalence of wasting (weight for height >+2 or <-2 standard deviation from the median of the WHO Child Growth Standards) % children under 5 years of age | D6: 2.2309085 | E6: 5.8629686 | F6: 6.7930741 | G6: 5.4676809 | H6: 16.318465 | I6: 3.6836782
A7: Nutrition | B7: Baseline data | C7: % of population unable to afford a healthy diet | D7: 22.261332 | E7: 37.375529 | F7: 84.372957 | G7: 82.105349 | H7: 73.246664 | I7: 24.396071
A8: Nutrition | B8: Baseline data | C8: Women not meeting minimum dietary diversity (MDD-W)(%) | D8: =100-D9 -> 22.613111 | E8: =100-E9 -> 26.568838 | F8: =100-F9 -> 52.174582 | G8: =100-G9 -> 52.544997 | H8: =100-H9 -> 55.210105 | I8: =100-I9 -> 15.387626
A9: Nutrition | B9: Baseline data | C9: Women meeting minimum dietary diversity (MDD-W)(%) | D9: 77.386889 | E9: 73.431162 | F9: 47.825418 | G9: 47.455003 | H9: 44.789895 | I9: 84.612374
A10: Nutrition | B10: Baseline data | C10: GloMIP Nutrition Priority Index based on indicators in rows 5-8 | D10: 0.080637 | E10: 0.1247 | F10: 0.2064 | G10: 0.1967 | H10: 0.2402 | I10: 0.085998
A11: Gender | B11: Baseline data | C11: Proportion of youth (aged 15-24 years) not in education, employment or training (NEET) (%) | D11: 20.353948 | E11: 28.808683 | F11: 22.22403 | G11: 22.032946 | H11: 25.579269 | I11: 13.900333
A12: Gender | B12: Baseline data | C12: Gender Development Index (GDI) | D12: 0.98711807 | E12: 0.86109472 | F12: 0.88128823 | G12: 0.92987576 | H12: 0.85713094 | I12: 0.96249076 | J12: GDI measures gender inequalities in achievement in three basic dimensions of human development: health, measured by female and male life expectancy at birth; education, measured by female and male expected years of schooling for children and female and male mean years of schooling for adults ages 25 years and older; and command over economic resources, measured by female and male estimated earned income.
A13: Gender | B13: Baseline data | C13: Gender Inequality Index (GII) | D13: 0.3786 | E13: 0.4202 | F13: 0.6154 | G13: 0.51 | H13: 0.4542 | I13: 0.2426 | J13: GII is a composite metric of gender inequality using three dimensions: reproductive health, empowerment and the labour market. A low GII value indicates low inequality between women and men, and vice-versa.
A14: Poverty | B14: Baseline data | C14: The ratio of the people employed in agriculture in rural areas over all people employed in rural areas" | D14: 46.830763 | E14: 34.609244 | F14: 64.335138 | G14: 71.949092 | H14: 56.611142 | I14: 44.992877
A15: Climate | B15: Baseline data | C15: Vulnerability index of the geography (exposure, sensitivity and adaptive capacity in six life-supporting sectors: food, water, health, ecosystem services, human habitat, and infrastructure). | D15: 0.38522854 | E15: 0.41856096 | F15: 0.52689312 | G15: 0.51707456 | H15: 0.50168331 | I15: 0.40802057
A16: Climate | B16: Baseline data | C16: Emissions intensity - CO2eq emissions from croplands (kg/ha) (Carlson et al., 2017) | D16: 386 | E16: 444 | F16: 312 | G16: 531 | H16: 2090 | I16: 3326
A17: Climate | B17: Baseline data | C17: CRI - Climate Risk Index - the index of the level of exposure and vulnerability to extreme events such as storms, floods and heatwaves based on historic data | D17: 46.593083 | E17: 71.63158 | F17: 73.530172 | G17: 45.434032 | H17: 18.194338 | I17: 40.16028
A18: Environment | B18: Baseline data | C18: Consumptive blue and green water used in food production (m3/ha) | D18: 5008.9819 | E18: 3795.1862 | F18: 4064.7898 | G18: 4368.5844 | H18: 5065.8423 | I18: 6113.5583
A19: Environment | B19: Baseline data | C19: Soil erosion rate (/Ha) | D19: 4480.2558 | E19: 2629.3874 | F19: 5858.9939 | G19: 7924.0507 | H19: 10121.16 | I19: 7076.2489
A20: Environment | B20: Baseline data | C20: Forest area lost (%) - the percentage of forested area (%) lost between 2010 and 2020 | D20: 4.0133292 | E20: 3.0328342 | F20: 8.736605 | G20: 6.4758874 | H20: 0.80036497 | I20: 1.9236632
A21: Environment | B21: Baseline data | C21: GBI - Global Biodiversity Index - Total number of plant, reptile, mammal, bird, fish and amphibian species | D21: 362.31193 | E21: 80.081948 | F21: 116.18798 | G21: 156.28684 | H21: 264.30093 | I21: 324.04395
A22: Environment | B22: Baseline data | C22: Sustainable agriculture score - Index quantifying progress toward productive and sustainable agriculture (current status score) | D22: 3.7142926 | E22: 3.0915505 | F22: 3.2533234 | G22: 2.8150793 | H22: 2.5514288 | I22: 3.9867322
A24: Impact Area | B24: Projected to 2040 (without CGIAR intervention) | C24: Indicator | D24: r_lac | X24: r_cwana | AR24: r_wca | BL24: r_esa | CF24: r_sa | CZ24: r_sea
D25: 2021 | E25: 2022 | F25: 2023 | G25: 2024 | H25: 2025 | I25: 2026 | J25: 2027 | K25: 2028 | L25: 2029 | M25: 2030 | N25: 2031 | O25: 2032 | P25: 2033 | Q25: 2034 | R25: 2035 | S25: 2036 | T25: 2037 | U25: 2038 | V25: 2039 | W25: 2040 | X25: 2021 | Y25: 2022 | Z25: 2023 | AA25: 2024 | AB25: 2025 | AC25: 2026 | AD25: 2027 | AE25: 2028 | AF25: 2029 | AG25: 2030 | AH25: 2031 | AI25: 2032 | AJ25: 2033 | AK25: 2034 | AL25: 2035 | AM25: 2036 | AN25: 2037 | AO25: 2038 | AP25: 2039 | AQ25: 2040 | AR25: 2021 | AS25: 2022 | AT25: 2023 | AU25: 2024 | AV25: 2025 | AW25: 2026 | AX25: 2027 | AY25: 2028 | AZ25: 2029 | BA25: 2030 | BB25: 2031 | BC25: 2032 | BD25: 2033 | BE25: 2034 | BF25: 2035 | BG25: 2036 | BH25: 2037 | BI25: 2038 | BJ25: 2039 | BK25: 2040 | BL25: 2021 | BM25: 2022 | BN25: 2023 | BO25: 2024 | BP25: 2025 | BQ25: 2026 | BR25: 2027 | BS25: 2028 | BT25: 2029 | BU25: 2030 | BV25: 2031 | BW25: 2032 | BX25: 2033 | BY25: 2034 | BZ25: 2035 | CA25: 2036 | CB25: 2037 | CC25: 2038 | CD25: 2039 | CE25: 2040 | CF25: 2021 | CG25: 2022 | CH25: 2023 | CI25: 2024 | CJ25: 2025 | CK25: 2026 | CL25: 2027 | CM25: 2028 | CN25: 2029 | CO25: 2030 | CP25: 2031 | CQ25: 2032 | CR25: 2033 | CS25: 2034 | CT25: 2035 | CU25: 2036 | CV25: 2037 | CW25: 2038 | CX25: 2039 | CY25: 2040 | CZ25: 2021 | DA25: 2022 | DB25: 2023 | DC25: 2024 | DD25: 2025 | DE25: 2026 | DF25: 2027 | DG25: 2028 | DH25: 2029 | DI25: 2030 | DJ25: 2031 | DK25: 2032 | DL25: 2033 | DM25: 2034 | DN25: 2035 | DO25: 2036 | DP25: 2037 | DQ25: 2038 | DR25: 2039 | DS25: 2040
A26: Nutrition | B26: Projected to 2040 | C26: Prevalence of Undernourishment - Share of total population living below the minimum calorie daily threshold | D26: 7.1892578 | E26: 6.68889 | F26: 6.2115266 | G26: 5.7570393 | H26: 5.3252329 | I26: 4.9158466 | J26: 4.5285569 | K26: 4.1629803 | L26: 3.8186764 | M26: 3.4951517 | N26: 3.1918631 | O26: 2.908223 | P26: 2.6436027 | Q26: 2.3973382 | R26: 2.1687341 | S26: 1.9570691 | T26: 1.7616009 | U26: 1.5815713 | V26: 1.4162109 | W26: 1.2647443 | X26: 9.1504665 | Y26: 8.9091662 | Z26: 8.6634743 | AA26: 8.4138444 | AB26: 8.160744 | AC26: 7.9046538 | AD26: 7.6460667 | AE26: 7.3854859 | AF26: 7.123424 | AG26: 6.8604013 | AH26: 6.5969443 | AI26: 6.3335834 | AJ26: 6.0708516 | AK26: 5.809282 | AL26: 5.5494058 | AM26: 5.2917502 | AN26: 5.0368357 | AO26: 4.7851739 | AP26: 4.537265 | AQ26: 4.2935953 | AR26: 18.91209 | AS26: 18.415278 | AT26: 17.911492 | AU26: 17.401678 | AV26: 16.886799 | AW26: 16.367828 | AX26: 15.845748 | AY26: 15.321548 | AZ26: 14.796218 | BA26: 14.270749 | BB26: 13.746128 | BC26: 13.223332 | BD26: 12.703327 | BE26: 12.187064 | BF26: 11.675475 | BG26: 11.169467 | BH26: 10.669921 | BI26: 10.177686 | BJ26: 9.6935781 | BK26: 9.2183741 | BL26: 22.510157 | BM26: 21.490211 | BN26: 20.474437 | BO26: 19.465188 | BP26: 18.464847 | BQ26: 17.475809 | BR26: 16.500465 | BS26: 15.541184 | BT26: 14.600291 | BU26: 13.680052 | BV26: 12.782652 | BW26: 11.910171 | BX26: 11.064571 | BY26: 10.247669 | BZ26: 9.4611245 | CA26: 8.7064163 | CB26: 7.9848318 | CC26: 7.2974499 | CD26: 6.645131 | CE26: 6.0285075 | CF26: 15.036352 | CG26: 13.50078 | CH26: 12.058387 | CI26: 10.711231 | CJ26: 9.460449 | CK26: 8.306251 | CL26: 7.2479364 | CM26: 6.2839238 | CN26: 5.4118015 | CO26: 4.6283937 | CP26: 3.9298411 | CQ26: 3.3116949 | CR26: 2.76902 | CS26: 2.2965049 | CT26: 1.8885759 | CU26: 1.53951 | CV26: 1.2435457 | CW26: 0.99498599 | CX26: 0.78829295 | CY26: 0.6181697 | CZ26: 2.9870488 | DA26: 2.5739841 | DB26: 2.2066181 | DC26: 1.8817105 | DD26: 1.5959854 | DE26: 1.3461739 | DF26: 1.1290543 | DG26: 0.94148797 | DH26: 0.78045059 | DI26: 0.64305899 | DJ26: 0.52659245 | DK26: 0.42850921 | DL26: 0.34645781 | DM26: 0.27828373 | DN26: 0.2220316 | DO26: 0.1759435 | DP26: 0.13845375 | DQ26: 0.10818092 | DR26: 0.083917403 | DS26: 0.06461742
A27: Gender | B27: WE CURRENTLY DON’T HAVE APPROPRIATE INDICATORS PROJECTED FOR THE GENDER IMPACT AREA - PLEASE USE BASELINE DATA ONLY
A28: Poverty | B28: Projected to 2040 | C28: Poverty Headcount Rate ($2.15) - Share of total population living below the poverty line | D28: 4.98557 | E28: 5.0242558 | F28: 5.0621172 | G28: 5.0991222 | H28: 5.1352386 | I28: 5.1704341 | J28: 5.2046757 | K28: 5.2379303 | L28: 5.2701643 | M28: 5.3013441 | N28: 5.3314354 | O28: 5.3604039 | P28: 5.3882149 | Q28: 5.4148334 | R28: 5.4402242 | S28: 5.4643519 | T28: 5.4871807 | U28: 5.5086747 | V28: 5.5287977 | W28: 5.5475134 | X28: 4.59918 | Y28: 4.4042124 | Z28: 4.2131091 | AA28: 4.02598 | AB28: 3.84293 | AC28: 3.6640582 | AD28: 3.4894579 | AE28: 3.319216 | AF28: 3.1534129 | AG28: 2.9921218 | AH28: 2.8354089 | AI28: 2.6833326 | AJ28: 2.5359435 | AK28: 2.3932841 | AL28: 2.2553884 | AM28: 2.1222821 | AN28: 1.9939817 | AO28: 1.8704952 | AP28: 1.7518213 | AQ28: 1.6379496 | AR28: 36.30807 | AS28: 36.185862 | AT28: 36.061701 | AU28: 35.935577 | AV28: 35.807479 | AW28: 35.677395 | AX28: 35.545315 | AY28: 35.411226 | AZ28: 35.275116 | BA28: 35.136975 | BB28: 34.996788 | BC28: 34.854543 | BD28: 34.710229 | BE28: 34.56383 | BF28: 34.415335 | BG28: 34.26473 | BH28: 34.112002 | BI28: 33.957135 | BJ28: 33.800117 | BK28: 33.640934 | BL28: 38.89568 | BM28: 38.85434 | BN28: 38.811608 | BO28: 38.767445 | BP28: 38.721807 | BQ28: 38.674652 | BR28: 38.625933 | BS28: 38.575602 | BT28: 38.523611 | BU28: 38.469907 | BV28: 38.414438 | BW28: 38.357148 | BX28: 38.297978 | BY28: 38.236869 | BZ28: 38.173758 | CA28: 38.10858 | CB28: 38.041268 | CC28: 37.97175 | CD28: 37.899953 | CE28: 37.825801 | CF28: 11.48274 | CG28: 10.469358 | CH28: 9.4825203 | CI28: 8.5274757 | CJ28: 7.6094386 | CK28: 6.7334754 | CL28: 5.904376 | CM28: 5.126516 | CN28: 4.4037126 | CO28: 3.7390816 | CP28: 3.134903 | CQ28: 2.5925037 | CR28: 2.1121683 | CS28: 1.6930861 | CT28: 1.3333448 | CU28: 1.0299761 | CV28: 0.77905634 | CW28: 0.57586239 | CX28: 0.41507324 | CY28: 0.29100712 | CZ28: 1.23059 | DA28: 0.88984793 | DB28: 0.6221891 | DC28: 0.41911725 | DD28: 0.27092336 | DE28: 0.16738356 | DF28: 0.098482932 | DG28: 0.055066945 | DH28: 0.029330068 | DI28: 0.015081471 | DJ28: 0.0077742847 | DK28: 0.0043346014 | DL28: 0.0028635352 | DM28: 0.0022984445 | DN28: 0.0021059525 | DO28: 0.0020486343 | DP28: 0.0020339519 | DQ28: 0.002030774 | DR28: 0.0020302043 | DS28: 0.0020301216
A29: Poverty | B29: Projected to 2040 | C29: Poverty Headcount Rate ($3.65) - Share of total population living below the poverty line | D29: 12.326178 | E29: 12.381889 | F29: 12.436252 | G29: 12.489232 | H29: 12.540798 | I29: 12.590913 | J29: 12.639544 | K29: 12.686654 | L29: 12.732209 | M29: 12.776171 | N29: 12.818504 | O29: 12.85917 | P29: 12.898132 | Q29: 12.935351 | R29: 12.970787 | S29: 13.004401 | T29: 13.036154 | U29: 13.066003 | V29: 13.093907 | W29: 13.119826 | X29: 14.288423 | Y29: 13.982703 | Z29: 13.67684 | AA29: 13.370967 | AB29: 13.065221 | AC29: 12.759739 | AD29: 12.454666 | AE29: 12.150146 | AF29: 11.846328 | AG29: 11.543362 | AH29: 11.241404 | AI29: 10.940608 | AJ29: 10.641135 | AK29: 10.343146 | AL29: 10.046804 | AM29: 9.7522739 | AN29: 9.4597232 | AO29: 9.1693202 | AP29: 8.8812344 | AQ29: 8.5956364 | AR29: 64.127509 | AS29: 64.124548 | AT29: 64.121536 | AU29: 64.118473 | AV29: 64.115359 | AW29: 64.112192 | AX29: 64.108972 | AY29: 64.105699 | AZ29: 64.102372 | BA29: 64.098991 | BB29: 64.095554 | BC29: 64.092063 | BD29: 64.088515 | BE29: 64.08491 | BF29: 64.081248 | BG29: 64.077527 | BH29: 64.073748 | BI29: 64.06991 | BJ29: 64.066011 | BK29: 64.062051 | BL29: 65.516569 | BM29: 65.515305 | BN29: 65.513998 | BO29: 65.512647 | BP29: 65.511251 | BQ29: 65.509807 | BR29: 65.508315 | BS29: 65.506774 | BT29: 65.50518 | BU29: 65.503534 | BV29: 65.501833 | BW29: 65.500075 | BX29: 65.498258 | BY29: 65.496382 | BZ29: 65.494442 | CA29: 65.492439 | CB29: 65.490368 | CC29: 65.488229 | CD29: 65.486018 | CE29: 65.483733 | CF29: 43.13417 | CG29: 42.785936 | CH29: 42.423103 | CI29: 42.045096 | CJ29: 41.651323 | CK29: 41.241181 | CL29: 40.814053 | CM29: 40.369309 | CN29: 39.906311 | CO29: 39.424414 | CP29: 38.922966 | CQ29: 38.401314 | CR29: 37.858808 | CS29: 37.294802 | CT29: 36.708661 | CU29: 36.099766 | CV29: 35.467522 | CW29: 34.811364 | CX29: 34.130765 | CY29: 33.425246 | CZ29: 6.6233529 | DA29: 5.5934126 | DB29: 4.6450586 | DC29: 3.7861739 | DD29: 3.0226307 | DE29: 2.3578335 | DF29: 1.7923687 | DG29: 1.323821 | DH29: 0.94680861 | DI29: 0.65326964 | DJ29: 0.43300161 | DK29: 0.2744137 | DL29: 0.16540941 | DM29: 0.094283044 | DN29: 0.050501138 | DO29: 0.025256507 | DP29: 0.011729008 | DQ29: 0.0050518673 | DR29: 0.0020459537 | DS29: 0.00082542745
A30: Poverty | B30: Projected to 2040 | C30: Poverty Headcount Rate ($6.85) - Share of total population living below the poverty line | D30: 31.99797 | E30: 32.039063 | F30: 32.079058 | G30: 32.117939 | H30: 32.155689 | I30: 32.192292 | J30: 32.227729 | K30: 32.261984 | L30: 32.295038 | M30: 32.326872 | N30: 32.357466 | O30: 32.386801 | P30: 32.414856 | Q30: 32.441611 | R30: 32.467043 | S30: 32.491131 | T30: 32.513851 | U30: 32.535181 | V30: 32.555096 | W30: 32.573571 | X30: 39.779017 | Y30: 39.643681 | Z30: 39.506381 | AA30: 39.367094 | AB30: 39.225797 | AC30: 39.082466 | AD30: 38.937077 | AE30: 38.789605 | AF30: 38.640025 | AG30: 38.488313 | AH30: 38.334443 | AI30: 38.178388 | AJ30: 38.020124 | AK30: 37.859624 | AL30: 37.69686 | AM30: 37.531806 | AN30: 37.364435 | AO30: 37.194718 | AP30: 37.022628 | AQ30: 36.848136 | AR30: 88.509867 | AS30: 88.506906 | AT30: 88.503894 | AU30: 88.500831 | AV30: 88.497716 | AW30: 88.494549 | AX30: 88.49133 | AY30: 88.488056 | AZ30: 88.48473 | BA30: 88.481348 | BB30: 88.477912 | BC30: 88.47442 | BD30: 88.470872 | BE30: 88.467267 | BF30: 88.463605 | BG30: 88.459885 | BH30: 88.456106 | BI30: 88.452267 | BJ30: 88.448368 | BK30: 88.444408 | BL30: 87.43947 | BM30: 87.438206 | BN30: 87.4369 | BO30: 87.435549 | BP30: 87.434152 | BQ30: 87.432709 | BR30: 87.431217 | BS30: 87.429675 | BT30: 87.428082 | BU30: 87.426435 | BV30: 87.424734 | BW30: 87.422976 | BX30: 87.42116 | BY30: 87.419283 | BZ30: 87.417344 | CA30: 87.41534 | CB30: 87.413269 | CC30: 87.41113 | CD30: 87.408919 | CE30: 87.406634 | CF30: 80.974435 | CG30: 80.959243 | CH30: 80.943388 | CI30: 80.92684 | CJ30: 80.909568 | CK30: 80.891539 | CL30: 80.872719 | CM30: 80.853071 | CN30: 80.832558 | CO30: 80.811141 | CP30: 80.788779 | CQ30: 80.765429 | CR30: 80.741045 | CS30: 80.71558 | CT30: 80.688986 | CU30: 80.66121 | CV30: 80.632198 | CW30: 80.601895 | CX30: 80.57024 | CY30: 80.537172 | CZ30: 29.55282 | DA30: 28.453081 | DB30: 27.310321 | DC30: 26.125513 | DD30: 24.900204 | DE30: 23.636605 | DF30: 22.337679 | DG30: 21.007236 | DH30: 19.650019 | DI30: 18.271781 | DJ30: 16.879345 | DK30: 15.480643 | DL30: 14.084712 | DM30: 12.701646 | DN30: 11.342485 | DO30: 10.019034 | DP30: 8.7435908 | DQ30: 7.528593 | DR30: 6.3861649 | DS30: 5.327589
A31: Poverty | B31: Projected to 2040 | C31: Agrifood System Jobs (incl. subsistence farming and informal sector) - millions of workers | D31: 79.453806 | E31: 81.086566 | F31: 82.7612 | G31: 84.478933 | H31: 86.241033 | I31: 88.048807 | J31: 89.903606 | K31: 91.806824 | L31: 93.759905 | M31: 95.764336 | N31: 97.821657 | O31: 99.933458 | P31: 102.10138 | Q31: 104.32713 | R31: 106.61247 | S31: 108.95919 | T31: 111.3692 | U31: 113.84443 | V31: 116.3869 | W31: 118.99868 | X31: 50.377779 | Y31: 51.475884 | Z31: 52.606947 | AA31: 53.772164 | AB31: 54.972781 | AC31: 56.210098 | AD31: 57.485472 | AE31: 58.800317 | AF31: 60.156109 | AG31: 61.554391 | AH31: 62.996771 | AI31: 64.48493 | AJ31: 66.020625 | AK31: 67.605691 | AL31: 69.242045 | AM31: 70.931693 | AN31: 72.676732 | AO31: 74.479356 | AP31: 76.341859 | AQ31: 78.266643 | AR31: 118.18601 | AS31: 122.23843 | AT31: 126.45317 | AU31: 130.8372 | AV31: 135.39785 | AW31: 140.14274 | AX31: 145.07984 | AY31: 150.21751 | AZ31: 155.56444 | BA31: 161.12976 | BB31: 166.92299 | BC31: 172.9541 | BD31: 179.23348 | BE31: 185.77203 | BF31: 192.58113 | BG31: 199.67268 | BH31: 207.05915 | BI31: 214.75354 | BJ31: 222.76947 | BK31: 231.1212 | BL31: 152.33566 | BM31: 158.07421 | BN31: 164.07237 | BO31: 170.34342 | BP31: 176.90137 | BQ31: 183.76104 | BR31: 190.93808 | BS31: 198.44902 | BT31: 206.31135 | BU31: 214.54355 | BV31: 223.16518 | BW31: 232.19692 | BX31: 241.66066 | BY31: 251.57954 | BZ31: 261.9781 | CA31: 272.88229 | CB31: 284.3196 | CC31: 296.31915 | CD31: 308.91182 | CE31: 322.1303 | CF31: 335.11902 | CG31: 345.66882 | CH31: 356.63814 | CI31: 368.04754 | CJ31: 379.91877 | CK31: 392.27487 | CL31: 405.14024 | CM31: 418.54076 | CN31: 432.50383 | CO31: 447.05854 | CP31: 462.23575 | CQ31: 478.06821 | CR31: 494.5907 | CS31: 511.84016 | CT31: 529.85585 | CU31: 548.6795 | CV31: 568.3555 | CW31: 588.93105 | CX31: 610.45641 | CY31: 632.98506 | CZ31: 430.51747 | DA31: 439.33041 | DB31: 448.38064 | DC31: 457.67536 | DD31: 467.22202 | DE31: 477.02828 | DF31: 487.10209 | DG31: 497.45165 | DH31: 508.08544 | DI31: 519.0122 | DJ31: 530.24097 | DK31: 541.7811 | DL31: 553.64225 | DM31: 565.8344 | DN31: 578.36786 | DO31: 591.25328 | DP31: 604.5017 | DQ31: 618.12449 | DR31: 632.13342 | DS31: 646.54069
A32: Poverty | B32: Projected to 2040 | C32: Agrifood System GDP Per Worker - US$ per worker | D32: 9757.9382 | E32: 9757.9382 | F32: 9757.9382 | G32: 9757.9382 | H32: 9757.9382 | I32: 9757.9382 | J32: 9757.9382 | K32: 9757.9382 | L32: 9757.9382 | M32: 9757.9382 | N32: 9757.9382 | O32: 9757.9382 | P32: 9757.9382 | Q32: 9757.9382 | R32: 9757.9382 | S32: 9757.9382 | T32: 9757.9382 | U32: 9757.9382 | V32: 9757.9382 | W32: 9757.9382 | X32: 11320.812 | Y32: 11320.812 | Z32: 11320.812 | AA32: 11320.812 | AB32: 11320.812 | AC32: 11320.812 | AD32: 11320.812 | AE32: 11320.812 | AF32: 11320.812 | AG32: 11320.812 | AH32: 11320.812 | AI32: 11320.812 | AJ32: 11320.812 | AK32: 11320.812 | AL32: 11320.812 | AM32: 11320.812 | AN32: 11320.812 | AO32: 11320.812 | AP32: 11320.812 | AQ32: 11320.812 | AR32: 2860.2434 | AS32: 2860.2434 | AT32: 2860.2434 | AU32: 2860.2434 | AV32: 2860.2434 | AW32: 2860.2434 | AX32: 2860.2434 | AY32: 2860.2434 | AZ32: 2860.2434 | BA32: 2860.2434 | BB32: 2860.2434 | BC32: 2860.2434 | BD32: 2860.2434 | BE32: 2860.2434 | BF32: 2860.2434 | BG32: 2860.2434 | BH32: 2860.2434 | BI32: 2860.2434 | BJ32: 2860.2434 | BK32: 2860.2434 | BL32: 1686.5692 | BM32: 1686.5692 | BN32: 1686.5692 | BO32: 1686.5692 | BP32: 1686.5692 | BQ32: 1686.5692 | BR32: 1686.5692 | BS32: 1686.5692 | BT32: 1686.5692 | BU32: 1686.5692 | BV32: 1686.5692 | BW32: 1686.5692 | BX32: 1686.5692 | BY32: 1686.5692 | BZ32: 1686.5692 | CA32: 1686.5692 | CB32: 1686.5692 | CC32: 1686.5692 | CD32: 1686.5692 | CE32: 1686.5692 | CF32: 2772.7337 | CG32: 2772.7337 | CH32: 2772.7337 | CI32: 2772.7337 | CJ32: 2772.7337 | CK32: 2772.7337 | CL32: 2772.7337 | CM32: 2772.7337 | CN32: 2772.7337 | CO32: 2772.7337 | CP32: 2772.7337 | CQ32: 2772.7337 | CR32: 2772.7337 | CS32: 2772.7337 | CT32: 2772.7337 | CU32: 2772.7337 | CV32: 2772.7337 | CW32: 2772.7337 | CX32: 2772.7337 | CY32: 2772.7337 | CZ32: 8556.862 | DA32: 8556.862 | DB32: 8556.862 | DC32: 8556.862 | DD32: 8556.862 | DE32: 8556.862 | DF32: 8556.862 | DG32: 8556.862 | DH32: 8556.862 | DI32: 8556.862 | DJ32: 8556.862 | DK32: 8556.862 | DL32: 8556.862 | DM32: 8556.862 | DN32: 8556.862 | DO32: 8556.862 | DP32: 8556.862 | DQ32: 8556.862 | DR32: 8556.862 | DS32: 8556.862
A33: Climate | B33: Projected to 2040 | C33: Agrifood System Greenhouse Gas (GHG) Emissions | D33: 1290.6349 | E33: 1299.4607 | F33: 1308.4565 | G33: 1317.627 | H33: 1326.977 | I33: 1336.5113 | J33: 1346.2348 | K33: 1356.1529 | L33: 1366.2709 | M33: 1376.5942 | N33: 1387.1287 | O33: 1397.8802 | P33: 1408.8548 | Q33: 1420.0587 | R33: 1431.4986 | S33: 1443.181 | T33: 1455.113 | U33: 1467.3017 | V33: 1479.7545 | W33: 1492.4791 | X33: 521.24598 | Y33: 532.37733 | Z33: 543.82156 | AA33: 555.58869 | AB33: 567.68908 | AC33: 580.13348 | AD33: 592.93304 | AE33: 606.09934 | AF33: 619.64439 | AG33: 633.58065 | AH33: 647.92106 | AI33: 662.67905 | AJ33: 677.86859 | AK33: 693.50417 | AL33: 709.60086 | AM33: 726.17432 | AN33: 743.24082 | AO33: 760.81729 | AP33: 778.92133 | AQ33: 797.57126 | AR33: 420.59141 | AS33: 431.825 | AT33: 443.40263 | AU33: 455.3357 | AV33: 467.63605 | AW33: 480.31594 | AX33: 493.38808 | AY33: 506.86563 | AZ33: 520.76222 | BA33: 535.09201 | BB33: 549.86963 | BC33: 565.11028 | BD33: 580.82972 | BE33: 597.04426 | BF33: 613.77085 | BG33: 631.02704 | BH33: 648.83104 | BI33: 667.20175 | BJ33: 686.15877 | BK33: 705.72241 | BL33: 552.78648 | BM33: 575.08538 | BN33: 598.466 | BO33: 622.98755 | BP33: 648.71274 | BQ33: 675.70795 | BR33: 704.0435 | BS33: 733.79384 | BT33: 765.03783 | BU33: 797.85902 | BV33: 832.34591 | BW33: 868.59228 | BX33: 906.69748 | BY33: 946.76683 | BZ33: 988.91191 | CA33: 1033.251 | CB33: 1079.9095 | CC33: 1129.0204 | CD33: 1180.7245 | CE33: 1235.1714 | CF33: 1337.1419 | CG33: 1368.6614 | CH33: 1401.2786 | CI33: 1435.0419 | CJ33: 1470.0024 | CK33: 1506.2136 | CL33: 1543.732 | CM33: 1582.6166 | CN33: 1622.9297 | CO33: 1664.7367 | CP33: 1708.1063 | CQ33: 1753.1111 | CR33: 1799.8271 | CS33: 1848.3343 | CT33: 1898.7173 | CU33: 1951.0646 | CV33: 2005.4699 | CW33: 2062.0314 | CX33: 2120.8529 | CY33: 2182.0435 | CZ33: 2408.5001 | DA33: 2440.4414 | DB33: 2473.2397 | DC33: 2506.9196 | DD33: 2541.5063 | DE33: 2577.0259 | DF33: 2613.5052 | DG33: 2650.9722 | DH33: 2689.4553 | DI33: 2728.9842 | DJ33: 2769.5894 | DK33: 2811.3024 | DL33: 2854.1556 | DM33: 2898.1827 | DN33: 2943.4182 | DO33: 2989.8979 | DP33: 3037.6588 | DQ33: 3086.7389 | DR33: 3137.1777 | DS33: 3189.0156
A36: Prevalence of Undernourishment
A54: Undernourished Population
A71: Poverty Headcount Rate ($2.15)
A87: Poverty Headcount Rate ($3.65)
A104: Poverty Headcount Rate ($6.85)
A121: Agrifood System Jobs (incl. subsistence farming and informal sector)
A139: Agricultural Jobs (incl. subsistence farming and informal sector)
A156: Agricultural Greenhouse Gas (GHG) Emissions

Sheet 1.Food_security
C1: FS Indicators
A2: VH | B2: 5 | D2: LAC | E2: CWANA | F2: WCA | G2: ESA | H2: SA | I2: SEA | J2: AoW1 | K2: =AVERAGE(D11:I13) -> 3.4 | L2: We proportionally reduced the scores to meet the maxima.
A3: H | B3: 4 | C3: Total score by column | D3: =SUM(D11:D59) -> 61 | E3: =SUM(E11:E59) -> 29 | F3: =SUM(F11:F59) -> 69 | G3: =SUM(G11:G59) -> 69 | H3: =SUM(H11:H59) -> 69 | I3: =SUM(I11:I59) -> 63 | J3: AoW2 | K3: =AVERAGE(D14:I16) -> 3
A4: MH | B4: 3 | C4: VH count by column | D4: =COUNTIF(D$11:D$59, 5) -> 2 | E4: =COUNTIF(E$11:E$59, 5) -> 0 | F4: =COUNTIF(F$11:F$59, 5) -> 1 | G4: =COUNTIF(G$11:G$59, 5) -> 2 | H4: =COUNTIF(H$11:H$59, 5) -> 1 | I4: =COUNTIF(I$11:I$59, 5) -> 1 | J4: AoW3 | K4: =AVERAGE(D17:I21) -> 3.36
A5: M | B5: 2 | C5: H count by column | D5: =COUNTIF(D$11:D$59, 4) -> 1 | E5: =COUNTIF(E$11:E$59, 4) -> 0 | F5: =COUNTIF(F$11:F$59, 4) -> 6 | G5: =COUNTIF(G$11:G$59, 4) -> 6 | H5: =COUNTIF(H$11:H$59, 4) -> 8 | I5: =COUNTIF(I$11:I$59, 4) -> 7 | J5: AoW4 | K5: =AVERAGE(D22:I26) -> 2.8333333
A6: L | B6: 1 | C6: MH count by column | D6: =COUNTIF(D$11:D$59, 3) -> 10 | E6: =COUNTIF(E$11:E$59, 3) -> 9 | F6: =COUNTIF(F$11:F$59, 3) -> 10 | G6: =COUNTIF(G$11:G$59, 3) -> 7 | H6: =COUNTIF(H$11:H$59, 3) -> 6 | I6: =COUNTIF(I$11:I$59, 3) -> 8 | J6: AoW5 | K6: =AVERAGE(D27:I27) -> 3.6
C7: M count by column | D7: =COUNTIF(D$11:D$59, 2) -> 8 | E7: =COUNTIF(E$11:E$59, 2) -> 1 | F7: =COUNTIF(F$11:F$59, 2) -> 5 | G7: =COUNTIF(G$11:G$59, 2) -> 7 | H7: =COUNTIF(H$11:H$59, 2) -> 7 | I7: =COUNTIF(I$11:I$59, 2) -> 3 | J7: AoW6 | K7: =AVERAGE(D28:I32) -> 2.8666667
C8: L count by column | D8: =COUNTIF(D$11:D$59, 1) -> 1 | E8: =COUNTIF(E$11:E$59, 1) -> 0 | F8: =COUNTIF(F$11:F$59, 1) -> 0 | G8: =COUNTIF(G$11:G$59, 1) -> 0 | H8: =COUNTIF(H$11:H$59, 1) -> 0 | I8: =COUNTIF(I$11:I$59, 1) -> 0 | K8: Current state (across the Global South) | L8: Ideal state (across the Global South) | M8: Assumptions (for region-specific scores) | N8: Requirements for success (internal to P/A) | O8: Requirements for success (from other P/As)
C10: HLO | D10: LAC | E10: CWANA | F10: WCA | G10: ESA | H10: SA | I10: SEA
A11: HLO count: | B11: =COUNTA(C11:C59) -> 22 | C11: AoW1-Suite of solutions focused on consumers that promote consumption of sustainable heathy diets co-developed, tested, and scaled with technical support and country engagement | D11: 3 | F11: 4 | G11: 4 | H11: 4 | I11: 3 | K11: 1. Behavior change solutions for consumers in LMICs exist (like national Food-Based Dietary Guidelines), but (a) evidence on their effectiveness is lacking, (b) they are not being used at scale, and (c) they do not address enough components of the food system to make an impact (in other words, they are not transformative solutions). 2. There are very few known solutions in LMICs that address the food environment. 3. Metrics are not all-encompassing. 4. Metrics are not being used by gov'ts for decisionmaking. 5. Uneven willingness to act 6. There may be information on what governments can do, but very little information on how do it. | L11: 1. Behavior change solutions for consumers in LMICs are evidence-based, used at scale and broad enough to contribute to meaningful positive food system transformation. 2. Key evidence-based solutions to shape LMIC food environments in favor of sustainable healthy diets are widely available and effecively used. 3. Coherent, complete and consistent metrics are widely used. 4. These metrics guide governmental decision-making contributing to greater consumption of sustainable healthy diets in LMICs. 5. Political barriers and lock-ins are overcome with governments and other food system stakeholders willing and able to act. 6. Clear policy roadmaps based on solid evidence exist to guide governmental decision-making. | M11: WCA - There are few behavior change solutions currently under implementation across WCA countries. Therefore there is potential for very high change in this region. ESA & SA - Some initial advances such as FBDG exist in some countries but there is limited work at scale, scant evidence and relatively low willingness to act. We feel that this region shows a high potential for impact. LAC & SEA - These regions have done more work on consumer-facing solutions including FBDG as well as innovations around food labeling, taxes on sugar sweetened beverages and policy control of food companies in terms of product formulation and marketing. Despite this, evidence remains spotty on the effectiveness of these approaches. CGIAR has much to learn here with solid partners. We estimate a medium high potential for impact here. | N11: Evidence is relevant (helps meet government actors' goals) and timely for government actors to use. Gov’t actors perceive their institutions have the capacity to implement the solutions. | O11: From CGIAR's production-oriented Programs: We need sustainable nutritious foods to be available, affordable, safe, sustainably produced even in the midst of local and global shocks and resilient in the face of climate change. Scaling for Impact: We'll need their expertise to help us scale our own tested solutions.
A12: Sets of 5: | B12: =_xlfn.FLOOR.MATH(B11/5) -> 4 | C12: AoW1-Suite of solutions focused on vendors that promote employment opportunities and the sale of sustainable nutritious foods co-developed, tested, and scaled with technical support and country engagement | D12: 3 | F12: 3 | G12: 3 | H12: 3 | I12: 4 | K12: 1. There is a lack of data about MSMEs and informal actors in LMICs - what are barriers and constraints to their businesses, what incentives are there to grow their business, and similar questions for barriers/constraints/incentives for selling sustainable nutritious foods. 2. There is a lack of data on the presence of healthy foods being sold by MSMEs and informal actors in LMICs. 3. There are few evidence-based solutions for how to improve conditions for MSMEs and informal actors in LMICs selling food. 4. The increasing presence of ultra-processed foods (UPFs) combined with infrastructure realities (e.g., widely variable access to cold storage and clean water) changes the cost-benefits for MSME and informal actors. 5. Successful and aggressive commercial strategies of multinational food companies increase the availability and affordability of UPFs being offered by MSMEs and informal actors in LMICs. | L12: 1. Deeper understanding of MSMEs and informal sector in LMICs drives effective support for them to provide sustainable nutritious foods. 2. The role of MSMEs and informal actors in providing sustainable nutritious foods is well documented and widely understood in LMICs. 3. A suite of evidence-based solutions exists to support the sale of sustainable nutritous foods by MSMEs and informal actors in LMICs. 4. There is growing recognition of how infrastructure realities and the rise of UPFs influence MSME decision-making, enabling more informed strategies to support healthier food environments. 5. Smart evidence-based gov't regulations are in place that constrain and limit the spread of UPFs and favor more sustainable nutritious foods. | M12: WCA, ESA, SA, SEA - These regions present low levels of data on the role of MSMEs and informal actors in the provision of sustainable nutritious foods. Likewise few evidenced-based solutions have been identified and tested at scale despite the increasing presence of UPFs in their food environments. If BDN can provide evidence to change this, we feel there is potential of high potential impact. LAC - This region has some modest advances compared to other regions in terms of data and understanding of the role of MSMEs and informal actors in the provision of sustainable nutritious foods. Despite that, there are significant political headwinds to act in the food environment which is further exacerbated by the rapid expansion of UPFs driven by agressive commercial strategies. There are modest attempts to counteract this with labeling, taxation and marketing control. If BDN and key regional partners can provide more consistent evidence, we assess a medium high potential for impact. | N12: Evidence is relevant (helps meet their goals) and timely for government actors to use. Gov’t actors perceive their institutions have the capacity to implement the solutions. MSMEs and informal actors perceive the solutions are not harmful to their profit margin and have the capacity to implement the solutions. | O12: We don't think any other Programs are addressing this. Scaling for Impact: We'll need their expertise to help us scale our own tested solutions.
A13: Remainder: | B13: =MOD(B11,5) -> 2 | C13: AoW1-Policy options and engagement that support effective management of national action plans and other policy processes, for food systems transformation in support of sustainable healthy diets | D13: 5 | F13: 2 | G13: 3 | H13: 2 | I13: 5 | K13: 1. Food System Transformation National Action Plans are being developed but at various levels of detail, and hardly being implemented. 2. Lack of policy coherence. There is a lack of clear and consistent food system policies across levels and sectors of government in LMICs. 3. Lack of policy alignment. For example, agricultural policies emphasize maximizing production for economic growth while health policies emphasize health promotion...in some cases, without putting enough emphasis on the role of diets. 4. Policies are on paper, but not in practice. 5. LMIC governments face difficulties to operationalize their aspirations for food systems transformation (issues relate to awareness, capacity, finance, the political economy and so on). 6. The policy landscape in many LMICs is behind the curve. Policies are framed by the issues from 50 years ago (undernourished population, calories) and not the present threats (obesity and overweight and NCDs). | L13: 1. Food system policies in LMICs are clear, consistent, and coherent across sectors and levels of government. 2. Agricultural, health, and other sectoral policies are well-aligned, with a shared emphasis on the role of diets in achieving both economic and health goals. 3. Food system policies are increasingly being translated into effective practice. 4. LMIC governments are successfully operationalizing food systems transformation, supported by growing awareness, stronger capacity, increased financing, and improved political alignment. 5. Policy frameworks in LMICs have been modernized, shifting focus from past challenges to today’s pressing issues such as obesity, overweight, and noncommunicable diseases. | M13: LAC & SEA - These regions show the greatest willingness to engage in building their capacities to achieve policy alignment that lead to food system transformation in practice and at scale. We feel there is very high potential for food system transformation at scale in these regions. ESA - This region has some willingness to engage in policy alignment in support of food system transformation, however this is constrained by political and financial challenges. We feel that that BDN can achieve high potential impact in this region for this HLO. WCA -- This region has shown limited willingess and capacity to engage meaningfully in policy alignment to support food system transformation. We estimate medium high potential for positive change in this HLO. SA -- This region has shown low willingess and capacity to engage meaningfully in policy alignment to support food system transformation. Given this reality, we estimate only a moderate chance to achieve significant change in this HLO. | N13: Decisionmakers have the awareness of political lock-ins and capacity to overcome them to improve sectoral alignment. Decisionmakers have the awareness of trade-offs and how to overcome them. The new governance mechanisms integrate various societal perspectives. | O13: Policy Innovations: we need their quantitative modelling of trade-off analysis Climate Action, Multifunctional Landscapes: we need their help to promote policy coherence across different agendas (climate, biodiversity).
A14: Max score: | B14: =(B12*SUM($B$2:$B$6))+SUM($B$2:INDEX(B:B, $B$13+1)) -> 69 | C14: AoW2-Suite of Solutions to lower transaction costs | D14: 5 | F14: 2 | G14: 4 | H14: 3 | K14: 1. Many products are not quality differentiated by markets, leading to low quality equilibria. This equilibrium holds when quality traits are unobservable (e.g. food safety, but environmental impact, anything that is not visually apparent). 2. Safety of perishable foods often perceived as low, and demand can be reduced for more nutrient dense foods if safe practices cannot be maintained throughout agri-food value chains for perishable products 3. Transaction costs within specific markets for more nutrient dense and perishable products thought to be high, reducing producer prices (and therefore production) and increasing consumer prices (and therefore reducing demand) 4. Post-harvest loss is high among perishable products, which leads to higher consumer prices 5. Technological solutions exist that can help reduce transaction costs, but the return to using those solutions must be high enough for some actor to overcome coordination costs 6. Policy solutions that can help increase availability of more nutrient dense products (quality certification, food safety regulations) often weakly or unevenly enforced | L14: 1. Quality is defined for specific products and markets reward quality with a high enough price difference to reward quality throughout specific value chains; 2. Affordable solutions for food safety concerns are implemented at scale, leading to fewer concerns about food safety and improved health from eating nutrient dense foods 3. More chains adopt technological solutions (e.g. logistics) to reduce transaction costs within value chains for nutrient dense products, increasing affordability 4. Cost-effective solutions to reduce post-harvest losses within chains are found, increasing affordability and accessibility 5. Policies support the implementation of solutions for food safety and other market level concerns | M14: 1. For Latin America, our work is focusing only on the suite of solutions making markets more efficient, so we score it highest. We may work on limiting UPC consumption there if resources come available, so we score it higher than 1. | N14: Internally it is best to understand what products are most required in the diet (AoW1) so we can prioritize them for diets; in this case so that we can target those markets if foodis produced but costly or not available enough for some reason. | O14: We are collaborating with SAAF to develop food safety solutions for animal source foods. To the extent that we are able to demonstrate positive solutions, we will attempt to work with the Scaling for Impact Science Program on scaling them.
C15: AoW2-Suite of Solutions to catalyze business growth | D15: 1 | F15: 3 | G15: 3 | H15: 4 | K15: 1. Many types of actors in markets for nutrient dense foods lack access to formal finance (traders, vendors in particular) 2. Formal financial products are not often tailored to the needs of agri-food businesses selling more nutrient dense foods 3. Demand for financial products may be uncertain in some markets 4. Climate finance funds are not necessarily aware of the nutritional and dietary impacts of their investments in small or medium enterprises 5. Technological solutions exist to reduce the standard transaction costs which drive adverse selection and moral hazard problems, but low uptake as of yet in most markets | L15: 1. Improved access to finance among businesses working in markets for more nutrient dense foods, leading to business growth and improved employment 2. Better designed products with clear explanation to users about how products work (interest rates, payment schedules, etc.) 3. Increased use of technology in loaning value chain actors money 4. Climate finance funds begin to lend to firms working in nutrient dense product markets | M15: 2. In West and Central Africa, coastal countries have more exposure to trade; there is less progress we believe on quality interventions and with our strained capacity we focus primarily on policy and finance for nutrient dense foods in West and Central Africa. Hence we give the lowest score to lowering transaction costs and the highest to trade, an a medium score to catalyzing business growth. | N15: Internally it is best to understand what products are most required in the diet (AoW1) so we can prioritize them for diets. Similarly with better info on UPC consumption we can envision targeting growth work most effectively. | O15: To the extent that we are able to demonstrate positive solutions, we will attempt to work with the Scaling for Impact Science Program on scaling them.
C16: AoW2-Trade and Limiting UPC Consumption | D16: 3 | F16: 4 | G16: 2 | H16: 2 | K16: 1. International Trade contributes to healthier diets in some countries, but not others, and agricultural trade policy can have implications for diets; 2. While subsidies not large enough in most LMICs to change demand for products, some countries with very large markets could repurpose subsidies to improve markets for more nutrient dense foods; 3. Well designed policies can hinder demand for ultra processed foods, but most countries outside of LAC and OECD do not have policies on ultra processed foods | L16: 1. Improved understanding of trade helps governments promote specific types of more nutrient dense foods that fill dietary requirements in countries with substantial food trade; 2. Subsidies are repurposed in India and other large LMICs with subsidies to reduce distortions to markets; 3. LMICs begin to implement policies (labeling, SSB taxes, others) that can help reduce the growth of demand for UPFs | M16: 3. In East and Southern Africa, technology capacity is high, meaning that we focus on use of tech in “solutions” and finance to try to improve affordability and availability of more nutrient dense foods. So we limit work on trade and UPC consumption. 4. In South Asia, finance is relatively important for increasing growth in trade of more nutrient dense products due to availability of solutions but lack of implementation. We then believe the suite of solutions for business growth is most important, followed reducing transaction costs and then by policy.
C17: AoW3-Suite of tested end-to-end solutions for health and agriculture extension agents, fruit and vegetable vendors/retailers, processors, traders and producers that promote healthy food choice behaviors of consumers, healthy food environments, food quality and safety, reduce food loss, and increase profits co-developed, tested, and scaled. | D17: 3 | F17: 3 | G17: 5 | H17: 5 | I17: 3 | K17: 1. In the Global South, fruit and vegetable consumption remains below the recommended 400g per day, which is crucial for preventing chronic diseases. Factors such as food preferences, diet and nutrition knowledge, education, affordability of fruit and vegetables, food safety and quality issues, inadequate supply due to perishability and complex marketing, and poor infrastructure hinder access to and consumption of these foods. 2. Behavior change towards healthier food choices, including increasing the intake of fruits and vegetables, is complex and evidence from interventions to increase fruit and vegetable intake are lacking, despite the exisitence of relevant tools such as national food based dietary guidelines. 3. Food environments incresingly favor promotion of unhealthy foods and there is limited evidence about the impact of changing food environments to support healthier food choices like increasing intake of fruits and vegetables. 4. Fruit and vegetable production has increased by 3.3% annually over the last two decades, but per capita growth is only 0.7%. 5. Supply is not keeping pace with demand and population growth due to a range of complex factors, including poor access to high-quality inputs, high post-harvest loss (up to 50%), significant contamination from pesticide residues due to improper use of chemical products and handling, limited market access, and a lack of improved technologies. 6. Climate change further exacerbates these challenges, leading to rising temperatures, erratic rainfall, and increased pest populations that can potentially reduce yields. 7. There is a growing demand for safe fruit and vegetables, and improved technologies for safe production, post-harvest handling, and storage are available. | L17: 1. Demand for fruit and vegetables increases such that most people meet the recommended intake of 400 g/d 2. Food environments change in ways that support and encourage healthier food choices, including increasing the access to and affordability of fruit and vegetables 3. Fruit and vegetable consumption demand in the Global South is met within planetary boundaries 4. Post-harvest practices improve such that pesitcide contamination and microbial contamination are reduced 5. Stakeholders across fruit and vegetable value chains adopt solutions that promote healthy food choice behaviors of consumers, healthy food environments, food quality and safety, reduce food loss. | M17: 1. WCA and ESA: Solutions are needed to improve fruit and vegetable consumption, production, post-harvest, safety, and market access. Partnerships have been established across the regions. 2. SEA: There are established partnerships in some countries, and the buy-in of stakeholders to deploy solutions that support increasing fruit and vegetable intake. 3. SA: There are established partnerships in some countries and buy-in from stakeholders to deploy solutions that support increaing fruit and vegetable intake. | N17: Evidence from pilot studies and innovations are relevant to the stakeholders they are designed to reach/support Stakeholders across the value chain work together to deploy solutions. Evidence is relevant to country priorities and policymakers have the will to use evidence to inform programs and policies | O17: For translation to urban environments we will work wtih the urban AOW in the Food Fronteirs and Security SP
C18: AoW3-Suite of end-to-end solutions for health and agriculture extension agents, aquatic food vendors/retailers processors, and traders that promote healthy food choice behaviors of consumers, healthy food environments, food quality and safety, reduce food loss, and increase profits co-developed, tested, and scaled. | D18: 3 | F18: 4 | G18: 4 | H18: 3 | I18: 4 | K18: 1. Worldwide in 2032, aquatic animal per capita consumption is likely to increase everywhere except in sub-Saharan Africa where alot of people depend on aquatic foods for animal protein and micronutrients 2. Fish loss and waste estimates in Africa is estimated at around 40% which is far above the global average of 25% having a significant impact of food and nutrition security. 3. In SEA diets are dominated by rice and fish provide the necessary micronutrients. Fish provide 50% of animal protein in Cambodia, Indonesia and Phillipines. Due to the immense pressure fisheries face as a result of high consumption, adressing loss and waste to ensure retention of nutrients within the system is crucial. | L18: 1. Aquatic animal consumption demand in Sub-Saharan Africa is met within planetary boundaries 2. Stakeholders within the aquatic foods value chain adopt climate smart loss and waste technologies | M18: 1. ESA & WCA- this region has had several countries conducting multi dimensional waste and loss studies along fish value chains and indication of willingness to address loss and waste issues. 2. The two regions also have fisheries regional and country specific policies that recognize the role of addressing losss and waste in the fisheries and aquaculture sector indicating a conducive envrionment for introducing waste and loss technologies 3. Several South East Asian countries have recognized the role of fisheries in their national nutrition action plans (LAO, Cambodia, Phillipines, Thailand, Myanmar, Indonesia, Malaysia) | N18: (i) Market actors perceive the food environment solutions as win-win and have the interest and capacity to implement the solutions. (ii) Social cultural factors that hinder consumption of animal source foods, especially for vulnerable populations are amenable to change | O18: (i) Collaboration with the SAAFs SP especially on the production aspects of the aquatic animal source food systems.
C19: AoW3-Suite of end-to-end solutions for health and agriculture extension agents, terrestrial animal-source vendors/retailers processors, and traders that promote healthy food choice behaviors of consumers, healthy food environments, food quality and safety, reduce food loss, and increase profits co-developed, tested, and scaled. | D19: 2 | F19: 3 | G19: 3 | H19: 4 | I19: 3 | K19: 1. High levels of micronutrient deficiencies in Eastern Africa, WCA and SEA - partly due to insufficient consumption of animal source foods. Eastern Africa is known for its large dairy animal populations, but still, most countries in the region consume only a third of the recommended amount of ASFs. 2. Solutions are needed to improve animal source foods intake to recommended levels as part of healthy diets, especially for vulnerable populations – young children, pregnant and lactating women; in addition to healthy food environment related challenges. 3. ESA: Established partnerships in some countries such as Uganda, Tanzania, Ethiopia, Kenya (from SAPLING efforts) | L19: 1. Terrestrial animal source foods demand in Sub-Saharan Africa is met within planetary boundaries 2. Actors within the terestrial animal source foods system adopt solutions that promote healthy food choice behaviors of consumers, healthy food environments, and food safety | M19: ESA: Several countries in this region have made strides in advocating for integration of terrestrial animal source foods as part of healthy diets- particularly targeting vulnerable populations through strong partnerships. Several studies have generated evidence on the impact of interventions that address social cultural constraints to consumption of animals source foods and nutrition education, on diets. Further interventions aimed at healthy food environment will enhance such benefits. | N19: (i) Market actors perceive the food environment solutions as win-win and have the interest and capacity to implement the solutions. (ii) Social cultural factors that hinder consumption of animal source foods, especially for vulnerable populations are amenable to change | O19: (i) Collaboration with the SAAFs SP especially on the production aspects of the terrestrial animal source food systems.
C20: AoW3-Suite of integrated end-to-end solutions for health and agriculture extension agents, perishable nutrient-rich food vendors/retailers, processors, traders and producers that promote healthy food choice behaviors of consumers, healthy food environments, food quality and safety, reduce food loss,and increase profits co-developed, tested, and scaled. | D20: 3 | F20: 3 | G20: 3 | H20: 4 | I20: 3 | K20: 1. In the Global South, fruit and vegetable consumption remains below the recommended 400g per day, which is crucial for preventing chronic diseases. Intake of aquatic foods is also suboptimal as is intake of terrestrial animal source foods (in some cases too high and others too low). Factors such as food preferences, diet and nutrition knowledge, education, affordability of fruit and vegetables, food safety and quality issues, inadequate supply due to perishability and complex marketing, and poor infrastructure hinder access to and consumption of these foods. 2. Behavior change towards healthier food choices, including increasing the intake of fruits and vegetables, is complex and evidence from interventions to increase fruit and vegetable intake are lacking, despite the exisitence of relevant tools such as national food based dietary guidelines. 3. Food environments incresingly favor promotion of unhealthy foods and there is limited evidence about the impact of changing food environments to support healthier food choices like increasing intake of fruits and vegetables. 4. Food loss and waste of fruits and vegetables and aquatic foods is high at around 40%. | L20: 1. Demand for sustainable healthy diets increases 2. Food environments change in ways that support and encourage healthier food choices, including increasing the access to and affordability of fruit and vegetables 3. Perinshable nutrient-rich food consumption demand in the Global South is met within planetary boundaries 4. Post-harvest practices improve such that pesitcide contamination and microbial contamination are reduced 5. Food loss and waste are reduced through improved practices and technoligies | M20: ESA: Well established partnerships exisit. There is buy-in from relevant stakehodlers intreseted in end-to-end solutions to improving diet and nutrition outcomes. Food-based dietary guidelines exist for forcal coutries. Good opportuinities for integration. WCA: Well established partnerships exisit. There is buy-in from relevant stakehodlers intreseted in end-to-end solutions to improving diet and nutrition outcomes. Food-based dietary guidelines exist for forcal coutries. SA: Well established partnerships exisit. There is buy-in from relevant stakehodlers intreseted in end-to-end solutions to improving diet and nutrition outcomes. Food-based dietary guidelines exist for forcal coutries. Good opportuinities for integration. | N20: Actors across sectors are able to work together to deploy more complex integrated solutions, Pilot studies can be conducted to support development of prototypes for integration. | O20: Collaboration with Sustainable Farming, Sustainable Animal and Aquatic Foods to test and pilot integrated solutions
C21: AoW3-Policy options that address constraints to sustainable healthy diets | D21: 4 | F21: 3 | G21: 2 | H21: 3 | I21: 4 | K21: 1. Many countries have multisectoral nutrition action plans, programs and policies, however there is limitied attention paid to how to achieve end-to-end solutions for perishable nutrient-rich foods. 2. While there is some evidence to support taxes on unheathy foods and other products, similar efforts are scant for using subisides, or other incentives to support healthy food choices. 3. In some cases regulations and laws exist to support food safety measures, however these are often not adequately monitored or enforced. 4. Fruits and vegetables are often not prioritized for investments, subsidies or other incentives to support growth of this sector, aside from actions to support development for export in some cases. | L21: 1. Multisectoral nutrition action plans, programs and policies include actions to support end-to-end solutions for increasing intake of perishable nutrient-rich foods. 2. Evidence is generated to understand the inflence of taxes, subsideis or other incentives to support healthy food production and consumption. 3. Regulations and laws related to food safety are updated enforced. 4. Stakeholders across perishable nutrient-rich food value chains adopt solutions that promote healthy food choice behaviors of consumers, healthy food environments, food quality and safety, reduce food loss. | M21: In WCA and ESA policy frameworks remain weak, and stakeholder engagement is often fragmented and inconsistent. Policymakers are open to evidence-based dialogue; institutional champions exist; multisector coordination platforms are functional; and governments are committed to improving diets, public health, and nutrition outcomes. The other regions also have weak policy frameworks and implementation strategies but LAC has some biofortification champions. In SEA policys remain insuffiecient addressing in particular over-nutrition and obesity, while in SA both under- and overnutrition are prevalent with weak policies addressing either. | N21: More syngery with AoW5 and AoW6 to translate evidences into actionable policy and engagement with policy makers
C22: AoW4-Suite of solutions for producers and processors that address constraints to sustainable healthy diets co-developed, tested, and scaled with technical support and country engagement. | D22: 2 | E22: 3 | F22: 2 | G22: 2 | H22: 2 | I22: 3 | K22: Many smallholder producers and processors lack access to inputs, infrastructure, technical support, and incentives to adopt and scale biofortified and health-enhancing crops. Post-harvest losses are high, and awareness of nutritional benefits remains low. Nutrient retention varies and is often not clearly defined. | L22: Widespread availability and adoption of solutions by producers and processors that are context-specific, technically supported, and commercially viable leading to increased production, reduced losses, and improved delivery of affordable biofortified and health-enhancing foods and minimally processed products to markets. | M22: Given the high prevalence of hidden hunger in general but even higher among vulnerable populations—particularly young children in West and Central Africa (WCA) and Eastern and Southern Africa (ESA)—products formulated with biofortified ingredients are essential to meet their nutritional needs. This prevalence is less pronounced in LAC, SEA and SA. However, in SA the triple burden of malnutrion is most pronounced. Furthermore, many farmers are resource-constrained. Farmers and processors are willing to adopt innovations when they see value and profitability; enabling environments exist in key countries; foundational research and delivery systems are strong; and national strategies align with scaling goals. | N22: Development of appropriate product profiles; availability of context-specific technologies; partnerships with NARS and processors; capacity building for farmer cooperatives and SMEs; robust monitoring of uptake and impact; generating evidence of possible impacts (ex-ante) to define highly probable investment cases. | O22: Coordination with breeding teams for biofortified and health enhancing-varieties; engagement with Breeding for Tomorrw (B4T) HLOs STEER, INVEST, DESIGN and TARGET to determine investment opportunities through targeted interventions and projection of benefits; engagement with extension services and market access initiatives; collaboration with food systems transformation and policy units to align incentives and standards.
C23: AoW4-Policy options and engagement that address constraints to sustainable healthy diets. | D23: 2 | E23: 3 | F23: 5 | G23: 5 | H23: 4 | I23: 4 | K23: Nutrition considerations are often missing or inconsistently addressed in agricultural, food systems, and public health policies. Limited engagement with policymakers and lack of coherent strategies hinder integration and adoption of biofortified and health-enhancing crops. | L23: Policies at national and regional levels consistently prioritize and integrate biofortified and health-enhancing crops into agriculture, food systems, nutrition, and health agendas driven by stakeholder demand and evidence-based guidance to improve fodd and nutrition security. | M23: In WCA and ESA policy frameworks remain weak, and stakeholder engagement is often fragmented and inconsistent. Policymakers are open to evidence-based dialogue; institutional champions exist; multisector coordination platforms are functional; and governments are committed to improving diets, public health, and nutrition outcomes. The other regions also have weak policy frameworks and implementation strategies but LAC has some biofortification champions. In SEA policys remain insuffiecient addressing in particular over-nutrition and obesity, while in SA both under- and overnutrition are prevalent with weak policies addressing either. | N23: Robust policy research and synthesis; strategic partnerships with policy influencers; targeted advocacy campaigns; monitoring policy impact on nutrition outcomes; generating evidence for valid investment cases through projected impact determination. Support from public health, legal, trade, and education sectors to harmonize and implement enabling legislation, standards, and cross-sector frameworks that align with improved diets and nutrition goals. | O23: Close collaboration with Policy Innovation; B4T AoW on Market Intelligence to generate Investment cases (INVEST), and benefit projections (STEER) in target geographies.
C24: AoW4-Framework for embedding nutrition into breeding pipelines and processes. | D24: 2 | E24: 3 | F24: 4 | G24: 4 | H24: 4 | I24: 4 | K24: Breeding programs do not consistently incorporate nutritional traits or consumer-demanded profiles. Integration of nutrition is often dependent on project-specific funding or champions and lacks institutionalization across CGIAR and NARS systems. There is often an argument of potential trade-offs between nutrient increase and yield. | L24: Breeding pipelines mainstream nutritional traits in target product profiles (TPPs), guided by evidence on dietary gaps and consumer needs resulting in varieties that are agronomically competitive, nutrient-dense, high yielding, and desired by consumers. | M24: In WCA and ESA, only a limited number of Target Product Profiles (TPPs) have integrated and evaluated nutrition traits in a systematic manner and only for selctive crops. Breeding teams lack recognizing the importance of nutrition and health-enhancing traits and are primarily focussed on improving yield; while food security has improved across all the regions, nutrition security has not and high levels of micronutrient deficiencies exists in WCA, ESA, SA while there is a rise in NCD occurances in SEA and SA. tools and methods for nutritional assessment are not accessible currently; and leadership support is limited for the interdisciplinary collaboration between nutrition and breeding teams in all regions. | N24: Development of demand-driven TPPs that integrate diet quality needs; shared metrics for nutritional quality; capacity building of breeding teams; investment in screening and diagnostic infrastructure. Collaboration with nutrition and health research teams and socioeconomics research teams to generate evidence on consumer needs, dietary gaps, and policy priorities that guide breeding decisions. | O24: Collaboration with B4T, in particular the areas of work on Accelerated Breeding, Breeding resources, Market Intelligence and ENABLE. I special focus needs to be on sub-AoW DESIGN to ensure the full integration of diet improving traits in product concepts and the product design standard.
C25: AoW4-Suite of solutions for traders and vendors that address constraints to sustainable healthy diets co-developed, tested, and scaled with technical support and country engagement. | D25: 2 | E25: 3 | F25: 2 | G25: 2 | H25: 2 | I25: 2 | K25: Traders and vendors have limited incentives or awareness to prioritize the sourcing and marketing of biofortified and health-enhancing products. Market demand is weak or unclear, and regulatory frameworks for labeling or differentiation are often absent. | L25: Traders and vendors actively source, promote, and sell biofortified and health-enhancing crops and products, supported by a strong value proposition, clear quality standards, and informed consumers who demand such options. | M25: In WCA and ESA, traders and vendors often lack strong market linkages and face significant knowledge asymmetries, limiting their ability to make informed decisions which is also present in the other regions. Traders and vendors respond to consumer demand and profit opportunities; market channels and regulatory structures currently do not allow for differentiation; traceability systems for 'invisible trait' are not feasible and affordable in all regions. However, malnutrition is most pronounced in ESA, WCA and SA. | N25: Clear labeling standards and branding for biofortified and health-enhancing products; training and market linkages for vendors; development of traceability tools and quality assurance mechanisms. Support from consumer awareness campaigns, policy advocacy for enabling regulations, and collaboration with market systems and private sector engagement teams. | O25: Collaboration from STEER and INVEST (B4T, AoW MArket Intelligence) are needed to provide evidence of valid investment opportunities to support trader and vendor decision making. Policy Innovation is needed to support labeling and tracability policies.
C26: AoW4-Suite of solutions to support consumers awareness, preference, affordability, and utilization of biofortified and health-enhancing crops in their diets. | D26: 2 | E26: 3 | F26: 3 | G26: 2 | H26: 2 | I26: 2 | K26: Consumer awareness and demand for biofortified and health-enhancing foods are generally low. Many consumers are not aware of their micronutrient deficiancies. Misconceptions from the GMO debates, lack of clear labeling, and limited availability or affordability hinder widespread adoption especially among low-income and nutritionally vulnerable populations. Social norms around prosperity and overnutrition exist and affect the development of NCDs. | L26: Consumers are aware of their micronutrient status and its importance. Consumers are informed, motivated, and able to include biofortified and health-enhancing foods in their diets driven by clear value propositions, affordable options, positive Behavior Change Communication (BCC), and supportive food environments. | M26: Consumer awareness of nutrition, health, and how to maintain a healthy diet remains low and underdeveloped in all regions. Consumers have limited access to trusted information and have little purchasing power; cultural beliefs and taste preferences can be positively influenced through evidence-based BCC in all regions; supportive policy and retail environments are lacking to enable availability. | N26: Strategic BCC and social marketing campaigns; consumer research to tailor messaging and product development; partnerships with community organizations and retailers. Support from media, education, and health sectors to amplify messaging; collaboration with market and food policy teams to ensure affordability and retail availability. | O26: Gender accelerator to tailor BCCs to reach all consumers equitably.
C27: AoW5-Suite of multisectoral solutions for government and non-government organizations that address constraints to sustainable healthy diets co-developed, tested, and scaled with technical support and country engagement | D27: 2 | F27: 4 | G27: 4 | H27: 4 | I27: 4 | K27: Food system actions and making food environments healthy are essential, but insufficient, to increase the consumption of sustainable healthy diets by all: Consumers often lack knowledge about nutritious diets, sufficient (monetary) resources, autonomy, and empowerment to acquire foods. Once foods have been acquired, they need to be consumed. The transformation of foods into a sustainable healthy diet for all requires, amongst other things, nutrition knowledge (which is often missing), an equitable (i.e., based on nutritional needs) distribution of foods within the household (often not the case), and autonomy and empowerment (often lacking). Complementary policies that unlock the full potential of food systems transformation are missing. | L27: 1) Consumers have adequate knowledge about nutritious diets and sufficient (monetary) resources, autonomy, and empowerment to acquire foods. 2) The transformation of foods into a sustainable healthy diet for all is not hindered by limited nutrition knowledge, inequitable (i.e., based on nutritional needs) distribution of foods within the household, or limited autonomy and empowerment. Health, and other sectoral policies are well-aligned, with a shared emphasis on the role of diets in achieving both economic and health goals. | M27: WCA, ESA, SA, SEA - The factors limiting the effective 'translation' of food systems action into the consumption of healthy diets are diverse across these regions but strongly present. We estimate that the impact of our work in these regions is very high. LAC - This region had done more work on social protection, informing consumers about healthiness of foods, limiting promotion of and access to unhealthy foods. CGIAR has much to learn here with solid partners. We estimate a medium potential for impact here. | N27: Evidence is relevant (helps meet government actors' goals) and timely for government actors to use. Gov’t actors perceive their institutions have the capacity to implement the solutions. | O27: Scaling for Impact: We'll need their expertise to help us scale our own tested solutions. Collaboration with Gender Accelerator to understand better equity issues in addressing drivers of food choices.
C28: AoW6-Synthesized knowledge products across AoWs and disseminated | D28: 2 | E28: 2 | F28: 3 | G28: 3 | H28: 3 | I28: 2 | K28: Limited synthesis of knowledge to inform FST towards better diets. | L28: A framework to guide the synthesis. Active (ongoing) synthesis of knowledge. | M28: Efforts by BDN will be recognized as being useful and taken up as approaches for evidence synthesis | N28: Adequate coordination across AoWs to collate the emerging evidence | O28: Adequate coordination across other P/As
C29: AoW6-Regional food systems transformation coordination mechanisms disseminated | D29: 3 | E29: 3 | F29: 4 | G29: 4 | H29: 4 | I29: 4 | K29: Inadequate coordination and governance for FST within regions | L29: Adequate coordination and governace for FST towards BDN within regions | M29: Regional bodies will be willing and able to make use of BDN knowledge products. Alignement with other P/As on keys messages for BDN | N29: Effective engagement by BDN scientists in regional processes/events to be able to influence | O29: Robust engagement by other P/As to share products that can be used in the engagments. Complete alignment on key messages for BDN
C30: AoW6-Targeted capacity-sharing events addressing evidence to policy actions and strategic engagement to influence food systems thinking to promote positive transformative change among different stakeholders including CoPs. | D30: 3 | E30: 3 | F30: 3 | G30: 2 | H30: 2 | I30: 3
C31: AoW6-Regional, continental FS leadership development events to promote BDN outcomes for FST | D31: 3 | E31: 3 | F31: 2 | G31: 2 | H31: 2 | I31: 3
C32: AoW6-Task force that guides the CGIAR Portfolio along pathways that lead to credible impacts on nutrition, health, and food security | D32: 3 | E32: 3 | F32: 3 | G32: 3 | H32: 3 | I32: 3 | K32: Lack of coordination, knowledge and systmes thinking across P/As around FST towards BDN from the respective P/As perspective | L32: Good coordination, adequate knowledge; and adoption of systems thinking across P/As around FST towards BDN from the respective P/As perspective | M32: There is willingness and ability among P/As in BDN led activities to strengthem coordination, knowledge uptake and adoption of systems thinking | N32: Ability to convene the P/As in the planned activities and adequate resources | O32: Thinking beyond the immediate (economic) outputs P/As and focusing on how they can contribute to BDN

Sheet 2.Poverty_reduction
C1: Poverty Indicators
A2: VH | B2: 5 | D2: LAC | E2: CWANA | F2: WCA | G2: ESA | H2: SA | I2: SEA | J2: AoW1 | K2: =AVERAGE(D11:I13) -> 3
A3: H | B3: 4 | C3: total score by column | D3: =SUM(D11:D59) -> 49 | E3: =SUM(E11:E59) -> 19 | F3: =SUM(F11:F59) -> 69 | G3: =SUM(G11:G59) -> 69 | H3: =SUM(H11:H59) -> 69 | I3: =SUM(I11:I59) -> 60 | J3: AoW2 | K3: =AVERAGE(D14:I16) -> 3.5833333
A4: MH | B4: 3 | C4: VH count by column | D4: =COUNTIF(D$11:D$59, 5) -> 2 | E4: =COUNTIF(E$11:E$59, 5) -> 0 | F4: =COUNTIF(F$11:F$59, 5) -> 4 | G4: =COUNTIF(G$11:G$59, 5) -> 4 | H4: =COUNTIF(H$11:H$59, 5) -> 4 | I4: =COUNTIF(I$11:I$59, 5) -> 4 | J4: AoW3 | K4: =AVERAGE(D17:I21) -> 3.4
A5: M | B5: 2 | C5: H count by column | D5: =COUNTIF(D$11:D$59, 4) -> 4 | E5: =COUNTIF(E$11:E$59, 4) -> 0 | F5: =COUNTIF(F$11:F$59, 4) -> 2 | G5: =COUNTIF(G$11:G$59, 4) -> 2 | H5: =COUNTIF(H$11:H$59, 4) -> 3 | I5: =COUNTIF(I$11:I$59, 4) -> 2 | J5: AoW4 | K5: =AVERAGE(D22:I26) -> 3.0666667
A6: L | B6: 1 | C6: MH count by column | D6: =COUNTIF(D$11:D$59, 3) -> 3 | E6: =COUNTIF(E$11:E$59, 3) -> 6 | F6: =COUNTIF(F$11:F$59, 3) -> 10 | G6: =COUNTIF(G$11:G$59, 3) -> 10 | H6: =COUNTIF(H$11:H$59, 3) -> 8 | I6: =COUNTIF(I$11:I$59, 3) -> 7 | J6: AoW5 | K6: =AVERAGE(D27:I27) -> 1.6666667
C7: M count by column | D7: =COUNTIF(D$11:D$59, 2) -> 5 | E7: =COUNTIF(E$11:E$59, 2) -> 0 | F7: =COUNTIF(F$11:F$59, 2) -> 5 | G7: =COUNTIF(G$11:G$59, 2) -> 5 | H7: =COUNTIF(H$11:H$59, 2) -> 6 | I7: =COUNTIF(I$11:I$59, 2) -> 5 | J7: AoW6 | K7: =AVERAGE(D28:I32) -> 2.7272727
C8: L count by column | D8: =COUNTIF(D$11:D$59, 1) -> 4 | E8: =COUNTIF(E$11:E$59, 1) -> 1 | F8: =COUNTIF(F$11:F$59, 1) -> 1 | G8: =COUNTIF(G$11:G$59, 1) -> 1 | H8: =COUNTIF(H$11:H$59, 1) -> 1 | I8: =COUNTIF(I$11:I$59, 1) -> 1 | K8: Current state (across the Global South) | L8: Ideal state (across the Global South) | M8: Assumptions (for region-specific scores) | N8: Requirements for success (internal to P/A) | O8: Requirements for success (from other P/As)
C10: HLO | D10: LAC | E10: CWANA | F10: WCA | G10: ESA | H10: SA | I10: SEA
A11: HLO count: | B11: =COUNTA(C11:C59) -> 22 | C11: AoW1-Suite of solutions focused on consumers that promote consumption of sustainable heathy diets co-developed, tested, and scaled with technical support and country engagement | D11: 1 | F11: 1 | G11: 1 | H11: 1 | I11: 1 | K11: 1. Solutions (behavior change, like FBDGs) are there, but there's lack of evidence on effectiveness and, do not address full components of food system, and/or are not in use 2. Few solutions address the food environment 3. Metrics are not all-encompassing 4. Metrics are not being used by gov'ts for decisionmaking 5. Many barriers prevent governments from taking actions and there is an uneven willingness to act across ministries and levels. 6. There's a lot of info on what governments can do, but very little information on how do it | L11: 1. Evidence-based, food system–wide solutions like FBDGs are now widely implemented and proven effective. 2. Comprehensive interventions now actively address the food environment alongside individual behavior change. 3. Robust, multidimensional metrics are in place to capture the full complexity of food systems. 4. Governments are effectively using these metrics to inform policy and decision-making. 5. Strong and consistent political will is driving coordinated action across sectors. 6. Clear, practical guidance is now available to support governments in implementing food systems transformation. | M11: We estimate that the potential of this HLO to contribute to povery reduction across all geographies is low given that consumer focused solutions will have limited to no impact on poverty. | N11: Evidence is relevant (helps meet their goals) and timely for government actors to use. Gov’t actors perceive their institutions have the capacity to implement the solutions. | O11: From CGIAR's production-oriented Programs: We need sustainable nutritious foods to be available, affordable, safe, sustainably produced even in the midst of local and global shocks and resilient in the face of climate change. Scaling for Impact: We'll need their expertise to help us scale our own tested solutions.
A12: Sets of 5: | B12: =_xlfn.FLOOR.MATH(B11/5) -> 4 | C12: AoW1-Suite of solutions focused on vendors that promote employment opportunities and the sale of sustainable nutritious foods co-developed, tested, and scaled with technical support and country engagement | D12: 5 | F12: 5 | G12: 5 | H12: 5 | I12: 5 | K12: 1. Lack of data about MSMEs and informal actors - what are their barriers, their constraints, their incentives, and so on. 2. Lack of data on the presence of healthy foods being sold by MSMEs and informal actors 3. Few evidence-based solutions for how to improve conditions for MSMEs and informal actors selling foods 4. Increasing presence of UPFs combined with infrastructure realities (widely variable access to cold storage, clean water) changes the cost-benefits for MSME and informal actors 5. Successful and aggressive commercial strategies of multinational food companies increase availability and affordability of UPFs | L12: 1. Comprehensive data now exists on the barriers, constraints, and incentives facing MSMEs and informal food actors. 2. Detailed insights are available on the availability of healthy foods sold by MSMEs and informal vendors. 3. Effective, evidence-based solutions are in place to support and improve conditions for food-selling MSMEs and informal actors. 4. The implications of UPFs and infrastructure challenges are well understood, enabling tailored support for MSMEs and informal vendors. 5. Nutritious food options are becoming more available and affordable, aided by strategic approaches adapted from successful commercial models. | M12: The importance of the food environment in LMICs for employment and income generation, especially for female vendors and the poor, is critical. We estimate that across all the geographies where BDN is working, positive results in this HLO will have very high impacts on poverty reduction for this specific population. | N12: Evidence is relevant (helps meet their goals) and timely for government actors to use. Gov’t actors perceive their institutions have the capacity to implement the solutions. MSMEs and informal actors perceive the solutions are not harmful to their profit margin and have the capacity to implement the solutions. | O12: Scaling for Impact: We'll need their expertise to help us scale our own tested solutions.
A13: Remainder: | B13: =MOD(B11,5) -> 2 | C13: AoW1-Policy options and engagement that support effective management of national action plans and other policy processes, for food systems transformation in support of sustainable healthy diets | D13: 3 | F13: 3 | G13: 3 | H13: 3 | I13: 3 | K13: 1. Food System Transformation National Action Plans are being developed but at various levels of detail, and hardly being implemented. 2. Lack of policy coherence. Lack of clear and consistent food system policies across levels and sectors of government mean 3. Lack of policy alignment. For example, ag policies that maximize production for economic growth vs health policies that promote health (without speaking to diets). 4. Policies are on paper, but not in practice 5. Difficulty of government to operationalize their aspirations for food systems transformation (issues relate to awareness, capacity, finance, political economy...) 6. Policy landscape is behind the curve, framed by the issues from 50 years ago (undernourished, calories), and not the present threats (obesity and overweight and NCDs) | L13: 1. Food system policies are now coherent, clearly defined, and consistently applied across all levels and sectors of government. 2. Policy alignment across agriculture, health, and other sectors now ensures shared goals around nutrition and sustainable diets. 3. Policies are actively implemented, with strong follow-through translating commitments into action. 4. Governments are effectively operationalizing food systems transformation, supported by improved awareness, capacity, financing, and political coordination. 5. Policy frameworks have been updated to reflect today’s challenges, focusing on obesity, overweight, and noncommunicable diseases alongside historical concerns. | M13: Across all the geographies where BDN is active, the achievement of forward looking policy coherence and alignment in support postitive of food system transformation could have important impacts on poverty reduction. As a result we estimate that advances against the HLO has a medium high potential to impact poverty reduction in our target countries. | N13: Decisionmakers have the awareness of political lock-ins and capacity to overcome them to improve sectoral alignment. Decisionmakers have the awareness of trade-offs and how to overcome them. The new governance mechanisms integrate various societal perspectives. | O13: Policy Innovations: we need their quantitative modelling of trade-off analysis Climate Action, Multifunctional Landscapes: we need their help to promote policy coherence across different agendas (climate, biodiversity).
A14: Max score: | B14: =(B12*SUM($B$2:$B$6))+SUM($B$2:INDEX(B:B, $B$13+1)) -> 69 | C14: AoW2-Suite of Solutions to lower transaction costs | D14: 5 | F14: 4 | G14: 4 | H14: 4 | K14: We discuss the current state in the "food security" tab. | L14: We discuss the ideal state in the "food security" tab. | M14: 1. Note, here all of the impacts must come through improved incomes. Policies we focus on are less likely to have direct impacts. As a result, we give a slightly lower score in the three main regions to lowering transaction costs. There are no clear regional variables that would or should differentiate these outcomes from a poverty reduction perspective. | N14: Internally it is best to understand what products are most required in the diet (AoW1) so we can prioritize them for diets; in this case so that we can target those markets if foodis produced but costly or not available enough for some reason. | O14: We are collaborating with SAAF to develop food safety solutions for animal source foods. To the extent that we are able to demonstrate positive solutions, we will attempt to work with the Scaling for Impact Science Program on scaling them.
C15: AoW2-Suite of Solutions to catalyze business growth | D15: 1 | F15: 5 | G15: 5 | H15: 5 | K15: We discuss the current state in the "food security" tab. | L15: We discuss the ideal state in the "food security" tab. | M15: 2. Business growth is more likely to drive income growth in general in the three regions we are prioritizing than lowering transaction costs or limiting UPC consumption. And there are no clear differentiating variables across the three regions as discussed above. | N15: Internally it is best to understand what products are most required in the diet (AoW1) so we can prioritize them for diets. Similarly with better info on UPC consumption we can envision targeting growth work most effectively. | O15: To the extent that we are able to demonstrate positive solutions, we will attempt to work with the Scaling for Impact Science Program on scaling them.
C16: AoW2-Trade and Limiting UPC Consumption | D16: 1 | F16: 3 | G16: 3 | H16: 3 | K16: We discuss the current state in the "food security" tab. | L16: We discuss the ideal state in the "food security" tab. | M16: Increased trade might have positive effects on income growth among value chain actors, but it is not necessary, and taxes or regulations on UPFs could negatively affect some vendors. Again there are not clear regional differences.
C17: AoW3-Suite of tested end-to-end solutions for health and agriculture extension agents, fruit and vegetable vendors/retailers, processors, traders and producers that promote healthy food choice behaviors of consumers, healthy food environments, food quality and safety, reduce food loss, and increase profits co-developed, tested, and scaled. | D17: 4 | F17: 3 | G17: 3 | H17: 5 | I17: 5 | K17: 1. Supply is not keeping pace with demand and population growth due to a range of complex factors, including poor access to high-quality inputs, high post-harvest loss (up to 50%). Given the need to increase production there is room for growth and new job creation in this sector. Horticulture products are also high value and thus, may be attractive for youth and others with interest in agriculture livelihoods. 2. There are also opportunities to transform fruits and vegetables into different types of products, creating further job opportunities. 3. Other livelihood opportunities also exist across the fruit and vegetable value chain. | L17: 1. Increased investment in the fruit and vegetable sector leads to more jobs with adeqaute wages. 2. Increased opportunities for small and medium enterprises in across the value chain. | M17: Both national and sub national governments recognize the role of fruit and vegetable sector as an avenue of poverty reduction | N17: Collaboration with private sector and market actors involved in fruit and vegetable sector and regulatory authorities | O17: Close collaboration with Scaling for impact to disseminate solutions that, if adopted, can provide decent jobs to actors
C18: AoW3-Suite of end-to-end solutions for health and agriculture extension agents, aquatic food vendors/retailers processors, and traders that promote healthy food choice behaviors of consumers, healthy food environments, food quality and safety, reduce food loss, and increase profits co-developed, tested, and scaled. | D18: 4 | F18: 2 | G18: 3 | H18: 5 | I18: 5 | K18: In 2020, the fisheries and aquaucultue sector employed approximately 49 million people (84%) in Asia and 6 million in Africa. In the small scale fisheries processing/post harvest sector up to 50% of those employed are women | L18: Increased opportunities and incomes for those involved in the fish value chain especially women | M18: Both national and sub national governments recognize the role of fisheries sector as an avenue of poverty reduction in their blue economy strategies among others | N18: Collaboration with private sector and market actors involved in aquatic animal source foods and regulatory authorities | O18: Close collaboration with Scaling for impact to disseminate solutions that, if adopted, can provide decent jobs to actors
C19: AoW3-Suite of end-to-end solutions for health and agriculture extension agents, terrestrial animal-source vendors/retailers processors, and traders that promote healthy food choice behaviors of consumers, healthy food environments, food quality and safety, reduce food loss, and increase profits co-developed, tested, and scaled. | D19: 3 | F19: 3 | G19: 2 | H19: 4 | I19: 3 | K19: The livestock sector employs around 60 million people in WCA, about 30% of the population in ESA and over 40million in SA. Animal source foods markets are largely informal and characterized by food safety concerns. Regulatory frameworks for food safety is weak in most countries. | L19: Increased opportunities and incomes for those involved in the terrestrial animal source foods system | M19: Governments recognize the role of the livestock sector as an avenue of poverty reduction in their plans and allocate investments | N19: Collaboration with private sector and market actors involved in terrestrial animal source foods and regulatory authorities | O19: Close collaboration with Scaling for impact to disseminate solutions that, if adopted, can provide decent jobs to actors
C20: AoW3-Suite of integrated end-to-end solutions for health and agriculture extension agents, perishable nutrient-rich food vendors/retailers, processors, traders and producers that promote healthy food choice behaviors of consumers, healthy food environments, food quality and safety, reduce food loss,and increase profits co-developed, tested, and scaled. | D20: 4 | F20: 2 | G20: 2 | H20: 4 | I20: 5 | K20: 1. Supply is not keeping pace with demand and population growth due to a range of complex factors, including poor access to high-quality inputs, high post-harvest loss (up to 50%). Given the need to increase production there is room for growth and new job creation in this sector. Horticulture products are also high value and thus, may be attractive for youth and others with interest in agriculture livelihoods. 2. There are also opportunities to transform fruits and vegetables into different types of products, creating further job opportunities. 3. Other livelihood opportunities also exist across the fruit and vegetable value chain. | L20: 1. Increased investment in the fruit and vegetable sector leads to more jobs with adeqaute wages. 2. Increased opportunities for small and medium enterprises across perisable nutrient-rich food value chains. | M20: Both national and sub national governments recognize the role of integrated solutions across fruit, vegetable, aquatic and terrestrial animal sources an avenue of poverty reduction | N20: Collaboration with private sector and market actors involved in vegetable, fruit, aquatic and terrestrial animal source foods and regulatory authorities | O20: Close collaboration with Scaling for impact to disseminate solutions that, if adopted, can provide decent jobs to actors
C21: AoW3-Policy options that address constraints to sustainable healthy diets | D21: 4 | F21: 2 | G21: 2 | H21: 2 | I21: 4 | K21: PNR poorly prioritized as sources of income and job creation | L21: Policies that recognize the potential of PNR for job creation, poverty reduction and enabling environment for private sector investment | M21: Higher score for SA because of favorable policy environment | N21: Generate evidence on models that enhance job creation along PNR value chains | O21: Close collaboration with Policy Innovation
C22: AoW4-Suite of solutions for producers and processors that address constraints to sustainable healthy diets co-developed, tested, and scaled with technical support and country engagement. | D22: 2 | E22: 3 | F22: 3 | G22: 3 | H22: 3 | I22: 3 | K22: Traders and vendors have limited incentives or awareness to prioritize the sourcing and marketing of biofortified and health-enhancing products. Market demand is weak or unclear, and regulatory frameworks for labeling or differentiation are often absent leaving farmers producing without additional monetary benefits. | L22: Traders and vendors actively source, promote, and sell biofortified and health-enhancing crops and products, supported by a strong value proposition, clear quality standards, and informed consumers who demand such options. This will improve the value of biofortified crops and producing farmers will economically benefit. | M22: In WCA and ESA, traders and vendors often lack strong market linkages and face significant knowledge asymmetries, limiting their ability to make informed decisions. Farmers do not benefite from value additions. Traders and vendors respond to consumer demand and profit opportunities if products are available; market channels and regulatory structures currently do not allow for differentiation; traceability systems for 'invisible traits' are fneed to be made easible and affordable so that producing farmers benefit from the value addition. | N22: Clear labeling standards and branding for biofortified and health-enhancing products; training and market linkages for vendors; development of traceability tools and quality assurance mechanisms. Support from consumer awareness campaigns, policy advocacy for enabling regulations, and collaboration with market systems and private sector engagement teams. | O22: collaboration with Policy Innovations to define regulatory and traceability systems, B4T to enhance and improve nutrional traits that support economic gain for producing farmers. AoW Market Intelligence (STEER, INVEST, DESIGN, TARGET) to provide evidence on projected benefits for farmers and processors in target localities.
C23: AoW4-Policy options and engagement that address constraints to sustainable healthy diets. | D23: 2 | E23: 3 | F23: 5 | G23: 5 | H23: 3 | I23: 4 | K23: Nutrition considerations that also increase economic gain for farmers and processors are often missing or inconsistently addressed in agricultural, food systems, and public health policies. Limited engagement with policymakers and lack of coherent strategies like subsidies for farmers hinder integration and adoption of biofortified and health-enhancing crops. | L23: Policies at national and regional levels consistently prioritize and integrate biofortified and health-enhancing crops into agriculture, food systems, nutrition, and health agendas driven by stakeholder demand and evidence-based guidance to improve fodd and nutrition security. These also focus on incentivising farmers to grow these varieties. | M23: In WCA and ESA policy frameworks remain weak, and stakeholder engagement is often fragmented and inconsistent, they also do not target farmers with respect in reducing poverty through nutrion policies. Integrated policies that address a variety of aspects, e.g. poverty, heatlh, nutrition, equity are lacking or are underdeveloped in all regions. | N23: Robust integrated policy research and synthesis; strategic partnerships with policy influencers; targeted advocacy campaigns to address poverty; monitoring policy impact on poverty and nutrition outcomes; generating evidence for valid investment cases through projected impact determination in the area of poverty reduction. Support from public health, legal, trade, and education sectors to harmonize and implement enabling legislation, standards, and cross-sector frameworks that align with improved diets and nutrition goals. | O23: Close collaboration with Policy Innovation; B4T AoW on Market Intelligence to generate Investment cases (INVEST), and benefit projections (STEER) in target geographies.
C24: AoW4-Framework for embedding nutrition into breeding pipelines and processes. | D24: 2 | E24: 3 | F24: 5 | G24: 5 | H24: 3 | I24: 3 | K24: Breeding programs do not consistently incorporate nutritional traits or consumer-demanded profiles that could improve farmers' economic status. Integration of nutrition is often dependent on project-specific funding or champions and lacks institutionalization across CGIAR and NARS systems. There is often an argument of potential trade-offs between nutrient increase and yield and little attention is paid to addressing both simultaneously | L24: Breeding pipelines mainstream nutritional traits in target product profiles (TPPs), guided by evidence on dietary gaps and consumer needs resulting in varieties that are agronomically competitive, nutrient-dense, high yielding, and desired by consumers. | M24: In WCA and ESA, only a limited number of Target Product Profiles (TPPs) have integrated and evaluated nutrition traits in a systematic manner and only for selctive crops. Breeding teams lack recognizing the importance of nutrition and health-enhancing traits and are primarily focussed on improving yield, without recognising the potential value addition; mainstreaming biofortification is more likely in WCA du to positive enabling envirnment of IITA and CIP; while food security has improved across all the regions, nutrition security has not and high levels of micronutrient deficiencies exists in WCA, ESA, SA while there is a rise in NCD occurances in SEA and SA. Value addition to high yielding varieties can improve farmer income considerably but has not materialised. Poverty is high in EAS, WCA, and SA. | N24: Development of demand-driven TPPs that integrate diet quality needs; shared metrics for nutritional quality; capacity building of breeding teams; investment in screening and diagnostic infrastructure. Collaboration with nutrition and health research teams and socioeconomics research teams to generate evidence on consumer needs, dietary gaps, and policy priorities that guide breeding decisions. | O24: Collaboration with B4T, in particular the areas of work on Accelerated Breeding, Breeding resources, Market Intelligence and ENABLE. I special focus needs to be on sub-AoW DESIGN to ensure the full integration of diet improving traits in product concepts and the product design standard. Furthermore, INVEST and STEER are needed to assess projected benefits for target regions.
C25: AoW4-Suite of solutions for traders and vendors that address constraints to sustainable healthy diets co-developed, tested, and scaled with technical support and country engagement. | D25: 2 | E25: 3 | F25: 3 | G25: 3 | H25: 3 | I25: 3 | K25: Traders and vendors have limited incentives or awareness to prioritize the sourcing and marketing of biofortified and health-enhancing products which can negatively affect farmers. Market demand is weak or unclear, and regulatory frameworks for labeling or differentiation are often absent. | L25: Traders and vendors actively source, promote, and sell biofortified and health-enhancing crops and products, supported by a strong value proposition, clear quality standards, and informed consumers who demand such options. This will increase farmer income and will reduce overall poverty. | M25: Across all regions weak frameworks exist that support the decision-making of traders and venders to invest more in biofortified and health-enhancing products and produce. This has negative effects on farmers who produce these crops. Poverty rates are highest in WCA, ESA and SA. | N25: Clear labeling standards and branding for biofortified and health-enhancing products; training and market linkages for vendors; development of traceability tools and quality assurance mechanisms. Incentive mechanisms for farmers. Support from consumer awareness campaigns, policy advocacy for enabling regulations, and collaboration with market systems and private sector engagement teams. Access for farmers to incetive mechanisims that are geared towards economic benefit. | O25: Collaboration from STEER and INVEST (B4T, AoW MArket Intelligence) are needed to provide evidence of valid investment opportunities to support trader and vendor decision making. Policy Innovation is needed to support labeling and tracability policies to ensure farmers receive incentives.
C26: AoW4-Suite of solutions to support consumers awareness, preference, affordability, and utilization of biofortified and health-enhancing crops in their diets. | D26: 2 | E26: 3 | F26: 2 | G26: 2 | H26: 3 | I26: 3 | K26: Consumer awareness and demand for biofortified and health-enhancing foods are generally low therefore farmers are not incentivised to grow the respective crops. Misconceptions from the GMO debates, lack of clear labeling, and limited availability or affordability hinder widespread adoption especially among low-income and nutritionally vulnerable populations. | L26: Consumers are informed, motivated, and demand and are able to include biofortified and health-enhancing foods in their diets driven by clear value propositions, affordable options, positive Behavior Change Communication (BCC), and supportive food environments. FArmers benefit economically from this demand. | M26: Across all regions consumers have difficulties assessing their health and nutrient status and are therefore not aware of any deficiencies. Therefore, farmers are not incentivisied to grow value added products. | N26: Strategic BCC and social marketing campaigns; consumer research to tailor messaging and product development; partnerships with community organizations and retailers. Support from media, education, and health sectors to amplify messaging; collaboration with market and food policy teams to ensure affordability and retail availability. This should increase demand and consequently economic benefits for farmers. | O26: Gender accelerator to tailor BCCs to reach all consumers equitably but also to ensure that economic benefits are equitably accessible.
C27: AoW5-Suite of multisectoral solutions for government and non-government organizations that address constraints to sustainable healthy diets co-developed, tested, and scaled with technical support and country engagement | D27: 1 | E27: 1 | F27: 2 | G27: 2 | H27: 2 | I27: 2 | K27: n.a. | L27: n.a. | M27: We estimate that the potential of this HLO to contribute to povery reduction across all geographies is low given that the solutions developed by this AOW will have limited impact on poverty in the short term. However, across all the countries where BDN is active, the achievement of forward looking policy coherence and alignment in support postitive of food system transformation could have important impacts on poverty reduction. As a result we estimate that advances against the HLO has a mediumpotential to impact poverty reduction in our target countries. | N27: n.a. | O27: n.a.
C28: AoW6-Synthesized knowledge products across AoWs and disseminated | F28: 3 | G28: 3 | H28: 2 | I28: 2 | K28: Limited synthesis of knowledge to inform FST towards better diets. | L28: A framework to guide the synthesis. Active (ongoing) synthesis of knowledge. | M28: Efforts by BDN will be recognized as being useful and taken up as approaches for evidence synthesis. BDN will not have any direct impacts on poverty reduction but may lead to poverty reduction in the longer term as populations are well nourished and more productive. | N28: Adequate coordination across AoWs to collate the emerging evidence | O28: Adequate coordination across other P/As
C29: AoW6-Regional food systems transformation coordination mechanisms disseminated | F29: 3 | G29: 3 | H29: 2 | I29: 2 | K29: Inadequate coordination and governance for FST within regions | L29: Adequate coordination and governace for FST towards BDN within regions | M29: Regional bodies will be willing and able to make use of BDN knowledge products. Alignement with other P/As on keys messages for BDN. BDN will not have any direct impacts on poverty reduction but may lead to poverty reduction in the longer term as populations are well nourished and more productive. | N29: Effective engagement by BDN scientists in regional processes/events to be able to influence | O29: Robust engagement by other P/As to share products that can be used in the engagments. Complete alignment on key messages for BDN
C30: AoW6-Targeted capacity-sharing events addressing evidence to policy actions and strategic engagement to influence food systems thinking to promote positive transformative change among different stakeholders including CoPs. | F30: 3 | G30: 3 | H30: 2 | I30: 2 | K30: Lack of understanding of capacity and leadership needs for food systems thinking to promote transformative change among different stakeholders | L30: Good understanding of capacity and leadership needs for food systems thinking to promote transformative change among different stakeholders | M30: Regional bodies will be willing and able to make use of BDN capacity sharing products/services/reccommendations. Alignment with other P/As on keys messages for BDN. BDN will not have any direct impacts on poverty reduction but may lead to poverty reduction in the longer term as populations are well nourished and more productive. | N30: Effective engagement by BDN scientists in regional processes/events to be able to influence | O30: Robust engagement by other P/As to share products that can be used in the engagments. Complete alignment on key messages for BDN
C31: AoW6-Regional, continental FS leadership development events to promote BDN outcomes for FST | F31: 3 | G31: 3 | H31: 2 | I31: 2 | K31: Lack of understanding of capacity and leadership needs for food systems thinking to promote transformative change among different stakeholders | L31: Good understanding of capacity and leadership needs for food systems thinking to promote transformative change among different stakeholders | M31: Regional bodies will be willing and able to make use of BDN capacity sharing products/services/reccommendations. Alignement with other P/As on keys messages for BDN. BDN will not have any direct impacts on poverty reduction but may lead to poverty reduction in the longer term as populations are well nourished and more productive. | N31: Effective engagement by BDN scientists in regional processes/events to be able to influence | O31: Robust engagement by other P/As to share products that can be used in the engagments. Complete alignment on key messages for BDN
C32: AoW6-Task force that guides the CGIAR Portfolio along pathways that lead to credible impacts on nutrition, health, and food security | D32: 3 | E32: 3 | F32: 4 | G32: 4 | H32: 3 | I32: 3 | K32: Lack of coordination, knowledge and systmes thinking across P/As around FST towards BDN from the respective P/As perspective | L32: Good coordination, adequate knowledge; and adoption of systems thinking across P/As around FST towards BDN from the respective P/As perspective | M32: There is willingness and ability among P/As in BDN led activities to strengthem coordination, knowledge uptake and adoption of systems thinking. BDN will not impact poverty directly but this coordinated effort along with other SP/As can help them achieve their targets faster and lead to higher incomes/lower poverty in the long term | N32: Ability to convene the P/As in the planned activities and adequate resources | O32: Thinking beyond the immediate (economic) outputs P/As and focusing on how they can contribute to BDN

Sheet 3.Social_inclusion
C1: Social inclusion Indicator
A2: VH | B2: 5 | D2: LAC | E2: CWANA | F2: WCA | G2: ESA | H2: SA | I2: SEA | J2: AoW1 | K2: =AVERAGE(D11:I13) -> 3.6666667
A3: H | B3: 4 | C3: Total score by column | D3: =SUM(D11:D58) -> 53 | E3: =SUM(E11:E58) -> 18 | F3: =SUM(F11:F58) -> 72 | G3: =SUM(G11:G58) -> 74 | H3: =SUM(H11:H58) -> 70 | I3: =SUM(I11:I58) -> 63 | J3: AoW2 | K3: =AVERAGE(D14:I16) -> 3.5833333
A4: MH | B4: 3 | C4: VH count by column | D4: =COUNTIF(D$11:D$58, 5) -> 3 | E4: =COUNTIF(E$11:E$58, 5) -> 0 | F4: =COUNTIF(F$11:F$58, 5) -> 4 | G4: =COUNTIF(G$11:G$58, 5) -> 4 | H4: =COUNTIF(H$11:H$58, 5) -> 3 | I4: =COUNTIF(I$11:I$58, 5) -> 2 | J4: AoW3 | K4: =AVERAGE(D17:I21) -> 3.52
A5: M | B5: 2 | C5: H count by column | D5: =COUNTIF(D$11:D$58, 4) -> 4 | E5: =COUNTIF(E$11:E$58, 4) -> 0 | F5: =COUNTIF(F$11:F$58, 4) -> 4 | G5: =COUNTIF(G$11:G$58, 4) -> 5 | H5: =COUNTIF(H$11:H$58, 4) -> 4 | I5: =COUNTIF(I$11:I$58, 4) -> 5 | J5: AoW4 | K5: =AVERAGE(D22:I26) -> 2.9666667
A6: L | B6: 1 | C6: MH count by column | D6: =COUNTIF(D$11:D$58, 3) -> 2 | E6: =COUNTIF(E$11:E$58, 3) -> 6 | F6: =COUNTIF(F$11:F$58, 3) -> 10 | G6: =COUNTIF(G$11:G$58, 3) -> 8 | H6: =COUNTIF(H$11:H$58, 3) -> 10 | I6: =COUNTIF(I$11:I$58, 3) -> 9 | J6: AoW5 | K6: =AVERAGE(D27:I27) -> 3.2
C7: M count by column | D7: =COUNTIF(D$11:D$58, 2) -> 7 | E7: =COUNTIF(E$11:E$58, 2) -> 0 | F7: =COUNTIF(F$11:F$58, 2) -> 3 | G7: =COUNTIF(G$11:G$58, 2) -> 5 | H7: =COUNTIF(H$11:H$58, 2) -> 4 | I7: =COUNTIF(I$11:I$58, 2) -> 3 | J7: AoW6 | K7: =AVERAGE(D28:I32) -> 2.8095238
C8: L count by column | D8: =COUNTIF(D$11:D$58, 1) -> 2 | E8: =COUNTIF(E$11:E$58, 1) -> 0 | F8: =COUNTIF(F$11:F$58, 1) -> 0 | G8: =COUNTIF(G$11:G$58, 1) -> 0 | H8: =COUNTIF(H$11:H$58, 1) -> 1 | I8: =COUNTIF(I$11:I$58, 1) -> 0 | K8: Current state (across the Global South) | L8: Ideal state (across the Global South) | M8: Assumptions (for region-specific scores) | N8: Requirements for success (internal to P/A) | O8: Requirements for success (from other P/As)
C10: HLO | D10: LAC | E10: CWANA | F10: WCA | G10: ESA | H10: SA | I10: SEA
A11: HLO count: | B11: =COUNTA(C11:C58) -> 22 | C11: AoW1-Suite of solutions focused on consumers that promote consumption of sustainable heathy diets co-developed, tested, and scaled with technical support and country engagement | D11: 5 | F11: 3 | G11: 3 | H11: 4 | I11: 4 | K11: 1. Solutions (behavior change, like FBDGs) are there, but there's lack of evidence on effectiveness and, do not address full components of food system, nor equity issues, and/or are not in use 2. Few solutions address the food environment, and not based on understanding the role of equity issues. 3. Metrics are not all-encompassing 4. Metrics are not being used by gov'ts for decisionmaking 5. Many barriers prevent governments from taking actions and there is an uneven willingness to act across ministries and levels. 6. There is a lot of info on what governments can do, but very little information on how to do it | L11: 1. Behavior change solutions, such as FBDGs, are now widely adopted, evidence-based, and address the full spectrum of the food system. 2. Interventions now effectively target both individual behaviors and the broader food environment 3. Comprehensive, system-wide metrics are in place to capture all key dimensions of food systems. 4. Governments are actively using these metrics to guide and inform policy decisions. 5. There is strong and consistent commitment across stakeholders to act on food systems transformation. 6. Clear, actionable guidance now enables governments to move from knowing what to do to knowing how to do it. | M11: Poor diets originate from processes of social exclusion of population groups and individuals based on characteristics such as gender, age, geographic location, ethnicity, education, and wealth. Promoting healthy diets have to address these characteristics. As such we expect that this HLO can potentially contribute to social inclusion, but we expect a low impact on this aspect of development in all geographies given that many other (more) essential aspects need to be addressed to improve social inclusion. | N11: Evidence is relevant (helps meet their goals) and timely for government actors to use. Gov’t actors perceive their institutions have the capacity to implement the solutions. | O11: Collaboration with Gender Accelerator to understand better equity issues in addressing drivers of food choices.
A12: Sets of 5: | B12: =_xlfn.FLOOR.MATH(B11/5) -> 4 | C12: AoW1-Suite of solutions focused on vendors that promote employment opportunities and the sale of sustainable nutritious foods co-developed, tested, and scaled with technical support and country engagement | D12: 2 | F12: 5 | G12: 5 | H12: 2 | I12: 4 | K12: 1. Lack of data about MSMEs and informal actors - what are their barriers, their constraints, their incentives, and so on, with no specifics on the situation of female vendors. 2. Lack of data on the presence of healthy foods being sold by MSMEs and informal actors 3. Few evidence-based solutions for how to improve conditions for MSMEs and informal actors selling foods 4. Increasing presence of UPFs combined with infrastructure realities (widely variable access to cold storage, clean water) changes the cost-benefits for MSME and informal actors 5. Successful and aggressive commercial strategies of multinational food companies increase availability and affordability of UPFs | L12: 1. Extensive data now exists on the barriers, constraints, and incentives shaping MSME and informal actors’ roles in food systems. 2. Clear, reliable data tracks the availability and sale of healthy foods by MSMEs and informal vendors. 3. Evidence-based strategies are effectively improving the conditions and opportunities for MSMEs and informal food actors. 4. The impact of UPFs and infrastructure realities is well understood, enabling more supportive and context-specific policies for MSMEs. 5. Strategic lessons from multinational food companies are being adapted to enhance the distribution and affordability of nutritious foods. | M12: The importance of the food environment in LMICs as an opportunity to improving working conditions for female vendors is variable across regions. In regions where cultural norms allow women in those spaces, the potential for impact is higher than in places where women are not allowed. | N12: Evidence is relevant (helps meet their goals) and timely for government actors to use. Gov’t actors perceive their institutions have the capacity to implement the solutions. MSMEs and informal actors perceive the solutions are not harmful to their profit margin and have the capacity to implement the solutions. | O12: Collaboration with Gender Accelerator to understand better equity issues in addressing constraints of MSMEs delivering nutritious food to consumers
A13: Remainder: | B13: =MOD(B11,5) -> 2 | C13: AoW1-Policy options and engagement that support effective management of national action plans and other policy processes, for food systems transformation in support of sustainable healthy diets | D13: 5 | F13: 4 | G13: 4 | H13: 1 | I13: 4 | K13: 1. Food System Transformation National Action Plans are being developed but at various levels of detail, and hardly being implemented. 2. Lack of policy coherence. Lack of clear and consistent food system policies across levels and sectors of government mean 3. Lack of policy alignment. For example, ag policies that maximize production for economic growth vs health policies that promote health (without speaking to diets). 4. Policies are on paper, but not in practice 5. Difficulty of government to operationalize their aspirations for food systems transformation (issues relate to awareness, capacity, finance, political economy...) 6. Policy landscape is behind the curve, framed by the issues from 50 years ago (undernourished, calories), and not the present threats (obesity and overweight and NCDs) | L13: 1. Food system policies are now coherent, clearly articulated, and consistently implemented across sectors and levels of government. 2. Agricultural and health policies are well-aligned, with a shared focus on promoting sustainable, nutritious diets. 3. Policy commitments are being fully implemented, translating into tangible action and impact. 4. Governments are successfully turning food systems transformation goals into action, supported by strengthened capacity, financing, and political momentum. 5. Policy frameworks have been modernized to address today’s nutrition challenges, including obesity, overweight, and noncommunicable diseases. | M13: Across all the geographies where BDN is active, the achievement of forward looking policy coherence and alignment in support of postitive of food system transformation could have important impacts on social inclusion. As a result we estimate that advances against the HLO has a medium high potential to improve aspects of social inclusion in our target countries. | N13: Decisionmakers have the awareness of political lock-ins and capacity to overcome them to improve sectoral alignment. Decisionmakers have the awareness of trade-offs and how to overcome them. The new governance mechanisms integrate various societal perspectives. | O13: Collaboration with Gender Accelerator to understand equity issues in food system policies.
A14: Max score: | B14: =(B12*SUM($B$2:$B$6))+SUM($B$2:INDEX(B:B, $B$13+1)) -> 69 | C14: AoW2-Suite of Solutions to lower transaction costs | D14: 5 | F14: 4 | G14: 4 | H14: 3 | K14: We discuss the current state in the "food security" tab. | L14: We discuss the ideal state in the "food security" tab. | M14: 1. Gender plays a role both as "owners" of businesses and in employment. This is more true in Africa than Asia (where most businesses are run by men). We are only working on the lowering transaction costs goal in Latin America (not the other two), so we score it high in this regard relative to the other two HLOs. | N14: Internally it is best to understand what products are most required in the diet (AoW1) so we can prioritize them for diets; in this case so that we can target those markets if foodis produced but costly or not available enough for some reason. | O14: Working with the Gender Accelerator to develop evaluation strategies.
C15: AoW2-Suite of Solutions to catalyze business growth | D15: 1 | F15: 5 | G15: 5 | H15: 4 | K15: We discuss the current state in the "food security" tab. | L15: We discuss the ideal state in the "food security" tab. | M15: 2. In Africa generally, we think there are more likely to be more women employed closer to consumers so we target the growth solution more than lowering transaction costs, though they are awfully close (this is evidence based). On the other hand, in South Asia women are not highly employed in the middle of value chains, only in the food environment.. | N15: Internally it is best to understand what products are most required in the diet (AoW1) so we can prioritize them for diets. Similarly with better info on UPC consumption we can envision targeting growth work most effectively. | O15: Working with the Gender Accelerator to develop evaluation strategies.
C16: AoW2-Trade and Limiting UPC Consumption | D16: 1 | F16: 3 | G16: 3 | H16: 5 | K16: We discuss the current state in the "food security" tab. | L16: We discuss the ideal state in the "food security" tab. | M16: UPC consumption is highest among the four regions we are working on in South Asia, and so we rate it highest among the 3 HLOs in AoW2. Meanwhile, trade is less clearly socially inclusive in the two African regions, so it receives a lower score.
C17: AoW3-Suite of tested end-to-end solutions for health and agriculture extension agents, fruit and vegetable vendors/retailers, processors, traders and producers that promote healthy food choice behaviors of consumers, healthy food environments, food quality and safety, reduce food loss, and increase profits co-developed, tested, and scaled. | D17: 4 | F17: 4 | G17: 4 | H17: 5 | I17: 5 | K17: Existence of social cultural barriers that limit access to resources for production, and consumption of fruit and vegetable for some groups, particularly the vulnerable populations in some comunities, mostly women | L17: Communities and households adopt more gender equitable behaviours in food production, marketing and nutrition decisions | M17: While inequality between men and women is higher in WCA and ESA than the other regions, we assigned slighly higher scores for SA and SEA because of policy environment that can help achieve higher impacts | N17: Solutions that address barriers to production, marketing, and consumption of fruit and vegetable and participation of various social groups in fruit and vegetable value chains | O17: Close collaboration with the gender accelerator to ensure interventions are targeting the right social groups
C18: AoW3-Suite of end-to-end solutions for health and agriculture extension agents, aquatic food vendors/retailers processors, and traders that promote healthy food choice behaviors of consumers, healthy food environments, food quality and safety, reduce food loss, and increase profits co-developed, tested, and scaled. | D18: 4 | F18: 4 | G18: 4 | H18: 5 | I18: 5 | K18: In 2012, the World Bank estimated that in certain segments of the processing sector worldwide up to 85% of the employees were women. Preliminary results of the recent illuminating hidden harvests study show half of the workers in the small scale post harvest sector to be women | L18: The women in this points of the value chain accept lower pay. Introduction of our approaches will ideally result in better quality product and also prevention of physical loss to secure better pay and have impact on poverty | M18: Higher score for WCA and SA because of the absolute number of people employed in this sector. | N18: Solutions that address barriers to consumption of aquatic and participation of various social groups in the aquatic source foods value chains | O18: Close collaboration with the gender accelerator to ensure interventions are targeting the right social groups
C19: AoW3-Suite of end-to-end solutions for health and agriculture extension agents, terrestrial animal-source vendors/retailers processors, and traders that promote healthy food choice behaviors of consumers, healthy food environments, food quality and safety, reduce food loss, and increase profits co-developed, tested, and scaled. | D19: 3 | F19: 3 | G19: 2 | H19: 3 | I19: 3 | K19: Existence of social cultural barriers that limit consumption of terrestrial animal source foods for some groups, particularly the vulnerable populations in some comunities. In most countries women | L19: Communities and households adopt more gender equitable behaviours in food and nutrition decisions | M19: In ESA and WCA | N19: Solutions that address barriers to consumption of animal source food and participation of various social groups in the animal source foods value chains | O19: Close collaboration with the gender accelerator to ensure interventions are targeting the right social groups
C20: AoW3-Suite of integrated end-to-end solutions for health and agriculture extension agents, perishable nutrient-rich food vendors/retailers, processors, traders and producers that promote healthy food choice behaviors of consumers, healthy food environments, food quality and safety, reduce food loss,and increase profits co-developed, tested, and scaled. | D20: 4 | F20: 3 | G20: 2 | H20: 3 | I20: 4 | K20: Existence of social cultural barriers that limit access to resources for production, and consumption of perishable and nutritious foods for some groups, particularly the vulnerable populations in some comunities, mostly women | L20: Communities and households adopt more gender equitable behaviours in food production, marketing and nutrition decisions | M20: While inequality between men and women is higher in WCA and ESA than the other regions, we assigned slighly higher scores for SA and SEA because of policy environment that can help achieve higher impacts | N20: Solutions that address barriers to production, marketing and consumption of persihable and nutritious foods and participation of various social groups PNR value chains | O20: Close collaboration with the gender accelerator to ensure interventions are targeting the right social groups
C21: AoW3-Policy options that address constraints to sustainable healthy diets | D21: 4 | F21: 2 | G21: 2 | H21: 2 | I21: 4 | K21: Fragmented information on how current policies are actually addressing gender inclusion | L21: Policies addressing gender inclusion are formulated and implemented | M21: Higher score for SA because of favorable policy environment for gender inclusion | N21: Translate evidences into actionable policy that reduce gender inequalities | O21: Close collaboration with the gender accelerator to ensure interventions are targeting the right social groups
C22: AoW4-Suite of solutions for producers and processors that address constraints to sustainable healthy diets co-developed, tested, and scaled with technical support and country engagement. | D22: 2 | E22: 3 | F22: 3 | G22: 3 | H22: 3 | I22: 2 | K22: Traders and vendors have limited incentives or awareness to prioritize the sourcing and marketing of biofortified and health-enhancing products and are also not aware of how to market it to the right populations. Market demand is weak or unclear, and regulatory frameworks for labeling or differentiation are often absent. This impacts social equity negatively as women and children are disproportionally affected by malnutrition. | L22: Traders and vendors actively source, promote, and sell biofortified and health-enhancing crops and products, supported by a strong value proposition, clear quality standards, and informed consumers who demand such options. They are able to market their products to the respective consumer segments. | M22: In WCA and ESA, traders and vendors often lack strong market linkages and face significant knowledge asymmetries, limiting their ability to make informed decisions and market products accordingly. In other regions this is also present but less extreme. | N22: Clear labeling standards and branding for biofortified and health-enhancing products to the respective consumer segments addressing malnutrion and providing information; training and market linkages for vendors; development of traceability tools and quality assurance mechanisms. Support from consumer awareness campaigns, policy advocacy for enabling regulations, and collaboration with market systems and private sector engagement teams. | O22: Strong collaboration with the gender accelerator to ensure interventions are targeting the right social groups
C23: AoW4-Policy options and engagement that address constraints to sustainable healthy diets. | D23: 2 | E23: 3 | F23: 5 | G23: 5 | H23: 4 | I23: 3 | K23: Policy options that consider nutrition and address social inequalities are lacking or are inconsistently addressed in agricultural, food systems, and public health policies. Limited engagement with policymakers and lack of coherent strategies that are gender-sensitive and address social inequalities hinder integration and adoption of biofortified and health-enhancing crops. | L23: Policies addressing nutrition in conjunction with social equity at national and regional levels consistently prioritize and integrate biofortified and health-enhancing crops into agriculture, food systems, nutrition, and health agendas driven by stakeholder demand and evidence-based guidance to improve food and nutrition security. | M23: In WCA, ESA, and SA policy frameworks remain weak and do not include social aspects, and stakeholder engagement is often fragmented, inconsistent and gender blind, they also do not target farmers with respect in reducing inequities through nutrition policies. Gender transformative policies that address a variety of aspects, e.g. poverty, heatlh, nutrition, equity are lacking or are underdeveloped in all regions. | N23: Robust integrated policy research and synthesis with a focus on gender and social equity; strategic partnerships with policy influencers; targeted advocacy campaigns to address social inequities and nutrition; monitoring policy impact on equity and nutrition outcomes; generating evidence for valid investment cases through projected impact determination in the area of social equity. Support from public health, legal, trade, and education sectors to harmonize and implement enabling legislation, standards, and cross-sector frameworks that align with improved diets and nutrition goals. | O23: Close collaboration with Policy Innovation; B4T AoW on Market Intelligence to generate Investment cases (INVEST), and benefit projections (STEER) in target geographies. Close alignment with the Gender accelerator to ensure a gender-intentioanl process.
C24: AoW4-Framework for embedding nutrition into breeding pipelines and processes. | D24: 2 | E24: 3 | F24: 5 | G24: 5 | H24: 3 | I24: 3 | K24: Breeding programs do not consistently incorporate nutritional traits or consumer-demanded profiles that could improve gender equality or address other societal inequalities. Integration of nutrition is often dependent on project-specific funding or champions and lacks institutionalization across CGIAR and NARS systems and is often gender blind. | L24: Breeding pipelines mainstream nutritional traits in target product profiles (TPPs), guided by evidence on dietary gaps, social inequity, gender disadvantages and consumer needs resulting in varieties that are agronomically competitive, nutrient-dense, high yielding, gender-intentional and desired by consumers. | M24: In WCA, ESA, and SA only a limited number of Target Product Profiles (TPPs) have integrated and evaluated nutrition and gender traits in a systematic manner and only for selctive crops. Breeding teams lack recognizing the importance of nutrition and health-enhancing traits for particilar consumer groups such as women and small children. However, there is an enabling enviroment created by IITA and CIP that allow further mainstreaming gender intentionality. While food security has improved across all the regions, nutrition security has not and high levels of micronutrient deficiencies exists in WCA, ESA, SA with women, children and othermarginalised groups disproportionaly affected. | N24: Development of demand-driven, gender-intentional TPPs that integrate diet quality needs; shared metrics for nutritional quality and gender equality; capacity building of breeding teams; investment in screening and diagnostic infrastructure. Collaboration with nutrition and health research teams and socioeconomics research teams to generate evidence on consumer needs, dietary gaps, and policy priorities that guide breeding decisions. | O24: Collaboration with B4T, in particular the areas of work on Accelerated Breeding, Breeding Resources, Market Intelligence and ENABLE. I special focus needs to be on sub-AoW DESIGN to ensure the full integration of diet improving and gender-intentional traits in product concepts and the product design standard. Furthermore, INVEST and STEER are needed to assess projected benefits for target regions.
C25: AoW4-Suite of solutions for traders and vendors that address constraints to sustainable healthy diets co-developed, tested, and scaled with technical support and country engagement. | D25: 2 | E25: 3 | F25: 3 | G25: 3 | H25: 3 | I25: 3 | K25: Traders and vendors have limited incentives or awareness to prioritize the sourcing and marketing, especially to disadvantaged groups such as women, children, elderly and people suffering from chronic condictions or other health conditions, of biofortified and health-enhancing products. Market demand is weak or unclear and evidence is scarce, and regulatory frameworks for labeling or differentiation are often absent. | L25: Traders and vendors actively source, promote, and sell biofortified and health-enhancing crops and products to women, children and elderly people, supported by a strong value proposition, clear quality standards, and informed consumers who demand such options. | M25: In WCA, ESA, and SA traders and vendors often lack strong market linkages and face significant knowledge asymmetries especially about specific consumer groups such as women, children and elderly people, limiting their ability to make informed decisions which is also present in the other regions. Traders and vendors respond to consumer demand and profit opportunities if they are correctly informed; market channels and regulatory structures currently do not allow for differentiation; traceability systems for 'invisible trait' are not feasible and affordable in all regions. However, malnutrition is most pronounced in ESA, WCA and SA. | N25: Clear labeling standards for target groups such as women, children and elderly health impacted people and branding for biofortified and health-enhancing products; training and market linkages for vendors; development of traceability tools and quality assurance mechanisms. Support from consumer awareness campaigns, policy advocacy for enabling regulations, and collaboration with market systems and private sector engagement teams. | O25: Collaboration from STEER and INVEST (B4T, AoW MArket Intelligence) are needed to provide evidence of valid investment opportunities to support trader and vendor decision making. Policy Innovation is needed to support labeling and tracability policies. Collaboration with the gender accelerator to ensure that the design and marketing is not gender blind.
C26: AoW4-Suite of solutions to support consumers awareness, preference, affordability, and utilization of biofortified and health-enhancing crops in their diets. | D26: 2 | E26: 3 | F26: 2 | G26: 2 | H26: 2 | I26: 2 | K26: Consumer awareness and demand for biofortified and health-enhancing foods are generally low and many consumers are not aware of their deficiencies. Misconceptions from the GMO debates, lack of clear labeling to target groups such as women, children and elderly people, and limited availability or affordability hinder widespread adoption especially among low-income and nutritionally vulnerable populations. | L26: Consumers are informed, motivated, and demand and are able to include biofortified and health-enhancing foods in their diets driven by clear value propositions, affordable options, positive Behavior Change Communication (BCC), and supportive food environments. FArmers benefit economically from this demand. There is a clearly definde consumer market segment that addresses the needs of women, children and elderly health impaired people. | M26: Across all regions consumers have difficulties assessing their health and nutrient status and are therefore not aware of any deficiencies. Especially vulnerable populations without access to health care or information. | N26: Strategic BCC and social marketing campaigns addressing the needs of women, childrenand elderly, health-impaired people; consumer research to tailor messaging and product development to target populations; partnerships with community organizations and retailers. Support from media, education, and health sectors to amplify messaging; collaboration with market and food policy teams to ensure affordability and retail availability. | O26: Gender accelerator to tailor BCCs to reach all consumers equitably but also to ensure that economic benefits are equitably accessible.
C27: AoW5-Suite of multisectoral solutions for government and non-government organizations that address constraints to sustainable healthy diets co-developed, tested, and scaled with technical support and country engagement | D27: 2 | F27: 3 | G27: 4 | H27: 4 | I27: 3 | K27: Food system actions and making food environments healthy are essential, but insufficient, to increase the consumption of sustainable healthy diets by all: Consumers often lack knowledge about nutritious diets, sufficient (monetary) resources, autonomy, and empowerment to acquire foods. Once foods have been acquired, they need to be consumed. The transformation of foods into a sustainable healthy diet for all requires, amongst other things, nutrition knowledge (which is often missing), an equitable (i.e., based on nutritional needs) distribution of foods within the household (often not the case), and autonomy and empowerment (often lacking). Complementary policies that unlock the full potential of food systems transformation are missing | L27: 1) Consumers have adequate knowledge about nutritious diets and sufficient (monetary) resources, autonomy, and empowerment to acquire foods. 2) The transformation of foods into a sustainable healthy diet for all is not hindered by limited nutrition knowledge, inequitable (i.e., based on nutritional needs) distribution of foods within the household, or limited autonomy and empowerment. Health, and other sectoral policies are well-aligned, with a shared emphasis on the role of diets in achieving both economic and health goals. | M27: The potential for impact is highest in the areas with the lowest social inclusion today | N27: Evidence is relevant (helps meet their goals) and timely for government actors to use. Gov’t actors perceive their institutions have the capacity to implement the solutions. | O27: Scaling for Impact: We'll need their expertise to help us scale our own tested solutions. Collaboration with Gender Accelerator to understand better equity issues in addressing drivers of food choices.
C28: AoW6-Synthesized knowledge products across AoWs and disseminated | F28: 3 | G28: 3 | H28: 3 | I28: 3 | K28: Limited synthesis of knowledge to inform FST towards better diets. | L28: A framework to guide the synthesis. Active (ongoing) synthesis of knowledge. | M28: Efforts by BDN will be recognized as being useful and taken up as approaches for evidence synthesis. BDN will not have any direct impacts on social inclusion but may affect it indirectly by improving diets of the most vulnerable. | N28: Adequate coordination across AoWs to collate the emerging evidence | O28: Adequate coordination across other P/As
C29: AoW6-Regional food systems transformation coordination mechanisms disseminated | F29: 2 | G29: 2 | H29: 2 | I29: 2 | K29: Inadequate coordination and governance for FST within regions | L29: Adequate coordination and governace for FST towards BDN within regions | M29: Regional bodies will be willing and able to make use of BDN knowledge products. Alignement with other P/As on keys messages for BDN. BDN will not have any direct impacts on social inclusion but may affect it indirectly by improving diets among the most vulnerable groups. | N29: Effective engagement by BDN scientists in regional processes/events to be able to influence | O29: Robust engagement by other P/As to share products that can be used in the engagments. Complete alignment on key messages for BDN
C30: AoW6-Targeted capacity-sharing events addressing evidence to policy actions and strategic engagement to influence food systems thinking to promote positive transformative change among different stakeholders including CoPs. | F30: 3 | G30: 3 | H30: 3 | I30: 3 | K30: Lack of understanding of capacity and leadership needs for food systems thinking to promote transformative change among different stakeholders | L30: Good understanding of capacity and leadership needs for food systems thinking to promote transformative change among different stakeholders | M30: Regional bodies will be willing and able to make use of BDN capacity sharing products/services/reccommendations. Alignement with other P/As on keys messages for BDN. BDN will not have any direct impacts on social inclusion but may lead to a more equal society by improving diets of the most vulnerable. | N30: Effective engagement by BDN scientists in regional processes/events to be able to influence | O30: Robust engagement by other P/As to share products that can be used in the engagments. Complete alignment on key messages for BDN
C31: AoW6-Regional, continental FS leadership development events to promote BDN outcomes for FST | G31: 3 | H31: 3 | I31: 3 | K31: Lack of understanding of capacity and leadership needs for food systems thinking to promote transformative change among different stakeholders | L31: Good understanding of capacity and leadership needs for food systems thinking to promote transformative change among different stakeholders | M31: Regional bodies will be willing and able to make use of BDN capacity sharing products/services/reccommendations. Alignement with other P/As on keys messages for BDN. BDN will not have any direct impacts on poverty reduction but may lead to poverty reduction in the longer term as populations are well nourished and more productive. | N31: Effective engagement by BDN scientists in regional processes/events to be able to influence | O31: Robust engagement by other P/As to share products that can be used in the engagments. Complete alignment on key messages for BDN
C32: AoW6-Task force that guides the CGIAR Portfolio along pathways that lead to credible impacts on nutrition, health, and food security | D32: 3 | E32: 3 | F32: 3 | G32: 3 | H32: 3 | I32: 3 | K32: Lack of coordination, knowledge and systmes thinking across P/As around FST towards BDN from the respective P/As perspective | L32: Good coordination, adequate knowledge; and adoption of systems thinking across P/As around FST towards BDN from the respective P/As perspective | M32: There is willingness and ability among P/As in BDN led activities to strengthem coordination, knowledge uptake and adoption of systems thinking. BDN will not social inclusion directly, but given that nutritionally vulnerable groups are also socially vulnerable - it addresses social inclusion indierctly. Addtionally, this coordinated effort along with other SP/As can help them achieve their targets faster and lead to a more equitable and equal society. | N32: Ability to convene the P/As in the planned activities and adequate resources | O32: Thinking beyond the immediate (economic) outputs P/As and focusing on how they can contribute to BDN

Sheet 4.Climate_adaptation
C1: Climate adaptation Indicator
A2: VH | B2: 5 | D2: LAC | E2: CWANA | F2: WCA | G2: ESA | H2: SA | I2: SEA | J2: AoW1 | K2: =AVERAGE(D11:I13) -> 2.6666667
A3: H | B3: 4 | C3: Total score by column | D3: =SUM(D11:D58) -> 56 | E3: =SUM(E11:E58) -> 28 | F3: =SUM(F11:F58) -> 64 | G3: =SUM(G11:G58) -> 64 | H3: =SUM(H11:H58) -> 60 | I3: =SUM(I11:I58) -> 46 | J3: AoW2 | K3: =AVERAGE(D14:I16) -> 2.3333333
A4: MH | B4: 3 | C4: VH count by column | D4: =COUNTIF(D$11:D$58, 5) -> 1 | E4: =COUNTIF(E$11:E$58, 5) -> 0 | F4: =COUNTIF(F$11:F$58, 5) -> 4 | G4: =COUNTIF(G$11:G$58, 5) -> 4 | H4: =COUNTIF(H$11:H$58, 5) -> 1 | I4: =COUNTIF(I$11:I$58, 5) -> 1 | J4: AoW3 | K4: =AVERAGE(D17:I21) -> 3.24
A5: M | B5: 2 | C5: H count by column | D5: =COUNTIF(D$11:D$58, 4) -> 3 | E5: =COUNTIF(E$11:E$58, 4) -> 0 | F5: =COUNTIF(F$11:F$58, 4) -> 1 | G5: =COUNTIF(G$11:G$58, 4) -> 1 | H5: =COUNTIF(H$11:H$58, 4) -> 1 | I5: =COUNTIF(I$11:I$58, 4) -> 2 | J5: AoW4 | K5: =AVERAGE(D22:I26) -> 3.1
A6: L | B6: 1 | C6: MH count by column | D6: =COUNTIF(D$11:D$58, 3) -> 7 | E6: =COUNTIF(E$11:E$58, 3) -> 8 | F6: =COUNTIF(F$11:F$58, 3) -> 10 | G6: =COUNTIF(G$11:G$58, 3) -> 10 | H6: =COUNTIF(H$11:H$58, 3) -> 15 | I6: =COUNTIF(I$11:I$58, 3) -> 9 | J6: AoW5 | K6: 0
C7: M count by column | D7: =COUNTIF(D$11:D$58, 2) -> 8 | E7: =COUNTIF(E$11:E$58, 2) -> 2 | F7: =COUNTIF(F$11:F$58, 2) -> 4 | G7: =COUNTIF(G$11:G$58, 2) -> 4 | H7: =COUNTIF(H$11:H$58, 2) -> 2 | I7: =COUNTIF(I$11:I$58, 2) -> 3 | J7: AoW6 | K7: 0
C8: L count by column | D8: =COUNTIF(D$11:D$58, 1) -> 2 | E8: =COUNTIF(E$11:E$58, 1) -> 0 | F8: =COUNTIF(F$11:F$58, 1) -> 2 | G8: =COUNTIF(G$11:G$58, 1) -> 2 | H8: =COUNTIF(H$11:H$58, 1) -> 2 | I8: =COUNTIF(I$11:I$58, 1) -> 0 | K8: Current state (across the Global South) | L8: Ideal state (across the Global South) | M8: Assumptions (for region-specific scores) | N8: Requirements for success (internal to P/A) | O8: Requirements for success (from other P/As)
C10: HLO | D10: LAC | E10: CWANA | F10: WCA | G10: ESA | H10: SA | I10: SEA
A11: HLO count: | B11: =COUNTA(C11:C58) -> 22 | C11: AoW1-Suite of solutions focused on consumers that promote consumption of sustainable heathy diets co-developed, tested, and scaled with technical support and country engagement | D11: 3 | F11: 3 | G11: 3 | H11: 3 | K11: Current diets are not sustainable and have a high environmental footprint contributing to climate change. Mitigation solutions do normally not include healthy diet considerations. Current diets lack diversity that could contribute to biodiversity and as such to mitigate climate change | L11: Current diets are diverse and have a low environmental impact (in terms of GHGe, water and land use). Deman from consumers for sustainabel healthy diets act as pull to change production and processing towards more envornmental sustainability and as such contribute to mitigation of climate change. Climate smart itigation strategies do include sustianble diet considerations (i.e. understanding of trade-off and synergies to improve diets). | M11: wilingness and ability to produce in a sustainable way. FBDGs include sustainability in diet formulation. Consumers are willing and able to consume sustainable diets and their demand form a pull factor and stimulation of sustianbale production and processing. We cannot differentiate regional differences in this regard without further data collection. | N11: Understanding of how diets can be formulated that are diverse and environmentally sustainability without affecting the healthyness of diets. | O11: Collaboration with Climate accelerator to identify major research questions still open in the climate-nutrition nexus.
A12: Sets of 5: | B12: =_xlfn.FLOOR.MATH(B11/5) -> 4 | C12: AoW1-Suite of solutions focused on vendors that promote employment opportunities and the sale of sustainable nutritious foods co-developed, tested, and scaled with technical support and country engagement | D12: 2 | F12: 2 | G12: 2 | H12: 2 | K12: we discuss the current state in the Environment tab | L12: we discuss the ideal state in the Environment tab | M12: 1. The only real solution we are working on that would have climate adaptation impacts would be related to food loss and waste (and food safety, which can relate to food loss and waste).So we mark it high; other components are less likely to lead to climate adaptation and there are no regional differences we can think of. | N12: Internally it is best to understand what products are most required in the diet (AoW1) so we can prioritize them for diets; in this case so that we can target those markets if foodis produced but costly or not available enough for some reason. | O12: We are collaborating with SAAF to develop food safety solutions for animal source foods. To the extent that we are able to demonstrate positive solutions, we will attempt to work with the Scaling for Impact Science Program on scaling them.
A13: Remainder: | B13: =MOD(B11,5) -> 2 | C13: AoW1-Policy options and engagement that support effective management of national action plans and other policy processes, for food systems transformation in support of sustainable healthy diets | D13: 3 | F13: 3 | G13: 3 | H13: 3 | K13: we discuss the current state in the Environment tab | L13: we discuss the current state in the Environment tab | M13: we discuss the assumptions in the Environment tab | N13: we discuss the requirements in the Environment tab | O13: we discuss the requirements in the environment tab
A14: Max score: | B14: =(B12*SUM($B$2:$B$6))+SUM($B$2:INDEX(B:B, $B$13+1)) -> 69 | C14: AoW2-Suite of Solutions to lower transaction costs | D14: 5 | F14: 5 | G14: 5 | H14: 5 | K14: We discuss the current state in the "food security" tab. | L14: We discuss the ideal state in the "food security" tab. | M14: 1. The only real solution we are working on that would have climate adaptation impacts would be related to food loss and waste (and food safety, which can relate to food loss and waste).So we mark it high; other components are less likely to lead to climate adaptation and there are no regional differences we can think of. | N14: Internally it is best to understand what products are most required in the diet (AoW1) so we can prioritize them for diets; in this case so that we can target those markets if foodis produced but costly or not available enough for some reason. | O14: We are collaborating with SAAF to develop food safety solutions for animal source foods. To the extent that we are able to demonstrate positive solutions, we will attempt to work with the Scaling for Impact Science Program on scaling them.
C15: AoW2-Suite of Solutions to catalyze business growth | D15: 1 | F15: 1 | G15: 1 | H15: 1 | K15: We discuss the current state in the "food security" tab. | L15: We discuss the ideal state in the "food security" tab.
C16: AoW2-Trade and Limiting UPC Consumption | D16: 1 | F16: 1 | G16: 1 | H16: 1 | K16: We discuss the current state in the "food security" tab. | L16: We discuss the ideal state in the "food security" tab.
C17: AoW3-Suite of tested end-to-end solutions for health and agriculture extension agents, fruit and vegetable vendors/retailers, processors, traders and producers that promote healthy food choice behaviors of consumers, healthy food environments, food quality and safety, reduce food loss, and increase profits co-developed, tested, and scaled. | D17: 4 | F17: 5 | G17: 4 | H17: 4 | I17: 4 | K17: Fruit and vegetable production is negatively affected by increased temperature, drought, increase pests and disease pressure. In addition, actors currently have low access to climate-smart technologies. Abusive application of fertilizers, phytosanitary and water increased fruit and vegetable production environmental footprint. | L17: Actors adopt climate smart technologies to adapt to the effects of climate changes to improve supply of safe fruit and vegetables. | M17: Exposure to climate change effect is high in ESA and WCA and there is demand from governments and value chains actors to have affordable climate smart technologies. | N17: Identify and scale fruit and vegetable solutions that support adaptation to climate change | O17: Strong collaboration with Sustainable farming especially on climate smart production systems
C18: AoW3-Suite of end-to-end solutions for health and agriculture extension agents, aquatic food vendors/retailers processors, and traders that promote healthy food choice behaviors of consumers, healthy food environments, food quality and safety, reduce food loss, and increase profits co-developed, tested, and scaled. | D18: 4 | F18: 4 | G18: 5 | H18: 3 | I18: 3 | K18: Climate change has a huge impact on the loss experienced in the fisheries sector. Post harvest & processing activities often have a significant environmental impact as wood for firewood for example is used. The role of new climate smart technologies to minimize food loss and waste at all stages of the fish value chain will allow for a more efficient use of resources | L18: Actors adopt climate smart technologies to address loss and waste post harvest | M18: ESA and WCA have active bilaterals and demand from governments to have affordable climate smart technologies. For Bangladesh for example depending on species and season, the post harvest quality loss of wet fish ranges from 10-39%. This is similar across the South Asia region where demand for low cost climate smart post harvest technologies is high | N18: Identify and scale aquatic source food solutions that support adaptation to climate change | O18: Strong collaboration with SAAFs especially on climate smart aquatic source foods systems
C19: AoW3-Suite of end-to-end solutions for health and agriculture extension agents, terrestrial animal-source vendors/retailers processors, and traders that promote healthy food choice behaviors of consumers, healthy food environments, food quality and safety, reduce food loss, and increase profits co-developed, tested, and scaled. | D19: 4 | F19: 2 | G19: 2 | H19: 3 | I19: 3 | K19: Terrestrial animal surce foods production impacts negatively on the environment through GHG emissions and is also negatively impacted by increased temperature, and climate induced pests and diseases. Actors currently have low access to climate-smart technologies. | L19: Actors adopt climate smart technologies along the post-production nodes of the value chain, for instance best practices in slaiughter waste management | M19: In WCA, ESA, and SA livetock traders and vendors often face significant knowledge asymmetries especially about livestock's impact on climate change and how climate change impacts on livestock. | N19: Identify and scale terrestrial animal source food solutions that support adaptation to climate change | O19: Strong collaboration with SAAFs especially on climate smart animal source foods systems
C20: AoW3-Suite of integrated end-to-end solutions for health and agriculture extension agents, perishable nutrient-rich food vendors/retailers, processors, traders and producers that promote healthy food choice behaviors of consumers, healthy food environments, food quality and safety, reduce food loss,and increase profits co-developed, tested, and scaled. | D20: 3 | F20: 3 | G20: 3 | H20: 3 | I20: 3 | K20: Non-sustainable food systems pratices contributing to environmental degradation, and high post-harvest increase environmental footprint of fruit and vegetable, aquatic and terrestrial animal source food value chains. Low access to technologies that are environmental-friendly. | L20: Actors adopt sustainable integrated solutions for fruit, vegetable, aquatic and terrestrial animal source food production, marketing and consumption | M20: In WCA, ESA, and SA, considering the interest of actors in accessing and using climat-smart solutions, more impact can be achieved in these regions. | N20: Include environmental sustainability in the selection of developed solutions to be scaled | O20: Strong collaboration with SAAF and Sustainable farming, especially on climate smart crops and animal source foods systems
C21: AoW3-Policy options that address constraints to sustainable healthy diets | D21: 3 | F21: 2 | G21: 2 | H21: 2 | I21: 3 | K21: Fragmented policy options to inform links between diets and climate on food systems transformation towards better diets. | L21: Policy prioritize sustainable food system transformations and create enabling environment for their implementation | M21: SA has a more conducive policy environment where impact can be made compared to the other regions, which, despite the high need for climate-smart solutions, have less conducive policy implementation environment. | N21: Translate evidence into policy and identify the right entry for policy maker engagement | O21: Close collaboration with Policy Innovation
C22: AoW4-Suite of solutions for producers and processors that address constraints to sustainable healthy diets co-developed, tested, and scaled with technical support and country engagement. | D22: 2 | E22: 3 | F22: 3 | G22: 3 | H22: 3 | I22: 3 | K22: Traders and vendors have limited incentives or awareness to prioritize the sourcing and marketing of biofortified and health-enhancing products. Market demand is weak or unclear, and regulatory frameworks for labeling or differentiation are often absent. Nutritious crops that are climate resilient are needed for sustainable development but addressing multiple goals with one commodity is often disregarded. | L22: Traders and vendors actively source, promote, and sell biofortified and health-enhancing crops and products, that are also climate resilient. These are supported by a strong value proposition, clear quality standards, and informed consumers who demand such options, especially climate concious consumers. They are able to market their products to the respective consumer segments. | M22: In WCA, ESA, and SA are all highly affected by climate change and traders and vendors often lack strong market linkages and face significant knowledge asymmetries, limiting their ability to make informed decisions and market products accordingly. In other regions this is also present but less extreme. | N22: Clear labeling standards and branding for biofortified and health-enhancing products to the respective climate aware consumer segments addressing malnutrion and providing information on climate resilience, adaptation and mitigation; training and market linkages for vendors; development of traceability tools and quality assurance mechanisms. Support from consumer awareness campaigns, policy advocacy for enabling regulations, and collaboration with market systems and private sector engagement teams. | O22: Collaboration from STEER and INVEST (B4T, AoW MArket Intelligence) are needed to provide evidence of valid investment opportunities to support trader and vendor decision making. Policy Innovation is needed to support labeling and tracability policies with special regards to climate.
C23: AoW4-Policy options and engagement that address constraints to sustainable healthy diets. | D23: 2 | E23: 3 | F23: 5 | G23: 5 | H23: 3 | I23: 5 | K23: Policy options that consider nutrition and address climate change together are lacking or are inconsistently addressed in agricultural, food systems, and public health policies. Limited engagement with policymakers and lack of coherent strategies that are climate and nutrition sensitive hinder integration and adoption of biofortified and health-enhancing crops. | L23: Policies addressing climate together with nutrition at national and regional levels consistently prioritize and integrate biofortified and health-enhancing crops into agriculture, food systems, nutrition, climate and health agendas driven by stakeholder demand and evidence-based guidance to improve food and nutrition security. | M23: In WCA, ESA, and SA policy frameworks remain weak and do not include multiple aspects, and stakeholder engagement is often fragmented and inconsistent, they also do not target farmers with respect to climate adaptation and mitigation through nutrition policies. Policies that address a variety of aspects, e.g. climate, poverty, heatlh, nutrition, equity are lacking or are underdeveloped in all regions. | N23: Robust integrated policy research and synthesis with a focus on climate and nutrition; strategic partnerships with policy influencers; targeted advocacy campaigns to address climate and nutrition; monitoring policy impact on equity, climate, and nutrition outcomes; generating evidence for valid investment cases through projected impact determination in the area of social equity. Support from public health, legal, trade, and education sectors to harmonize and implement enabling legislation, standards, and cross-sector frameworks that align with improved diets and nutrition goals. | O23: Close collaboration with Policy Innovation; B4T AoW on Market Intelligence to generate Investment cases (INVEST), and benefit projections (STEER) in target geographies and close alignment with the Climate Science Program.
C24: AoW4-Framework for embedding nutrition into breeding pipelines and processes. | D24: 2 | E24: 3 | F24: 5 | G24: 5 | H24: 3 | I24: 4 | K24: Breeding programs do not consistently incorporate nutritional traits or consumer-demanded profiles in combination with climate traits. Integration of nutrition is often dependent on project-specific funding or champions and lacks institutionalization across CGIAR and NARS systems. | L24: Breeding pipelines mainstream nutritional traits in addition to climate traits (stress, diesease and pest tolerances) in target product profiles (TPPs), guided by evidence on dietary gaps, social inequity, climatic needs and consumer needs resulting in varieties that are agronomically competitive, nutrient-dense, high yielding, climate adapted and desired by consumers. | M24: In WCA, ESA, and SA only a limited number of Target Product Profiles (TPPs) have integrated and evaluated nutrition and climate traits in a systematic manner and only for selctive crops. Breeding teams lack recognizing the importance of nutrition and health-enhancing traits fin combination with climate traits. While food security has improved across all the regions, nutrition security has not and high levels of micronutrient deficiencies exists in WCA, ESA, SA with some areas disproportionaly affected by climate change | N24: Development of demand-driven, gender-intentional TPPs that integrate diet quality needs; shared metrics for nutritional quality and gender equality; capacity building of breeding teams; investment in screening and diagnostic infrastructure. Collaboration with nutrition and health research teams and socioeconomics research teams to generate evidence on consumer needs, dietary gaps, and policy priorities that guide breeding decisions. | O24: Collaboration with B4T, in particular the areas of work on Accelerated Breeding, Breeding Resources, Market Intelligence and ENABLE. I special focus needs to be on sub-AoW DESIGN to ensure the full integration of diet improving and gender-intentional traits in product concepts and the product design standard. Furthermore, INVEST and STEER are needed to assess projected benefits for target regions.
C25: AoW4-Suite of solutions for traders and vendors that address constraints to sustainable healthy diets co-developed, tested, and scaled with technical support and country engagement. | D25: 2 | E25: 3 | F25: 3 | G25: 3 | H25: 3 | I25: 3 | K25: Traders and vendors have limited incentives or awareness to prioritize the sourcing and marketing, especially with regards to climate adaptation and mitigation, of biofortified and health-enhancing products. Market demand is weak or unclear and evidence is scarce, and regulatory frameworks for labeling or differentiation are often absent. | L25: Traders and vendors actively source, promote, and sell biofortified and health-enhancing crops and products with additional climate benefitis, supported by a strong value proposition, clear quality standards, and informed consumers who demand such options. | M25: In WCA, ESA, and SA traders and vendors often lack strong market linkages and face significant knowledge asymmetries especially about climate change, limiting their ability to make informed decisions which is also present in the other regions. Traders and vendors respond to consumer demand and profit opportunities if they are correctly informed; market channels and regulatory structures currently do not allow for differentiation; traceability systems for 'invisible trait' are not feasible and affordable in all regions. However, malnutrition is most pronounced in ESA, WCA and SA where climate change is also prevalent and products are needed that address multiple aspects simultaneously. | N25: Clear labeling standards for target groups and branding for biofortified and health-enhancing products with additional climate benefits; training and market linkages for vendors; development of traceability tools and quality assurance mechanisms. Support from consumer awareness campaigns, policy advocacy for enabling regulations, and collaboration with market systems and private sector engagement teams. | O25: Collaboration from STEER and INVEST (B4T, AoW MArket Intelligence) are needed to provide evidence of valid investment opportunities to support trader and vendor decision making. Policy Innovation is needed to support labeling and tracability policies. Collaboration with the gender accelerator to ensure that the design and marketing is not gender blind.
C26: AoW4-Suite of solutions to support consumers awareness, preference, affordability, and utilization of biofortified and health-enhancing crops in their diets. | D26: 2 | E26: 3 | F26: 2 | G26: 2 | H26: 3 | I26: 2 | K26: Consumer awareness and demand for biofortified and health-enhancing foods are generally low and many consumers are not aware of their deficiencies and the impact of climate change. Misconceptions from the GMO debates, lack of clear labeling, and limited availability or affordability hinder widespread adoption especially among low-income and nutritionally vulnerable populations. | L26: Consumers are informed, motivated, and demand and are able to include biofortified and health-enhancing foods in their diets driven by clear value propositions, affordable options, positive Behavior Change Communication (BCC), and supportive food environments. Climate change aspects are also adequately addressed. There is a clearly definde consumer market segment that addresses the needs of climate aware people. | M26: Across all regions consumers have difficulties assessing their health, nutrient status, and how they are impacted by climate change. TPPs are not mainstreamed for multiple aspects such as nutrition, climate and gender. | N26: Strategic BCC and social marketing campaigns addressing nutrition and climate change; consumer research to tailor messaging and product development to target populations; partnerships with community organizations and retailers. Support from media, education, and health sectors to amplify messaging; collaboration with market and food policy teams to ensure affordability and retail availability. | O26: Climate Program to tailor BCCs to reach all consumers equitably but also to ensure that economic benefits are equitably accessible.
C27: AoW5-Suite of multisectoral solutions for government and non-government organizations that address constraints to sustainable healthy diets co-developed, tested, and scaled with technical support and country engagement | K27: n.a. | L27: n.a. | M27: n.a. | N27: n.a. | O27: n.a.
C28: AoW6-Synthesized knowledge products across AoWs and disseminated | D28: 2 | E28: 2 | F28: 3 | G28: 3 | H28: 3 | I28: 2 | K28: Limited synthesis of knowledge to inform links between diets and climate on FST towards better diets. | L28: Clear framework to guide knowledge synthesis that links climate to diets and nutrition on FST. Active (ongoing) synthesis of knowledge. | M28: There is willingness and ability among P/As in BDN led activities to strengthen coordination, deliberate efforts to link climate to BDN as part of knowledge uptake and adoption of systems thinking | N28: Ability to convene the BDN-AoWs in the planned activities and adequate resources complemented by willingnes of AoWs to engage | O28: P/As addressing climate willing and able to focus on how climate can be better linked to BDN as part of FST efforts.
C29: AoW6-Regional food systems transformation coordination mechanisms disseminated | D29: 3 | E29: 3 | F29: 3 | G29: 3 | H29: 3 | I29: 3 | K29: Inadequate inclusion of climate considerations as part of coordination and governance for a diet-centred FST within regions | L29: Adequate inclusion of climate considerations as part of coordination and governace efforts for diet-centred FST towards BDN within regions | M29: Effective engagement by BDN scientists in regional processes/events where climate can be integrated to be able to influence climate considerations towards BDN | N29: Robust engagement by other AoWs to share products that can be used in the engagments to link climate considerations to FST towards BDN. Complete alignment on key messages for BDN | O29: Robust engagement by other P/As to share products that can be used in the engagments to link climate considerations to FST towards BDN. Complete alignment on key messages for BDN
C30: AoW6-Targeted capacity-sharing events addressing evidence to policy actions and strategic engagement to influence food systems thinking to promote positive transformative change among different stakeholders including CoPs. | D30: 3 | E30: 3 | F30: 3 | G30: 3 | H30: 3 | I30: 3 | K30: Limited capcity sharing applying sytems thinking to linking climate to FST efforts towards BDN | L30: Strong capcity to deliberately link climate to systems thinking on FST efforts in capcity strenthening efforts | M30: Stakeholders in countries and regions see the importance to include climate in capcity sharing efforts focusing on systems thinking to accelrate progress on FST towards BDN | N30: Adequate resources and willingness of AoWs to engage with the needed linking of climate to BDN in capacity sharing events for FST | O30: Adequate resources, willingness and ability of P/As to link climate to BDN in engagements on capacity sharing events on FST
C31: AoW6-Regional, continental FS leadership development events to promote BDN outcomes for FST | D31: 2 | E31: 2 | F31: 3 | G31: 3 | H31: 3 | I31: 2 | K31: Limited ability to lead the process to link climate to diet-centered food systems transformation efforts | L31: Strong leadership ability to link climate to diet-centered food systems thinking | M31: Implementers of FST pathways and roadmaps are willing and able to consider linking climate to a diet centred food systems thinking in their implementation efforts | N31: Adequate resources, willingness and ability of AoW to engage with AoW6 efforts on linking climate to BDN in the process of leading FST with systems thinking | O31: Other P/As adopt climate considerations as part of adopting systems thinking beyond their own outputs towards BDN
C32: AoW6-Task force that guides the CGIAR Portfolio along pathways that lead to credible impacts on nutrition, health, and food security | D32: 3 | E32: 3 | F32: 3 | G32: 3 | H32: 3 | I32: 3 | K32: Lack of coordination, knowledge and systmes thinking across P/As around linking climate to FST towards BDN from the perspective P/As | L32: Good coordination, adequate knowledge; and adoption of systems thinking that links climate to BDN across P/As around FST from the perspective of P/As | M32: There is willingness and ability among P/As in BDN led activities to strengthen coordination, knowledge uptake and adoption of climate as part of systems thinking towards BDN | N32: adequate resources, ability to convene the AoWs and their willingnes to engage in the planned activities to link climate to FST towards BDN | O32: P/As adopt systems thinking beyond the immediate (economic) outputs P/As and include climate considerations in linking their FST efforts to contribute to BDN.

Sheet 5.Environmental_health
C1: Environmental Indicators
A2: VH | B2: 5 | D2: LAC | E2: CWANA | F2: WCA | G2: ESA | H2: SA | I2: SEA | J2: AoW1 | K2: =AVERAGE(D15:I19) -> 3.8
A3: H | B3: 4 | C3: Total score by column | D3: =SUM(D11:D58) -> 50 | E3: =SUM(E11:E58) -> 31 | F3: =SUM(F11:F58) -> 63 | G3: =SUM(G11:G58) -> 64 | H3: =SUM(H11:H58) -> 61 | I3: =SUM(I11:I58) -> 60 | J3: AoW2 | K3: 0
A4: MH | B4: 3 | C4: VH count by column | D4: =COUNTIF(D$11:D$58, 5) -> 0 | E4: =COUNTIF(E$11:E$58, 5) -> 0 | F4: =COUNTIF(F$11:F$58, 5) -> 3 | G4: =COUNTIF(G$11:G$58, 5) -> 3 | H4: =COUNTIF(H$11:H$58, 5) -> 0 | I4: =COUNTIF(I$11:I$58, 5) -> 1 | J4: AoW3 | K4: =AVERAGE(D17:I21) -> 3.6
A5: M | B5: 2 | C5: H count by column | D5: =COUNTIF(D$11:D$58, 4) -> 3 | E5: =COUNTIF(E$11:E$58, 4) -> 2 | F5: =COUNTIF(F$11:F$58, 4) -> 5 | G5: =COUNTIF(G$11:G$58, 4) -> 5 | H5: =COUNTIF(H$11:H$58, 4) -> 7 | I5: =COUNTIF(I$11:I$58, 4) -> 4 | J5: AoW4 | K5: =AVERAGE(D22:I26) -> 3.1
A6: L | B6: 1 | C6: MH count by column | D6: =COUNTIF(D$11:D$58, 3) -> 8 | E6: =COUNTIF(E$11:E$58, 3) -> 7 | F6: =COUNTIF(F$11:F$58, 3) -> 8 | G6: =COUNTIF(G$11:G$58, 3) -> 9 | H6: =COUNTIF(H$11:H$58, 3) -> 11 | I6: =COUNTIF(I$11:I$58, 3) -> 13 | J6: AoW5 | K6: 0
C7: M count by column | D7: =COUNTIF(D$11:D$58, 2) -> 7 | E7: =COUNTIF(E$11:E$58, 2) -> 1 | F7: =COUNTIF(F$11:F$58, 2) -> 2 | G7: =COUNTIF(G$11:G$58, 2) -> 1 | H7: =COUNTIF(H$11:H$58, 2) -> 0 | I7: =COUNTIF(I$11:I$58, 2) -> 0 | J7: AoW6 | K7: =AVERAGE(D28:I32) -> 3.3
C8: L count by column | D8: =COUNTIF(D$11:D$58, 1) -> 0 | E8: =COUNTIF(E$11:E$58, 1) -> 0 | F8: =COUNTIF(F$11:F$58, 1) -> 0 | G8: =COUNTIF(G$11:G$58, 1) -> 0 | H8: =COUNTIF(H$11:H$58, 1) -> 0 | I8: =COUNTIF(I$11:I$58, 1) -> 0 | K8: Current state (across the Global South) | L8: Ideal state (across the Global South) | M8: Assumptions (for region-specific scores) | N8: Requirements for success (internal to P/A) | O8: Requirements for success (from other P/As)
C10: HLO | D10: LAC | E10: CWANA | F10: WCA | G10: ESA | H10: SA | I10: SEA
A11: HLO count: | B11: =COUNTA(C11:C58) -> 22 | C11: AoW1-Suite of solutions focused on consumers that promote consumption of sustainable heathy diets co-developed, tested, and scaled with technical support and country engagement | D11: 3 | F11: 3 | G11: 3 | H11: 4 | I11: 3 | K11: With increasing income, populations start to eat more animal and aquatic source foods, contributing to an increased environmental footprint. However, a large proportion of populations in LMICs consume a mainly staple food based diet, so improving diet quality requires an increase in consumption of animal and/or aquatic foods. Moreover, FBDGs in LMICs often do not include environmental sustainability considerations. | L11: Consumers consume healthy diets with foods produced in an environmental sustainable way. This means moderation of for example animal and/or aquatic foods in populations who consume beyond what is recommended in FBDGs or global recommendations. This also means accepting that for populations with inadequate diets, moderate increase in animal and aquatic foods should be promoted (taking into account that reduced consumption in HICs should compensate for that increase at the very least). | M11: Consumers are willing to adjust their diets to become more environmentally sustainable. LAC should focus on reducing consumption of foods with a large environmental footprint (e.g. GHGE, water and land use). In WCA and ESA, attention should go to improving (e.g. quantity and quality) of animal/aquatic food consumption to improve diet quality, accepting that the environmental footprint will increase. In SA, the attention depends on the segment of consumers, and either implies moderation or an increase in the consumption of animal/aquatic foods. FBDGs, when available, do not address environmental sustainability in the diets recommended, and few focus on general messages, for example reducing food loss and waste. | N11: Incorporation of environmental sustainability in the Food Based Dietary Guidelines. Incorporation of environmental sustainability considerations in the development of solutions promoting consumption of sustainable healthy diets. This should be supported by influencing drivers in other components of the food system (for example sustainable production and processing, sustainable transport, and policies enabling them). | O11: Willingness to incorporate environmental sustainability in production methods through collaboraton with B4T and SAAF.
A12: Sets of 5: | B12: =_xlfn.FLOOR.MATH(B11/5) -> 4 | C12: AoW1-Suite of solutions focused on vendors that promote employment opportunities and the sale of sustainable nutritious foods co-developed, tested, and scaled with technical support and country engagement | D12: 3 | F12: 3 | G12: 3 | H12: 3 | I12: 3 | K12: Sales of packages unhealthy and unsustainable foods is increasing. There is food waste at the MSMEs level . There is no attention or preference to sell environmentally sustainable foods as not profitable. | L12: reduced environmental polution through packaging of food, reduced food waste at MSMEs level. Selling environmental sustainale food is prefered because it is profitable and follow demand of consumers for sustainable healthy diets. | M12: For all regions: MSMEs are willing, have the capacity and ability to sell environmental sustainable (and nutritious) foods and reduce food waste. No real regional differences in this goal. | N12: Solutions developed need to address environmental sustainability, in all regions.
A13: Remainder: | B13: =MOD(B11,5) -> 2 | C13: AoW1-Policy options and engagement that support effective management of national action plans and other policy processes, for food systems transformation in support of sustainable healthy diets | D13: 3 | F13: 4 | G13: 3 | H13: 3 | I13: 3 | K13: There are no specific policies on food environment and those available hardly address environmental sustainability. Environmental sustainability is addressed in the national plans for food system transformation, but only in terms of agricultural production and reduction of food loss and waste. There are policies to support consumption of healthy diets, but environmental sustainability is not or hardly included. | L13: Policies and strategies that support sustainable health diets exist and are enforced; Ministries of Health incorporates promoting sustainable heathy diets in nutrition and health polcicies. | M13: Policy makers and decision makers are willing and have the capacity to (re)formulate policies that support consumption of sustainable healthy diets. See above for regional discussion. | N13: Close engagement with policy and decision makers to advocate for inclusion of sustainable healthy diets. | O13: Incorporation of sustainable heathy diet perspectives in other sector policies such as in agricultural policies, through collaboration with Policy Innovations. Collaboration with Policy Innovations to identify and quantify trade-offs and synergies when incorporating sustainable healthy diets considerations.
A14: Max score: | B14: =(B12*SUM($B$2:$B$6))+SUM($B$2:INDEX(B:B, $B$13+1)) -> 69 | C14: AoW2-Suite of Solutions to lower transaction costs | K14: We are only very indirectly working on environmental health, and given the poor state of indicators as well we are not filling this sheet out.
C15: AoW2-Suite of Solutions to catalyze business growth
C16: AoW2-Trade and Limiting UPC Consumption
C17: AoW3-Suite of tested end-to-end solutions for health and agriculture extension agents, fruit and vegetable vendors/retailers, processors, traders and producers that promote healthy food choice behaviors of consumers, healthy food environments, food quality and safety, reduce food loss, and increase profits co-developed, tested, and scaled. | D17: 4 | F17: 5 | G17: 5 | H17: 4 | I17: 4 | K17: Non-sustainable production pratices contributing to forest degradation, soil erosion and high post-harvest increase environmental footprint of fruit and vegetable value chains. | L17: Actors adopt sustainable vegetable and fruit technologies that optimize resources use and reduce post-harvest loss. | M17: ESA and WCA have high needs for sustainable solutions and there is demand from governments and value chains actors to access sustainable technologies. We can achieve higher impact in these regions. | N17: Include environmental sustainability in the selection of developed solutions to be scaled | O17: Strong collaboration with Sustainable farming especially on climate smart production systems
C18: AoW3-Suite of end-to-end solutions for health and agriculture extension agents, aquatic food vendors/retailers processors, and traders that promote healthy food choice behaviors of consumers, healthy food environments, food quality and safety, reduce food loss, and increase profits co-developed, tested, and scaled. | D18: 3 | F18: 4 | G18: 4 | H18: 4 | I18: 4 | K18: Environmental health directly influences the safety and quality of aquatic products. Climate smart post harvest innovations reduce waste and ensure consistent supply | L18: Actors adopt climate smart technologies to address loss and waste post harvest | M18: ESA and WCA have active bilaterals and demand from governments to have affordable climate smart technologies. For Bangladesh for example depending on species and season, the post harvest quality loss of wet fish ranges from 10-39%. This is similar across the South Asia region where demand for low cost climate smart post harvest technologies is high | N18: Include environmental sustainability in the selection of developed solutions to be scaled | O18: Strong collaboration with SAAFs especially on climate smart animal source foods systems
C19: AoW3-Suite of end-to-end solutions for health and agriculture extension agents, terrestrial animal-source vendors/retailers processors, and traders that promote healthy food choice behaviors of consumers, healthy food environments, food quality and safety, reduce food loss, and increase profits co-developed, tested, and scaled. | D19: 2 | F19: 3 | G19: 4 | H19: 4 | I19: 3 | K19: Terrestrial animal surce foods production impacts negatively on the environment through GHG emissions and is also negatively impacted by increased temperature, and climate induced pests and diseases. Actors currently have low access to climate-smart technologies. | L19: Actors adopt climate smart technologies along the post-production nodes of the value chain, for instance best practices in slaiughter waste management | M19: In WCA, ESA, and SA livetock traders and vendors often face significant knowledge asymmetries especially about livestock's impact on climate change and how climate change impacts on livestock. | N19: Include environmental sustainability in the selection of developed solutions to be scaled | O19: Strong collaboration with SAAFs especially on climate smart animal source foods systems
C20: AoW3-Suite of integrated end-to-end solutions for health and agriculture extension agents, perishable nutrient-rich food vendors/retailers, processors, traders and producers that promote healthy food choice behaviors of consumers, healthy food environments, food quality and safety, reduce food loss,and increase profits co-developed, tested, and scaled. | D20: 3 | F20: 4 | G20: 4 | H20: 4 | I20: 3 | K20: Non-sustainable production pratices contributing to environmental degradation, and high post-harvest increase environmental footprint of fruit and vegetable, aquatic and terrestrial animal source food value chains. Low access to technologies that are environmental-friendly | L20: Actors adopt sustainable integrated solutions for fruit, vegetable, aquatic and terrestrial animal source food production, marketing and consumption | M20: In WCA, ESA, and SA, considering the interest of actors in accessing and using sustainable solutions, more impact can be achieved in these regions. | N20: Include environmental sustainability in the selection of developed solutions to be scaled | O20: Strong collaboration with SAAFs and Sustainable farming especially on climate smart crops and animal source foods systems
C21: AoW3-Policy options that address constraints to sustainable healthy diets | D21: 3 | F21: 3 | G21: 3 | H21: 3 | I21: 3
C22: AoW4-Suite of solutions for producers and processors that address constraints to sustainable healthy diets co-developed, tested, and scaled with technical support and country engagement. | D22: 2 | E22: 3 | F22: 3 | G22: 3 | H22: 3 | I22: 3 | K22: Traders and vendors have limited incentives or awareness to prioritize the sourcing and marketing of biofortified and health-enhancing products. Market demand is weak or unclear, and regulatory frameworks for labeling or differentiation are often absent. Nutritious crops that do not harm the environment and improve biodiversity are needed for sustainable development but addressing multiple goals with one commodity is often disregarded. | L22: Traders and vendors actively source, promote, and sell biofortified and health-enhancing crops and products, that are do not harm the environment. These are supported by a strong value proposition, clear quality standards, and informed consumers who demand such options, especially environmental concious consumers. They are able to market their products to the respective consumer segments. | M22: In WCA, ESA, and SA are all highly affected by climate change and environmental degradation and traders and vendors often lack strong market linkages and face significant knowledge asymmetries, limiting their ability to make informed decisions and market products accordingly. In other regions this is also present but less extreme. | N22: Clear labeling standards and branding for biofortified and health-enhancing products to the respective environmental aware consumer segments addressing malnutrion and providing information on climate resilience, adaptation and mitigation; training and market linkages for vendors; development of traceability tools and quality assurance mechanisms. Support from consumer awareness campaigns, policy advocacy for enabling regulations, and collaboration with market systems and private sector engagement teams. | O22: Collaboration from STEER and INVEST (B4T, AoW MArket Intelligence) are needed to provide evidence of valid investment opportunities to support trader and vendor decision making. Policy Innovation is needed to support labeling and tracability policies with special regards to climate.
C23: AoW4-Policy options and engagement that address constraints to sustainable healthy diets. | D23: 2 | E23: 3 | F23: 5 | G23: 5 | H23: 3 | I23: 5 | K23: Policy options that consider nutrition and address environmental health together are lacking or are inconsistently addressed in agricultural, food systems, and public health policies. Limited engagement with policymakers and lack of coherent strategies that are environmental and nutrition sensitive hinder integration and adoption of biofortified and health-enhancing crops. | L23: Policies addressing environmental health together with nutrition at national and regional levels consistently prioritize and integrate biofortified and health-enhancing crops into agriculture, food systems, nutrition, climate, environment and health agendas driven by stakeholder demand and evidence-based guidance to improve food and nutrition security. | M23: In WCA, ESA, and SA policy frameworks remain weak and do not include multiple aspects, and stakeholder engagement is often fragmented and inconsistent, they also do not target farmers with respect to environmental health through nutrition policies. Policies that address a variety of aspects, e.g. climate, poverty, heatlh, nutrition, equity are lacking or are underdeveloped in all regions. | N23: Robust integrated policy research and synthesis with a focus on environmental health and nutrition; strategic partnerships with policy influencers; targeted advocacy campaigns to addressenvironmental health and nutrition; monitoring policy impact on equity, climate, and nutrition outcomes; generating evidence for valid investment cases through projected impact determination in the area of social equity. Support from public health, legal, trade, and education sectors to harmonize and implement enabling legislation, standards, and cross-sector frameworks that align with improved diets and nutrition goals. | O23: Close collaboration with Policy Innovation; B4T AoW on Market Intelligence to generate Investment cases (INVEST), and benefit projections (STEER) in target geographies and close alignment with the Climate Science Program.
C24: AoW4-Framework for embedding nutrition into breeding pipelines and processes. | D24: 2 | E24: 3 | F24: 5 | G24: 5 | H24: 3 | I24: 3 | K24: Breeding programs do not consistently incorporate nutritional traits or consumer-demanded profiles in combination with climate traits. Integration of nutrition is often dependent on project-specific funding or champions and lacks institutionalization across CGIAR and NARS systems. | L24: Breeding pipelines mainstream nutritional traits in addition to climate traits (stress, diesease and pest tolerances) in target product profiles (TPPs), guided by evidence on dietary gaps, social inequity, climatic needs and consumer needs resulting in varieties that are agronomically competitive, nutrient-dense, high yielding, climate adapted and desired by consumers. | M24: In WCA, ESA, and SA only a limited number of Target Product Profiles (TPPs) have integrated and evaluated nutrition and climate traits in a systematic manner and only for selctive crops. Breeding teams lack recognizing the importance of nutrition and health-enhancing traits fin combination with climate traits. While food security has improved across all the regions, nutrition security has not and high levels of micronutrient deficiencies exists in WCA, ESA, SA with some areas disproportionaly affected by climate change | N24: Development of demand-driven, gender-intentional TPPs that integrate diet quality needs; shared metrics for nutritional quality and gender equality; capacity building of breeding teams; investment in screening and diagnostic infrastructure. Collaboration with nutrition and health research teams and socioeconomics research teams to generate evidence on consumer needs, dietary gaps, and policy priorities that guide breeding decisions. | O24: Collaboration with B4T, in particular the areas of work on Accelerated Breeding, Breeding Resources, Market Intelligence and ENABLE. I special focus needs to be on sub-AoW DESIGN to ensure the full integration of diet improving and gender-intentional traits in product concepts and the product design standard. Furthermore, INVEST and STEER are needed to assess projected benefits for target regions.
C25: AoW4-Suite of solutions for traders and vendors that address constraints to sustainable healthy diets co-developed, tested, and scaled with technical support and country engagement. | D25: 2 | E25: 3 | F25: 3 | G25: 3 | H25: 3 | I25: 3 | K25: Traders and vendors have limited incentives or awareness to prioritize the sourcing and marketing, especially with regards to climate adaptation and mitigation, of biofortified and health-enhancing products. Market demand is weak or unclear and evidence is scarce, and regulatory frameworks for labeling or differentiation are often absent. | L25: Traders and vendors actively source, promote, and sell biofortified and health-enhancing crops and products with additional climate benefitis, supported by a strong value proposition, clear quality standards, and informed consumers who demand such options. | M25: In WCA, ESA, and SA traders and vendors often lack strong market linkages and face significant knowledge asymmetries especially about climate change, limiting their ability to make informed decisions which is also present in the other regions. Traders and vendors respond to consumer demand and profit opportunities if they are correctly informed; market channels and regulatory structures currently do not allow for differentiation; traceability systems for 'invisible trait' are not feasible and affordable in all regions. However, malnutrition is most pronounced in ESA, WCA and SA where climate change is also prevalent and products are needed that address multiple aspects simultaneously. | N25: Clear labeling standards for target groups and branding for biofortified and health-enhancing products with additional climate benefits; training and market linkages for vendors; development of traceability tools and quality assurance mechanisms. Support from consumer awareness campaigns, policy advocacy for enabling regulations, and collaboration with market systems and private sector engagement teams. | O25: Collaboration from STEER and INVEST (B4T, AoW MArket Intelligence) are needed to provide evidence of valid investment opportunities to support trader and vendor decision making. Policy Innovation is needed to support labeling and tracability policies. Collaboration with the gender accelerator to ensure that the design and marketing is not gender blind.
C26: AoW4-Suite of solutions to support consumers awareness, preference, affordability, and utilization of biofortified and health-enhancing crops in their diets. | D26: 2 | E26: 3 | F26: 2 | G26: 2 | H26: 3 | I26: 3 | K26: Consumer awareness and demand for biofortified and health-enhancing foods are generally low and many consumers are not aware of their deficiencies and the impact of climate change. Misconceptions from the GMO debates, lack of clear labeling, and limited availability or affordability hinder widespread adoption especially among low-income and nutritionally vulnerable populations. | L26: Consumers are informed, motivated, and demand and are able to include biofortified and health-enhancing foods in their diets driven by clear value propositions, affordable options, positive Behavior Change Communication (BCC), and supportive food environments. Climate change aspects are also adequately addressed. There is a clearly definde consumer market segment that addresses the needs of climate aware people. | M26: Across all regions consumers have difficulties assessing their health, nutrient status, and how they are impacted by climate change. TPPs are not mainstreamed for multiple aspects such as nutrition, climate and gender. | N26: Strategic BCC and social marketing campaigns addressing nutrition and climate change; consumer research to tailor messaging and product development to target populations; partnerships with community organizations and retailers. Support from media, education, and health sectors to amplify messaging; collaboration with market and food policy teams to ensure affordability and retail availability. | O26: Climate Program to tailor BCCs to reach all consumers equitably but also to ensure that economic benefits are equitably accessible.
C27: AoW5-Suite of multisectoral solutions for government and non-government organizations that address constraints to sustainable healthy diets co-developed, tested, and scaled with technical support and country engagement | K27: n.a. | L27: n.a. | M27: n.a. | N27: n.a. | O27: n.a.
C28: AoW6-Synthesized knowledge products across AoWs and disseminated | D28: 3 | E28: 3 | F28: 3 | G28: 3 | H28: 3 | I28: 3 | K28: Disconnected evidence between human health/nutrition/diets and environmental health | L28: Evidence is better connected | M28: Efforts by BDN will be recognized as being useful and integrated into linked impact areas | N28: Adequate coordination across AoWs to collate the emerging evidence | O28: Adequate coordination across other P/As
C29: AoW6-Regional food systems transformation coordination mechanisms disseminated | D29: 4 | E29: 4 | F29: 4 | G29: 4 | H29: 4 | I29: 4 | K29: Inadequate coordination across FS sectors within regions | L29: Adequate coordination across FS sectors towards BDN and environment linkages within regions | M29: Regional bodies will consider diets/nutrition as important to their area and be willing to incorporate evidence of the linkages into discussions and action plans. | N29: Effective engagement across BDN and CGIAR Environment IA/ SP/A scientists in regional processes/events to be able to influence discussions, plans and actions | O29: Robust engagement by other P/As to share products that can be used in the engagments. Complete alignment on key messages linking diets/nutrition to environment
C30: AoW6-Targeted capacity-sharing events addressing evidence to policy actions and strategic engagement to influence food systems thinking to promote positive transformative change among different stakeholders including CoPs. | D30: 3 | E30: 3 | F30: 3 | G30: 3 | H30: 3 | I30: 3 | K30: Capacity sharing events are often, but not always sector specific | L30: Growing number of cross-sector capacity sharing events | M30: Regional capacity sharing initiatives will consider diets/nutrition as important to their area and be willing to incorporate evidence of the linkages into discussions and action plans. | N30: Collaboration at SP level to demonstrate how BDN outputs are relevant to this IA | O30: Collaboration at CGIAR level to jointly work together across thematic areas
C31: AoW6-Regional, continental FS leadership development events to promote BDN outcomes for FST | D31: 2 | E31: 2 | F31: 2 | G31: 3 | H31: 3 | I31: 3 | K31: Leadership trainings are often, but not always sector specific | L31: Growing number of cross-sector leadership training opportunities the incorporate this IA | M31: Regional leasership training initiatives will consider cross-thematic linkages and important focus of training | N31: Collaboration at SP level to demonstrate how BDN outputs are relevant to this IA | O31: Collaboration at CGIAR level to jointly work together across thematic areas
C32: AoW6-Task force that guides the CGIAR Portfolio along pathways that lead to credible impacts on nutrition, health, and food security | D32: 4 | E32: 4 | F32: 4 | G32: 4 | H32: 4 | I32: 4 | K32: Lack of coordination, knowledge and cross-disciplinary systems thinking across SP/As toward achievement of all IAs | L32: Good coordination, adequate knowledge; and adoption of cross-disciplinary systems thinking across P/As toward achieving all CGIAR IAs | M32: There is willingness and ability among SP/As to strengthem coordination, knowledge uptake and adoption of systems thinking toward achieving all CGIAR IAs | N32: Ability to convene the P/As in the planned activities and adequate resources | O32: Thinking beyond the individual IAs toward synergies and trade-offs across them

Sheet Step B weights
A1: Link to spreadsheet with raw data: Projected Benefits Data (Nov 2024) - With Analysis.xlsx
A2: Food Security | I2: Poverty reduction | Q2: Social Inclusion | Y2: Climate Adaptation | AG2: Environmental health
A3: Prevalence of Undernourishment | I3: Poor Population ($2.15) | Q3: Gender Inclusivity Index | Y3: Agricultural Greenhouse Gas (GHG) Emissions | AG3: Agricultural Greenhouse Gas (GHG) Emissions
A4: Coverage | B4: Region totals | I4: Coverage | J4: Region totals | Q4: Coverage | R4: Region totals | Y4: Coverage | Z4: Region totals | AG4: Coverage | AH4: Region totals
A5: Units | B5: Share of total population living below the minimum calorie daily threshold | I5: Units | J5: Millions of people living below the poverty line | Q5: Units | Y5: Units | Z5: Millions of tons of CO2eq emissions | AG5: Units | AH5: Millions of tons of CO2eq emissions
A6: Region | B6: 2021 | C6: 2022 | D6: 2023 | E6: 2024 | F6: 2025 | I6: Region | J6: 2021 | K6: 2022 | L6: 2023 | M6: 2024 | N6: 2025 | Q6: Region | V6: 2022 | Y6: Region | Z6: 2021 | AA6: 2022 | AB6: 2023 | AC6: 2024 | AD6: 2025 | AG6: Region | AH6: 2021 | AI6: 2022 | AJ6: 2023 | AK6: 2024 | AL6: 2025
A7: r_wld | B7: 8.8427009 | C7: 8.2286613 | D7: 7.6489309 | E7: 7.1031772 | F7: 6.5908679 | I7: r_wld | J7: 751.13725 | K7: 737.74175 | L7: 726.16698 | M7: 716.37814 | N7: 708.31417
A8: LAC | B8: 7.1892578 | C8: 6.68889 | D8: 6.2115266 | E8: 5.7570393 | F8: 5.3252329 | H8: LAC | I8: r_lac | J8: 31.202645 | K8: 31.753595 | L8: 32.307095 | M8: 32.862885 | N8: 33.420694 | P8: LAC | Q8: r_lac | V8: 0.3786 | X8: LAC | Y8: r_lac | Z8: 1062.158 | AA8: 1066.2886 | AB8: 1070.4689 | AC8: 1074.6999 | AD8: 1078.9828 | AF8: LAC | AG8: r_lac | AH8: 1062.158 | AI8: 1066.2886 | AJ8: 1070.4689 | AK8: 1074.6999 | AL8: 1078.9828
A9: CWANA | B9: 9.1504665 | C9: 8.9091662 | D9: 8.6634743 | E9: 8.4138444 | F9: 8.160744 | H9: CWANA | I9: r_cwana | J9: 26.653279 | K9: 25.965677 | L9: 25.26942 | M9: 24.565485 | N9: 23.854888 | P9: CWANA | Q9: r_cwana | V9: 0.4202 | X9: CWANA | Y9: r_cwana | Z9: 267.73908 | AA9: 273.34463 | AB9: 279.09723 | AC9: 285.00085 | AD9: 291.05959 | AF9: CWANA | AG9: r_cwana | AH9: 267.73908 | AI9: 273.34463 | AJ9: 279.09723 | AK9: 285.00085 | AL9: 291.05959
