Workbook

Sheet Country-regions
A1: Countries, per region, worked on by [Insert Program/Accelerator name]
A2: CGIAR regions and countries.xlsx | B2: <-- Spreadsheet showing the CGIAR regions and the countries that fall into these regions
A3: Program and Accelerator's Countries (2024).xlsx | B3: <-- Spreadsheet showing the countries that each Program/Accelerator is working on (as per what was submitted in 2024 for the original methodology).
A4: LAC | B4: CWANA | C4: WCA | D4: ESA | E4: SA | F4: SEA
A5: Colombia | B5: Egypt | C5: Benin | D5: Ethiopia | E5: Bangladesh | F5: Cambodia
A6: Guatemala | B6: Morocco | C6: Côte d’Ivoire | D6: Kenya | E6: India | F6: Indonesia
A7: Honduras | B7: Tunisia | C7: DR Congo | D7: Malawi | E7: Nepal | F7: Myanmar
A8: Mexico | B8: Uzbekistan | C8: Nigeria | D8: Tanzania | E8: Pakistan | F8: Philippines
A9: Peru | C9: Senegal | D9: Uganda | E9: Sri Lanka | F9: Viet Nam
C10: Sudan | D10: Zambia
D11: Zimbabwe
A12: Primary countries
A13: Secondary countries

Sheet HLOs
A2: VH | B2: 5
A3: H | B3: 4
A4: MH | B4: 3
A5: M | B5: 2
A6: L | B6: 1
C7: # | D7: HLO Title | E7: HLO Concise description
A8: HLO count: | B8: =COUNTA(D8:D23) -> 15 | C8: 1 | D8: HLO 1.1.1: Demand signaling | E8: A toolbox of quantitative and qualitative methods, data, and dashboards articulating stakeholders’ priorities, supporting research and scaling activity demand signaling and adaptive anagement of CGIAR’s Portfolio
A9: Sets of 5: | B9: =_xlfn.FLOOR.MATH(B8/5) -> 3 | C9: 2 | D9: HLO 1.1.2: Feedback and adaptive research and scaling prioritization | E9: CGIAR’s Programs, Accelerators, and bilaterals engage with information supporting the adaptive management of Program, Accelerator, and bilateral research and scaling activities
A10: Remainder: | B10: =MOD(B8,5) -> 0 | C10: 3 | D10: HLO 1.1.3: Enhance strategies and coordination | E10: Comprehensive, forward-looking regional and country-level strategies, enhancing Portfolio-wide research prioritization, scaling coordination, and policy alignment
A11: Max score: | B11: =(B9*SUM($B$2:$B$6))+IF(B8=0,0,SUM(B2:INDEX(B:B,$B$10+1))) -> 50 | C11: 4 | D11: HLO 2.2.1: Innovation networks enhance agrifood system solution scaling | E11: Regional scaling hubs supporting stakeholders in impact pathway diagnosis, design, deployment, and refinement
C12: 5 | D12: HLO 2.2.2: Methods evaluating agrifood system solutions for scale | E12: Co-designed scaling pathways for regional and national agrifood systems through improved stakeholder capacity
C13: 6 | D13: HLO 2.2.3: Scale-ready agrifood system solution bundles and packages | E13: Impact pathways evaluated and ranked for their potential to advance innovation bundles and packages to scale in regional- and country-specific agrifood systems
C14: 7 | D14: HLO 2.2.4: Agrifood system solution scaling strategies | E14: Demand-driven and scale-ready agrifood system solution bundles and packages and strategies for scaling, with pathways and strategies identified for refinement, adaptation, and amplification
C15: 8 | D15: HLO 3.3.1: Enabling environment diagnostics | E15: Co-created tools and analyses to assess opportunities and constraints in the enabling environment for innovation bundle scaling in targeted countries and regions and in the three primary pathways
C16: 9 | D16: HLO 3.3.2: Scaling support services for enabling environments and institutions | E16: Innovative institution building and capacity sharing activities; training materials and targeted deployment of demand-driven targeted EE technical assistance to enhance institutional and analytical as well as operational capacities to achieve scale
C17: 10 | D17: HLO 3.3.3: Science-policy partnership interfaces for responsible scaling | E17: Innovative partnerships, policy hubs, economic and environment networks, community-building efforts, and NARES/farmer cooperatives supported to increase research-based public and private investments and policy improvements and address normative barriers
C18: 11 | D18: HLO 4.4.1: CGIAR Expertise and Solutions Embedded in Development Investments and Partnerships | E18: CGIAR engages with financing bodies—including IFIs and the private sector, including banks, impact investors, and CSR funds—through technical assistance and advisory support, to ensure innovations are positioned to support impact at scale
C19: 12 | D19: HLO 4.4.2: Innovation portfolio management and scaling strategy support teams | E19: Scaling capacity toolbox in support of CGIAR Programs and bilateral projects strengthening the design, implementation, and monitoring of evidence-based and responsible scaling strategies
C20: 13 | D20: HLO 5.5.1: Enhancing scaling science for societal impact | E20: An applied scaling science and innovation systems research agenda strengthening South–South learning and capacities to implement more responsible and context-aware scaling strategies
C21: 14 | D21: HLO 5.5.2: Insights for CGIAR scaling success through impact assessments | E21: Evidence-based, context-specific recommendations on optimal scaling outcomes for selected CGIAR scaling efforts and solutions are based on rigorous impact assessments and nalysis of diverse scaling pathways and are supported by co-created scaling metrics, monitoring, and evaluations.
C22: 15 | D22: HLO 5.5.3: Custom analytics for managing innovation portfolios and decision-making | E22: Curated analytics for innovation portfolio management and decision-making, including Scaling Readiness evaluations and customized assessment tools for target countries, both ongoing and as part of the annual adaptive management process, to ensure continuous learning and improvement

Sheet Indicators
A1: BASE Indicator database - (from 2024).xlsx | C1: <-- source of Baseline data
A2: Projected Benefits Data (Nov 2024) - With Analysis.xlsx | C2: <-- source of Projected data (with graphs)
A3: Impact Area | B3: Projected to 2040 (without CGIAR intervention) or baseline data? | C3: Indicator | D3: r_lac | E3: r_cwana | F3: r_wca | G3: r_esa | H3: r_sa | I3: r_sea
K4: Mean | L4: SD | M4: r_lac | N4: r_cwana | O4: r_wca | P4: r_esa | Q4: r_sa | R4: r_sea
A5: Nutrition | B5: Baseline data | C5: Prevalence of stunting (height for age <-2 standard deviation from the median of the World Health Organization (WHO) Child Growth Standards) % children under 5 years of age | D5: 11.679145 | E5: 17.238147 | F5: 31.597628 | G5: 30.494793 | H5: 34.286344 | I5: 11.083749 | K5: 0.2267 | L5: 0.1144 | M5: =D5*5/$H5 -> 1.7031774 | N5: =E5*5/$H5 -> 2.5138502 | O5: =F5*5/$H5 -> 4.6079027 | P5: =G5*5/$H5 -> 4.4470756 | Q5: =H5*5/$H5 -> 5 | R5: =I5*5/$H5 -> 1.6163504 | Y5: r_lac | Z5: r_cwana | AA5: r_wca | AB5: r_esa | AC5: r_sa | AD5: r_sea
A6: Nutrition | B6: Baseline data | C6: Prevalence of wasting (weight for height >+2 or <-2 standard deviation from the median of the WHO Child Growth Standards) % children under 5 years of age | D6: 2.2309085 | E6: 5.8629686 | F6: 6.7930741 | G6: 5.4676809 | H6: 16.318465 | I6: 3.6836782 | K6: 0.0667 | L6: 0.0476 | M6: =D6*5/$H6 -> 0.6835534 | N6: =E6*5/$H6 -> 1.7964216 | O6: =F6*5/$H6 -> 2.0814072 | P6: =G6*5/$H6 -> 1.6753049 | Q6: =H6*5/$H6 -> 5 | R6: =I6*5/$H6 -> 1.128684 | S6: =AVERAGE(M5:M8) -> 2.0697443 | T6: =AVERAGE(N5:N8) -> 2.71611 | U6: =AVERAGE(O5:O8) -> 3.6288645 | V6: =AVERAGE(P5:P8) -> 3.4480649 | W6: =AVERAGE(Q5:Q8) -> 4.2468545 | X6: =AVERAGE(R5:R8) -> 2.2976906 | Y6: =S6*1.1 -> 2.2767187 | Z6: =T6*1.1 -> 2.987721 | AA6: =U6*1.1 -> 3.9917509 | AB6: =V6*1.1 -> 3.7928713 | AC6: =W6*1.1 -> 4.6715399 | AD6: =X6*1.1 -> 2.5274597
A7: Nutrition | B7: Baseline data | C7: % of population unable to afford a healthy diet | D7: 22.261332 | E7: 37.375529 | F7: 84.372957 | G7: 82.105349 | H7: 73.246664 | I7: 24.396071 | K7: 0.5367 | L7: 0.2812 | M7: =D7*5/$F7 -> 1.319222 | N7: =E7*5/$F7 -> 2.2148998 | O7: =F7*5/$F7 -> 5 | P7: =G7*5/$F7 -> 4.86562 | Q7: =H7*5/$F7 -> 4.3406482 | R7: =I7*5/$F7 -> 1.4457281
A8: Nutrition | B8: Baseline data | C8: Women meeting minimum dietary diversity (MDD-W)(%) | D8: 77.386889 | E8: 73.431162 | F8: 47.825418 | G8: 47.455003 | H8: 44.789895 | I8: 84.612374 | J8: MDD-W - higher value indicates more women meeting the minimum (i.e., a lower potential for impact) --- Minimum Dietary Diversity for Women is a population-level food group-based indicator that captures dietary diversity, a core construct of healthy diets. MDD-W is used to estimate the proportion of non-pregnant women aged 15-49 years who consumed at least five out of ten defined food groups over the previous 24 hours, signalling better micronutrient intake. indicator that captures dietary diversity, a core construct of healthy diets. MDD-W is used to estimate the proportion of non-pregnant women aged 15-49 years who consumed at least five out of ten defined food groups over the previous 24 hours, signalling better micronutrient intake. -- Note that we calculated it as 100% minus the MDD-W (i.e., women not meeting ...) such that higher values correspond with higher potential for impact, | K8: 0.625 | L8: 0.1764 | M8: =D8*5/$I8 -> 4.5730243 | N8: =E8*5/$I8 -> 4.3392685 | O8: =F8*5/$I8 -> 2.826148 | P8: =G8*5/$I8 -> 2.804259 | Q8: =H8*5/$I8 -> 2.6467698 | R8: =I8*5/$I8 -> 5
A9: Gender | B9: Baseline data | C9: Proportion of youth (aged 15-24 years) not in education, employment or training (NEET) (%) | D9: 20.353948 | E9: 28.808683 | F9: 22.22403 | G9: 22.032946 | H9: 25.579269 | I9: 13.900333 | K9: 0.2217 | L9: 0.0531
A10: Gender | B10: Baseline data | C10: Gender Development Index (GDI) | D10: 0.98711807 | E10: 0.86109472 | F10: 0.88128823 | G10: 0.92987576 | H10: 0.85713094 | I10: 0.96249076 | J10: GDI measures gender inequalities in achievement in three basic dimensions of human development: health, measured by female and male life expectancy at birth; education, measured by female and male expected years of schooling for children and female and male mean years of schooling for adults ages 25 years and older; and command over economic resources, measured by female and male estimated earned income. | K10: 1 | L10: 0
A11: Gender | B11: Baseline data | C11: Gender Inequality Index (GII) | D11: 0.3786 | E11: 0.4202 | F11: 0.6154 | G11: 0.51 | H11: 0.4542 | I11: 0.2426 | J11: GII is a composite metric of gender inequality using three dimensions: reproductive health, empowerment and the labour market. A low GII value indicates low inequality between women and men, and vice-versa. | K11: 0.33 | L11: 0.47
A12: Poverty | B12: Baseline data | C12: The ratio of the people employed in agriculture in rural areas over all people employed in rural areas" | D12: 46.830763 | E12: 34.609244 | F12: 64.335138 | G12: 71.949092 | H12: 56.611142 | I12: 44.992877 | K12: 0.5333 | L12: 0.1376
A13: Climate | B13: Baseline data | C13: Vulnerability index of the geography (exposure, sensitivity and adaptive capacity in six life-supporting sectors: food, water, health, ecosystem services, human habitat, and infrastructure). | D13: 0.38522854 | E13: 0.41856096 | F13: 0.52689312 | G13: 0.51707456 | H13: 0.50168331 | I13: 0.40802057 | K13: 0.5 | L13: 0.5
A14: Climate | B14: Baseline data | C14: Emissions intensity - CO2eq emissions from croplands (kg/ha) (Carlson et al., 2017) | D14: 386 | E14: 444 | F14: 312 | G14: 531 | H14: 2090 | I14: 3326 | K14: 1181.5 | L14: 1335.13
A15: Climate | B15: Baseline data | C15: CRI - Climate Risk Index - the index of the level of exposure and vulnerability to extreme events such as storms, floods and heatwaves based on historic data | D15: 46.593083 | E15: 71.63158 | F15: 73.530172 | G15: 45.434032 | H15: 18.194338 | I15: 40.16028 | K15: 49.33 | L15: 19.89
A16: Environment | B16: Baseline data | C16: Consumptive blue and green water used in food production (m3/ha) | D16: 5008.9819 | E16: 3795.1862 | F16: 4064.7898 | G16: 4368.5844 | H16: 5065.8423 | I16: 6113.5583 | K16: 4736.33 | L16: 834.12
A17: Environment | B17: Baseline data | C17: Soil erosion rate (/Ha) | D17: 4480.2558 | E17: 2629.3874 | F17: 5858.9939 | G17: 7924.0507 | H17: 10121.16 | I17: 7076.2489 | K17: 6348.17 | L17: 2682.76
A18: Environment | B18: Baseline data | C18: Forest area lost (%) - the percentage of forested area (%) lost between 2010 and 2020 | D18: 4.0133292 | E18: 3.0328342 | F18: 8.736605 | G18: 6.4758874 | H18: 0.80036497 | I18: 1.9236632 | K18: 0.0417 | L18: 0.0286
A19: Environment | B19: Baseline data | C19: GBI - Global Biodiversity Index - Total number of plant, reptile, mammal, bird, fish and amphibian species | D19: 362.31193 | E19: 80.081948 | F19: 116.18798 | G19: 156.28684 | H19: 264.30093 | I19: 324.04395 | K19: 217 | L19: 118.76
A20: Environment | B20: Baseline data | C20: Sustainable agriculture score - Index quantifying progress toward productive and sustainable agriculture (current status score) | D20: 3.7142926 | E20: 3.0915505 | F20: 3.2533234 | G20: 2.8150793 | H20: 2.5514288 | I20: 3.9867322 | K20: 3.33 | L20: 0.47
A22: Impact Area | B22: Projected to 2040 (without CGIAR intervention) | C22: Indicator | D22: r_lac | X22: r_cwana | AR22: r_wca | BL22: r_esa | CF22: r_sa | CZ22: r_sea
D23: 2021 | E23: 2022 | F23: 2023 | G23: 2024 | H23: 2025 | I23: 2026 | J23: 2027 | K23: 2028 | L23: 2029 | M23: 2030 | N23: 2031 | O23: 2032 | P23: 2033 | Q23: 2034 | R23: 2035 | S23: 2036 | T23: 2037 | U23: 2038 | V23: 2039 | W23: 2040 | X23: 2021 | Y23: 2022 | Z23: 2023 | AA23: 2024 | AB23: 2025 | AC23: 2026 | AD23: 2027 | AE23: 2028 | AF23: 2029 | AG23: 2030 | AH23: 2031 | AI23: 2032 | AJ23: 2033 | AK23: 2034 | AL23: 2035 | AM23: 2036 | AN23: 2037 | AO23: 2038 | AP23: 2039 | AQ23: 2040 | AR23: 2021 | AS23: 2022 | AT23: 2023 | AU23: 2024 | AV23: 2025 | AW23: 2026 | AX23: 2027 | AY23: 2028 | AZ23: 2029 | BA23: 2030 | BB23: 2031 | BC23: 2032 | BD23: 2033 | BE23: 2034 | BF23: 2035 | BG23: 2036 | BH23: 2037 | BI23: 2038 | BJ23: 2039 | BK23: 2040 | BL23: 2021 | BM23: 2022 | BN23: 2023 | BO23: 2024 | BP23: 2025 | BQ23: 2026 | BR23: 2027 | BS23: 2028 | BT23: 2029 | BU23: 2030 | BV23: 2031 | BW23: 2032 | BX23: 2033 | BY23: 2034 | BZ23: 2035 | CA23: 2036 | CB23: 2037 | CC23: 2038 | CD23: 2039 | CE23: 2040 | CF23: 2021 | CG23: 2022 | CH23: 2023 | CI23: 2024 | CJ23: 2025 | CK23: 2026 | CL23: 2027 | CM23: 2028 | CN23: 2029 | CO23: 2030 | CP23: 2031 | CQ23: 2032 | CR23: 2033 | CS23: 2034 | CT23: 2035 | CU23: 2036 | CV23: 2037 | CW23: 2038 | CX23: 2039 | CY23: 2040 | CZ23: 2021 | DA23: 2022 | DB23: 2023 | DC23: 2024 | DD23: 2025 | DE23: 2026 | DF23: 2027 | DG23: 2028 | DH23: 2029 | DI23: 2030 | DJ23: 2031 | DK23: 2032 | DL23: 2033 | DM23: 2034 | DN23: 2035 | DO23: 2036 | DP23: 2037 | DQ23: 2038 | DR23: 2039 | DS23: 2040
A24: Nutrition | B24: Projected to 2040 | C24: Prevalence of Undernourishment - Share of total population living below the minimum calorie daily threshold | D24: 7.1892578 | E24: 6.68889 | F24: 6.2115266 | G24: 5.7570393 | H24: 5.3252329 | I24: 4.9158466 | J24: 4.5285569 | K24: 4.1629803 | L24: 3.8186764 | M24: 3.4951517 | N24: 3.1918631 | O24: 2.908223 | P24: 2.6436027 | Q24: 2.3973382 | R24: 2.1687341 | S24: 1.9570691 | T24: 1.7616009 | U24: 1.5815713 | V24: 1.4162109 | W24: 1.2647443 | X24: 9.1504665 | Y24: 8.9091662 | Z24: 8.6634743 | AA24: 8.4138444 | AB24: 8.160744 | AC24: 7.9046538 | AD24: 7.6460667 | AE24: 7.3854859 | AF24: 7.123424 | AG24: 6.8604013 | AH24: 6.5969443 | AI24: 6.3335834 | AJ24: 6.0708516 | AK24: 5.809282 | AL24: 5.5494058 | AM24: 5.2917502 | AN24: 5.0368357 | AO24: 4.7851739 | AP24: 4.537265 | AQ24: 4.2935953 | AR24: 18.91209 | AS24: 18.415278 | AT24: 17.911492 | AU24: 17.401678 | AV24: 16.886799 | AW24: 16.367828 | AX24: 15.845748 | AY24: 15.321548 | AZ24: 14.796218 | BA24: 14.270749 | BB24: 13.746128 | BC24: 13.223332 | BD24: 12.703327 | BE24: 12.187064 | BF24: 11.675475 | BG24: 11.169467 | BH24: 10.669921 | BI24: 10.177686 | BJ24: 9.6935781 | BK24: 9.2183741 | BL24: 22.510157 | BM24: 21.490211 | BN24: 20.474437 | BO24: 19.465188 | BP24: 18.464847 | BQ24: 17.475809 | BR24: 16.500465 | BS24: 15.541184 | BT24: 14.600291 | BU24: 13.680052 | BV24: 12.782652 | BW24: 11.910171 | BX24: 11.064571 | BY24: 10.247669 | BZ24: 9.4611245 | CA24: 8.7064163 | CB24: 7.9848318 | CC24: 7.2974499 | CD24: 6.645131 | CE24: 6.0285075 | CF24: 15.036352 | CG24: 13.50078 | CH24: 12.058387 | CI24: 10.711231 | CJ24: 9.460449 | CK24: 8.306251 | CL24: 7.2479364 | CM24: 6.2839238 | CN24: 5.4118015 | CO24: 4.6283937 | CP24: 3.9298411 | CQ24: 3.3116949 | CR24: 2.76902 | CS24: 2.2965049 | CT24: 1.8885759 | CU24: 1.53951 | CV24: 1.2435457 | CW24: 0.99498599 | CX24: 0.78829295 | CY24: 0.6181697 | CZ24: 2.9870488 | DA24: 2.5739841 | DB24: 2.2066181 | DC24: 1.8817105 | DD24: 1.5959854 | DE24: 1.3461739 | DF24: 1.1290543 | DG24: 0.94148797 | DH24: 0.78045059 | DI24: 0.64305899 | DJ24: 0.52659245 | DK24: 0.42850921 | DL24: 0.34645781 | DM24: 0.27828373 | DN24: 0.2220316 | DO24: 0.1759435 | DP24: 0.13845375 | DQ24: 0.10818092 | DR24: 0.083917403 | DS24: 0.06461742
A25: Gender | B25: WE CURRENTLY DON’T HAVE APPROPRIATE INDICATORS PROJECTED FOR THE GENDER IMPACT AREA - PLEASE USE BASELINE DATA ONLY
A26: Poverty | B26: Projected to 2040 | C26: Poverty Headcount Rate ($2.15) - Share of total population living below the poverty line | D26: 4.98557 | E26: 5.0242558 | F26: 5.0621172 | G26: 5.0991222 | H26: 5.1352386 | I26: 5.1704341 | J26: 5.2046757 | K26: 5.2379303 | L26: 5.2701643 | M26: 5.3013441 | N26: 5.3314354 | O26: 5.3604039 | P26: 5.3882149 | Q26: 5.4148334 | R26: 5.4402242 | S26: 5.4643519 | T26: 5.4871807 | U26: 5.5086747 | V26: 5.5287977 | W26: 5.5475134 | X26: 4.59918 | Y26: 4.4042124 | Z26: 4.2131091 | AA26: 4.02598 | AB26: 3.84293 | AC26: 3.6640582 | AD26: 3.4894579 | AE26: 3.319216 | AF26: 3.1534129 | AG26: 2.9921218 | AH26: 2.8354089 | AI26: 2.6833326 | AJ26: 2.5359435 | AK26: 2.3932841 | AL26: 2.2553884 | AM26: 2.1222821 | AN26: 1.9939817 | AO26: 1.8704952 | AP26: 1.7518213 | AQ26: 1.6379496 | AR26: 36.30807 | AS26: 36.185862 | AT26: 36.061701 | AU26: 35.935577 | AV26: 35.807479 | AW26: 35.677395 | AX26: 35.545315 | AY26: 35.411226 | AZ26: 35.275116 | BA26: 35.136975 | BB26: 34.996788 | BC26: 34.854543 | BD26: 34.710229 | BE26: 34.56383 | BF26: 34.415335 | BG26: 34.26473 | BH26: 34.112002 | BI26: 33.957135 | BJ26: 33.800117 | BK26: 33.640934 | BL26: 38.89568 | BM26: 38.85434 | BN26: 38.811608 | BO26: 38.767445 | BP26: 38.721807 | BQ26: 38.674652 | BR26: 38.625933 | BS26: 38.575602 | BT26: 38.523611 | BU26: 38.469907 | BV26: 38.414438 | BW26: 38.357148 | BX26: 38.297978 | BY26: 38.236869 | BZ26: 38.173758 | CA26: 38.10858 | CB26: 38.041268 | CC26: 37.97175 | CD26: 37.899953 | CE26: 37.825801 | CF26: 11.48274 | CG26: 10.469358 | CH26: 9.4825203 | CI26: 8.5274757 | CJ26: 7.6094386 | CK26: 6.7334754 | CL26: 5.904376 | CM26: 5.126516 | CN26: 4.4037126 | CO26: 3.7390816 | CP26: 3.134903 | CQ26: 2.5925037 | CR26: 2.1121683 | CS26: 1.6930861 | CT26: 1.3333448 | CU26: 1.0299761 | CV26: 0.77905634 | CW26: 0.57586239 | CX26: 0.41507324 | CY26: 0.29100712 | CZ26: 1.23059 | DA26: 0.88984793 | DB26: 0.6221891 | DC26: 0.41911725 | DD26: 0.27092336 | DE26: 0.16738356 | DF26: 0.098482932 | DG26: 0.055066945 | DH26: 0.029330068 | DI26: 0.015081471 | DJ26: 0.0077742847 | DK26: 0.0043346014 | DL26: 0.0028635352 | DM26: 0.0022984445 | DN26: 0.0021059525 | DO26: 0.0020486343 | DP26: 0.0020339519 | DQ26: 0.002030774 | DR26: 0.0020302043 | DS26: 0.0020301216
A27: Poverty | B27: Projected to 2040 | C27: Poverty Headcount Rate ($3.65) - Share of total population living below the poverty line | D27: 12.326178 | E27: 12.381889 | F27: 12.436252 | G27: 12.489232 | H27: 12.540798 | I27: 12.590913 | J27: 12.639544 | K27: 12.686654 | L27: 12.732209 | M27: 12.776171 | N27: 12.818504 | O27: 12.85917 | P27: 12.898132 | Q27: 12.935351 | R27: 12.970787 | S27: 13.004401 | T27: 13.036154 | U27: 13.066003 | V27: 13.093907 | W27: 13.119826 | X27: 14.288423 | Y27: 13.982703 | Z27: 13.67684 | AA27: 13.370967 | AB27: 13.065221 | AC27: 12.759739 | AD27: 12.454666 | AE27: 12.150146 | AF27: 11.846328 | AG27: 11.543362 | AH27: 11.241404 | AI27: 10.940608 | AJ27: 10.641135 | AK27: 10.343146 | AL27: 10.046804 | AM27: 9.7522739 | AN27: 9.4597232 | AO27: 9.1693202 | AP27: 8.8812344 | AQ27: 8.5956364 | AR27: 64.127509 | AS27: 64.124548 | AT27: 64.121536 | AU27: 64.118473 | AV27: 64.115359 | AW27: 64.112192 | AX27: 64.108972 | AY27: 64.105699 | AZ27: 64.102372 | BA27: 64.098991 | BB27: 64.095554 | BC27: 64.092063 | BD27: 64.088515 | BE27: 64.08491 | BF27: 64.081248 | BG27: 64.077527 | BH27: 64.073748 | BI27: 64.06991 | BJ27: 64.066011 | BK27: 64.062051 | BL27: 65.516569 | BM27: 65.515305 | BN27: 65.513998 | BO27: 65.512647 | BP27: 65.511251 | BQ27: 65.509807 | BR27: 65.508315 | BS27: 65.506774 | BT27: 65.50518 | BU27: 65.503534 | BV27: 65.501833 | BW27: 65.500075 | BX27: 65.498258 | BY27: 65.496382 | BZ27: 65.494442 | CA27: 65.492439 | CB27: 65.490368 | CC27: 65.488229 | CD27: 65.486018 | CE27: 65.483733 | CF27: 43.13417 | CG27: 42.785936 | CH27: 42.423103 | CI27: 42.045096 | CJ27: 41.651323 | CK27: 41.241181 | CL27: 40.814053 | CM27: 40.369309 | CN27: 39.906311 | CO27: 39.424414 | CP27: 38.922966 | CQ27: 38.401314 | CR27: 37.858808 | CS27: 37.294802 | CT27: 36.708661 | CU27: 36.099766 | CV27: 35.467522 | CW27: 34.811364 | CX27: 34.130765 | CY27: 33.425246 | CZ27: 6.6233529 | DA27: 5.5934126 | DB27: 4.6450586 | DC27: 3.7861739 | DD27: 3.0226307 | DE27: 2.3578335 | DF27: 1.7923687 | DG27: 1.323821 | DH27: 0.94680861 | DI27: 0.65326964 | DJ27: 0.43300161 | DK27: 0.2744137 | DL27: 0.16540941 | DM27: 0.094283044 | DN27: 0.050501138 | DO27: 0.025256507 | DP27: 0.011729008 | DQ27: 0.0050518673 | DR27: 0.0020459537 | DS27: 0.00082542745
A28: Poverty | B28: Projected to 2040 | C28: Poverty Headcount Rate ($6.85) - Share of total population living below the poverty line | D28: 31.99797 | E28: 32.039063 | F28: 32.079058 | G28: 32.117939 | H28: 32.155689 | I28: 32.192292 | J28: 32.227729 | K28: 32.261984 | L28: 32.295038 | M28: 32.326872 | N28: 32.357466 | O28: 32.386801 | P28: 32.414856 | Q28: 32.441611 | R28: 32.467043 | S28: 32.491131 | T28: 32.513851 | U28: 32.535181 | V28: 32.555096 | W28: 32.573571 | X28: 39.779017 | Y28: 39.643681 | Z28: 39.506381 | AA28: 39.367094 | AB28: 39.225797 | AC28: 39.082466 | AD28: 38.937077 | AE28: 38.789605 | AF28: 38.640025 | AG28: 38.488313 | AH28: 38.334443 | AI28: 38.178388 | AJ28: 38.020124 | AK28: 37.859624 | AL28: 37.69686 | AM28: 37.531806 | AN28: 37.364435 | AO28: 37.194718 | AP28: 37.022628 | AQ28: 36.848136 | AR28: 88.509867 | AS28: 88.506906 | AT28: 88.503894 | AU28: 88.500831 | AV28: 88.497716 | AW28: 88.494549 | AX28: 88.49133 | AY28: 88.488056 | AZ28: 88.48473 | BA28: 88.481348 | BB28: 88.477912 | BC28: 88.47442 | BD28: 88.470872 | BE28: 88.467267 | BF28: 88.463605 | BG28: 88.459885 | BH28: 88.456106 | BI28: 88.452267 | BJ28: 88.448368 | BK28: 88.444408 | BL28: 87.43947 | BM28: 87.438206 | BN28: 87.4369 | BO28: 87.435549 | BP28: 87.434152 | BQ28: 87.432709 | BR28: 87.431217 | BS28: 87.429675 | BT28: 87.428082 | BU28: 87.426435 | BV28: 87.424734 | BW28: 87.422976 | BX28: 87.42116 | BY28: 87.419283 | BZ28: 87.417344 | CA28: 87.41534 | CB28: 87.413269 | CC28: 87.41113 | CD28: 87.408919 | CE28: 87.406634 | CF28: 80.974435 | CG28: 80.959243 | CH28: 80.943388 | CI28: 80.92684 | CJ28: 80.909568 | CK28: 80.891539 | CL28: 80.872719 | CM28: 80.853071 | CN28: 80.832558 | CO28: 80.811141 | CP28: 80.788779 | CQ28: 80.765429 | CR28: 80.741045 | CS28: 80.71558 | CT28: 80.688986 | CU28: 80.66121 | CV28: 80.632198 | CW28: 80.601895 | CX28: 80.57024 | CY28: 80.537172 | CZ28: 29.55282 | DA28: 28.453081 | DB28: 27.310321 | DC28: 26.125513 | DD28: 24.900204 | DE28: 23.636605 | DF28: 22.337679 | DG28: 21.007236 | DH28: 19.650019 | DI28: 18.271781 | DJ28: 16.879345 | DK28: 15.480643 | DL28: 14.084712 | DM28: 12.701646 | DN28: 11.342485 | DO28: 10.019034 | DP28: 8.7435908 | DQ28: 7.528593 | DR28: 6.3861649 | DS28: 5.327589
A29: Poverty | B29: Projected to 2040 | C29: Agrifood System Jobs (incl. subsistence farming and informal sector) - millions of workers | D29: 79.453806 | E29: 81.086566 | F29: 82.7612 | G29: 84.478933 | H29: 86.241033 | I29: 88.048807 | J29: 89.903606 | K29: 91.806824 | L29: 93.759905 | M29: 95.764336 | N29: 97.821657 | O29: 99.933458 | P29: 102.10138 | Q29: 104.32713 | R29: 106.61247 | S29: 108.95919 | T29: 111.3692 | U29: 113.84443 | V29: 116.3869 | W29: 118.99868 | X29: 50.377779 | Y29: 51.475884 | Z29: 52.606947 | AA29: 53.772164 | AB29: 54.972781 | AC29: 56.210098 | AD29: 57.485472 | AE29: 58.800317 | AF29: 60.156109 | AG29: 61.554391 | AH29: 62.996771 | AI29: 64.48493 | AJ29: 66.020625 | AK29: 67.605691 | AL29: 69.242045 | AM29: 70.931693 | AN29: 72.676732 | AO29: 74.479356 | AP29: 76.341859 | AQ29: 78.266643 | AR29: 118.18601 | AS29: 122.23843 | AT29: 126.45317 | AU29: 130.8372 | AV29: 135.39785 | AW29: 140.14274 | AX29: 145.07984 | AY29: 150.21751 | AZ29: 155.56444 | BA29: 161.12976 | BB29: 166.92299 | BC29: 172.9541 | BD29: 179.23348 | BE29: 185.77203 | BF29: 192.58113 | BG29: 199.67268 | BH29: 207.05915 | BI29: 214.75354 | BJ29: 222.76947 | BK29: 231.1212 | BL29: 152.33566 | BM29: 158.07421 | BN29: 164.07237 | BO29: 170.34342 | BP29: 176.90137 | BQ29: 183.76104 | BR29: 190.93808 | BS29: 198.44902 | BT29: 206.31135 | BU29: 214.54355 | BV29: 223.16518 | BW29: 232.19692 | BX29: 241.66066 | BY29: 251.57954 | BZ29: 261.9781 | CA29: 272.88229 | CB29: 284.3196 | CC29: 296.31915 | CD29: 308.91182 | CE29: 322.1303 | CF29: 335.11902 | CG29: 345.66882 | CH29: 356.63814 | CI29: 368.04754 | CJ29: 379.91877 | CK29: 392.27487 | CL29: 405.14024 | CM29: 418.54076 | CN29: 432.50383 | CO29: 447.05854 | CP29: 462.23575 | CQ29: 478.06821 | CR29: 494.5907 | CS29: 511.84016 | CT29: 529.85585 | CU29: 548.6795 | CV29: 568.3555 | CW29: 588.93105 | CX29: 610.45641 | CY29: 632.98506 | CZ29: 430.51747 | DA29: 439.33041 | DB29: 448.38064 | DC29: 457.67536 | DD29: 467.22202 | DE29: 477.02828 | DF29: 487.10209 | DG29: 497.45165 | DH29: 508.08544 | DI29: 519.0122 | DJ29: 530.24097 | DK29: 541.7811 | DL29: 553.64225 | DM29: 565.8344 | DN29: 578.36786 | DO29: 591.25328 | DP29: 604.5017 | DQ29: 618.12449 | DR29: 632.13342 | DS29: 646.54069
A30: Poverty | B30: Projected to 2040 | C30: Agrifood System GDP Per Worker - US$ per worker | D30: 9757.9382 | E30: 9757.9382 | F30: 9757.9382 | G30: 9757.9382 | H30: 9757.9382 | I30: 9757.9382 | J30: 9757.9382 | K30: 9757.9382 | L30: 9757.9382 | M30: 9757.9382 | N30: 9757.9382 | O30: 9757.9382 | P30: 9757.9382 | Q30: 9757.9382 | R30: 9757.9382 | S30: 9757.9382 | T30: 9757.9382 | U30: 9757.9382 | V30: 9757.9382 | W30: 9757.9382 | X30: 11320.812 | Y30: 11320.812 | Z30: 11320.812 | AA30: 11320.812 | AB30: 11320.812 | AC30: 11320.812 | AD30: 11320.812 | AE30: 11320.812 | AF30: 11320.812 | AG30: 11320.812 | AH30: 11320.812 | AI30: 11320.812 | AJ30: 11320.812 | AK30: 11320.812 | AL30: 11320.812 | AM30: 11320.812 | AN30: 11320.812 | AO30: 11320.812 | AP30: 11320.812 | AQ30: 11320.812 | AR30: 2860.2434 | AS30: 2860.2434 | AT30: 2860.2434 | AU30: 2860.2434 | AV30: 2860.2434 | AW30: 2860.2434 | AX30: 2860.2434 | AY30: 2860.2434 | AZ30: 2860.2434 | BA30: 2860.2434 | BB30: 2860.2434 | BC30: 2860.2434 | BD30: 2860.2434 | BE30: 2860.2434 | BF30: 2860.2434 | BG30: 2860.2434 | BH30: 2860.2434 | BI30: 2860.2434 | BJ30: 2860.2434 | BK30: 2860.2434 | BL30: 1686.5692 | BM30: 1686.5692 | BN30: 1686.5692 | BO30: 1686.5692 | BP30: 1686.5692 | BQ30: 1686.5692 | BR30: 1686.5692 | BS30: 1686.5692 | BT30: 1686.5692 | BU30: 1686.5692 | BV30: 1686.5692 | BW30: 1686.5692 | BX30: 1686.5692 | BY30: 1686.5692 | BZ30: 1686.5692 | CA30: 1686.5692 | CB30: 1686.5692 | CC30: 1686.5692 | CD30: 1686.5692 | CE30: 1686.5692 | CF30: 2772.7337 | CG30: 2772.7337 | CH30: 2772.7337 | CI30: 2772.7337 | CJ30: 2772.7337 | CK30: 2772.7337 | CL30: 2772.7337 | CM30: 2772.7337 | CN30: 2772.7337 | CO30: 2772.7337 | CP30: 2772.7337 | CQ30: 2772.7337 | CR30: 2772.7337 | CS30: 2772.7337 | CT30: 2772.7337 | CU30: 2772.7337 | CV30: 2772.7337 | CW30: 2772.7337 | CX30: 2772.7337 | CY30: 2772.7337 | CZ30: 8556.862 | DA30: 8556.862 | DB30: 8556.862 | DC30: 8556.862 | DD30: 8556.862 | DE30: 8556.862 | DF30: 8556.862 | DG30: 8556.862 | DH30: 8556.862 | DI30: 8556.862 | DJ30: 8556.862 | DK30: 8556.862 | DL30: 8556.862 | DM30: 8556.862 | DN30: 8556.862 | DO30: 8556.862 | DP30: 8556.862 | DQ30: 8556.862 | DR30: 8556.862 | DS30: 8556.862
A31: Climate | B31: Projected to 2040 | C31: Agrifood System Greenhouse Gas (GHG) Emissions | D31: 1290.6349 | E31: 1299.4607 | F31: 1308.4565 | G31: 1317.627 | H31: 1326.977 | I31: 1336.5113 | J31: 1346.2348 | K31: 1356.1529 | L31: 1366.2709 | M31: 1376.5942 | N31: 1387.1287 | O31: 1397.8802 | P31: 1408.8548 | Q31: 1420.0587 | R31: 1431.4986 | S31: 1443.181 | T31: 1455.113 | U31: 1467.3017 | V31: 1479.7545 | W31: 1492.4791 | X31: 521.24598 | Y31: 532.37733 | Z31: 543.82156 | AA31: 555.58869 | AB31: 567.68908 | AC31: 580.13348 | AD31: 592.93304 | AE31: 606.09934 | AF31: 619.64439 | AG31: 633.58065 | AH31: 647.92106 | AI31: 662.67905 | AJ31: 677.86859 | AK31: 693.50417 | AL31: 709.60086 | AM31: 726.17432 | AN31: 743.24082 | AO31: 760.81729 | AP31: 778.92133 | AQ31: 797.57126 | AR31: 420.59141 | AS31: 431.825 | AT31: 443.40263 | AU31: 455.3357 | AV31: 467.63605 | AW31: 480.31594 | AX31: 493.38808 | AY31: 506.86563 | AZ31: 520.76222 | BA31: 535.09201 | BB31: 549.86963 | BC31: 565.11028 | BD31: 580.82972 | BE31: 597.04426 | BF31: 613.77085 | BG31: 631.02704 | BH31: 648.83104 | BI31: 667.20175 | BJ31: 686.15877 | BK31: 705.72241 | BL31: 552.78648 | BM31: 575.08538 | BN31: 598.466 | BO31: 622.98755 | BP31: 648.71274 | BQ31: 675.70795 | BR31: 704.0435 | BS31: 733.79384 | BT31: 765.03783 | BU31: 797.85902 | BV31: 832.34591 | BW31: 868.59228 | BX31: 906.69748 | BY31: 946.76683 | BZ31: 988.91191 | CA31: 1033.251 | CB31: 1079.9095 | CC31: 1129.0204 | CD31: 1180.7245 | CE31: 1235.1714 | CF31: 1337.1419 | CG31: 1368.6614 | CH31: 1401.2786 | CI31: 1435.0419 | CJ31: 1470.0024 | CK31: 1506.2136 | CL31: 1543.732 | CM31: 1582.6166 | CN31: 1622.9297 | CO31: 1664.7367 | CP31: 1708.1063 | CQ31: 1753.1111 | CR31: 1799.8271 | CS31: 1848.3343 | CT31: 1898.7173 | CU31: 1951.0646 | CV31: 2005.4699 | CW31: 2062.0314 | CX31: 2120.8529 | CY31: 2182.0435 | CZ31: 2408.5001 | DA31: 2440.4414 | DB31: 2473.2397 | DC31: 2506.9196 | DD31: 2541.5063 | DE31: 2577.0259 | DF31: 2613.5052 | DG31: 2650.9722 | DH31: 2689.4553 | DI31: 2728.9842 | DJ31: 2769.5894 | DK31: 2811.3024 | DL31: 2854.1556 | DM31: 2898.1827 | DN31: 2943.4182 | DO31: 2989.8979 | DP31: 3037.6588 | DQ31: 3086.7389 | DR31: 3137.1777 | DS31: 3189.0156
A34: Prevalence of Undernourishment
A52: Undernourished Population
A69: Poverty Headcount Rate ($2.15)
A85: Poverty Headcount Rate ($3.65)
A102: Poverty Headcount Rate ($6.85)
A119: Agrifood System Jobs (incl. subsistence farming and informal sector)
A137: Agricultural Jobs (incl. subsistence farming and informal sector)
A154: Agricultural Greenhouse Gas (GHG) Emissions

Sheet 1.Food_security
C1: FS Indicators
A2: VH | B2: 5 | D2: LAC | E2: CWANA | F2: WCA | G2: ESA | H2: SA | I2: SEA
A3: H | B3: 4 | C3: Total score by column | D3: =SUM(D11:D49) -> 34 | E3: =SUM(E11:E49) -> 34 | F3: =SUM(F11:F49) -> 41 | G3: =SUM(G11:G49) -> 41 | H3: =SUM(H11:H49) -> 48 | I3: =SUM(I11:I49) -> 34
A4: MH | B4: 3 | C4: VH count by column | D4: =COUNTIF(D$11:D$49, 5) -> 0 | E4: =COUNTIF(E$11:E$49, 5) -> 0 | F4: =COUNTIF(F$11:F$49, 5) -> 0 | G4: =COUNTIF(G$11:G$49, 5) -> 0 | H4: =COUNTIF(H$11:H$49, 5) -> 3 | I4: =COUNTIF(I$11:I$49, 5) -> 0
A5: M | B5: 2 | C5: H count by column | D5: =COUNTIF(D$11:D$49, 4) -> 3 | E5: =COUNTIF(E$11:E$49, 4) -> 3 | F5: =COUNTIF(F$11:F$49, 4) -> 3 | G5: =COUNTIF(G$11:G$49, 4) -> 3 | H5: =COUNTIF(H$11:H$49, 4) -> 3 | I5: =COUNTIF(I$11:I$49, 4) -> 3
A6: L | B6: 1 | C6: MH count by column | D6: =COUNTIF(D$11:D$49, 3) -> 3 | E6: =COUNTIF(E$11:E$49, 3) -> 3 | F6: =COUNTIF(F$11:F$49, 3) -> 6 | G6: =COUNTIF(G$11:G$49, 3) -> 6 | H6: =COUNTIF(H$11:H$49, 3) -> 4 | I6: =COUNTIF(I$11:I$49, 3) -> 3
C7: M count by column | D7: =COUNTIF(D$11:D$49, 2) -> 4 | E7: =COUNTIF(E$11:E$49, 2) -> 4 | F7: =COUNTIF(F$11:F$49, 2) -> 5 | G7: =COUNTIF(G$11:G$49, 2) -> 5 | H7: =COUNTIF(H$11:H$49, 2) -> 4 | I7: =COUNTIF(I$11:I$49, 2) -> 4
C8: L count by column | D8: =COUNTIF(D$11:D$49, 1) -> 5 | E8: =COUNTIF(E$11:E$49, 1) -> 5 | F8: =COUNTIF(F$11:F$49, 1) -> 1 | G8: =COUNTIF(G$11:G$49, 1) -> 1 | H8: =COUNTIF(H$11:H$49, 1) -> 1 | I8: =COUNTIF(I$11:I$49, 1) -> 5 | K8: Current state (across the Global South) | L8: Ideal state (across the Global South) | M8: Assumptions (for region-specific scores) | N8: Requirements for success (internal to P/A) | O8: Requirements for success (from other P/As) | P8: Regional Implication
C10: HLO | D10: LAC | E10: CWANA | F10: WCA | G10: ESA | H10: SA | I10: SEA
A11: HLO count: | B11: =COUNTA(C11:C49) -> 15 | C11: =HLOs!D8 -> HLO 1.1.1: Demand signaling | D11: 4 | E11: 4 | F11: 4 | G11: 4 | H11: 5 | I11: 4 | K11: Existing demand signaling systems for food security are fragmented, poorly institutionalized, and largely reactive. Most mechanisms operate in silos—within projects or national programs—without a coordinated structure to capture or aggregate regional scaling needs. As a result, innovation and investment decisions often lack grounding in localized food insecurity drivers or emergent farmer and market demands (FAO, 2021; Wigboldus et al., 2016). | L11: Integrated, anticipatory demand signaling systems that are regionally coordinated, data-informed, and driven by farmer and market needs. These systems enable continuous identification and prioritization of innovations based on evolving food security challenges and scaling opportunities. They combine participatory inputs with digital infrastructure and foresight tools to guide investment and policy decisions across CGIAR and national systems (FAO & WEF, 2022). | M11: Higher regional scores indicate weak or absent mechanisms to systematically capture and prioritize local innovation and scaling demands related to food security. This includes the absence of interoperable data systems, low institutional capacity to aggregate grassroots needs, and limited coordination among research, policy, and implementation actors (Gálvez, 2022; CGIAR, 2023; Schut et al., 2024). | N11: Within CGIAR, success requires the development and institutionalization of participatory platforms that enable systematic capture of farmer, partner, and market signals across geographies. This must be coupled with the integration of real-time, interoperable data systems across Initiatives and Centers to ensure that regional scaling demands are continuously monitored, shared, and fed into research prioritization and innovation pipelines (CGIAR GENDER Impact Platform, 2023). | O11: Collaborate with ministries, ICT actors, and farmer groups to design and maintain real-time, inclusive platforms for demand articulation and foresight analytics (FAO & ITU, 2022). National research agencies and digital service providers must be engaged to operationalize subnational data layers and innovation targeting. | P11: SA and ESA scored highest for this HLO (Table 1), indicating strong relevance due to persistent food insecurity and undernutrition alongside weak regional innovation targeting. WCA also showed moderate priority. Investment in structured demand articulation systems—including digital tools and participatory platforms—is critical in these regions to align CGIAR innovation pipelines with ground-level needs and reduce misallocation of scaling efforts.
A12: Sets of 5: | B12: =_xlfn.FLOOR.MATH(B11/5) -> 3 | C12: =HLOs!D9 -> HLO 1.1.2: Feedback and adaptive research and scaling prioritization | D12: 3 | E12: 3 | F12: 3 | G12: 3 | H12: 4 | I12: 3 | K12: Feedback loops between agricultural research and the realities of farmers, markets, and local food systems remain weak, slow, and inconsistently applied. While some CGIAR Initiatives integrate field-based learning into research prioritization, these practices are not systematically institutionalized across regions. Most mechanisms rely on end-of-project evaluations or disconnected surveys, lacking real-time learning channels that could dynamically inform research pipelines and scaling priorities. This delay undermines the adaptability and local relevance of food system innovations (World Bank, 2020). | L12: Well-functioning, iterative feedback systems are embedded within CGIAR’s research and scaling processes. These systems capture insights from field implementation, extension networks, farmer groups, and partners in real time, and use them to continuously update research priorities and refine scaling strategies. The ideal state enables two-way learning—between science and practice—grounded in region-specific food security challenges. (Pingali & Aiyar, 2022). | M12: Higher scores reflect the need to institutionalize adaptive research systems, especially in WCA and ESA, where informal feedback channels are not supported by digital tools or policy linkages. SA shows early progress due to established CGIAR presence and stronger research-extension interfaces. Assumes real-time feedback is essential to prevent mismatched innovations and improve scale-readiness (Gálvez, 2022; CGIAR, 2023; Schut et al., 2024). | N12: Institutionalize real-time, adaptive monitoring and learning (MEL) systems across CGIAR research-for-development projects. These should include structured feedback loops, scaling readiness indicators, and dynamic dashboards. Support capacity building of researchers and MEL staff in adaptive management (Douthwaite & Hoffecker, 2017). | O12: Build partnerships with national extension systems, cooperatives, and innovation intermediaries that can relay implementation-level data and enable rapid adjustment of CGIAR’s scaling approaches. Align feedback systems with government M&E platforms to enhance uptake of recommendations (Anderson et al., 2020). | P12: SA, ESA, and WCA scored highest for this HLO, reflecting the urgency to embed feedback loops into innovation scaling. While SA demonstrates relative progress, ESA and WCA face significant feedback fragmentation and limited responsiveness. These regions require support to establish digital feedback infrastructure and partnerships that enable dynamic prioritization and realignment of scaling pipelines with localized food security conditions.
A13: Remainder: | B13: =MOD(B11,5) -> 0 | C13: =HLOs!D10 -> HLO 1.1.3: Enhance strategies and coordination | D13: 2 | E13: 2 | F13: 3 | G13: 3 | H13: 3 | I13: 2 | K13: While numerous food security strategies exist at national and regional levels, coordination across actors—government agencies, CGIAR centers, donors, NGOs, and private sector—is often weak or inconsistent. Many initiatives operate in parallel, resulting in duplication of efforts, fragmented resource use, and reduced impact. Strategic planning tends to be top-down and project-driven, rather than co-developed across systems. Sectoral silos—between agriculture, health, nutrition, and climate—further hinder integrated responses to food insecurity (OECD, 2021). | L13: A coherent, multi-actor strategic framework exists to guide system-level food security transformation through aligned priorities, investments, and delivery mechanisms. CGIAR and national actors co-develop and implement strategies that span research, policy, and implementation levels. These are dynamic, learning-oriented, and grounded in cross-sector coordination, fostering joint ownership across stakeholders (HLPE, 2020). | M13: High scores in SA and WCA indicate weak institutional coordination, where overlapping mandates and under-resourced coordination platforms limit integrated strategy implementation. ESA faces similar challenges. It is assumed that addressing fragmentation will improve program effectiveness and enable alignment between food production, access, and nutrition goals (FAO, 2022). | N13: CGIAR must co-develop cross-Initiative strategies with clear alignment mechanisms, shared performance metrics, and learning loops. Strengthen internal convening roles at regional levels to ensure unified delivery on food security objectives across Centers and Initiatives (CGIAR, 2022). | O13: National governments and regional organizations should activate or strengthen formal coordination platforms that bring together agriculture, health, climate, and food security stakeholders. Development partners must align their support with nationally led strategies and invest in joint planning, reviews, and accountability mechanisms (UNESCAP, 2023). | P13: SA and WCA are top priorities, with ESA also requiring action. These regions exhibit fragmented institutional ecosystems, limiting joint planning and delivery. Strengthening coordination mechanisms—both within CGIAR and externally—is vital for scaling food security innovations. Joint strategy development, inter-agency taskforces, and harmonized investment frameworks can help bridge current silos and amplify system-wide outcomes.
A14: Max score: | B14: =(B12*SUM($B$2:$B$6))+IF(B11=0,0,SUM($B$2:INDEX(B:B,$B$13+1))) -> 50 | C14: =HLOs!D11 -> HLO 2.2.1: Innovation networks enhance agrifood system solution scaling | D14: 1 | E14: 1 | F14: 1 | G14: 1 | H14: 1 | I14: 1 | K14: Innovation networks in the agrifood sector remain underdeveloped across most regions, especially where institutional and private sector capacity is limited. Existing linkages between CGIAR and local actors—such as farmer organizations, ag-tech startups, and extension agencies—are fragmented and project-dependent. Platforms intended to support innovation co-creation often lack sustainability, funding, and inclusion of market actors. As a result, promising food security solutions remain isolated and poorly scaled (Davis et al., 2023). | L14: A dynamic and inclusive innovation ecosystem exists in which CGIAR, national research systems, local innovators, and private sector actors collaborate to co-develop and scale food system solutions. These networks are supported by dedicated hubs, digital platforms, and financing mechanisms that enable rapid piloting, feedback, and adaptation. Innovation networks operate not only within countries but also across borders to respond to region-specific food security challenges (World Bank, 2024). | M14: Although innovation networks across regions remain weak, the uniformly low scores for this HLO in the KBP exercise suggest that—relative to other Food Security HLOs—this area currently offers limited strategic leverage for near-term scaling. It is assumed that strengthening networks without parallel improvements in demand signaling, bundling, and enabling policy environments will not deliver substantial short-term returns (Gálvez, 2022; CGIAR, 2023; Schut et al., 2024). | N14: CGIAR should prioritize foundational efforts such as mapping innovation actors, identifying coordination gaps, and building early-stage partnerships across Initiatives and Centers. A lean, learning-oriented approach that emphasizes institutional readiness, ecosystem diagnostics, and piloting innovation brokerage mechanisms is appropriate at this stage (van Rijn et al., 2020). | O14: Externally, CGIAR should selectively engage with innovation intermediaries, incubators, and regional platforms that are already facilitating agricultural innovation. Rather than creating new structures, partnerships should reinforce existing national systems and support inclusive participation by farmer groups, women, and youth innovators (FAO, 2021). | P14: This HLO received the lowest prioritization across all regions in the KBP. While SA, ESA, and WCA face weak innovation ecosystems, other HLOs—such as demand signaling and bundling—are more urgent entry points for food security scaling. In these regions, innovation network investments should remain exploratory and diagnostic, preparing the ground for deeper engagement once enabling conditions are strengthened.
C15: =HLOs!D12 -> HLO 2.2.2: Methods evaluating agrifood system solutions for scale | D15: 1 | E15: 1 | F15: 2 | G15: 2 | H15: 2 | I15: 1 | K15: Evaluation methods used to assess the scalability of agrifood system innovations are largely ad hoc, inconsistent across programs, and often introduced only at the end of the project cycle. There is limited use of prospective tools or metrics that assess whether innovations are socially, economically, and institutionally scalable in diverse contexts. This results in missed opportunities to adapt innovations early or avoid scaling solutions that lack contextual fit or stakeholder ownership (Rogers et al., 2021). | L15: A robust and standardized suite of methods is available and routinely used across CGIAR programs to assess the scalability of agrifood innovations. These methods are applied early and iteratively throughout the innovation and scaling process, incorporating system dynamics, contextual fit, stakeholder engagement, and long-term sustainability considerations. Scalability assessments are embedded within CGIAR’s adaptive management frameworks, enabling more effective decision-making on investment and scale-out (Wigboldus, 2018). | M15: The KBP results indicate that SA and ESA have begun to apply basic scalability diagnostics, but institutional uptake remains partial and uncoordinated. In contrast, WCA and SEA lag behind due to limited evaluation capacity and disconnected research and scaling teams. Scores reflect both demand for improved methods and current institutional gaps (Gálvez, 2022; CGIAR, 2023; Schut et al., 2024). | N15: Internally, CGIAR must develop and institutionalize evaluation toolkits for scaling, integrated into project design and MEL systems. Capacity development is needed for research teams and MELIA specialists to use these tools and feed insights into adaptive decision-making. Tools should be designed for both formative and summative evaluation stages (Glover et al., 2019). | O15: Externally, CGIAR should partner with academic institutions, think tanks, and independent evaluators to validate methods and support uptake. Public and private sector stakeholders must be trained to interpret scalability assessments and apply them in investment decisions. Donor alignment with evidence-based scaling frameworks will be critical (IFPRI, 2023). | P15: SA, ESA, and WCA show high alignment with this HLO and should be prioritized for the rollout of new methods. These regions face intense pressure to deliver scalable solutions to food insecurity, and improved evaluation will enhance targeting, efficiency, and equity of CGIAR innovation portfolios. Investment in these regions will improve scale-readiness and support systemic learning.
C16: =HLOs!D13 -> HLO 2.2.3: Scale-ready agrifood system solution bundles and packages | D16: 3 | E16: 3 | F16: 3 | G16: 3 | H16: 4 | I16: 3 | K16: Agrifood system innovations are often delivered in isolation—such as improved seed varieties, digital tools, or training modules—rather than as cohesive, mutually reinforcing packages. Where bundling exists, it tends to be inconsistent, poorly contextualized, and disconnected from farmer realities or market ecosystems. This undermines scalability and sustainability, as individual components often fail without complementary inputs like finance, policy support, or behavior change strategies (Herrero et al., 2021). | L16: Integrated, locally adapted innovation bundles that respond to farmer typologies and agroecological contexts, combining technological, institutional, and service innovations. These bundles are co-developed with users and market actors and aligned with delivery systems to ensure adoption at scale. CGIAR Initiatives and national partners share tools and processes for bundling that reflect local realities and system interdependencies (Gálvez, 2022; CGIAR, 2023; Schut et al., 2024). | M16: High prioritization scores for this HLO in SA, ESA, and WCA reflect critical gaps in integrated delivery of solutions. It is assumed that while multiple innovations are being promoted, their lack of contextual bundling hinders adoption and sustained use. The need for bundling is particularly high in SA, where input-output-market linkages remain fragmented, and in ESA and WCA, where capacity to package innovations with services and policy support is limited (FAO, 2022). | N16: CGIAR must develop bundling protocols across Initiatives, ensuring that research outputs are integrated into locally adapted solution packages. This includes working across themes (e.g., seed systems, digital, finance) and aligning bundling with agroecological and livelihood typologies. Initiatives should pilot and refine bundled approaches in diverse contexts, using feedback from users to iterate on content and delivery (HLPE, 2020). | O16: Collaborations with private sector actors, cooperatives, NGOs, and government extension services are essential to co-design, deliver, and refine bundled packages. These actors bring insights into user preferences, cost structures, and delivery logistics. Market incentives and policy support mechanisms (e.g., subsidies or extension platforms) must be aligned to encourage bundle uptake (Anderson et al., 2020). | P16: SA, ESA, and WCA are high-priority regions for bundling due to their diverse production systems, high levels of input-output fragmentation, and limited adoption of standalone innovations. Bundling offers an efficient entry point to improve food security outcomes by aligning technical solutions with farmers’ contextual realities. Investments in these regions should prioritize co-design of bundles with farmers and integration into broader delivery systems.
C17: =HLOs!D14 -> HLO 2.2.4: Agrifood system solution scaling strategies | D17: 4 | E17: 4 | F17: 4 | G17: 4 | H17: 5 | I17: 4 | K17: Current scaling efforts are fragmented, project-driven, and rarely embedded within national or regional food system transformation strategies. CGIAR programs often lack long-term, system-level scaling pathways. Where strategies exist, they tend to focus on technology dissemination rather than system integration or sustainability. Weak linkages between scaling efforts and enabling policy, institutional, and market frameworks limit impact (Wigboldus, 2018). | L17: Systemic, forward-looking scaling strategies are developed and institutionalized across CGIAR and partner ecosystems. These strategies embed innovation scaling within broader food system transformation pathways, integrate enabling environment analysis, and include flexible, evidence-based scaling pathways. They emphasize sustainability, equity, and adaptive learning to respond to dynamic regional contexts (Gálvez, 2022; CGIAR, 2023; Schut et al., 2024). | M17: High prioritization in SA, ESA, and WCA reflects the recognized need to move beyond piecemeal scaling approaches and institutionalize systemic strategies. It is assumed that while pilot models and successful innovations exist in these regions, their scaling potential remains underutilized due to lack of strategic guidance and system-wide engagement. Cross-initiative coordination and long-term visioning are especially limited (FAO, 2022). | N17: CGIAR must embed scaling strategies as a core design and planning component across all Initiatives, linked to innovation pipelines, MEL systems, and policy engagement. Internal success requires clear accountability for scaling within research teams, the use of scenario-based foresight, and the establishment of cross-Initiative coordination units to harmonize scaling pathways. CGIAR must also invest in internal capacity development for scaling strategy design and systems thinking (Woltering et al., 2019). | O17: Scaling strategies must be co-developed with governments, funders, private sector actors, and civil society to ensure alignment with national food security priorities and development plans. Success requires enabling policy frameworks, long-term financing, and programmatic integration with national delivery systems. Multi-stakeholder governance platforms and regional development actors (e.g., RECs, IFIs) play a critical role in anchoring strategies (World Bank, 2024). | P17: SA, ESA, and WCA are high-priority regions for institutionalizing food system scaling strategies. These regions host numerous fragmented scaling efforts that, if strategically aligned, could drive significant food security gains. Support should focus on scaling diagnostics, co-creation of long-term scaling roadmaps, and embedding these within national food system transformation agendas. Institutionalization of scaling strategy frameworks is essential to achieve coherence and sustained impact in these contexts.
C18: =HLOs!D15 -> HLO 3.3.1: Enabling environment diagnostics | D18: 2 | E18: 2 | F18: 3 | G18: 3 | H18: 3 | I18: 2 | K18: Diagnostics that assess the readiness of policy, institutional, financial, and regulatory environments to support innovation scaling are sparse, sporadic, and often disconnected from program cycles. In many CGIAR programs, barriers to scaling—such as land tenure issues, weak extension systems, or policy misalignment—are acknowledged late or not addressed systematically, resulting in ineffective or unsustainable scaling (World Bank, 2020). | L18: Institutionalized, evidence-based diagnostic frameworks are embedded into the design and implementation of CGIAR and national programs. These diagnostics regularly assess enabling and disabling factors for scaling across institutions, policy regimes, and markets. They are implemented collaboratively with national actors and feed directly into program adaptation, investment planning, and policy dialogue (FAO & WEF, 2022). | M18: SA and SEA received relatively higher priority scores, reflecting urgent gaps in systematic diagnostics to identify institutional and policy bottlenecks. It is assumed that while enabling conditions are often known anecdotally, structured diagnostics—such as political economy analyses or delivery readiness assessments—remain underutilized. WCA also requires strengthening, though data systems and coordination mechanisms are weaker (Gálvez, 2022; CGIAR, 2023; Schut et al., 2024). | N18: Within CGIAR, success requires the mainstreaming of diagnostic tools that assess system readiness across initiatives. These tools must be integrated into programmatic design templates, MEL frameworks, and ex-ante investment appraisal systems. Capacity development is needed across centers to apply political economy, regulatory, and institutional diagnostics, and ensure learning is used to inform scaling strategies (Woltering et al., 2019). | O18: Governments, regional institutions, and donors must commit to using diagnostic evidence to inform food security programming. This includes supporting integrated data systems, incentivizing joint problem analysis across sectors, and aligning diagnostic outputs with national investment planning and reform processes. Platforms for cross-country learning and technical support will help scale diagnostic use (HLPE, 2020). | P18: SA and SEA are priority regions where targeted diagnostic strengthening can improve the strategic focus and coherence of food security investments. These regions require structured tools to identify why certain innovations fail to scale, and to guide reforms in land, extension, subsidy, or institutional frameworks. WCA also merits diagnostic support to overcome governance and coordination barriers. Investments should focus on scaling-relevant diagnostics embedded early in the innovation cycle.
C19: =HLOs!D16 -> HLO 3.3.2: Scaling support services for enabling environments and institutions | D19: 3 | E19: 3 | F19: 3 | G19: 3 | H19: 4 | I19: 3 | K19: Services critical to scaling—such as access to finance, mechanization, technical support, insurance, and digital advisory systems—remain fragmented and uneven across regions. Many CGIAR-aligned innovations are delivered without the ecosystem of services needed for sustained uptake, especially in under-resourced regions. Current efforts often rely on short-term pilots or isolated delivery models, limiting their ability to support wide-scale adoption of food security solutions (FAO, 2022). | L19: A supportive service ecosystem is in place, with bundled offerings—including financial products, capacity development, digital advisory services, and technical assistance—available at scale and aligned with the innovation needs of food-insecure populations. These services are regionally anchored, delivered through public-private partnerships, and designed with inclusivity and affordability in mind (IFPRI, 2023). | M19: Higher regional scores in SA and ESA reflect urgent needs to develop service ecosystems that can enable large-scale deployment of food security innovations. It is assumed that in these regions, fragmented service delivery, limited rural finance penetration, and weak capacity among public extension and private actors continue to constrain scaling. WCA also demonstrates high need, but the ecosystem remains more nascent and resource-constrained (Gálvez, 2022; CGIAR, 2023; Schut et al., 2024). | N19: CGIAR must work across Initiatives to identify critical service bottlenecks tied to innovation adoption. Internal success depends on embedding service gap assessments into scaling diagnostics, piloting bundled support models, and developing tools to monitor service performance. Collaboration between research, scaling, and MELIA teams is essential to co-design scalable service delivery mechanisms adapted to different geographies (Anderson et al., 2020). | O19: CGIAR must partner with public extension, rural finance institutions, agribusinesses, and service provider networks to deliver bundled services that respond to scaling needs. Support is also needed from ministries and donors to build enabling policies (e.g., service delivery subsidies, performance-based contracts) and invest in last-mile infrastructure and service platforms (IFAD, 2019; FAO, 2022). | P19: SA and ESA are high-priority regions for this HLO, where immediate investments in service ecosystems can unlock scaling for food security innovations. WCA also presents opportunities for long-term systems development. Strategic focus should be placed on supporting inclusive, decentralized service delivery models that integrate finance, input access, and advisory tools. These efforts are critical to ensuring adoption beyond early adopters and building sustainable market ecosystems around CGIAR innovations.
C20: =HLOs!D17 -> HLO 3.3.3: Science-policy partnership interfaces for responsible scaling | D20: 1 | E20: 1 | F20: 2 | G20: 2 | H20: 2 | I20: 1 | K20: Science-policy platforms related to food security remain fragmented, underfunded, or ad hoc across most CGIAR regions. Many CGIAR initiatives engage with policymakers episodically or during proposal or dissemination phases, rather than embedding science-policy dialogue throughout research and scaling cycles. As a result, evidence uptake into national food system policies is often inconsistent, and co-creation of scaling pathways with policy actors is rare (Diao et al., 2023). | L20: Institutionalized, trusted science-policy interfaces exist across regions, facilitating continuous and reciprocal engagement between researchers, policymakers, and implementers. These platforms integrate CGIAR-generated evidence into national food security agendas and enable policy co-design, feedback loops, and mutual accountability mechanisms. Interfaces are inclusive, transparent, and aligned with both research priorities and development goals (FAO & WEF, 2022). | M20: Low prioritization scores for this HLO in SA, WCA, and especially SEA and CWANA reflect a current lack of structured and impactful science-policy engagement mechanisms. It is assumed that weak institutional linkages, limited political economy analysis capacity, and siloed communication approaches contribute to low uptake of CGIAR innovations into policy. High food insecurity does not always translate into strong evidence-informed policy processes (Gálvez, 2022; CGIAR, 2023; Schut et al., 2024). | N20: CGIAR must invest in building internal capacity for policy engagement—through staff training in political economy analysis, policy communication, and co-creation processes. Each Initiative should establish dedicated policy engagement strategies aligned with national and regional scaling goals. Stronger integration of policy research and implementation science within innovation portfolios is also critical (Douthwaite & Hoffecker, 2017). | O20: National governments and regional organizations must create formal policy platforms that allow for regular engagement with research actors. CGIAR can play a convening role but must also collaborate with think tanks, universities, and regional networks to ensure legitimacy and local ownership. Donor support is essential to fund long-term policy dialogue processes rather than one-off consultations (OECD, 2021). | P20: Despite strong food security challenges in SA and WCA, this HLO remains low priority due to the absence of sustained science-policy platforms. SEA and CWANA lag further in institutional readiness and CGIAR engagement history. Efforts in these regions should focus on building the foundations for trusted interfaces—through long-term partnerships, evidence synthesis platforms, and capacity sharing with national planning agencies. Investments here will have long-term payoffs in scaling legitimacy and policy alignment.
C21: =HLOs!D18 -> HLO 4.4.1: CGIAR Expertise and Solutions Embedded in Development Investments and Partnerships | D21: 4 | E21: 4 | F21: 4 | G21: 4 | H21: 5 | I21: 4 | K21: CGIAR-generated innovations are not systematically embedded in large-scale national food security investments. Collaborations with public investment programs and IFIs (e.g., WB, IFAD) are often limited to short-term projects or technical support roles. This limits the opportunity for CGIAR solutions to inform national priorities and investment pipelines. Moreover, partnerships tend to be fragmented, non-institutionalized, and dependent on personal networks or donor mandates (Gálvez, 2022; CGIAR, 2023; Schut et al., 2024). | L21: CGIAR operates as a strategic technical partner embedded within national agricultural and food security investment platforms. Its innovations are systematically integrated into program design, implementation, and M&E frameworks of public investments supported by IFIs, development banks, and national budgets. Long-term partnerships with government agencies and key funders are formalized, enabling scale-aligned delivery and policy coherence (World Bank, 2020; FAO, 2022). | M21: High prioritization scores for this HLO in SA and ESA reflect both the severity of food insecurity and the strategic relevance of linking research to investment systems. It is assumed that SA and ESA have significant volumes of ongoing or planned public and IFI-supported investments that CGIAR could influence. However, success depends on CGIAR's ability to move from project-driven engagement to long-term partnership and advisory roles (Gálvez, 2022; CGIAR, 2023; Schut et al., 2024). | N21: CGIAR must strengthen internal capacity for strategic engagement with IFIs and government investment programs. This includes identifying “integration entry points” in national investment plans, building staff capacity in programmatic alignment, and developing value propositions that highlight CGIAR's role in risk reduction, innovation, and results delivery. Establishing dedicated partnership units within Initiatives will be key (IFPRI, 2023; Davis et al., 2023). | O21: Governments and development partners must formally invite CGIAR as a knowledge and implementation partner in investment programs. This requires political will, coordination across ministries, and commitment from donors to support long-term institutional partnerships. IFIs must also recognize the value of embedding CGIAR innovations into lending operations and country strategy support frameworks (FAO, 2022; UNESCAP, 2023). | P21: SA and ESA are high-priority regions for this HLO due to the convergence of food insecurity, large-scale public investments, and CGIAR presence. In these regions, strengthening partnerships with IFIs and ministries of agriculture can rapidly expand the reach of CGIAR innovations. WCA also presents emerging opportunities through donor-funded food system recovery initiatives. Prioritization should focus on embedding CGIAR roles within major programs through formal agreements, technical advisory platforms, and co-developed investment pipelines.
C22: =HLOs!D19 -> HLO 4.4.2: Innovation portfolio management and scaling strategy support teams | D22: 1 | E22: 1 | F22: 2 | G22: 2 | H22: 2 | I22: 1 | K22: Dedicated hubs or platforms that coordinate scaling activities across CGIAR programs are currently nascent or fragmented. Most scaling support is project-based, with limited institutional memory or continuity across countries or initiatives. Few mechanisms exist to capture, synthesize, and repurpose learning on scaling across geographies or impact areas, limiting consistency and synergy in delivery (Gálvez, 2022; CGIAR, 2023; Schut et al., 2024). | L22: Institutionalized regional or country-level hubs function as coordination points to support scaling efforts across CGIAR Initiatives and national partners. These hubs provide technical assistance, curate scaling evidence, broker partnerships, and align innovation portfolios with country food security priorities. They serve as the operational backbone for scaling pathways across systems (World Bank, 2024). | M22: The relatively low scores for this HLO across regions reflect the emergent nature of scaling hubs and the limited demonstration of their added value to date. It is assumed that CGIAR centers and national systems have yet to establish strong, sustained infrastructure to manage cross-Initiative scaling functions. Scaling hubs are seen as necessary but not yet mission-critical compared to direct investment, bundling, or policy alignment (Gálvez, 2022; CGIAR, 2023; Schut et al., 2024). | N22: CGIAR must pilot and institutionalize flexible, multi-functional hubs that offer services such as scaling diagnostics, capacity development, monitoring, and partnership facilitation. These hubs should be co-hosted with national institutions where possible and anchored in country delivery strategies. Internal coordination mechanisms must ensure that hubs serve multiple Initiatives and create coherence in scaling approaches (HLPE, 2020). | O22: External success depends on national governments recognizing the value of scaling hubs and allocating institutional support (e.g., secondments, funding, or policy mandates). Development partners and IFIs must be engaged as co-investors and users of scaling support services. Regional platforms (e.g., SAARC, AUC) can legitimize hubs and connect them to broader development architecture (IFAD, 2021). | P22: Despite current low prioritization, SA, ESA, and SEA would benefit from piloting CGIAR-aligned scaling hubs to address fragmented delivery and learning across initiatives. In SA and ESA in particular, the hubs could anchor national innovation strategies and strengthen institutional interfaces between research, policy, and practice. These regions offer opportunities for hub co-location with national agricultural innovation systems to enhance sustainability and local ownership.
C23: =HLOs!D20 -> HLO 5.5.1: Enhancing scaling science for societal impact | D23: 2 | E23: 2 | F23: 2 | G23: 2 | H23: 3 | I23: 2 | K23: Scaling science within CGIAR remains underdeveloped, with limited institutional capacities to assess, document, and apply scaling theories and evidence systematically. Tools for learning and decision-making are scattered, and structured exchange mechanisms—especially South-South learning—are rare or ad hoc. These gaps constrain CGIAR’s ability to build a global evidence base and adapt innovations to diverse food system contexts (Wigboldus, 2018; Woltering et al., 2019; IFAD, 2021). | L23: Scaling science is embedded in CGIAR’s operating model and supported by institutionalized toolkits, adaptive learning loops, and resourced capacities for research on scaling. Programs systematically assess scaling readiness and outcomes, share evidence across contexts, and engage in structured South-South learning platforms that support innovation transfer and equitable outcomes. This HLO connects research rigor with real-world implementation at scale (FAO & WEF, 2022; CGIAR, 2023). | M23: Low scores across regions reflect limited uptake and institutional investment in scaling science relative to other food security HLOs. While SA and SEA show slightly higher readiness—due to ongoing innovation exchanges and scaling partnerships—the overall maturity of scaling science is low. It is assumed that without internal incentives and dedicated funding, uptake of scaling science tools and methods will remain marginal (Gálvez, 2022; CGIAR, 2023; Schut et al., 2024). | N23: CGIAR must invest in core capacities for scaling science, including methodologies to assess scaling potential, track enabling conditions, and document lessons. Research teams should be trained in adaptive management and learning approaches. Programs must also establish platforms for structured cross-country exchanges to transfer learning, build capacity, and foster South-South partnerships. An integrated research-for-scaling agenda should be embedded into CGIAR’s innovation pipeline (Pingali & Aiyar, 2022; HLPE, 2020). | O23: External success requires aligning with regional knowledge platforms, universities, and South-South cooperation mechanisms (e.g., ASEAN, SAARC, African Union) to institutionalize learning exchanges and amplify locally generated insights. Donors and IFIs must fund scaling science as a public good. CGIAR should also work with independent evaluators and data science networks to improve analytics, transparency, and decision support (World Bank, 2024; IFAD, 2021). | P23: While scaling science is currently underdeveloped, SA and SEA represent priority regions due to ongoing innovation exchanges and emerging learning platforms. These regions also host CGIAR programs with strong national partnerships, making them ideal for piloting South-South scaling platforms. In WCA and ESA, foundational investments in analytics, evaluation, and regional learning will be needed to enhance future readiness for scaling science. Strategic support in these regions can ensure that equity and context-specific learning inform scaling decisions.
C24: =HLOs!D21 -> HLO 5.5.2: Insights for CGIAR scaling success through impact assessments | D24: 2 | E24: 2 | F24: 3 | G24: 3 | H24: 3 | I24: 2 | K24: CGIAR programs rarely conduct scaling-focused impact assessments. When evaluations occur, they typically emphasize outputs (e.g., reach) or intermediate outcomes without systematically analyzing what enables or constrains innovation uptake at scale. As a result, scaling efforts often lack a strong empirical foundation for learning and course correction. Evaluations remain disconnected from strategic decision-making in most Initiatives (Rogers et al., 2021). | L24: CGIAR routinely conducts high-quality, scaling-specific impact assessments that generate actionable insights for program improvement, strategic investment, and policy dialogue. Assessments go beyond attribution to explore contribution, contextual drivers, scaling enablers, and risks. Findings are used to refine innovation portfolios and guide scaling pathways, fostering a learning culture across the system (IFPRI, 2023). | M24: Regional scores reflect that while impact assessments are widely recognized as important, they are underutilized in most regions. SA and ESA have the greatest needs and opportunities for scaling impact evaluations due to large-scale programs and food insecurity burdens. It is assumed that capacity gaps, limited MEL integration, and lack of donor incentives hinder broader uptake, especially in WCA and SEA (Gálvez, 2022; CGIAR, 2023; Schut et al., 2024). | N24: CGIAR needs to institutionalize scaling impact assessment as a standard function within research and innovation programs. This includes dedicated resources, staff with impact evaluation expertise, and methodological guidance on contribution analysis, systems modeling, and participatory assessment. MEL systems should integrate learning loops that allow findings to influence innovation portfolio management (Douthwaite & Hoffecker, 2017). | O24: CGIAR must collaborate with evaluation partners, donors, and national systems to co-design contextually relevant assessment strategies. Independent evaluation bodies and platforms like 3ie should be engaged for credibility and cross-learning. Governments and donors need to value scaling impact insights as public goods and embed them in funding conditionalities or policy dialogue (3ie, 2022; World Bank, 2024). | P24: SA and ESA are high-priority regions for scaling-focused impact assessments due to their food insecurity burdens and active CGIAR engagement. WCA also warrants investment in evaluation systems, though current institutional capacities are weaker. Prioritized impact assessments in these regions can guide scaling decisions, foster accountability, and enhance learning, especially where large-scale investments or vulnerable populations are involved. Scaling success will depend on building a robust evidence base for what works—and why—in complex food system contexts.
C25: =HLOs!D22 -> HLO 5.5.3: Custom analytics for managing innovation portfolios and decision-making | D25: 1 | E25: 1 | F25: 2 | G25: 2 | H25: 2 | I25: 1 | K25: Decision-making around innovation scaling in CGIAR remains heavily reliant on qualitative judgment and experience-based learning. While some dashboards and data platforms exist, they are fragmented and not integrated into portfolio design or resource allocation processes. Most Centers lack analytics that connect real-time data with scenario planning, risk analysis, or prioritization of scaling opportunities (World Bank, 2024). | L25: CGIAR employs dynamic, data-driven portfolio management tools that support real-time decision-making across regions and impact areas. These tools use machine learning, systems modeling, and multi-criteria decision analysis to evaluate trade-offs, optimize innovation mixes, and respond to contextual shifts. Analytics are embedded in governance structures and tied to research and scaling performance (FAO, 2022). | M25: Scores for this HLO are low across regions, including SA, SEA, and ESA, suggesting that despite recognition of the value of advanced analytics, this area remains underdeveloped and underprioritized. It is assumed that weak data systems, siloed information, and limited institutional capacity for applied data science hinder uptake. In many regions, analytics is not yet seen as a critical enabler for strategic scaling (Gálvez, 2022; CGIAR, 2023; Schut et al., 2024). | N25: CGIAR must strengthen its internal capacity for data science and analytics, building interdisciplinary teams that can bridge research, MEL, and portfolio management. A shared suite of tools—co-developed with users—should be developed to support real-time performance tracking, predictive modeling, and resource allocation across Initiatives. Data interoperability across Centers is essential, alongside clearer guidance on how to use analytics in decision-making (Anderson et al., 2020). | O25: CGIAR should partner with external data science institutions, tech firms, and innovation analytics platforms to co-create tools and build capacity. Governments, donors, and regional bodies should be engaged to align CGIAR analytics with broader food system monitoring platforms, ensuring relevance and uptake. Enabling environments that support open data sharing, privacy safeguards, and digital infrastructure are also critical (UNESCAP, 2023). | P25: SA, SEA, and ESA are priority regions for improving innovation analytics due to their complex, data-scarce environments and active CGIAR programming. Despite low current scores, the potential for impact is high if data systems and decision-support tools are systematically developed and embedded. Regional investments should focus on building foundational data infrastructure, integrating MEL with analytics, and demonstrating the value of these tools for adaptive scaling. Early wins in portfolio diagnostics and scenario testing could catalyze wider adoption.

Sheet 2.Poverty_reduction
C1: Poverty Indicators
A2: VH | B2: 5 | D2: LAC | E2: CWANA | F2: WCA | G2: ESA | H2: SA | I2: SEA
A3: H | B3: 4 | C3: total score by column | D3: =SUM(D11:D48) -> 34 | E3: =SUM(E11:E48) -> 34 | F3: =SUM(F11:F48) -> 38 | G3: =SUM(G11:G48) -> 41 | H3: =SUM(H11:H48) -> 45 | I3: =SUM(I11:I48) -> 34
A4: MH | B4: 3 | C4: VH count by column | D4: =COUNTIF(D$11:D$48, 5) -> 0 | E4: =COUNTIF(E$11:E$48, 5) -> 0 | F4: =COUNTIF(F$11:F$48, 5) -> 0 | G4: =COUNTIF(G$11:G$48, 5) -> 0 | H4: =COUNTIF(H$11:H$48, 5) -> 0 | I4: =COUNTIF(I$11:I$48, 5) -> 0
A5: M | B5: 2 | C5: H count by column | D5: =COUNTIF(D$11:D$48, 4) -> 3 | E5: =COUNTIF(E$11:E$48, 4) -> 3 | F5: =COUNTIF(F$11:F$48, 4) -> 3 | G5: =COUNTIF(G$11:G$48, 4) -> 3 | H5: =COUNTIF(H$11:H$48, 4) -> 6 | I5: =COUNTIF(I$11:I$48, 4) -> 3
A6: L | B6: 1 | C6: MH count by column | D6: =COUNTIF(D$11:D$48, 3) -> 3 | E6: =COUNTIF(E$11:E$48, 3) -> 3 | F6: =COUNTIF(F$11:F$48, 3) -> 3 | G6: =COUNTIF(G$11:G$48, 3) -> 6 | H6: =COUNTIF(H$11:H$48, 3) -> 4 | I6: =COUNTIF(I$11:I$48, 3) -> 3
C7: M count by column | D7: =COUNTIF(D$11:D$48, 2) -> 4 | E7: =COUNTIF(E$11:E$48, 2) -> 4 | F7: =COUNTIF(F$11:F$48, 2) -> 8 | G7: =COUNTIF(G$11:G$48, 2) -> 5 | H7: =COUNTIF(H$11:H$48, 2) -> 4 | I7: =COUNTIF(I$11:I$48, 2) -> 4
C8: L count by column | D8: =COUNTIF(D$11:D$48, 1) -> 5 | E8: =COUNTIF(E$11:E$48, 1) -> 5 | F8: =COUNTIF(F$11:F$48, 1) -> 1 | G8: =COUNTIF(G$11:G$48, 1) -> 1 | H8: =COUNTIF(H$11:H$48, 1) -> 1 | I8: =COUNTIF(I$11:I$48, 1) -> 5 | K8: Current state (across the Global South) | L8: Ideal state (across the Global South) | M8: Assumptions (for region-specific scores) | N8: Requirements for success (internal to P/A) | O8: Requirements for success (from other P/As) | P8: Regional Implication
C10: HLO | D10: LAC | E10: CWANA | F10: WCA | G10: ESA | H10: SA | I10: SEA
A11: HLO count: | B11: =COUNTA(C11:C48) -> 15 | C11: =HLOs!D8 -> HLO 1.1.1: Demand signaling | D11: 4 | E11: 4 | F11: 4 | G11: 4 | H11: 4 | I11: 4 | K11: Across CGIAR regions, systems to identify poverty-related innovation and scaling demands remain weak, fragmented, and reactive. Most mechanisms rely on general development planning or donor-led priority setting, with limited articulation of localized poverty dynamics. This leads to a mismatch between scaling strategies and actual poverty reduction needs on the ground (FAO, 2022; Gálvez, 2022; CGIAR, 2023; Schut et al., 2024). | L11: Inclusive and evidence-based demand signaling systems that systematically identify the poverty-related needs of target populations. These systems are grounded in real-time data, community-based diagnostics, and participatory methods, enabling scaling pathways to align with localized drivers of poverty and livelihood insecurity (IFPRI, 2023). | M11: Uniform high priority scores across regions reflect the widespread absence of structured platforms for poverty-focused demand identification. It is assumed that CGIAR and partners currently lack the institutional capacity, data infrastructure, and outreach mechanisms to continuously surface regional poverty reduction priorities (World Bank, 2020). | N11: Within CGIAR, success depends on the development of localized, real-time poverty-oriented demand platforms. These platforms must incorporate participatory poverty diagnostics, social mapping, and community feedback systems to capture unmet needs, especially among vulnerable populations (Pingali & Aiyar, 2022). | O11: External success hinges on strong collaboration with ministries of social development, national poverty alleviation programs, NGOs, and rural grassroots organizations. These actors play a critical role in identifying and communicating place-specific drivers of poverty and in ensuring equitable participation in scaling prioritization (HLPE, 2020). | P11: SA and ESA are high-priority regions due to entrenched poverty, high rural vulnerability, and weak state mechanisms for capturing real-time poverty-related demands. WCA also demonstrates strong alignment, given its low coverage of targeted social programs. CGIAR should focus on building inclusive, digital-enabled poverty signaling systems in these regions to strengthen the relevance and equity of scaling investments.
A12: Sets of 5: | B12: =_xlfn.FLOOR.MATH(B11/5) -> 3 | C12: =HLOs!D9 -> HLO 1.1.2: Feedback and adaptive research and scaling prioritization | D12: 3 | E12: 3 | F12: 3 | G12: 3 | H12: 4 | I12: 3 | K12: Feedback loops linking on-the-ground poverty realities to CGIAR research and scaling agendas remain weak and inconsistent. Most feedback mechanisms rely on periodic assessments or project close-out reviews, which are poorly suited for real-time adaptation. In South Asia, these gaps are particularly pronounced due to complex governance and high rural poverty, although some Initiatives have begun experimenting with iterative learning tools (Anderson et al., 2020). | L12: CGIAR research-for-development programs function as adaptive learning systems, continuously informed by implementation feedback and poverty data. Feedback mechanisms are real-time, decentralized, and embedded within Monitoring, Evaluation, Learning and Impact Assessment (MELIA) systems. They dynamically inform program design, innovation pipelines, and scaling strategies based on localized poverty drivers and stakeholder inputs (Gálvez, 2022; CGIAR, 2023; Schut et al., 2024). | M12: This HLO was prioritized based on region-specific feedback capacity gaps, particularly in SA and ESA. SA’s research infrastructure shows modest readiness for adaptive feedback integration, but struggles with institutional inertia. ESA is marked by weak Monitoring, Evaluation, Learning and Impact Assessment (MELIA) systems and sparse local data, while WCA faces constraints in extension coordination and digital feedback infrastructure. The scores assume these feedback limitations hinder poverty-reduction targeting and responsiveness (FAO, 2022). | N12: CGIAR must strengthen internal MEL architectures to capture timely, disaggregated feedback on poverty-related outcomes. This includes embedding adaptive learning modules into research and innovation design, linking Monitoring, Evaluation, Learning and Impact Assessment (MELIA) systems to real-time field insights, and building researcher capacity to act on emerging evidence. Institutionalizing feedback loops should become standard across Initiatives (Wigboldus, 2018). | O12: External success requires close collaboration with public extension systems, rural development agencies, and grassroots organizations. These actors can generate hyperlocal insights into poverty dynamics. Partnership frameworks should enable continuous exchange of field realities and support real-time adaptation. Leveraging rural cooperatives, advisory services, and digital feedback tools will be critical (World Bank, 2024). | P12: SA and ESA are top-priority regions due to their high poverty density and underutilized feedback systems. CGIAR should concentrate its efforts on embedding adaptive learning approaches in these regions to enable rapid course correction in poverty-targeted scaling. WCA also requires attention, particularly in strengthening local partnerships and establishing functional Monitoring, Evaluation, Learning and Impact Assessment (MELIA) systems that bridge implementation and strategy.
A13: Remainder: | B13: =MOD(B11,5) -> 0 | C13: =HLOs!D10 -> HLO 1.1.3: Enhance strategies and coordination | D13: 2 | E13: 2 | F13: 2 | G13: 3 | H13: 3 | I13: 2 | K13: Coordination between poverty reduction and agrifood system innovation efforts remains limited and fragmented across most CGIAR regions. While sectoral strategies exist—often focused on agriculture, livelihoods, or social protection—these are typically designed in isolation and implemented in silos. There is little systemic integration between research institutions, national planning processes, and poverty reduction initiatives. This results in duplication of efforts and underutilization of evidence and innovations for achieving poverty outcomes (IFAD, 2021). | L13: A fully integrated, cross-sectoral strategic framework is developed and institutionalized to align agrifood system innovations with national and regional poverty reduction priorities. This framework enables collaboration among CGIAR, national governments, and partners to co-design and co-implement poverty-sensitive strategies that span agriculture, social protection, employment, and rural development sectors. The ideal state envisions joint ownership, resource alignment, and coordinated delivery of innovations with clear pathways to poverty impact (FAO & WEF, 2022). | M13: Based on the revised prioritization, South Asia (SA) and East and Southern Africa (ESA) exhibit the greatest need for improving strategy alignment and coordination for poverty reduction. It is assumed that in these regions, institutional fragmentation and overlapping mandates hinder the scaling of innovations that can directly alleviate poverty. Weak linkages between agriculture and broader development frameworks, along with under-resourced coordination platforms, contribute to inconsistent results (Gálvez, 2022; CGIAR, 2023; Schut et al., 2024). | N13: Internally, CGIAR must embed poverty reduction objectives and coordination principles into its Initiative-level theories of change, investment plans, and MELIA systems. This involves strengthening strategic foresight, building capacity for systems thinking, and enabling cross-Initiative collaboration that transcends thematic boundaries. Shared indicators for poverty outcomes and inter-initiative learning mechanisms are necessary to institutionalize integrated planning and delivery (Douthwaite & Hoffecker, 2017). | O13: Externally, national governments, ministries of planning, and regional development organizations must lead in creating multi-stakeholder platforms that bring together actors across agriculture, livelihoods, rural infrastructure, and social protection. These platforms must have political backing, joint funding mechanisms, and robust accountability frameworks. Development partners, NGOs, and the private sector should also align their investments and interventions with these strategic coordination frameworks (UNESCAP, 2023). | P13: SA and ESA are priority regions where institutional fragmentation has historically undermined the coherence and effectiveness of poverty reduction efforts. Improved coordination is essential to integrate agricultural innovation into broader rural development goals. These regions require support in convening multi-sectoral platforms, fostering strategy co-creation, and ensuring that food system innovation investments contribute directly to poverty outcomes. WCA shows moderate alignment needs, while LAC and CWANA remain lower priority.
A14: Max score: | B14: =(B12*SUM($B$2:$B$6))+IF(B11=0,0,SUM($B$2:INDEX(B:B,$B$13+1))) -> 50 | C14: =HLOs!D11 -> HLO 2.2.1: Innovation networks enhance agrifood system solution scaling | D14: 1 | E14: 1 | F14: 1 | G14: 1 | H14: 1 | I14: 1 | K14: Innovation networks that link agrifood solutions to poverty outcomes remain underdeveloped and poorly institutionalized across CGIAR regions. Where networks exist, they are typically project-based, short-lived, and disconnected from marginalized communities and rural entrepreneurs. There is limited engagement with grassroots innovators, inclusive enterprises, or financial actors who could help deliver and scale pro-poor innovations. As a result, innovations often fail to reach the rural poor at scale or reflect their needs (Davis et al., 2023). | L14: A robust, inclusive, and sustainable network of innovation actors exists—connecting CGIAR, national systems, grassroots innovators, private sector actors, and development intermediaries. These networks foster co-creation and contextualization of agrifood solutions that are directly linked to poverty reduction goals. Supported by enabling policies, digital tools, and financing mechanisms, such ecosystems allow for continuous exchange, testing, and scaling of inclusive innovations tailored to rural poverty contexts (World Bank, 2020). | M14: Revised prioritization indicates that innovation networks for poverty outcomes are at an early stage across all regions, reflected in uniformly low scores. It is assumed that even where innovation actors are present, structural barriers—such as exclusion of poor and marginalized groups, lack of pro-poor financing, and weak network governance—limit their effectiveness. The current low maturity suggests that focusing solely on innovation networks without strengthening enabling ecosystems will have limited poverty impact in the short term (Gálvez, 2022; CGIAR, 2023; Schut et al., 2024). | N14: Internally, CGIAR must map, convene, and support innovation actors focused on poverty reduction, including inclusive agritech start-ups, youth-led enterprises, and women’s innovation networks. Initiatives should strengthen internal collaboration mechanisms that allow for sharing pro-poor innovations across contexts. Pilot platforms can help test network-based delivery models in high-poverty geographies. Prioritizing equity and inclusion principles in innovation network design is essential for sustainability (van Rijn et al., 2020). | O14: Externally, partnerships are needed with inclusive entrepreneurship incubators, local cooperatives, microfinance institutions, and pro-poor innovation platforms. Development actors should support long-term investment in network governance, coordination, and capacity-building. Regional innovation hubs must explicitly include and amplify the voices of marginalized communities to ensure relevance and legitimacy. CGIAR should also collaborate with public and private sector actors to co-finance innovation network infrastructure (IFAD, 2019 & 2022; FAO, 2022). | P14: Although regions like SA, ESA, and WCA exhibit strong poverty reduction needs, innovation networks have not yet emerged as a key strategic lever for impact at scale. These regions currently score low on this HLO, suggesting that investments should focus on foundational work—mapping actors, building trust, and piloting inclusive delivery platforms. While not a near-term priority for Scaling for Impact, early ecosystem-building efforts can lay the groundwork for future pro-poor innovation diffusion and scaling pathways.
C15: =HLOs!D12 -> HLO 2.2.2: Methods evaluating agrifood system solutions for scale | D15: 1 | E15: 1 | F15: 2 | G15: 2 | H15: 2 | I15: 1 | K15: CGIAR programs lack standardized frameworks and tools to evaluate the scalability of agrifood innovations with respect to poverty reduction. Evaluations are often retrospective and fail to account for the socio-economic, cultural, and institutional dynamics that influence whether a solution will benefit the rural poor at scale. The absence of forward-looking, poverty-sensitive assessments means that potentially impactful innovations may be deprioritized—or inappropriately scaled—without evidence of their equity, feasibility, or affordability for poor populations (Rogers et al., 2021). | L15: Scalable agrifood innovations are systematically assessed through robust, forward-looking evaluation frameworks that incorporate poverty-sensitive metrics. These methods consider the multidimensional nature of poverty and are applied early and iteratively across the innovation cycle. CGIAR and partners use such tools to prioritize, adapt, or abandon innovations based on their scale potential and inclusivity. These methods are institutionalized within Monitoring, Evaluation, Learning and Impact Assessment (MELIA) systems and inform strategic investment decisions (Glover et al., 2019; Woltering et al., 2019). | M15: SA, ESA, and WCA are assigned higher priority due to their need for context-specific, poverty-aware evaluation systems. It is assumed that although some Initiatives have begun piloting scalability frameworks, few have embedded poverty reduction metrics or tools that anticipate differential outcomes for marginalized populations. There is also limited capacity to integrate such evaluations into decision-making processes. Uniform scoring reflects widespread recognition of the need to enhance evaluation rigor to target the poor more effectively (Gálvez, 2022; CGIAR, 2023; Schut et al., 2024). | N15: Internally, CGIAR must co-design and mainstream poverty-relevant scalability assessment tools across Initiatives. These should be embedded within MELIA systems and include dimensions such as affordability, reach to poor households, empowerment potential, and resilience outcomes. Capacity building for researchers and MELIA teams will be critical to ensure consistent application and interpretation of results. Evaluative learning must feed into research prioritization and investment planning (Woltering et al., 2019). | O15: CGIAR should partner with poverty research institutes, scaling science communities, and evaluation networks to develop and validate context-specific assessment tools. Governments and development partners need to align their scaling criteria with equity-focused frameworks. Impact investors and donors must also be encouraged to adopt these poverty-sensitive evaluation criteria in their funding decisions, fostering demand for evidence-driven inclusive scaling (IFPRI, 2023). | P15: SA, ESA, and WCA are high-priority regions for investing in scalable evaluation frameworks for poverty reduction. These regions face deep multidimensional poverty, and poorly targeted scaling efforts risk reinforcing inequalities. Introducing scalable, poverty-aware evaluation methods will enhance targeting accuracy and accountability, ensuring that agrifood innovations reach the most underserved populations. These regions offer fertile ground for piloting and institutionalizing such evaluative approaches.
C16: =HLOs!D13 -> HLO 2.2.3: Scale-ready agrifood system solution bundles and packages | D16: 3 | E16: 3 | F16: 3 | G16: 3 | H16: 4 | I16: 3 | K16: In most CGIAR contexts, solutions for poverty reduction—such as improved varieties, extension tools, market access initiatives, or input subsidies—are deployed as standalone interventions. These fragmented approaches fail to account for the multidimensional constraints facing poor households, including lack of capital, weak service ecosystems, and social exclusion. Bundling efforts are typically inconsistent, insufficiently localized, and not designed with affordability, gender equity, or vulnerability dynamics in mind (Herrero et al., 2021; FAO, 2022). | L16: Coherent, contextually adapted solution bundles are designed and delivered to address multiple drivers of rural poverty. These bundles combine technical, financial, institutional, and behavioral components tailored to the needs of the poor. They are co-created with marginalized groups, iteratively refined based on real-world performance, and aligned with national poverty reduction strategies. CGIAR programs institutionalize bundling as a core principle for pro-poor scaling (Gálvez, 2022; CGIAR, 2023; Schut et al., 2024). | M16: High prioritization in SA and ESA reflects both the intensity of poverty and the lack of effective solution integration. It is assumed that in these regions, stand-alone interventions fail to achieve sustainable livelihood outcomes for poor populations. Bundling is particularly critical where enabling services are weak, risk exposure is high, and access to inputs or markets is limited. Effective scaling depends on the bundling of innovations with financing, extension, and inclusion mechanisms (Gálvez, 2022; CGIAR, 2023; Schut et al., 2024). | N16: Internally, CGIAR must mainstream bundling approaches within program design and implementation, with explicit targeting of the poor. This requires developing guidelines for pro-poor bundling, establishing cross-Initiative bundling task forces, and enhancing capacity for participatory solution design. Monitoring, Evaluation, Learning and Impact Assessment (MELIA) systems should track the performance of bundles on poverty-related outcomes across regions (HLPE, 2020). | O16: CGIAR should work closely with microfinance institutions, rural service providers, farmer cooperatives, and social enterprises to co-deploy integrated bundles. Engagement with local governments and social protection programs can ensure that bundles reach the most vulnerable. Donors and investors should be encouraged to fund bundled solutions as cohesive packages rather than disjointed pilots (Anderson et al., 2020; World Bank, 2024). | P16: SA and ESA are top-priority regions for scaling solution bundles tailored to poverty dynamics. These regions exhibit complex poverty traps where bundled innovations are essential to break interlocking constraints. WCA also shows emerging relevance. CGIAR should focus on developing ecosystem-specific bundles for women, land-poor farmers, and youth, and work with local actors to validate and refine these packages at scale.
C17: =HLOs!D14 -> HLO 2.2.4: Agrifood system solution scaling strategies | D17: 4 | E17: 4 | F17: 4 | G17: 4 | H17: 4 | I17: 4 | K17: In most CGIAR programs, scaling strategies rarely include poverty reduction as an explicit objective. Where scaling is pursued, it tends to emphasize yield increases or technology diffusion without adequate attention to the equity, affordability, and access dimensions that determine impact on poor populations. Poverty-specific risks and structural barriers are often overlooked, limiting the transformative potential of agrifood innovation for vulnerable groups (Wigboldus, 2018). | L17: System-oriented scaling strategies are designed to explicitly reduce poverty. These strategies incorporate poverty diagnostics, equity frameworks, gender and youth inclusion criteria, and risk mitigation mechanisms into the scaling process. Scaling pathways are designed to ensure that innovations reach and benefit marginalized populations, are co-owned by local stakeholders, and are embedded in supportive ecosystems and financing architectures (Gálvez, 2022; CGIAR, 2023; Schut et al., 2024). | M17: High and consistent prioritization across SA, ESA, and WCA reflects the recognition that current scaling efforts fail to reach the rural poor. It is assumed that effective poverty reduction requires tailored scaling strategies that address structural inequalities, especially in contexts with limited assets, low market integration, or vulnerability to shocks. These regions demand pathways that are inclusive, pro-poor, and resilience-oriented (FAO & WEF, 2022; Pingali & Aiyar, 2022). | N17: Internally, CGIAR must develop and adopt a shared framework for pro-poor scaling that is integrated into program design, performance indicators, and strategic planning. Research teams need to build capabilities in systems thinking, inclusion mapping, and adaptive scaling design. Initiatives should pilot and refine scaling models that are equity-sensitive and co-created with the poor. Monitoring, Evaluation, Learning and Impact Assessment (MELIA) systems should include metrics to assess inclusive reach and poverty outcomes (Woltering et al., 2019). | O17: External success requires alignment with government social protection systems, rural development programs, and donor funding streams that prioritize poverty alleviation. CGIAR must engage with ministries of agriculture, finance, and planning to ensure scaling strategies are embedded in national investment plans. Regional cooperation platforms should be leveraged to share pro-poor scaling experiences and foster south–south collaboration (World Bank, 2020). | P17: SA and ESA are high-priority regions for pro-poor scaling strategies, where large populations of resource-poor farmers remain excluded from current innovation diffusion models. WCA also demonstrates strategic relevance given its structural poverty dynamics. Across these regions, scaling strategies must go beyond technology promotion and focus on systemic bottlenecks, enabling services, and sustained inclusion of the poor.
C18: =HLOs!D15 -> HLO 3.3.1: Enabling environment diagnostics | D18: 2 | E18: 2 | F18: 2 | G18: 3 | H18: 3 | I18: 2 | K18: Diagnostics that assess barriers to scaling innovations rarely account for poverty-specific constraints such as access to finance, tenure insecurity, labor dynamics, or gendered barriers. Where diagnostics exist, they tend to focus on technical feasibility or market conditions, overlooking social exclusion and structural inequalities. As a result, scaling strategies are often designed without fully understanding the institutional and socioeconomic conditions that affect poor populations (World Bank, 2024). | L18: Diagnostics of enabling environments for scaling are institutionalized and systematically integrate poverty-related indicators. These tools identify policy, institutional, and service delivery barriers to equitable scaling and feed into both program design and policy reform processes. Diagnostics are disaggregated by gender, age, and socioeconomic status, and tailored to specific poverty contexts to guide pro-poor innovation pathways (FAO, 2022). | M18: Higher prioritization in SA and ESA reflects significant gaps in diagnostic systems that can meaningfully guide poverty-targeted scaling. It is assumed that in these regions, the lack of structured analysis of enabling environments contributes to ineffective targeting of the poor in agricultural innovation programs. Poverty is not only a condition but a systemic outcome of weak institutions and exclusionary policies—understanding these dynamics is essential for meaningful scale (Gálvez, 2022; CGIAR, 2023; Schut et al., 2024). | N18: Within CGIAR, poverty-sensitive diagnostic frameworks must be developed and embedded into research design and scaling strategies. This includes co-developing tools with national partners that assess institutional, social, and economic barriers for poor populations to benefit from innovation. Monitoring, Evaluation, Learning and Impact Assessment (MELIA) systems should include diagnostic feedback loops that guide adaptive scaling (Douthwaite & Hoffecker, 2017). | O18: Governments and policy institutions must collaborate to deploy diagnostics as part of rural development and poverty reduction planning. CGIAR should support ministries and subnational bodies to institutionalize diagnostic processes and translate findings into regulatory and budgetary reforms. Civil society organizations can serve as intermediaries to validate diagnostics with poor communities and ensure bottom-up relevance (UNESCAP, 2023). | P18: SA and ESA are high-priority regions where diagnostics must be strengthened to reveal and address systemic barriers to inclusive scaling. WCA also demonstrates relevance due to persistent institutional bottlenecks and fragile enabling environments. Improving diagnostics in these regions is essential for directing innovations toward the poor and for supporting broader reforms in agricultural systems and rural development policy.
C19: =HLOs!D16 -> HLO 3.3.2: Scaling support services for enabling environments and institutions | D19: 3 | E19: 3 | F19: 3 | G19: 3 | H19: 4 | I19: 3 | K19: In many regions, essential services that support the scaling of pro-poor innovations—such as finance, legal aid, advisory services, input delivery, and digital access—are fragmented, underfunded, or inaccessible to the rural poor. These services often fail to reach marginalized populations, including women, youth, and landless workers. As a result, promising innovations remain out of reach for those who need them most, limiting poverty reduction potential (FAO, 2021). | L19: Inclusive and functional service ecosystems exist to support the scaling of pro-poor innovations. These systems provide bundled, accessible services tailored to the needs of vulnerable groups and facilitate the uptake of innovations through coordinated delivery mechanisms. Services span financial inclusion (e.g., microcredit, insurance), extension and advisory platforms, infrastructure support, and digital tools to ensure scalability is equitable and sustainable (IFAD, 2021). | M19: High regional scores for SA and ESA reflect urgent gaps in service access and affordability for poor populations. It is assumed that without strengthening these support systems, even scalable innovations will fail to reach intended beneficiaries. In many low-resource settings, particularly in SA, the informal nature of rural economies compounds challenges in scaling pro-poor solutions (Gálvez, 2022; CGIAR, 2023; Schut et al., 2024). | N19: CGIAR must develop models for bundling complementary services into innovation packages tailored to poor and vulnerable populations. Internally, this requires collaboration across Initiatives working on finance, mechanization, digital tools, and institutional innovation. Monitoring, Evaluation, Learning and Impact Assessment (MELIA) systems should track service access as a scaling enabler and identify which support gaps inhibit uptake (Anderson et al., 2020). | O19: Externally, CGIAR should engage with financial institutions, microinsurance providers, public extension systems, and NGOs to co-design inclusive service models. Development partners, including bilateral donors and multilateral banks, must be mobilized to co-invest in service infrastructure and institutional capacity building. Local governments and private actors need to be incentivized to deliver services at scale, with accountability to marginalized users (IFAD, 2019 & 2022; FAO, 2022). | P19: SA shows the highest urgency for scaling support ecosystem development due to widespread poverty, fragmented public services, and low financial inclusion. ESA also requires significant investments to improve rural service delivery. In WCA, state fragility and geographic dispersion make service innovation especially important. Scaling support systems in these regions is essential to ensure that poverty-reducing innovations are accessible and adopted widely.
C20: =HLOs!D17 -> HLO 3.3.3: Science-policy partnership interfaces for responsible scaling | D20: 1 | E20: 1 | F20: 2 | G20: 2 | H20: 2 | I20: 1 | K20: Across most regions, platforms facilitating dialogue between researchers and policymakers on poverty reduction are weak, fragmented, or non-existent. Where they exist, these platforms often lack continuity, political traction, or institutional mandates. Consequently, research insights and innovations with the potential to reduce poverty are rarely translated into policy or scaled through national programs. CGIAR’s role in policy formulation remains largely advisory and project-dependent, limiting its long-term influence on poverty-targeted reforms (Diao et al., 2023). | L20: Trusted, institutionalized science-policy platforms that embed CGIAR research into the design and implementation of public programs focused on poverty reduction. These platforms enable iterative exchange between evidence producers and decision-makers, resulting in policies grounded in empirical insights and adapted to local poverty dynamics. They promote sustained collaboration between CGIAR, ministries, national research systems, and development partners (FAO & WEF, 2022). | M20: The high prioritization of this HLO for SA, ESA, and WCA reflects persistent weaknesses in evidence-based policymaking, particularly on poverty-related issues. It is assumed that many countries in these regions lack institutionalized channels for integrating research into national poverty reduction strategies. Further, limited trust between science and policy actors, bureaucratic inertia, and misalignment of timelines reduce the influence of research in driving large-scale, pro-poor outcomes (Gálvez, 2022; CGIAR, 2023; Schut et al., 2024). | N20: Within CGIAR, building internal capacity for policy engagement is critical. This includes training researchers in science communication, policy advocacy, and political economy analysis, as well as investing in dedicated policy engagement staff and coordination mechanisms across Centers. Policy engagement should be included in MELIA systems as a cross-cutting success factor. CGIAR must also develop standardized frameworks for co-producing research with policy actors to ensure alignment from the outset (Douthwaite & Hoffecker, 2017). | O20: CGIAR should partner with ministries of rural development, planning commissions, and social protection agencies to institutionalize science-policy collaboration. Support is needed from bilateral and multilateral donors to fund long-term interface platforms, including national observatories, working groups, and policy labs. Engagement with regional economic communities (e.g., SAARC, ECOWAS) and global networks (e.g., UNDP, IFAD) will be essential to scale impact across borders and embed CGIAR’s poverty reduction innovations into national policy frameworks (World Bank, 2020). | P20: SA, ESA, and WCA require targeted strengthening of science-policy partnerships to enable research-based scaling of poverty reduction solutions. In SA, growing policy engagement presents opportunities for embedding CGIAR tools and evidence in social protection and livelihood programs. In ESA and WCA, fragile governance and capacity limitations highlight the need for externally supported but nationally owned platforms that can sustain engagement and policy influence.
C21: =HLOs!D18 -> HLO 4.4.1: CGIAR Expertise and Solutions Embedded in Development Investments and Partnerships | D21: 4 | E21: 4 | F21: 4 | G21: 4 | H21: 4 | I21: 4 | K21: CGIAR’s integration into large-scale, poverty-focused investments remains weak across most regions. Existing partnerships with national governments, IFIs, and social protection programs are often fragmented, short-term, or limited to specific projects. This results in a disconnect between CGIAR’s innovations and the delivery systems needed to achieve wide-scale poverty impacts. Long-term co-investment models and institutionalized partnerships targeting poverty are rare (Gálvez, 2022; CGIAR, 2023; Schut et al., 2024). | L21: Systematic integration of CGIAR expertise, evidence, and innovations into scalable public investment programs and multi-stakeholder partnerships focused on poverty reduction. CGIAR contributions are embedded in national poverty alleviation strategies, rural development programs, and financing mechanisms. Partnerships are governed by long-term frameworks that ensure joint accountability, resource sharing, and mutual influence over policy, research, and implementation (IFPRI, 2023). | M21: Uniform high prioritization of this HLO across regions reflects widespread gaps in institutionalizing CGIAR’s role in poverty-targeted investments. SA shows slightly greater urgency due to the scale and complexity of national anti-poverty programs like MGNREGA and rural livelihood missions. It is assumed that stronger partnerships with public and private actors could greatly amplify CGIAR’s reach, yet current engagement mechanisms are insufficiently structured or under-resourced (FAO, 2022; Gálvez, 2022). | N21: Internally, CGIAR must invest in long-term partnership governance models that define roles, responsibilities, and joint planning processes. This includes establishing CGIAR advisory functions within national poverty programs and aligning innovation pipelines with country-led poverty agendas. Success will require dedicated partnership teams, robust coordination between Initiatives, and knowledge-sharing systems that track joint results across regions (Woltering et al., 2019; HLPE, 2020). | O21: Externally, strategic engagement is needed with national rural development and poverty reduction ministries, regional economic commissions, and IFIs such as the World Bank and IFAD. Partnerships should aim to embed CGIAR technical assistance and evidence into poverty-focused funding pipelines, social safety net programs, and agro-enterprise schemes. CGIAR should also co-develop regional investment platforms, including innovation accelerators and results-based financing mechanisms (World Bank, 2024; UNESCAP, 2023). | P21: SA, ESA, and WCA should be prioritized for embedding CGIAR innovations in scalable investments due to their large-scale rural poverty burdens and active public programs targeting livelihoods and food security. SA, in particular, offers opportunities to influence flagship anti-poverty schemes with strong policy visibility. In ESA and WCA, CGIAR can strengthen its influence by forging alliances with IFIs and aligning with regionally coordinated investment frameworks. Institutionalized partnerships will be critical to translating innovation into lasting poverty impact.
C22: =HLOs!D19 -> HLO 4.4.2: Innovation portfolio management and scaling strategy support teams | D22: 1 | E22: 1 | F22: 2 | G22: 2 | H22: 2 | I22: 1 | K22: Dedicated scaling hubs that explicitly integrate poverty reduction goals are rare or non-existent across most CGIAR regions. Where hubs exist, they tend to be project-bound, short-term, or loosely connected to national poverty frameworks. The absence of institutional anchoring, sustained funding, and tailored tools for poverty-focused scaling limits their utility in driving systemic change for the poor (Gálvez, 2022; CGIAR, 2023; Schut et al., 2024). | L22: Fully functional scaling hubs serve as regional platforms that facilitate the packaging, adaptation, and delivery of pro-poor agrifood innovations. These hubs coordinate across CGIAR Initiatives, national systems, and development partners to connect innovations with funding pipelines, rural institutions, and service providers. They provide methodological support, partnership brokering, and monitoring functions to accelerate inclusive scaling (World Bank, 2020). | M22: High prioritization of this HLO, particularly in SA and ESA, reflects the urgent need to strengthen institutional infrastructure for scaling innovations that directly target poverty. It is assumed that the absence of such hubs limits CGIAR’s ability to coordinate with rural development and social protection systems. The assumption also reflects the need for platforms that can address regional disparities and fragmentation in innovation scaling efforts (FAO, 2022). | N22: Internally, CGIAR must establish multi-Initiative scaling hubs that integrate poverty diagnostics, innovation bundling, demand articulation, and MELIA systems. These hubs should be staffed with interdisciplinary teams and embedded within national research or rural development institutions to ensure contextual alignment. Clear roles, decision-making protocols, and accountability mechanisms are essential to ensure CGIAR-wide coordination and learning (IFAD, 2021). | O22: Externally, partnerships must be forged with government agencies responsible for rural livelihoods, social protection, and local development. Regional economic bodies, donor consortia, and innovation accelerators should be engaged to co-invest in hub operations. Success will also depend on leveraging South-South learning networks, including public-private platforms that address rural poverty and agri-enterprise support (FAO & WEF, 2022). | P22: SA and ESA are top priorities for establishing scaling hubs focused on poverty reduction, given their high rural poverty densities and presence of large-scale public development programs. These regions also host significant CGIAR activity, making hub localization feasible. WCA is moderately relevant, particularly in countries with weak institutional platforms for inclusive innovation. Hubs should be designed to support cross-sector coordination and to channel scalable innovations into national poverty reduction investments.
C23: =HLOs!D20 -> HLO 5.5.1: Enhancing scaling science for societal impact | D23: 2 | E23: 2 | F23: 2 | G23: 2 | H23: 3 | I23: 2 | K23: The integration of poverty-focused perspectives into scaling science remains weak across CGIAR. Tools for scaling science often overlook poverty heterogeneity, structural exclusion, and the dynamics of informal economies. Furthermore, structured South-South learning exchanges on scaling pro-poor innovations are few and uncoordinated. As a result, opportunities to embed equity, contextual adaptation, and mutual learning into scaling processes are missed, limiting both reach and impact (Woltering et al., 2019; IFAD, 2021). | L23: Scaling science is embedded in CGIAR’s research, MELIA systems, and innovation portfolios, with clear poverty-sensitive metrics and institutional learning loops. South-South exchange programs are formalized through regional hubs, knowledge networks, and cross-country fellowships, enabling shared learning on inclusive scaling. CGIAR Centers and national systems co-produce knowledge on poverty dynamics in scaling processes, and systematically test and adapt methods for equitable innovation diffusion (Gálvez, 2022; CGIAR, 2023; Schut et al., 2024; FAO & WEF, 2022). | M23: High priority scores across SA, ESA, and WCA reflect widespread recognition that scaling success depends on integrating poverty reduction principles into the science and practice of scaling. The assumption is that unless poverty dimensions—such as social exclusion, marginality, and livelihood diversity—are embedded into evidence tools and scaling frameworks, pro-poor outcomes will remain incidental or poorly measured. The lack of South-South knowledge flows further limits the potential for contextual adaptation (FAO, 2022). | N23: Internally, CGIAR must develop training modules, learning platforms, and institutional guidance for integrating poverty dimensions into scaling frameworks. This includes disaggregated metrics, user typologies, inclusion indicators, and adaptive learning tools tailored to marginalized contexts. South-South exchange should be institutionalized through staff exchanges, peer-to-peer learning visits, and documentation of scaling innovations from Global South regions. MELIA systems must be aligned to track equity outcomes systematically (Glover et al., 2019; HLPE, 2020). | O23: Externally, CGIAR should partner with South-based universities, regional centers of excellence, and intergovernmental platforms (e.g., African Union, SAARC) to design and manage cross-country learning mechanisms focused on inclusive scaling. Development partners must fund long-term exchange platforms and support the translation of learning into policy and investment practices. South-South innovation consortia and digital learning tools can further democratize access to scaling science methods (World Bank, 2024; UNESCAP, 2023). | P23: SA is the highest priority for this HLO, given its large rural poor population, high density of innovations, and strong potential for peer learning. ESA and WCA also present compelling cases due to their diversity of scaling environments and poverty challenges. Structured South-South exchange mechanisms across these regions can accelerate learning, reduce duplication, and foster inclusive adaptation of CGIAR innovations. Investments in equity-centered scaling science and mutual learning infrastructure are essential to avoid reinforcing existing inequalities through scaling.
C24: =HLOs!D21 -> HLO 5.5.2: Insights for CGIAR scaling success through impact assessments | D24: 2 | E24: 2 | F24: 2 | G24: 3 | H24: 3 | I24: 2 | K24: Impact assessment practices across CGIAR Initiatives tend to focus on productivity and environmental indicators, with limited emphasis on poverty-related outcomes. Where assessments exist, they are typically ex-post, narrow in scope, or disconnected from scaling decisions. Few evaluations explicitly assess whether scaled innovations have reached and benefited poor or marginalized populations. Consequently, lessons for improving the pro-poor performance of innovation scaling remain underdeveloped (Rogers et al., 2021). | L24: CGIAR impact assessments are routinely used to generate actionable insights on how, for whom, and under what conditions scaling contributes to poverty reduction. These evaluations are embedded into program cycles and aligned with scaling frameworks, using both qualitative and quantitative methods to capture distributional impacts. Lessons from impact assessments inform the design, targeting, and adaptation of innovation portfolios, especially in low-income and vulnerable contexts (IFPRI, 2023). | M24: Priority scores for this HLO are elevated in SA and ESA due to the high incidence of poverty and the demand for evidence on which scaling approaches reach the poorest. It is assumed that while some impact evaluations are conducted, they rarely disaggregate by poverty status or directly influence scaling decisions. WCA also shows emerging interest in linking impact evidence with strategy refinement, but capacity constraints persist (Gálvez, 2022; CGIAR, 2023; Schut et al., 2024). | N24: Internally, CGIAR must develop a standardized impact assessment framework that integrates poverty metrics and equity indicators, and aligns with Scaling for Impact objectives. Evaluation design should be anticipatory—beginning at program inception—and include counterfactual methods, longitudinal tracking, and participatory approaches. MELIA teams need resources, training, and institutional support to conduct rigorous poverty-sensitive impact evaluations, and to embed learning loops into decision processes (Douthwaite & Hoffecker, 2017; 3ie, 2022). | O24: Externally, partnerships with impact evaluation organizations such as 3ie, JPAL, IPA, and national statistics offices are critical to strengthen methodological rigor and policy relevance. Donors and implementing partners should require and support poverty-focused assessments, while national governments can facilitate data access and policy dialogue on findings. Multi-actor learning platforms can enhance uptake of insights and increase accountability for pro-poor outcomes (World Bank, 2020). | P24: SA and ESA are high-priority regions for scaling impact assessments due to the scale of poverty and the intensity of CGIAR intervention. Generating robust evidence in these regions can help ensure that scaling efforts benefit the most marginalized. WCA also presents an opportunity for institutionalizing learning-oriented impact assessment, particularly as new scaling initiatives expand. Strategic investment in this HLO will increase the credibility, targeting, and inclusivity of scaling outcomes.
C25: =HLOs!D22 -> HLO 5.5.3: Custom analytics for managing innovation portfolios and decision-making | D25: 1 | E25: 1 | F25: 2 | G25: 2 | H25: 2 | I25: 1 | K25: CGIAR programs currently rely on fragmented and ad hoc data systems to track innovation performance, with limited integration of poverty-related indicators. Portfolio management tools often focus on outputs rather than outcomes and lack the analytical depth to support equity-sensitive decision-making. As a result, decision-makers face challenges in prioritizing innovations that are most relevant for poverty alleviation (FAO, 2022). | L25: A robust suite of analytics tools is available to support dynamic, real-time decision-making for innovation portfolio management. These tools integrate poverty, vulnerability, and livelihood data alongside technical and financial metrics. CGIAR Initiatives use dashboards and AI-enhanced platforms to allocate resources, prioritize interventions, and refine innovation bundles to maximize pro-poor outcomes (Gálvez, 2022; CGIAR, 2023; Schut et al., 2024). | M25: The relatively high scores in SA, ESA, and SEA reflect urgent gaps in using analytics to drive pro-poor innovation management. It is assumed that while some regional Initiatives use dashboards or results frameworks, these are rarely linked to disaggregated poverty indicators or tailored decision tools. Decision-making is often reactive rather than evidence-driven due to insufficient institutional capacity or lack of data integration (World Bank, 2024). | N25: Internally, CGIAR needs to develop integrated analytics platforms that support portfolio optimization based on poverty impact potential. This involves harmonizing data collection across Initiatives, embedding poverty-relevant KPIs into innovation tracking systems, and building analytical dashboards that support scenario modeling. Investment in data architecture, AI-assisted tools, and MELIA staff capacity is critical to operationalize equity-sensitive decision systems (Wigboldus, 2018). | O25: Externally, collaboration with geospatial analytics firms, AI developers, and poverty data platforms (e.g., DHS, WorldPop) is required to enhance data granularity and analytical power. CGIAR must also work with national governments, development finance institutions, and research networks to align data-sharing protocols and create enabling conditions for real-time, demand-driven portfolio management (UNESCAP, 2023). | P25: SA, ESA, and SEA are regions where enhanced analytics could yield major gains in innovation targeting and efficiency. These regions face complex poverty dynamics, requiring tailored decision support tools to ensure that innovation portfolios align with regional development priorities. Investing in advanced analytics in these regions will strengthen evidence-based scaling strategies and increase the effectiveness of resource allocation.

Sheet 3.Social_inclusion
C1: Social inclusion Indicator
A2: VH | B2: 5 | D2: LAC | E2: CWANA | F2: WCA | G2: ESA | H2: SA | I2: SEA
A3: H | B3: 4 | C3: Total score by column | D3: =SUM(D11:D49) -> 34 | E3: =SUM(E11:E49) -> 34 | F3: =SUM(F11:F49) -> 41 | G3: =SUM(G11:G49) -> 38 | H3: =SUM(H11:H49) -> 48 | I3: =SUM(I11:I49) -> 34
A4: MH | B4: 3 | C4: VH count by column | D4: =COUNTIF(D$11:D$49, 5) -> 0 | E4: =COUNTIF(E$11:E$49, 5) -> 0 | F4: =COUNTIF(F$11:F$49, 5) -> 0 | G4: =COUNTIF(G$11:G$49, 5) -> 0 | H4: =COUNTIF(H$11:H$49, 5) -> 3 | I4: =COUNTIF(I$11:I$49, 5) -> 0
A5: M | B5: 2 | C5: H count by column | D5: =COUNTIF(D$11:D$49, 4) -> 3 | E5: =COUNTIF(E$11:E$49, 4) -> 3 | F5: =COUNTIF(F$11:F$49, 4) -> 3 | G5: =COUNTIF(G$11:G$49, 4) -> 3 | H5: =COUNTIF(H$11:H$49, 4) -> 3 | I5: =COUNTIF(I$11:I$49, 4) -> 3
A6: L | B6: 1 | C6: MH count by column | D6: =COUNTIF(D$11:D$49, 3) -> 3 | E6: =COUNTIF(E$11:E$49, 3) -> 3 | F6: =COUNTIF(F$11:F$49, 3) -> 6 | G6: =COUNTIF(G$11:G$49, 3) -> 3 | H6: =COUNTIF(H$11:H$49, 3) -> 4 | I6: =COUNTIF(I$11:I$49, 3) -> 3
C7: M count by column | D7: =COUNTIF(D$11:D$49, 2) -> 4 | E7: =COUNTIF(E$11:E$49, 2) -> 4 | F7: =COUNTIF(F$11:F$49, 2) -> 5 | G7: =COUNTIF(G$11:G$49, 2) -> 8 | H7: =COUNTIF(H$11:H$49, 2) -> 4 | I7: =COUNTIF(I$11:I$49, 2) -> 4
C8: L count by column | D8: =COUNTIF(D$11:D$49, 1) -> 5 | E8: =COUNTIF(E$11:E$49, 1) -> 5 | F8: =COUNTIF(F$11:F$49, 1) -> 1 | G8: =COUNTIF(G$11:G$49, 1) -> 1 | H8: =COUNTIF(H$11:H$49, 1) -> 1 | I8: =COUNTIF(I$11:I$49, 1) -> 5 | K8: Current state (across the Global South) | L8: Ideal state (across the Global South) | M8: Assumptions (for region-specific scores) | N8: Requirements for success (internal to P/A) | O8: Requirements for success (from other P/As) | P8: Regional Implication
C10: HLO | D10: LAC | E10: CWANA | F10: WCA | G10: ESA | H10: SA | I10: SEA
A11: HLO count: | B11: =COUNTA(C11:C49) -> 15 | C11: =HLOs!D8 -> HLO 1.1.1: Demand signaling | D11: 4 | E11: 4 | F11: 4 | G11: 4 | H11: 5 | I11: 4 | K11: Existing mechanisms to identify innovation and scaling demands from women, youth, Indigenous Peoples, and marginalized groups are fragmented, underfunded, or absent in most CGIAR regions. Where systems do exist, they are often sector-specific, non-participatory, and disconnected from formal decision-making. This results in research and investment agendas that insufficiently respond to social exclusion dynamics in agrifood systems (FAO, 2022; UN Women, 2021). | L11: A well-functioning, inclusive demand signaling system is established across CGIAR and national programs, capturing region-specific needs of structurally excluded groups. These systems are co-designed with civil society, youth organizations, and Indigenous networks, and are grounded in real-time data and participatory foresight. They serve as critical inputs to CGIAR’s prioritization and scaling strategies (HLPE, 2020). | M11: Higher prioritization in SA reflects deep-rooted social exclusion patterns—linked to caste, gender norms, and youth marginalization—which limit representation in agricultural innovation processes. WCA and ESA also show elevated needs due to weak institutional channels for youth and minority voices. These assumptions are based on existing CGIAR regional diagnostics and stakeholder feedback (Gálvez, 2022; CGIAR, 2023; Schut et al., 2024). | N11: Within CGIAR, inclusive demand signaling must be embedded into the design of Innovation Packages and Scaling Pathways (IPSPs). This requires CGIAR Initiatives to adopt participatory tools such as social network mapping, intersectional demand surveys, and gender/youth scorecards. Strong internal partnerships between research, MELIA, and social inclusion teams are critical to sustain these systems (IFAD, 2021). | O11: Build long-term partnerships with civil society actors, Indigenous organizations, youth platforms, and ministries of women and social development. External support is needed to finance inclusive data systems, community-led consultations, and decentralized feedback mechanisms that ensure demand identification reflects the lived realities of marginalized groups (World Bank, 2020). | P11: SA is the highest priority due to systemic exclusion and demographic pressure. WCA and ESA also require dedicated investment in building participatory demand ecosystems. In these regions, social marginalization is compounded by institutional barriers to voice and agency. Scaling should begin with regional pilots that demonstrate inclusive demand capture across key subgroups.
A12: Sets of 5: | B12: =_xlfn.FLOOR.MATH(B11/5) -> 3 | C12: =HLOs!D9 -> HLO 1.1.2: Feedback and adaptive research and scaling prioritization | D12: 3 | E12: 3 | F12: 3 | G12: 3 | H12: 4 | I12: 3 | K12: Feedback mechanisms that channel insights from socially excluded groups into CGIAR’s research and scaling pipelines are largely absent or tokenistic. Existing feedback structures often privilege elite or formal actors and fail to systematically integrate perspectives from women, youth, Indigenous Peoples, or persons with disabilities. As a result, research agendas may overlook barriers to participation and adoption that these groups face (Douthwaite & Hoffecker, 2017). | L12: Feedback and adaptive learning systems are fully institutionalized within CGIAR and enable routine updating of research and scaling priorities in response to intersectional social inclusion needs. These systems are decentralized, real-time, and embedded across project lifecycles. They ensure continuous learning from program implementation, especially among marginalized populations (Gálvez, 2022; CGIAR, 2023; Schut et al., 2024). | M12: SA and ESA are prioritized due to widespread gaps in participatory learning systems and under-representation of excluded groups in formal R&D processes. While some Initiatives have piloted inclusive MELIA approaches, they are not yet institutionalized. It is assumed that feedback channels must be strengthened through digital access, local partnerships, and trust-building with marginalized communities (FAO, 2022). | N12: CGIAR must institutionalize inclusive Monitoring, Evaluation, Learning and Impact Assessment (MELIA) systems that gather disaggregated feedback on barriers to participation, uptake, and benefit distribution. Initiatives should allocate dedicated resources to develop reflexive learning cycles and empower researchers with tools for adaptive design responsive to social equity dynamics (Wigboldus, 2018). | O12: Collaboration with grassroots organizations, cooperatives, and social movements is critical to ensure marginalized groups are meaningfully engaged in adaptive research cycles. These actors can act as trusted intermediaries and facilitators of localized monitoring, ensuring feedback reaches research institutions in real time (UNESCAP, 2023). | P12: SA and ESA are high-priority regions for this HLO due to persistent social inequalities, youth disengagement, and fragile trust in formal research systems. Strengthening inclusive feedback loops in these contexts will help realign CGIAR’s innovation agenda with the lived experiences of the most excluded. Piloting feedback platforms through trusted intermediaries can catalyze more responsive, equitable innovation pathways.
A13: Remainder: | B13: =MOD(B11,5) -> 0 | C13: =HLOs!D10 -> HLO 1.1.3: Enhance strategies and coordination | D13: 2 | E13: 2 | F13: 3 | G13: 2 | H13: 3 | I13: 2 | K13: Current CGIAR and national-level strategies for scaling innovations rarely embed clear goals or frameworks for advancing gender equality, youth empowerment, or the inclusion of Indigenous and marginalized groups. Coordination among actors working on agriculture, social protection, and youth/gender policy remains weak, leading to parallel efforts that often bypass the most excluded (IFPRI, 2023). | L13: Multi-actor strategies for agrifood innovation and scaling are explicitly aligned with inclusion priorities. These strategies bridge agricultural development with gender, youth, Indigenous, and minority policy agendas. They are developed and implemented in coordination with ministries of social welfare, civil society organizations, and underrepresented groups. They also include accountability structures for tracking and adjusting inclusive impact (FAO & WEF, 2022). | M13: SA and WCA are prioritized due to their deeply entrenched social hierarchies and policy fragmentation across inclusion domains. These regions face systemic coordination challenges among ministries (agriculture, gender, youth, Indigenous affairs), which hamper efforts to deliver inclusive innovation at scale. It is assumed that closing coordination gaps will require both top-down leadership and grassroots policy influence (Gálvez, 2022; CGIAR, 2023; Schut et al., 2024). | N13: CGIAR must establish cross-Initiative working groups on social inclusion that feed into overarching strategic frameworks. Inclusion metrics and stakeholder mapping should be systematically integrated into strategic planning and outcome monitoring. Researchers and program managers must also receive training in intersectionality and inclusive systems thinking to harmonize actions across portfolios (World Bank, 2024). | O13: External actors—including national ministries, regional bodies, and inclusion-focused CSOs—must be engaged through formal policy platforms to co-develop and co-own inclusive innovation strategies. These platforms should foster alignment between agricultural innovation and social policy agendas, supported by shared targets and coordinated funding mechanisms (UN Women, 2021). | P13: SA and WCA require urgent improvements in strategic coordination to ensure inclusive scaling outcomes. In these regions, siloed policymaking and weak inter-ministerial collaboration have hindered efforts to reach excluded populations. Developing integrated strategies that link agriculture, social protection, and education will be critical to advancing inclusive transformation. CGIAR should take a convening role in these regions, aligning efforts through policy dialogue and shared delivery frameworks.
A14: Max score: | B14: =(B12*SUM($B$2:$B$6))+IF(B11=0,0,SUM($B$2:INDEX(B:B,$B$13+1))) -> 50 | C14: =HLOs!D11 -> HLO 2.2.1: Innovation networks enhance agrifood system solution scaling | D14: 1 | E14: 1 | F14: 1 | G14: 1 | H14: 1 | I14: 1 | K14: Innovation ecosystems that support inclusive agrifood solutions remain nascent or missing across most regions. Existing networks are often gender-blind, urban-centric, or focused on technological elites, leaving out marginalized innovators such as women, Indigenous entrepreneurs, youth groups, and informal innovators. Few platforms exist to systematically nurture inclusive co-creation or to connect excluded actors to value chains, finance, or knowledge flows (Davis et al., 2023). | L14: Innovation networks are dynamic and inclusive, actively engaging marginalized groups—especially women, youth, and Indigenous innovators—in designing, testing, and scaling agrifood solutions. These networks are supported by incubators, rural innovation hubs, and blended finance models tailored to underserved innovators. They operate within national and regional platforms that connect research, entrepreneurship, and policy ecosystems to foster inclusive scaling (IFAD, 2021). | M14: All regions scored low on this HLO, suggesting that despite widespread gaps in inclusive innovation networks, it is not seen as an immediate leverage point for scaling social inclusion outcomes. It is assumed that without complementary improvements in bundling, policy integration, and support services, investment in inclusive innovation networks alone may yield limited short-term returns. However, they remain a foundational medium-term priority (Gálvez, 2022; CGIAR, 2023; Schut et al., 2024). | N14: CGIAR should begin by mapping existing informal and formal innovation actors working in marginalized communities and investing in inclusive design principles within its Initiatives. Innovation grants and challenges that prioritize solutions from excluded groups should be piloted, and internal capacities must be strengthened to engage with community innovators and social entrepreneurs (van Rijn et al., 2020). | O14: External success depends on partnerships with inclusive business accelerators, rural incubators, social enterprise networks, and national innovation platforms. Investment from donors and regional development banks is needed to create enabling environments for underserved innovators. Support from governments should prioritize regulatory and financial mechanisms that lower barriers for marginalized actors (FAO, 2022; IFAD, 2019 & 2022). | P14: Although WCA, ESA, and SA show a strong need for inclusive innovation ecosystems, this HLO received lower prioritization in the KBP due to the perception that systemic enablers must first be strengthened. In these regions, CGIAR should pursue diagnostic studies and test pilot partnerships with inclusive incubators as groundwork for longer-term transformation. Medium-term investments will be essential to ensure future equity in agrifood innovation pipelines.
C15: =HLOs!D12 -> HLO 2.2.2: Methods evaluating agrifood system solutions for scale | D15: 1 | E15: 1 | F15: 2 | G15: 2 | H15: 2 | I15: 1 | K15: Evaluation methods used across CGIAR programs often fail to incorporate equity dimensions, including how innovations perform for women, youth, Indigenous peoples, and other marginalized groups. Standard tools primarily assess technical, economic, or environmental scalability but lack metrics or frameworks to evaluate differential access, uptake, and outcomes across social groups. This results in blind spots and missed opportunities to design for inclusive scaling (Rogers et al., 2021). | L15: CGIAR and partner programs routinely apply inclusive scalability assessment methods that explicitly consider social equity. These tools assess whether innovations reinforce or reduce structural inequalities, and how different groups experience benefits and risks of scaling. The ideal system includes context-sensitive indicators for gender, age, ethnicity, and socioeconomic status, integrated throughout the research and scaling cycle (Glover et al., 2019). | M15: SA, ESA, and WCA received higher scores for this HLO, reflecting significant gaps in inclusion-sensitive evaluation capacity. It is assumed that current practices overlook how scaling processes affect different social groups. These regions face deep-rooted structural exclusions, making inclusion-aware assessment methods critical to ensure equitable innovation outcomes (Gálvez, 2022; CGIAR, 2023; Schut et al., 2024). | N15: Internally, CGIAR must revise its scaling diagnostics and monitoring, evaluation, learning and impact assessment (MELIA) systems to incorporate disaggregated indicators and intersectional analysis. This includes capacity building for staff on equity-informed evaluation and the development of standardized guidance and toolkits to assess social inclusion in scalability potential (Woltering et al., 2019). | O15: External partnerships should involve universities, think tanks, and evaluation bodies with expertise in social inclusion and equity. These partners can help co-design and validate inclusive evaluation frameworks and support regional trainings. National statistics agencies and ministries should be engaged to ensure alignment with equity monitoring standards and data systems (HLPE, 2020). | P15: SA, ESA, and WCA should be prioritized for rollout of equity-aware scalability assessment methods. These regions face some of the most entrenched barriers to inclusion in agrifood systems. Embedding these methods in programming can help CGIAR improve accountability, tailor interventions, and avoid reinforcing inequality during scale-out. A phased introduction, aligned with program planning cycles, can ensure institutionalization.
C16: =HLOs!D13 -> HLO 2.2.3: Scale-ready agrifood system solution bundles and packages | D16: 3 | E16: 3 | F16: 3 | G16: 3 | H16: 4 | I16: 3 | K16: Agrifood innovations are often designed and scaled as uniform packages without attention to the differentiated needs, roles, and constraints of marginalized populations. Bundles tend to exclude enabling components such as finance, labor support, or gender-sensitive training. As a result, they often fail to reach or benefit women, youth, Indigenous peoples, or persons with disabilities—limiting the equity and effectiveness of scaling outcomes (FAO, 2022). | L16: Agrifood innovation bundles are co-designed with marginalized groups and adapted to context-specific needs. Bundles include both technological and institutional components—such as social protection linkages, inclusive finance, or labor-saving tools—tailored to overcome structural barriers. These bundles are tested for uptake and scalability across diverse user groups, and institutionalized in CGIAR scaling pipelines (Gálvez, 2022; CGIAR, 2023; Schut et al., 2024). | M16: SA shows the highest need for inclusive bundling due to persistent gender, caste, and land access inequalities. ESA and WCA also show strong demand for better contextualization of innovation packages to reach youth, women-headed households, and marginalized ethnic groups. The prioritization assumes that inclusive bundling is key to ensuring equitable reach and scalable impact across socially diverse contexts (IFAD, 2021). | N16: Internally, CGIAR must embed inclusion criteria and social targeting principles into the design and delivery of agrifood innovation bundles. This requires cross-disciplinary teams—including gender, youth, and social inclusion specialists—engaged early in the design phase. CGIAR should also strengthen guidance for adapting bundles to agroecological and sociocultural contexts, and include metrics to assess inclusivity and equity outcomes (HLPE, 2020). | O16: External engagement should focus on validating bundles with marginalized community groups through participatory testing, and working with intermediaries (e.g., women's cooperatives, youth organizations, Indigenous associations) to ensure relevance and ownership. Partnerships with microfinance institutions and local private sector actors are also essential to support distribution and affordability of bundles (World Bank, 2024). | P16: SA, ESA, and WCA are high-priority regions for inclusive bundling efforts. In these areas, standard packages often exclude marginalized communities. CGIAR programs should prioritize co-design and adaptation of innovation bundles that explicitly address structural barriers and local preferences. Bundles that combine technology, training, finance, and institutional linkages will increase uptake and foster more equitable food system transformation.
C17: =HLOs!D14 -> HLO 2.2.4: Agrifood system solution scaling strategies | D17: 4 | E17: 4 | F17: 4 | G17: 4 | H17: 5 | I17: 4 | K17: Current scaling strategies often treat inclusion as a secondary objective or overlook it entirely. Gender, youth, Indigenous, and minority considerations are rarely embedded in the design, implementation, or monitoring of scaling efforts. Programs tend to focus on technological adoption rates rather than equitable access or distribution of benefits, reinforcing existing social and economic disparities (Wigboldus, 2018). | L17: Scaling strategies explicitly integrate social inclusion objectives—ensuring innovations reach marginalized groups and address intersectional exclusion. These strategies adopt equity-based targets, monitor distributional impacts, and are co-created with underrepresented communities. CGIAR and national actors embed inclusion in the core logic of scaling pathways from design to impact assessment (Gálvez, 2022; CGIAR, 2023; Schut et al., 2024). | M17: SA and SEA are prioritized for action due to deeply entrenched structural inequalities—including gendered access to resources, caste-based discrimination, and youth unemployment. These contexts require the redesign of existing scaling strategies to focus on equitable access and benefit-sharing. It is assumed that addressing inclusion at the strategy level will have a multiplier effect across scaling outcomes (FAO, 2022). | N17: CGIAR needs to operationalize inclusion within its scaling frameworks by applying intersectionality principles and developing inclusive scaling metrics. Scaling logic models should integrate disaggregated targets and indicators from the outset. This also requires upskilling program teams on inclusive design, institutionalizing social inclusion checklists, and aligning scaling priorities with gender, youth, and Indigenous Peoples’ strategies across CGIAR Initiatives (UN Women, 2021). | O17: National governments, donors, and civil society must be involved in redesigning scaling strategies to ensure social equity. External actors should provide technical support on intersectional analysis, fund equity-oriented scaling pilots, and facilitate policy dialogue to embed inclusive scaling in national rural development frameworks. UNDP, UN Women, and social protection ministries are key allies in aligning scaling with national inclusion agendas (World Bank, 2020). | P17: SA and SEA require immediate redesign of agrifood scaling strategies to ensure inclusion is a core objective, not a peripheral concern. CGIAR programs operating in these regions must shift from output-based scaling to equity-driven pathways. Prioritizing inclusion in strategy development will enable scalable innovations to serve as levers for social transformation rather than reinforcing existing marginalization.
C18: =HLOs!D15 -> HLO 3.3.1: Enabling environment diagnostics | D18: 2 | E18: 2 | F18: 3 | G18: 2 | H18: 3 | I18: 2 | K18: Diagnostics of enabling environments often fail to identify or measure structural barriers to inclusion, such as gender bias in land tenure, youth exclusion from extension services, or Indigenous Peoples’ lack of formal recognition. Where diagnostics exist, they tend to focus on economic or institutional constraints without disaggregating the impacts by social group. This limits the design of inclusive scaling interventions (World Bank, 2024). | L18: Institutionalized diagnostic tools that regularly assess inclusion-related barriers within enabling environments. These diagnostics evaluate legal, policy, market, and sociocultural factors affecting marginalized groups and feed directly into scaling strategies. Inclusive diagnostics are recognized as a prerequisite for designing equitable innovations and responsible scaling pathways (FAO & WEF, 2022). | M18: SA and WCA scored high in prioritization due to the persistence of exclusionary systems rooted in legal, cultural, or institutional norms. These regions lack comprehensive diagnostics that reveal barriers faced by women, youth, Indigenous groups, and other marginalized populations. It is assumed that diagnostics that do not explicitly address inclusion risks perpetuating inequality in scaling (Gálvez, 2022; CGIAR, 2023; Schut et al., 2024). | N18: CGIAR must integrate social inclusion metrics and intersectionality frameworks into its diagnostic tools. This includes adapting existing assessment tools to track power dynamics, access disparities, and social norms. Programs should institutionalize diagnostic reviews at key program phases and develop staff capacities in gender and inclusion-sensitive analysis (Douthwaite & Hoffecker, 2017). | O18: Externally, CGIAR should collaborate with ministries of gender, youth, Indigenous affairs, and social development to embed inclusive diagnostics in national food system policies. Partnerships with organizations that specialize in rights-based development and social safeguards (e.g., UN Women, UNDP, CARE) can enhance diagnostic rigor and relevance (UNESCAP, 2023). | P18: SA and WCA require immediate strengthening of diagnostics to expose structural inequalities that hinder the scaling of inclusive innovations. Investments should focus on integrating social indicators into existing policy diagnostics and fostering government ownership of these tools. CGIAR can play a key role in translating these insights into targeted reforms and innovation design improvements.
C19: =HLOs!D16 -> HLO 3.3.2: Scaling support services for enabling environments and institutions | D19: 3 | E19: 3 | F19: 3 | G19: 3 | H19: 4 | I19: 3 | K19: Inclusive support services—such as financial, legal, technical, and advisory mechanisms—remain inaccessible to marginalized populations across many regions. Barriers include complex eligibility criteria, lack of gender- or youth-responsive service models, and weak outreach to Indigenous and minority communities. Services are often urban-centric or designed for better-off farmers, limiting their utility for inclusive scaling (FAO, 2022). | L19: Functional, inclusive ecosystems of scaling support services that are accessible, affordable, and responsive to the distinct needs of excluded groups. These include bundled services (e.g., microcredit, advisory, legal aid) tailored to reach women, youth, Indigenous Peoples, and persons with disabilities. Services are embedded within local institutions and integrated into innovation delivery models (IFAD, 2021). | M19: High prioritization scores in SA and ESA reflect the acute service delivery gaps for socially excluded groups. It is assumed that without intentionally designed and targeted support ecosystems, scaling efforts risk reinforcing exclusion by only serving well-connected or resourced actors. Social inclusion in scaling depends on systemic redesign of how services are delivered, financed, and evaluated (Gálvez, 2022; CGIAR, 2023; Schut et al., 2024). | N19: CGIAR must embed inclusion-sensitive service delivery models into its innovation scaling pipelines. This includes co-designing services with marginalized communities, piloting delivery through women- or youth-led organizations, and developing tools to assess the accessibility and equity of support ecosystems. Centers must also document and share good practices across Initiatives (Anderson et al., 2020). | O19: Partnerships with microfinance institutions, youth platforms, legal aid organizations, and inclusive extension providers are essential. Collaborations with global inclusive finance initiatives (e.g., UNCDF, Women’s World Banking) and national social protection schemes can enhance reach. Donor investments should be channeled to create bundled, gender-transformative services (IFAD, 2019 & 2022; FAO, 2022). | P19: SA and ESA show urgent need to scale up inclusive support services. In both regions, exclusion from critical services significantly hinders the scaling of innovations among women, youth, and Indigenous communities. CGIAR should prioritize pilot programs that build local service ecosystems through collaborative design and invest in partnerships that extend coverage to underserved areas.
C20: =HLOs!D17 -> HLO 3.3.3: Science-policy partnership interfaces for responsible scaling | D20: 1 | E20: 1 | F20: 2 | G20: 2 | H20: 2 | I20: 1 | K20: Science-policy partnerships in many regions remain weak or underutilized for advancing social inclusion in scaling. Where partnerships exist, they often overlook equity outcomes, lack mandates to integrate evidence on gender, youth, and marginalization, and are disconnected from ministries responsible for social protection, Indigenous rights, or youth affairs (Diao et al., 2023). | L20: Institutionalized, trust-based science-policy interfaces that systematically prioritize social inclusion in agrifood innovation scaling. These platforms enable joint agenda-setting, support inclusive policy reforms, and ensure the translation of research evidence on exclusion into actionable programs and investments (Gálvez, 2022; CGIAR, 2023; Schut et al., 2024). | M20: SA and SEA have been identified as regions where the absence of equity-focused science-policy engagement is especially acute. It is assumed that limited political voice among marginalized groups, institutional fragmentation, and lack of inclusion mandates in agricultural policy contribute to this gap. Higher scores reflect both institutional demand and readiness for inclusive policy engagement (FAO, 2022). | N20: Internally, CGIAR must strengthen the policy engagement skills of researchers, particularly around social inclusion themes. Initiatives should establish dedicated focal points for policy dialogue on equity and inclusion, develop policy briefs with disaggregated data, and invest in long-term relationships with national ministries of gender, youth, and rural development (Douthwaite & Hoffecker, 2017). | O20: External efforts should include fostering policy dialogues that link agriculture, food systems, and social inclusion mandates. Engagements with ministries of social development, women’s affairs, and Indigenous rights are critical. International partners such as UN Women, UNDP, and CARE should be mobilized to support policy alignment and capacity development for inclusive governance (World Bank, 2020). | P20: SA and SEA are priority regions for strengthening science-policy interfaces for social inclusion. Building credible, inclusion-centered dialogue platforms in these regions will improve the integration of equity goals in national food systems strategies. CGIAR should leverage its evidence base to advocate for policy change while anchoring engagement in ministries with equity mandates.
C21: =HLOs!D18 -> HLO 4.4.1: CGIAR Expertise and Solutions Embedded in Development Investments and Partnerships | D21: 4 | E21: 4 | F21: 4 | G21: 4 | H21: 5 | I21: 4 | K21: CGIAR innovations and technical expertise related to social inclusion are insufficiently embedded in large-scale national investments and strategic partnerships. Inclusion objectives are often viewed as secondary to productivity or climate goals, resulting in short-lived, fragmented partnerships that fail to institutionalize inclusion outcomes (Gálvez, 2022; CGIAR, 2023; Schut et al., 2024; Wigboldus, 2018). | L21: CGIAR’s inclusion-related innovations and evidence base are systematically integrated into national scaling programs, investments, and policy reforms. Durable partnerships are built with governments, donors, and multilaterals to mainstream gender, youth, and equity outcomes in agrifood system transformation strategies (IFPRI, 2023). | M21: SA and SEA score highest due to strong national commitments to social inclusion, but also show major gaps in embedding inclusion within investment pipelines. The assumption is that despite political will, enabling mechanisms—such as advisory roles for CGIAR and long-term coordination platforms—are weak or missing (FAO, 2022). | N21: Internally, CGIAR must develop formal strategies for positioning inclusion innovations within major scaling investments. This includes assigning inclusion specialists to work with public and private sector stakeholders, creating investment-readiness profiles for inclusive innovations, and tracking inclusion KPIs across partnerships (Woltering et al., 2019; HLPE, 2020). | O21: Externally, partnerships must be formalized through MOUs and investment frameworks that explicitly prioritize social inclusion. Governments should designate equity-related indicators in public investment strategies. Collaboration with UN agencies, regional development platforms, and civil society is essential to anchor inclusive innovation within national programs (UN Women, 2021; UNESCAP, 2023). | P21: SA and SEA require urgent action to embed CGIAR’s inclusion expertise in national agricultural development programs. In both regions, the potential for large-scale impact exists—but requires stronger institutional commitments, cross-ministerial coordination, and technical support to integrate social equity across investment decision-making.
C22: =HLOs!D19 -> HLO 4.4.2: Innovation portfolio management and scaling strategy support teams | D22: 1 | E22: 1 | F22: 2 | G22: 2 | H22: 2 | I22: 1 | K22: Existing CGIAR scaling hubs generally lack embedded expertise, systems, or personnel dedicated to social inclusion. Most hubs focus on technical scaling dimensions (e.g., yield improvement, climate adaptation), with minimal engagement on gender, youth, ethnicity, or social equity. Inclusion is often retrofitted or treated as an add-on, resulting in low institutionalization and weak accountability for inclusive scaling (Gálvez, 2022; CGIAR, 2023; Schut et al., 2024). | L22: Fully functional scaling hubs that are institutionally equipped to lead inclusive scaling across CGIAR programs. These hubs integrate gender-transformative frameworks, have dedicated staff with expertise in social inclusion, and coordinate across programs to embed equity into all phases of scaling design, implementation, and monitoring (World Bank, 2024). | M22: High priority needs are evident in SA, ESA, and WCA, where inclusion capacity in existing scaling infrastructure is low despite high vulnerability of marginalized populations. The assumption is that without targeted resourcing and capacity-building, scaling hubs will fail to mainstream inclusion in strategy, design, or delivery (FAO, 2022). | N22: CGIAR must develop training curricula and institutional guidelines to integrate social inclusion into the mandate and operations of scaling hubs. Hubs should be staffed with specialists in gender and social inclusion, and linked with regional CGIAR centers and GENDER and Youth platforms to ensure consistency and capacity (IFAD, 2021). | O22: External support is needed from technical agencies and development partners with experience in gender-transformative programming, disability inclusion, and youth empowerment. This includes South-South peer learning, investment from development banks, and partnerships with local inclusion networks and advocacy organizations (UN Women, 2021). | P22: SA, ESA, and WCA represent the most urgent priorities for transforming scaling hubs into platforms that can deliver inclusive impact. These regions experience entrenched exclusion and lack institutional support mechanisms for marginalized groups. Without strengthened inclusion capabilities in scaling hubs, equity goals will remain peripheral to broader innovation scaling strategies.
C23: =HLOs!D20 -> HLO 5.5.1: Enhancing scaling science for societal impact | D23: 2 | E23: 2 | F23: 2 | G23: 2 | H23: 3 | I23: 2 | K23: Scaling science frameworks and methods largely overlook social inclusion dimensions such as gender inequality, youth marginalization, and structural exclusion. CGIAR’s contributions to scaling research are underutilized in equity-related decision-making, and South-South learning platforms for inclusive innovations are either missing or disconnected from CGIAR programming (Woltering et al., 2019; IFAD, 2021). | L23: A globally relevant scaling science architecture in which CGIAR mainstreams inclusion indicators, tools, and adaptive learning frameworks in research design, MELIA systems, and innovation pipelines. Institutionalized South-South exchange programs promote peer learning on inclusive scaling strategies, especially for vulnerable groups in the Global South (Gálvez, 2022; CGIAR, 2023; Schut et al., 2024; FAO & WEF, 2022). | M23: Most regions score low on this HLO, reflecting the early-stage development of inclusion-aware scaling science. South Asia (SA) emerges as the highest priority, given intersecting challenges of caste, gender, and youth exclusion. The assumption is that inclusion blind spots in scaling science persist due to limited institutional incentives and weak linkages with inclusion expertise (FAO, 2022). | N23: CGIAR must invest in research, tools, and capacity-building that embed inclusion dimensions—such as intersectionality, social norms, and marginality—into scaling science. This includes training scientists on inclusive innovation theories, mainstreaming disaggregated MELIA systems, and establishing platforms for learning across Initiatives and Centers (Glover et al., 2019). | O23: Development partners, social science institutions, and multilateral networks (e.g., UNDP, UN Women, South-South Cooperation platforms) must be engaged to support structured peer exchanges, fellowships, and joint publications focused on scaling inclusive innovations. Dedicated financing mechanisms for inclusive scaling knowledge products are also needed (World Bank, 2024; UNESCAP, 2023). | P23: SA is the highest priority region, with significant inclusion gaps but strong potential for institutional uptake. ESA and WCA also require support in strengthening equity dimensions within scaling frameworks. Investing in evidence-based tools and South-South learning platforms will help institutionalize inclusive scaling practices and accelerate equitable outcomes across these regions.
C24: =HLOs!D21 -> HLO 5.5.2: Insights for CGIAR scaling success through impact assessments | D24: 2 | E24: 2 | F24: 3 | G24: 2 | H24: 3 | I24: 2 | K24: Impact assessments in CGIAR programs rarely capture how scaling efforts affect social inclusion outcomes such as gender equity, youth empowerment, or support for Indigenous communities. Most evaluations focus on productivity or adoption, with limited analysis of who benefits or is left behind (Rogers et al., 2021). | L24: CGIAR routinely generates insights from impact assessments that explicitly address inclusion dimensions. These assessments are disaggregated by gender, age, ethnicity, and other social factors and are systematically used to inform program design, adaptive scaling strategies, and partnerships. Learning loops are institutionalized, and insights are shared across programs and geographies (IFPRI, 2023). | M24: Higher priority scores in SA and ESA reflect strong needs for equity-sensitive learning systems and underutilization of impact data to inform inclusive scaling. The assumption is that methodological gaps, capacity constraints, and low demand for socially disaggregated evidence have limited investment in inclusion-focused impact evaluation (Gálvez, 2022; CGIAR, 2023; Schut et al., 2024). | N24: CGIAR must mandate the inclusion of disaggregated impact indicators in MELIA systems and ensure that evaluation frameworks assess the distributional effects of scaling efforts. Institutional learning platforms must be strengthened to distill and disseminate insights related to social inclusion across Centers and Initiatives (3ie, 2022). | O24: External collaboration with global and regional impact evaluation networks (e.g., 3ie, JPAL) is essential to generate rigorous, context-specific evidence on inclusion outcomes. Partnerships with national statistics offices, gender research institutes, and social policy actors will improve data relevance and uptake (World Bank, 2024). | P24: SA and ESA are highest priority regions for this HLO, given structural barriers to inclusion and the opportunity to enhance accountability in scaling. Investing in impact assessments that focus on inclusion will help CGIAR adapt strategies and build trust with marginalized communities. WCA also requires strengthened systems, but data and institutional barriers remain significant.
C25: =HLOs!D22 -> HLO 5.5.3: Custom analytics for managing innovation portfolios and decision-making | D25: 1 | E25: 1 | F25: 2 | G25: 2 | H25: 2 | I25: 1 | K25: Analytics systems in CGIAR generally lack filters for inclusion, resulting in limited capacity to track and prioritize innovations that benefit women, youth, Indigenous groups, and other marginalized populations. Portfolio tools often emphasize efficiency and productivity metrics over equity considerations, constraining the ability to manage innovations for inclusive outcomes (FAO, 2022). | L25: CGIAR applies advanced, equity-sensitive analytics to innovation portfolio management. Decision-support tools integrate real-time, disaggregated data that capture gender, youth, and social inclusion dimensions. These tools guide prioritization of innovations that deliver inclusive benefits, helping to optimize investments for equitable scaling (Gálvez, 2022; CGIAR, 2023; Schut et al., 2024). | M25: The strong prioritization of this HLO in SA, SEA, and ESA stems from acute data and system gaps limiting the ability to make socially informed decisions. It is assumed that these regions face high inclusion challenges but also present opportunities to pioneer equity-driven analytics. WCA and LAC also require strengthening but have weaker digital and institutional readiness (World Bank, 2024). | N25: CGIAR must embed social inclusion metrics into portfolio tracking systems and dashboards, enabling Initiatives to monitor who benefits from innovations. MELIA systems should include modules for real-time equity analytics. Internal capacity building is needed in inclusive data management, gender-responsive analytics, and decision science (Wigboldus, 2018). | O25: Partner with AI and data analytics platforms focused on social equity to co-develop inclusive decision-support tools. Collaborate with tech companies, development banks, and civil society organizations to validate and scale analytics that inform inclusive innovation planning (UNESCAP, 2023). | P25: SA, SEA, and ESA are urgent priority regions for investment in inclusive analytics systems, as they combine high social vulnerability with low data visibility. Equipping these regions with gender- and youth-disaggregated decision-support tools will enhance scaling equity and effectiveness. WCA remains a medium priority due to slower digital transformation.

Sheet 4.Climate_adaptation
C1: Climate adaptation Indicator
A2: VH | B2: 5 | D2: LAC | E2: CWANA | F2: WCA | G2: ESA | H2: SA | I2: SEA
A3: H | B3: 4 | C3: Total score by column | D3: =SUM(D11:D59) -> 34 | E3: =SUM(E11:E59) -> 34 | F3: =SUM(F11:F59) -> 34 | G3: =SUM(G11:G59) -> 41 | H3: =SUM(H11:H59) -> 45 | I3: =SUM(I11:I59) -> 41
A4: MH | B4: 3 | C4: VH count by column | D4: =COUNTIF(D$11:D$59, 5) -> 0 | E4: =COUNTIF(E$11:E$59, 5) -> 0 | F4: =COUNTIF(F$11:F$59, 5) -> 0 | G4: =COUNTIF(G$11:G$59, 5) -> 0 | H4: =COUNTIF(H$11:H$59, 5) -> 0 | I4: =COUNTIF(I$11:I$59, 5) -> 0
A5: M | B5: 2 | C5: H count by column | D5: =COUNTIF(D$11:D$59, 4) -> 3 | E5: =COUNTIF(E$11:E$59, 4) -> 3 | F5: =COUNTIF(F$11:F$59, 4) -> 3 | G5: =COUNTIF(G$11:G$59, 4) -> 3 | H5: =COUNTIF(H$11:H$59, 4) -> 6 | I5: =COUNTIF(I$11:I$59, 4) -> 3
A6: L | B6: 1 | C6: MH count by column | D6: =COUNTIF(D$11:D$59, 3) -> 3 | E6: =COUNTIF(E$11:E$59, 3) -> 3 | F6: =COUNTIF(F$11:F$59, 3) -> 3 | G6: =COUNTIF(G$11:G$59, 3) -> 6 | H6: =COUNTIF(H$11:H$59, 3) -> 4 | I6: =COUNTIF(I$11:I$59, 3) -> 6
C7: M count by column | D7: =COUNTIF(D$11:D$59, 2) -> 4 | E7: =COUNTIF(E$11:E$59, 2) -> 4 | F7: =COUNTIF(F$11:F$59, 2) -> 4 | G7: =COUNTIF(G$11:G$59, 2) -> 5 | H7: =COUNTIF(H$11:H$59, 2) -> 4 | I7: =COUNTIF(I$11:I$59, 2) -> 5
C8: L count by column | D8: =COUNTIF(D$11:D$59, 1) -> 5 | E8: =COUNTIF(E$11:E$59, 1) -> 5 | F8: =COUNTIF(F$11:F$59, 1) -> 5 | G8: =COUNTIF(G$11:G$59, 1) -> 1 | H8: =COUNTIF(H$11:H$59, 1) -> 1 | I8: =COUNTIF(I$11:I$59, 1) -> 1 | K8: Current state (across the Global South) | L8: Ideal state (across the Global South) | M8: Assumptions (for region-specific scores) | N8: Requirements for success (internal to P/A) | O8: Requirements for success (from other P/As) | P8: Regional Implication
C10: HLO | D10: LAC | E10: CWANA | F10: WCA | G10: ESA | H10: SA | I10: SEA
A11: HLO count: | B11: =COUNTA(C11:C59) -> 15 | C11: =HLOs!D8 -> HLO 1.1.1: Demand signaling | D11: 4 | E11: 4 | F11: 4 | G11: 4 | H11: 4 | I11: 4 | K11: Climate-resilient demand signaling systems are largely underdeveloped across CGIAR regions. Existing mechanisms to identify adaptation and mitigation needs are either reactive or absent, especially at the local and regional levels. Most signals are top-down or project-driven, failing to capture evolving climate vulnerabilities or grassroots-level priorities (FAO, 2021; Gálvez, 2022; CGIAR, 2023; Schut et al., 2024). | L11: Integrated, anticipatory demand systems that proactively identify region-specific climate adaptation and mitigation needs. These systems are driven by participatory inputs, informed by climate risk data, and institutionalized across national and CGIAR frameworks to guide innovation scaling and investment (IPCC, 2022). | M11: The uniformly high scores for this HLO in SEA, SA, and LAC indicate the urgent need for demand systems that respond to region-specific climate shocks, rising exposure to extreme events, and lack of institutionalized feedback channels. It is assumed that these regions lack structured mechanisms to aggregate climate adaptation demands from local stakeholders into research and policy frameworks (World Bank, 2024). | N11: CGIAR must design and scale participatory climate demand platforms integrated with climate data, geospatial tools, and national research agendas. Initiatives should pilot real-time climate foresight systems and align research planning with demand signals emerging from vulnerable geographies (UNFCCC, 2022). | O11: Strong collaboration with national meteorological institutions, civil society actors, and local farmer organizations is needed to collect, validate, and institutionalize climate adaptation and mitigation needs. These external actors must be embedded in multi-level planning systems (FAO & WMO, 2021). | P11: SEA, SA, and LAC are top-priority regions where climate-related vulnerabilities are intensifying, but structured demand signaling systems remain absent. Strengthening regional demand articulation platforms is foundational to ensuring that climate-smart innovations address real and emerging adaptation and mitigation needs. Investments in data-enabled, inclusive mechanisms will offer the highest returns in these regions.
A12: Sets of 5: | B12: =_xlfn.FLOOR.MATH(B11/5) -> 3 | C12: =HLOs!D9 -> HLO 1.1.2: Feedback and adaptive research and scaling prioritization | D12: 3 | E12: 3 | F12: 3 | G12: 3 | H12: 4 | I12: 3 | K12: Feedback systems that connect climate risks and adaptation needs to CGIAR research remain weak, fragmented, and inconsistently used across regions. Research and scaling pathways are often rigid and unresponsive to real-time changes in climate exposure or farmer vulnerability, particularly in South Asia (Gálvez, 2022; CGIAR, 2023; Schut et al., 2024). | L12: Adaptive research frameworks that evolve with shifting climate risks, farmer experiences, and system shocks. These systems institutionalize two-way learning between field implementation and R&D teams, using early warning systems, participatory tools, and dynamic MELIA systems to continuously refine scaling strategies (IFPRI, 2023). | M12: The prioritization of SEA, SA, and LAC reflects both growing climate volatility and an absence of formal mechanisms to adapt research in response to these dynamics. It is assumed that CGIAR programs in these regions lack integration of real-time climate risk monitoring or localized learning loops, and that weak digital infrastructure hampers adaptive management (World Bank, 2020). | N12: CGIAR must embed climate monitoring and early warning systems into research pipelines and adaptive MELIA systems. This requires training scientists in anticipatory planning, standardizing climate-resilience indicators, and enabling internal responsiveness to farmer feedback under changing climate conditions (UNEP, 2021). | O12: Collaborations are needed with national meteorological agencies, grassroots adaptation networks, and community-based organizations to build robust data ecosystems and facilitate climate-responsive feedback into R&D agendas (WMO, 2022). | P12: SEA, SA, and LAC face urgent needs to strengthen adaptive research cycles that respond to local climate realities. Enhancing real-time feedback systems will be essential for ensuring climate innovations remain contextually relevant, particularly as these regions experience frequent extreme weather events and shifting seasonal patterns. Investments should prioritize regional learning platforms and community-anchored adaptation feedback channels.
A13: Remainder: | B13: =MOD(B11,5) -> 0 | C13: =HLOs!D10 -> HLO 1.1.3: Enhance strategies and coordination | D13: 2 | E13: 2 | F13: 2 | G13: 3 | H13: 3 | I13: 3 | K13: Climate adaptation and mitigation strategies often lack cross-sectoral coordination. Agricultural, environmental, and climate institutions frequently operate in silos, leading to fragmented investments, duplicative efforts, and gaps in the scaling of climate-resilient innovations. Integration with national climate plans is inconsistent, especially in SA and ESA (FAO, 2022). | L13: Highly coordinated, multi-actor strategies that align CGIAR innovation pipelines with national adaptation plans (NAPs), nationally determined contributions (NDCs), and other climate frameworks. These strategies bridge climate, agriculture, environment, and finance sectors and are co-developed with stakeholders to ensure locally grounded delivery (IPCC, 2022). | M13: Higher scores for SA and ESA reflect institutional fragmentation and poor inter-agency coordination, limiting the uptake of climate-smart innovations. SEA is moderately aligned but still lacks comprehensive integration of scaling strategies with climate priorities. It is assumed that without stronger national and regional coordination mandates, scaling will remain ad hoc (Gálvez, 2022; CGIAR, 2023; Schut et al., 2024). | N13: CGIAR must ensure that climate adaptation and mitigation goals are embedded in program strategies and scaling plans. This includes mapping alignment opportunities with NAPs and NDCs, establishing cross-Center coordination task forces, and fostering internal leadership capacity for climate strategy integration (HLPE, 2020). | O13: External success hinges on engagement with national climate planning bodies, regional adaptation platforms, and development partners working on climate mainstreaming. Strategic partnerships are needed with UNFCCC focal points, ministries of agriculture and environment, and multilateral funding agencies (UNESCAP, 2023). | P13: SA and ESA require urgent investment in institutional coordination for climate-related scaling. Strengthening inter-ministerial platforms and aligning CGIAR efforts with national climate strategies will help ensure innovations are not just climate-smart but also policy-relevant. SEA, while moderately aligned, would benefit from deeper integration of CGIAR programs with regional adaptation frameworks.
A14: Max score: | B14: =(B12*SUM($B$2:$B$6))+IF(B11=0,0,SUM($B$2:INDEX(B:B,$B$13+1))) -> 50 | C14: =HLOs!D11 -> HLO 2.2.1: Innovation networks enhance agrifood system solution scaling | D14: 1 | E14: 1 | F14: 1 | G14: 1 | H14: 1 | I14: 1 | K14: Innovation networks that support the co-development and diffusion of climate-smart agrifood solutions are generally underdeveloped. Where they exist, they are fragmented, short-term, and lack coordination across research, extension, and the private sector. Regional innovation ecosystems rarely prioritize climate resilience, leaving many innovations isolated from scaling pathways (World Bank, 2024). | L14: Inclusive, climate-smart innovation ecosystems that connect CGIAR Centers, NARES, agritech startups, extension services, and farmers across regions. These networks enable rapid piloting, knowledge exchange, and scaling of climate adaptation and mitigation innovations tailored to specific agroecological zones (Gálvez, 2022; CGIAR, 2023; Schut et al., 2024). | M14: Despite the recognized importance of innovation networks, this HLO received uniformly low prioritization across regions, including WCA, CWANA, and LAC, indicating that, relative to other climate adaptation needs, network-building currently holds limited strategic leverage. It is assumed that innovation networks will be more impactful when bundled with enabling policy reforms, demand signaling, and public-private investment platforms (FAO, 2022). | N14: CGIAR should focus on diagnostic groundwork—mapping climate innovation actors, identifying leverage points for engagement, and establishing protocols for co-creation. Emphasis should be on fostering internal coherence across Initiatives working on climate innovation, without duplicating national efforts (van Rijn et al., 2020). | O14: CGIAR must selectively support or partner with regional hubs, climate innovation accelerators, and inclusive business incubators. Public-private partnerships should be designed to complement existing platforms and avoid the creation of redundant systems (IFAD, 2021). | P14: Given low prioritization across all regions, including SA, ESA, SEA, WCA, and CWANA, this HLO is currently a medium- to long-term priority. Foundational investments—such as landscape analyses, relationship-building, and early-stage pilots—may be pursued, but immediate scaling gains are expected to be limited unless bundled with higher-priority HLOs like 1.1 (Demand signaling) and 2.3 (Bundling).
C15: =HLOs!D12 -> HLO 2.2.2: Methods evaluating agrifood system solutions for scale | D15: 1 | E15: 1 | F15: 1 | G15: 2 | H15: 2 | I15: 2 | K15: Current evaluation methods for agrifood innovations rarely integrate climate resilience metrics. Assessments of scalability are often ad hoc, retrospective, and disconnected from real-time adaptation and mitigation needs. Without structured tools, innovations may scale in ways that exacerbate vulnerabilities or ignore local climate contexts (Woltering et al., 2019). | L15: A standardized, climate-informed evaluation framework is embedded across CGIAR programs. This system proactively assesses the scalability of innovations in terms of resilience, mitigation potential, equity, and systems fit. Tools are applied iteratively throughout the innovation process to guide adaptive scaling decisions (Glover et al., 2019). | M15: Prioritization scores reflect high demand in SA, SEA, and ESA where adaptation challenges intersect with complex agroecological and social realities. It is assumed that scaling without robust climate-resilience diagnostics increases the risk of maladaptation. Lower capacity in WCA and CWANA may explain weaker uptake or recognition of this HLO’s relevance (Gálvez, 2022; CGIAR, 2023; Schut et al., 2024). | N15: CGIAR should develop and institutionalize evaluation toolkits that integrate climate adaptation/mitigation indicators. These tools must be built into MELIA systems, aligned with project cycles, and deployed at key decision points. Internal capacity building is required to use evaluation outputs for adaptive portfolio management (HLPE, 2020). | O15: External collaboration is needed with think tanks, climate science institutes, and evaluation networks to co-develop and validate methods. Development partners and national stakeholders must be engaged to align assessments with public planning and climate reporting requirements (FAO, 2022; IPCC, 2022). | P15: SA, SEA, LAC and ESA should be prioritized for deployment of climate-resilient scaling diagnostics. These regions show both the highest vulnerability and strongest demand for climate-smart innovation scaling. Although WCA and CWANA show lower readiness, early piloting may help build capacities for climate-informed evaluation systems.
C16: =HLOs!D13 -> HLO 2.2.3: Scale-ready agrifood system solution bundles and packages | D16: 3 | E16: 3 | F16: 3 | G16: 3 | H16: 4 | I16: 3 | K16: Agrifood innovations for climate adaptation are often implemented as standalone interventions—such as drought-tolerant seeds or climate advisory tools—without integration into holistic, climate-smart solution bundles. Existing efforts are fragmented, under-resourced, and poorly contextualized, limiting their scalability and long-term impact (Herrero et al., 2021). | L16: Ecosystem-specific, climate-resilient innovation bundles are developed, tested, and scaled. These bundles integrate technologies (e.g., resilient varieties), services (e.g., insurance, climate advisories), and enabling conditions (e.g., finance, behavior change communication) tailored to agroecological and socioeconomic contexts (Gálvez, 2022; CGIAR, 2023; Schut et al., 2024). | M16: High priority in SA, SEA, and LAC reflects urgent demand for localized climate adaptation bundles. In ESA, moderate prioritization indicates growing engagement but uneven bundling practices. WCA and CWANA score lower, suggesting limited bundling capacity or relevance perceived by regional stakeholders (FAO, 2022; World Bank, 2024). | N16: CGIAR must prioritize co-development of climate-smart bundles through cross-Center collaboration and local actor engagement. These efforts require harmonized bundling methodologies, knowledge-sharing platforms, and systems to test, adapt, and refine bundles across contexts. Internal alignment with the Climate and Resilience Initiatives is critical (HLPE, 2020). | O16: External success hinges on strategic partnerships with national agricultural research systems (NARS), farmer organizations, private input suppliers, and climate finance actors. Multi-stakeholder co-design, validation, and support systems are essential to ensure that bundles meet end-user needs and can be deployed at scale (UNFCCC, 2022; FAO, 2021). | P16: SA, SEA, and LAC should be prioritized for scaling climate-smart bundles, given their high vulnerability and stakeholder readiness. ESA shows potential for rapid gains with targeted investment, while WCA and CWANA require foundational work to build bundling capacity and stakeholder demand for integrated adaptation packages.
C17: =HLOs!D14 -> HLO 2.2.4: Agrifood system solution scaling strategies | D17: 4 | E17: 4 | F17: 4 | G17: 4 | H17: 4 | I17: 4 | K17: Agrifood system scaling strategies rarely integrate climate adaptation and mitigation coherently. Most approaches are fragmented, short-term, and reactive, focusing on pilot demonstrations rather than system-wide change. Alignment with National Adaptation Plans (NAPs) or Nationally Determined Contributions (NDCs) is often weak or missing (Wigboldus, 2018). | L17: Comprehensive scaling strategies are embedded within national climate adaptation and mitigation frameworks. These strategies emphasize systems thinking, coordinate across value chains and sectors, and align with long-term climate goals. CGIAR and partners implement adaptive, inclusive, and data-informed scaling pathways (Gálvez, 2022; CGIAR, 2023; Schut et al., 2024). | M17: SA, SEA, and LAC scored highest due to the urgency of climate threats and the need to transition from fragmented efforts to structured scaling strategies. ESA has ongoing efforts but requires stronger system orientation. WCA and CWANA scored lowest, indicating limited institutional traction and lower integration of scaling with climate strategies (FAO, 2022). | N17: CGIAR must integrate climate-responsive scaling frameworks into its research pipelines and delivery models. Internal alignment across Initiatives and the mainstreaming of climate adaptation/mitigation into Scaling Readiness tools and MELIA systems are key. Institutional leadership on climate-scaling convergence is needed (Woltering et al., 2019). | O17: External partners—including governments, donors, and climate finance institutions—must co-develop national and regional scaling roadmaps linked to NAPs/NDCs. Support is also needed to mobilize long-term financing and enable multistakeholder governance of climate-smart scaling (Green Climate Fund, 2021; IPCC, 2022). | P17: Scaling for Impact should prioritize SA, SEA, and LAC, where climate urgency aligns with institutional momentum for scaling transformation. In ESA, coordinated scaling strategies can reinforce emerging climate efforts. WCA and CWANA require foundational investments in institutional awareness, capacity, and cross-sector alignment.
C18: =HLOs!D15 -> HLO 3.3.1: Enabling environment diagnostics | D18: 2 | E18: 2 | F18: 2 | G18: 3 | H18: 3 | I18: 3 | K18: Diagnostic tools and processes that assess climate-specific barriers to scaling are poorly institutionalized across most regions. Where they exist, they tend to be general or sectoral, lacking climate vulnerability, governance, or finance lenses. As a result, CGIAR and national programs struggle to align innovations with enabling conditions for climate-smart scaling (World Bank, 2024). | L18: Institutionalized and iterative diagnostics identify regulatory, financial, institutional, and social barriers to climate-smart scaling. These diagnostics are embedded in program design and national planning cycles and aligned with climate risk and vulnerability assessments to ensure that scaling efforts target systemic constraints (FAO, 2022). | M18: SA and SEA show the greatest need for climate-informed diagnostics due to high climate vulnerability, fragmented governance, and weak policy integration. ESA shows moderate traction through some emerging diagnostic work. WCA and CWANA scored low, indicating limited diagnostic capacity or policy uptake (Gálvez, 2022; CGIAR, 2023; Schut et al., 2024). | N18: CGIAR must co-develop and institutionalize climate-smart diagnostic frameworks across Initiatives, ensuring these are tied to Scaling Readiness and MELIA systems. Diagnostics should assess factors like climate finance readiness, policy coherence, and inclusivity. These tools must be adaptable to regional contexts and support prioritization of climate-responsive interventions (UNEP, 2021). | O18: National governments and climate policy platforms must embed CGIAR-supported diagnostics into National Adaptation Plans (NAPs) and other instruments. External collaboration is essential with regional climate observatories, adaptation hubs, and donors who can translate diagnostic insights into enabling policy and investment reform (WMO, 2022; UNESCAP, 2023). | P18: SA and SEA should be the highest priority for CGIAR support to strengthen diagnostic capacity for scaling climate-smart solutions. In ESA, targeted partnerships can reinforce emerging diagnostic platforms. In WCA and CWANA, CGIAR should invest in foundational awareness-raising and pilot diagnostics to demonstrate relevance and build entry points.
C19: =HLOs!D16 -> HLO 3.3.2: Scaling support services for enabling environments and institutions | D19: 3 | E19: 3 | F19: 3 | G19: 3 | H19: 4 | I19: 3 | K19: Support services critical to scaling climate-smart innovations—such as insurance, climate finance, legal advisory, and technical assistance—are highly fragmented, underfunded, or inaccessible to vulnerable farmers and communities. Most CGIAR-linked projects rely on ad hoc partnerships, and public sector systems often lack the infrastructure and incentives to provide timely, localized support (FAO, 2022). | L19: Functional, inclusive ecosystems of climate-smart support services are developed and institutionalized. These ecosystems deliver bundled services—insurance, financial instruments, technical advisory, early warning access—tailored to the needs of vulnerable populations and aligned with climate adaptation and mitigation goals (IFAD, 2021). | M19: SA and SEA scored highest due to the critical gaps in climate finance access, limited insurance penetration, and weak advisory service ecosystems. ESA presents moderate opportunity due to emerging platforms and donor engagement. WCA and CWANA scored lowest, reflecting either systemic service delivery barriers or lower prioritization of climate-aligned service provision (Gálvez, 2022; CGIAR, 2023; Schut et al., 2024). | N19: CGIAR must work with Initiatives to map existing service gaps and develop models for bundling climate-relevant services into scaling programs. Internal coordination should focus on integrating support services into innovation delivery mechanisms and fostering partnerships with MELIA systems to monitor service uptake and effectiveness (UNFCCC, 2022). | O19: Externally, CGIAR should collaborate with global and regional microinsurance providers, rural climate finance platforms, and advisory extension networks to pilot and scale bundled services. National governments must also align regulatory frameworks and incentivize private sector engagement in climate-responsive service delivery (World Bank, 2020; IFAD, 2021). | P19: SA and SEA require urgent and targeted support to develop bundled, climate-smart services that reach vulnerable populations. In ESA, investments should build on existing service ecosystems and donor partnerships. In WCA and CWANA, foundational service diagnostics and awareness campaigns may be required before moving toward bundled support system development.
C20: =HLOs!D17 -> HLO 3.3.3: Science-policy partnership interfaces for responsible scaling | D20: 1 | E20: 1 | F20: 1 | G20: 2 | H20: 2 | I20: 2 | K20: Existing science-policy partnerships rarely prioritize climate adaptation and mitigation in a systematic way. Interactions between CGIAR researchers and national policymakers are often ad hoc or project-based, lacking formal platforms or sustained engagement on climate resilience and innovation scaling. This results in weak policy uptake of CGIAR climate innovations and limited co-design of adaptation strategies (Diao et al., 2023). | L20: Formalized, trusted platforms are established to connect CGIAR scientists, national governments, and climate policymakers. These platforms enable two-way communication, co-design of climate-smart policies, evidence-informed decision-making, and institutional learning across scaling programs for adaptation and mitigation (Gálvez, 2022; CGIAR, 2023; Schut et al., 2024). | M20: SA and SEA are scored as highest priority regions due to their vulnerability to climate extremes, ongoing climate policy development (e.g., NAPs, NDCs), and the lack of institutionalized science-policy interfaces. ESA presents moderate opportunity. WCA and CWANA scored lower, likely due to less active national adaptation agendas or limited CGIAR-policy engagement in these regions (FAO, 2022; World Bank, 2024). | N20: CGIAR must develop internal policy engagement capacities, including training researchers in policy communication and advocacy. A clear strategy is needed to embed policy influence goals into program design, and to integrate scientific evidence from adaptation pilots into national scaling policy frameworks (UNESCAP, 2023). | O20: Collaborations with ministries of environment, agriculture, and planning are critical. Governments should support the creation of CGIAR-linked climate policy working groups, integrate CGIAR findings into climate strategies, and fund joint agenda-setting processes. International organizations can catalyze these interfaces by convening regional dialogues and policy communities (World Bank, 2024; UNFCCC, 2022). | P20: SA and SEA are priority regions for strengthening CGIAR’s role in shaping climate scaling policy through institutionalized science-policy interfaces. ESA should be supported to build on existing structures. In WCA and CWANA, groundwork is needed through awareness-building, relationship development, and alignment with broader climate governance initiatives.
C21: =HLOs!D18 -> HLO 4.4.1: CGIAR Expertise and Solutions Embedded in Development Investments and Partnerships | D21: 4 | E21: 4 | F21: 4 | G21: 4 | H21: 4 | I21: 4 | K21: CGIAR’s climate adaptation and mitigation innovations are not systematically embedded in large-scale public or multilateral climate programs. Partnerships with national and regional investment programs are fragmented, short-term, and often limited to pilot phases. As a result, opportunities for broader uptake and funding of climate-smart technologies remain underutilized (Gálvez, 2022; CGIAR, 2023; Schut et al., 2024). | L21: CGIAR innovations and evidence directly inform the design, implementation, and scaling of national adaptation plans (NAPs), nationally determined contributions (NDCs), and multilateral climate investments. Long-term, institutionalized partnerships are established with ministries, IFIs, climate funds, and private investors to co-develop and scale climate-resilient innovations across geographies (IFPRI, 2023; FAO, 2022). | M21: SA, SEA, and LAC scored highest due to strong climate adaptation agendas, growing demand for scalable solutions, and alignment with global climate finance. However, CGIAR engagement in these regions is still evolving. It is assumed that institutional gaps, capacity constraints, and limited joint planning mechanisms hinder more systematic integration of CGIAR expertise in climate investment programs (World Bank, 2024; UNESCAP, 2023). | N21: Internally, CGIAR must develop structured engagement protocols and advisory frameworks for embedding climate-smart innovations into large-scale programs. Staff capacity in investment design, policy alignment, and cross-sector coordination needs strengthening. CGIAR must also establish climate-smart investment playbooks to support country teams in engaging public and private actors (Woltering et al., 2019). | O21: External success requires forging multi-stakeholder platforms and formal MOUs between CGIAR and government ministries, development banks (e.g., World Bank, GCF), and private climate investors. Stronger linkages with national climate plans and budgetary processes are essential. Engagement through global platforms like the UNFCCC (COP) can enhance visibility and uptake of CGIAR innovation portfolios (UNFCCC, 2022; Green Climate Fund, 2021). | P21: SA, SEA, and LAC are top-priority regions for embedding CGIAR innovations into climate investment frameworks. These regions have active climate policy and financing environments that align well with CGIAR’s scaling goals. ESA shows moderate opportunity, while WCA and CWANA need foundational engagement, awareness building, and partnership brokering to enable future integration.
C22: =HLOs!D19 -> HLO 4.4.2: Innovation portfolio management and scaling strategy support teams | D22: 1 | E22: 1 | F22: 1 | G22: 2 | H22: 2 | I22: 2 | K22: Existing scaling hubs across CGIAR are limited in their ability to integrate climate-smart innovation portfolios. Most do not specialize in climate adaptation or mitigation and often lack dedicated staff, tools, or regional linkages to support ecosystem-wide scaling for climate resilience (Gálvez, 2022; CGIAR, 2023; Schut et al., 2024). | L22: Fully functional climate-smart scaling hubs that operate across regions and programs, supporting the curation, contextualization, and deployment of innovations that enhance resilience and reduce emissions. These hubs serve as knowledge nodes, technical backstops, and conveners of public-private networks for accelerating climate-oriented scaling (World Bank, 2024). | M22: Based on the KBP exercise, SA, SEA, and LAC are considered priority regions due to rising climate vulnerabilities and active climate policy frameworks. The absence of specialized scaling hubs in these regions limits CGIAR’s capacity to coordinate delivery efforts aligned with national climate plans and multilateral investments. | N22: Internally, CGIAR must invest in upgrading existing hubs or establishing new regional platforms that explicitly integrate climate priorities. This includes developing climate-smart innovation repositories, staff training in resilience assessment and carbon accounting, and mainstreaming climate metrics into scaling tools and dashboards (UNESCAP, 2023; Woltering et al., 2019). | O22: External success requires coordinated engagement with national agricultural research and extension systems (NARES), climate funds (e.g., GCF, IFAD), and innovation intermediaries. Hubs must secure long-term financing and be linked to national climate policy bodies, including ministries of environment and agriculture, and be aligned with global climate action platforms (Green Climate Fund, 2021; UNFCCC, 2022). | P22: SA, SEA, and LAC require immediate establishment or upgrading of regional climate-focused scaling hubs. These regions face complex climate risks and house large smallholder populations needing tailored innovation delivery. ESA is moderately prepared but still needs functional integration. WCA and CWANA will benefit from knowledge exchange and hub replication models adapted to their climate and institutional contexts.
