Workbook

Sheet README
A1: Initial prioritization for the Sustainable Farming Program
A2: Method: Follows System Organization Guidance, March 2025
A3: Full methods document: under development
A4: Questions: Todd Rosenstock, t.rosenstock@cgiar.org

Sheet Country-regions
A1: Countries, per region, worked on by [Insert Program/Accelerator name]
A2: CGIAR regions and countries.xlsx | B2: <-- Spreadsheet showing the CGIAR regions and the countries that fall into these regions
A3: Program and Accelerator's Countries (2024).xlsx | B3: <-- Spreadsheet showing the countries that each Program/Accelerator is working on (as per what was submitted in 2024 for the original methodology).
A4: LAC | B4: CWANA | C4: WCA | D4: ESA | E4: SA | F4: SEA
A5: Colmbia | B5: Algeria | C5: Benin | D5: Burundi | E5: Bangladesh | F5: Cambodia
A6: Ecuador | B6: Bahrain | C6: Burkina Faso | D6: Eswatini | E6: India | F6: Laos PDR
A7: Mexico | B7: Egypt | C7: Cameroon | D7: Ethiopia | E7: Nepal | F7: Pilippines
A8: Peru | B8: Iraq | C8: Congo | D8: Kenya | E8: Pakistan | F8: Vietnam
B9: Jordan | C9: Côte d'Ivoire | D9: Lesotho
B10: Kuwait | C10: Democratic Republic of the Congo (DRC) | D10: Madagascar
B11: Lebanon | C11: Ghana | D11: Malawi
B12: Morocco | C12: Liberia | D12: Mozambique
B13: Oman | C13: Mali | D13: Namibia
B14: Palestine | C14: Niger | D14: Rwanda
B15: Qatar | C15: Nigeria | D15: South Africa
B16: Saudi Arabia | C16: Senegal | D16: Sudan
B17: Tunisia | C17: Sierra Leone | D17: Tanzania
B18: Turkey | C18: Togo | D18: Uganda
B19: United Arab Emirates (UAE) | D19: Zambia

Sheet HLOs
A2: VH | B2: 5
A3: H | B3: 4
A4: MH | B4: 3
A5: M | B5: 2
A6: L | B6: 1
C7: # | D7: HLO + concise description
A8: HLO count: | B8: =COUNTA(D8:D58) -> 34 | C8: 1 | D8: HLO 1.1: Quantified climate change-related hazards that affect the delivery of agronomic gain
A9: Sets of 5: | B9: =_xlfn.FLOOR.MATH(B8/5) -> 6 | C9: 2 | D9: HLO 1.2: Climate hazard-specific inclusive sustainable farming system innovations
A10: Remainder: | B10: =MOD(B8,5) -> 4 | C10: 3 | D10: HLO 1.3: Training materials for climate adaptation and mitigation
A11: Max score: | B11: =(B9*SUM($B$2:$B$6))+IF(B8=0,0,SUM(B2:INDEX(B:B,$B$10+1))) -> 104 | C11: 4 | D11: HLO 1.4: Policy and investment-ready information on sustainable farming solutions
C12: 5 | D12: HLO 2.1: Spatially-explicit recommendation decision support models for soil nutrient constraints
C13: 6 | D13: HLO 2.2: Expanded data-driven agronomic recommendations for site-specific nutrient management
C14: 7 | D14: HLO 2.3: Training materials for site-specific nutrient management
C15: 8 | D15: HLO 2.4: Evidence for policy recommendations for precision nutrient management
C16: 9 | D16: HLO 3.1: Soil health monitoring and assessment framework operationalized
C17: 10 | D17: HLO 3.2: Network of long-term monitoring sites for carbon storage assessment
C18: 11 | D18: HLO 3.3: Impacts of agricultural practices quantified and catalogued
C19: 12 | D19: HLO 3.4: Evidence for policy makers on soil health translated to accessible formats
C20: 13 | D20: HLO 4.1: Capacity and networks of plant health practitioners improved
C21: 14 | D21: HLO 4.2: Improved pest and disease monitoring and modeling tools
C22: 15 | D22: HLO 4.3: Surveillance data and prevention strategies available
C23: 16 | D23: HLO 4.4: Eco-friendly options for integrated pest management developed
... C41: 34 | D41: HLO 8.5: Policy-related information for sustainable farming systems
C42: 35
C43: 36
C44: 37
C45: 38
C46: 39
C47: 40
C48: 41
C49: 42
C50: 43
C51: 44
C52: 45
C53: 46
... C57: 50

Sheet Indicators
A1: BASE Indicator database - (from 2024).xlsx | C1: <-- source of Baseline data
A2: Projected Benefits Data (Nov 2024) - With Analysis.xlsx | C2: <-- source of Projected data (with graphs)
A3: Impact Area | B3: Projected to 2040 (without CGIAR intervention) or baseline data? | C3: Indicator | D3: r_lac | E3: r_cwana | F3: r_wca | G3: r_esa | H3: r_sa | I3: r_sea
A5: Nutrition | B5: Baseline data | C5: Prevalence of stunting (height for age <-2 standard deviation from the median of the World Health Organization (WHO) Child Growth Standards) % children under 5 years of age | D5: 11.679145 | E5: 17.238147 | F5: 31.597628 | G5: 30.494793 | H5: 34.286344 | I5: 11.083749
A6: Nutrition | B6: Baseline data | C6: Prevalence of wasting (weight for height >+2 or <-2 standard deviation from the median of the WHO Child Growth Standards) % children under 5 years of age | D6: 2.2309085 | E6: 5.8629686 | F6: 6.7930741 | G6: 5.4676809 | H6: 16.318465 | I6: 3.6836782
A7: Nutrition | B7: Baseline data | C7: % of population unable to afford a healthy diet | D7: 22.261332 | E7: 37.375529 | F7: 84.372957 | G7: 82.105349 | H7: 73.246664 | I7: 24.396071
A8: Nutrition | B8: Baseline data | C8: Women meeting minimum dietary diversity (MDD-W)(%) | D8: 77.386889 | E8: 73.431162 | F8: 47.825418 | G8: 47.455003 | H8: 44.789895 | I8: 84.612374 | J8: MDD-W - higher value indicates more women meeting the minimum (i.e., a lower potential for impact) --- Minimum Dietary Diversity for Women is a population-level food group-based indicator that captures dietary diversity, a core construct of healthy diets. MDD-W is used to estimate the proportion of non-pregnant women aged 15-49 years who consumed at least five out of ten defined food groups over the previous 24 hours, signalling better micronutrient intake. indicator that captures dietary diversity, a core construct of healthy diets. MDD-W is used to estimate the proportion of non-pregnant women aged 15-49 years who consumed at least five out of ten defined food groups over the previous 24 hours, signalling better micronutrient intake. -- Note that we calculated it as 100% minus the MDD-W (i.e., women not meeting ...) such that higher values correspond with higher potential for impact,
A9: Gender | B9: Baseline data | C9: Proportion of youth (aged 15-24 years) not in education, employment or training (NEET) (%) | D9: 20.353948 | E9: 28.808683 | F9: 22.22403 | G9: 22.032946 | H9: 25.579269 | I9: 13.900333
A10: Gender | B10: Baseline data | C10: Gender Development Index (GDI) | D10: 0.98711807 | E10: 0.86109472 | F10: 0.88128823 | G10: 0.92987576 | H10: 0.85713094 | I10: 0.96249076 | J10: GDI measures gender inequalities in achievement in three basic dimensions of human development: health, measured by female and male life expectancy at birth; education, measured by female and male expected years of schooling for children and female and male mean years of schooling for adults ages 25 years and older; and command over economic resources, measured by female and male estimated earned income.
A11: Gender | B11: Baseline data | C11: Gender Inequality Index (GII) | D11: 0.3786 | E11: 0.4202 | F11: 0.6154 | G11: 0.51 | H11: 0.4542 | I11: 0.2426 | J11: GII is a composite metric of gender inequality using three dimensions: reproductive health, empowerment and the labour market. A low GII value indicates low inequality between women and men, and vice-versa.
A12: Poverty | B12: Baseline data | C12: The ratio of the people employed in agriculture in rural areas over all people employed in rural areas" | D12: 46.830763 | E12: 34.609244 | F12: 64.335138 | G12: 71.949092 | H12: 56.611142 | I12: 44.992877
A13: Climate | B13: Baseline data | C13: Vulnerability index of the geography (exposure, sensitivity and adaptive capacity in six life-supporting sectors: food, water, health, ecosystem services, human habitat, and infrastructure). | D13: 0.38522854 | E13: 0.41856096 | F13: 0.52689312 | G13: 0.51707456 | H13: 0.50168331 | I13: 0.40802057
A14: Climate | B14: Baseline data | C14: Emissions intensity - CO2eq emissions from croplands (kg/ha) (Carlson et al., 2017) | D14: 386 | E14: 444 | F14: 312 | G14: 531 | H14: 2090 | I14: 3326
A15: Climate | B15: Baseline data | C15: CRI - Climate Risk Index - the index of the level of exposure and vulnerability to extreme events such as storms, floods and heatwaves based on historic data | D15: 46.593083 | E15: 71.63158 | F15: 73.530172 | G15: 45.434032 | H15: 18.194338 | I15: 40.16028
A16: Environment | B16: Baseline data | C16: Consumptive blue and green water used in food production (m3/ha) | D16: 5008.9819 | E16: 3795.1862 | F16: 4064.7898 | G16: 4368.5844 | H16: 5065.8423 | I16: 6113.5583
A17: Environment | B17: Baseline data | C17: Soil erosion rate (/Ha) | D17: 4480.2558 | E17: 2629.3874 | F17: 5858.9939 | G17: 7924.0507 | H17: 10121.16 | I17: 7076.2489
A18: Environment | B18: Baseline data | C18: Forest area lost (%) - the percentage of forested area (%) lost between 2010 and 2020 | D18: 4.0133292 | E18: 3.0328342 | F18: 8.736605 | G18: 6.4758874 | H18: 0.80036497 | I18: 1.9236632
A19: Environment | B19: Baseline data | C19: GBI - Global Biodiversity Index - Total number of plant, reptile, mammal, bird, fish and amphibian species | D19: 362.31193 | E19: 80.081948 | F19: 116.18798 | G19: 156.28684 | H19: 264.30093 | I19: 324.04395
A20: Environment | B20: Baseline data | C20: Sustainable agriculture score - Index quantifying progress toward productive and sustainable agriculture (current status score) | D20: 3.7142926 | E20: 3.0915505 | F20: 3.2533234 | G20: 2.8150793 | H20: 2.5514288 | I20: 3.9867322
A22: Impact Area | B22: Projected to 2040 (without CGIAR intervention) | C22: Indicator | D22: r_lac | X22: r_cwana | AR22: r_wca | BL22: r_esa | CF22: r_sa | CZ22: r_sea
D23: 2021 | E23: 2022 | F23: 2023 | G23: 2024 | H23: 2025 | I23: 2026 | J23: 2027 | K23: 2028 | L23: 2029 | M23: 2030 | N23: 2031 | O23: 2032 | P23: 2033 | Q23: 2034 | R23: 2035 | S23: 2036 | T23: 2037 | U23: 2038 | V23: 2039 | W23: 2040 | X23: 2021 | Y23: 2022 | Z23: 2023 | AA23: 2024 | AB23: 2025 | AC23: 2026 | AD23: 2027 | AE23: 2028 | AF23: 2029 | AG23: 2030 | AH23: 2031 | AI23: 2032 | AJ23: 2033 | AK23: 2034 | AL23: 2035 | AM23: 2036 | AN23: 2037 | AO23: 2038 | AP23: 2039 | AQ23: 2040 | AR23: 2021 | AS23: 2022 | AT23: 2023 | AU23: 2024 | AV23: 2025 | AW23: 2026 | AX23: 2027 | AY23: 2028 | AZ23: 2029 | BA23: 2030 | BB23: 2031 | BC23: 2032 | BD23: 2033 | BE23: 2034 | BF23: 2035 | BG23: 2036 | BH23: 2037 | BI23: 2038 | BJ23: 2039 | BK23: 2040 | BL23: 2021 | BM23: 2022 | BN23: 2023 | BO23: 2024 | BP23: 2025 | BQ23: 2026 | BR23: 2027 | BS23: 2028 | BT23: 2029 | BU23: 2030 | BV23: 2031 | BW23: 2032 | BX23: 2033 | BY23: 2034 | BZ23: 2035 | CA23: 2036 | CB23: 2037 | CC23: 2038 | CD23: 2039 | CE23: 2040 | CF23: 2021 | CG23: 2022 | CH23: 2023 | CI23: 2024 | CJ23: 2025 | CK23: 2026 | CL23: 2027 | CM23: 2028 | CN23: 2029 | CO23: 2030 | CP23: 2031 | CQ23: 2032 | CR23: 2033 | CS23: 2034 | CT23: 2035 | CU23: 2036 | CV23: 2037 | CW23: 2038 | CX23: 2039 | CY23: 2040 | CZ23: 2021 | DA23: 2022 | DB23: 2023 | DC23: 2024 | DD23: 2025 | DE23: 2026 | DF23: 2027 | DG23: 2028 | DH23: 2029 | DI23: 2030 | DJ23: 2031 | DK23: 2032 | DL23: 2033 | DM23: 2034 | DN23: 2035 | DO23: 2036 | DP23: 2037 | DQ23: 2038 | DR23: 2039 | DS23: 2040
A24: Nutrition | B24: Projected to 2040 | C24: Prevalence of Undernourishment - Share of total population living below the minimum calorie daily threshold | D24: 7.1892578 | E24: 6.68889 | F24: 6.2115266 | G24: 5.7570393 | H24: 5.3252329 | I24: 4.9158466 | J24: 4.5285569 | K24: 4.1629803 | L24: 3.8186764 | M24: 3.4951517 | N24: 3.1918631 | O24: 2.908223 | P24: 2.6436027 | Q24: 2.3973382 | R24: 2.1687341 | S24: 1.9570691 | T24: 1.7616009 | U24: 1.5815713 | V24: 1.4162109 | W24: 1.2647443 | X24: 9.1504665 | Y24: 8.9091662 | Z24: 8.6634743 | AA24: 8.4138444 | AB24: 8.160744 | AC24: 7.9046538 | AD24: 7.6460667 | AE24: 7.3854859 | AF24: 7.123424 | AG24: 6.8604013 | AH24: 6.5969443 | AI24: 6.3335834 | AJ24: 6.0708516 | AK24: 5.809282 | AL24: 5.5494058 | AM24: 5.2917502 | AN24: 5.0368357 | AO24: 4.7851739 | AP24: 4.537265 | AQ24: 4.2935953 | AR24: 18.91209 | AS24: 18.415278 | AT24: 17.911492 | AU24: 17.401678 | AV24: 16.886799 | AW24: 16.367828 | AX24: 15.845748 | AY24: 15.321548 | AZ24: 14.796218 | BA24: 14.270749 | BB24: 13.746128 | BC24: 13.223332 | BD24: 12.703327 | BE24: 12.187064 | BF24: 11.675475 | BG24: 11.169467 | BH24: 10.669921 | BI24: 10.177686 | BJ24: 9.6935781 | BK24: 9.2183741 | BL24: 22.510157 | BM24: 21.490211 | BN24: 20.474437 | BO24: 19.465188 | BP24: 18.464847 | BQ24: 17.475809 | BR24: 16.500465 | BS24: 15.541184 | BT24: 14.600291 | BU24: 13.680052 | BV24: 12.782652 | BW24: 11.910171 | BX24: 11.064571 | BY24: 10.247669 | BZ24: 9.4611245 | CA24: 8.7064163 | CB24: 7.9848318 | CC24: 7.2974499 | CD24: 6.645131 | CE24: 6.0285075 | CF24: 15.036352 | CG24: 13.50078 | CH24: 12.058387 | CI24: 10.711231 | CJ24: 9.460449 | CK24: 8.306251 | CL24: 7.2479364 | CM24: 6.2839238 | CN24: 5.4118015 | CO24: 4.6283937 | CP24: 3.9298411 | CQ24: 3.3116949 | CR24: 2.76902 | CS24: 2.2965049 | CT24: 1.8885759 | CU24: 1.53951 | CV24: 1.2435457 | CW24: 0.99498599 | CX24: 0.78829295 | CY24: 0.6181697 | CZ24: 2.9870488 | DA24: 2.5739841 | DB24: 2.2066181 | DC24: 1.8817105 | DD24: 1.5959854 | DE24: 1.3461739 | DF24: 1.1290543 | DG24: 0.94148797 | DH24: 0.78045059 | DI24: 0.64305899 | DJ24: 0.52659245 | DK24: 0.42850921 | DL24: 0.34645781 | DM24: 0.27828373 | DN24: 0.2220316 | DO24: 0.1759435 | DP24: 0.13845375 | DQ24: 0.10818092 | DR24: 0.083917403 | DS24: 0.06461742
A25: Gender | B25: WE CURRENTLY DON’T HAVE APPROPRIATE INDICATORS PROJECTED FOR THE GENDER IMPACT AREA - PLEASE USE BASELINE DATA ONLY
A26: Poverty | B26: Projected to 2040 | C26: Poverty Headcount Rate ($2.15) - Share of total population living below the poverty line | D26: 4.98557 | E26: 5.0242558 | F26: 5.0621172 | G26: 5.0991222 | H26: 5.1352386 | I26: 5.1704341 | J26: 5.2046757 | K26: 5.2379303 | L26: 5.2701643 | M26: 5.3013441 | N26: 5.3314354 | O26: 5.3604039 | P26: 5.3882149 | Q26: 5.4148334 | R26: 5.4402242 | S26: 5.4643519 | T26: 5.4871807 | U26: 5.5086747 | V26: 5.5287977 | W26: 5.5475134 | X26: 4.59918 | Y26: 4.4042124 | Z26: 4.2131091 | AA26: 4.02598 | AB26: 3.84293 | AC26: 3.6640582 | AD26: 3.4894579 | AE26: 3.319216 | AF26: 3.1534129 | AG26: 2.9921218 | AH26: 2.8354089 | AI26: 2.6833326 | AJ26: 2.5359435 | AK26: 2.3932841 | AL26: 2.2553884 | AM26: 2.1222821 | AN26: 1.9939817 | AO26: 1.8704952 | AP26: 1.7518213 | AQ26: 1.6379496 | AR26: 36.30807 | AS26: 36.185862 | AT26: 36.061701 | AU26: 35.935577 | AV26: 35.807479 | AW26: 35.677395 | AX26: 35.545315 | AY26: 35.411226 | AZ26: 35.275116 | BA26: 35.136975 | BB26: 34.996788 | BC26: 34.854543 | BD26: 34.710229 | BE26: 34.56383 | BF26: 34.415335 | BG26: 34.26473 | BH26: 34.112002 | BI26: 33.957135 | BJ26: 33.800117 | BK26: 33.640934 | BL26: 38.89568 | BM26: 38.85434 | BN26: 38.811608 | BO26: 38.767445 | BP26: 38.721807 | BQ26: 38.674652 | BR26: 38.625933 | BS26: 38.575602 | BT26: 38.523611 | BU26: 38.469907 | BV26: 38.414438 | BW26: 38.357148 | BX26: 38.297978 | BY26: 38.236869 | BZ26: 38.173758 | CA26: 38.10858 | CB26: 38.041268 | CC26: 37.97175 | CD26: 37.899953 | CE26: 37.825801 | CF26: 11.48274 | CG26: 10.469358 | CH26: 9.4825203 | CI26: 8.5274757 | CJ26: 7.6094386 | CK26: 6.7334754 | CL26: 5.904376 | CM26: 5.126516 | CN26: 4.4037126 | CO26: 3.7390816 | CP26: 3.134903 | CQ26: 2.5925037 | CR26: 2.1121683 | CS26: 1.6930861 | CT26: 1.3333448 | CU26: 1.0299761 | CV26: 0.77905634 | CW26: 0.57586239 | CX26: 0.41507324 | CY26: 0.29100712 | CZ26: 1.23059 | DA26: 0.88984793 | DB26: 0.6221891 | DC26: 0.41911725 | DD26: 0.27092336 | DE26: 0.16738356 | DF26: 0.098482932 | DG26: 0.055066945 | DH26: 0.029330068 | DI26: 0.015081471 | DJ26: 0.0077742847 | DK26: 0.0043346014 | DL26: 0.0028635352 | DM26: 0.0022984445 | DN26: 0.0021059525 | DO26: 0.0020486343 | DP26: 0.0020339519 | DQ26: 0.002030774 | DR26: 0.0020302043 | DS26: 0.0020301216
A27: Poverty | B27: Projected to 2040 | C27: Poverty Headcount Rate ($3.65) - Share of total population living below the poverty line | D27: 12.326178 | E27: 12.381889 | F27: 12.436252 | G27: 12.489232 | H27: 12.540798 | I27: 12.590913 | J27: 12.639544 | K27: 12.686654 | L27: 12.732209 | M27: 12.776171 | N27: 12.818504 | O27: 12.85917 | P27: 12.898132 | Q27: 12.935351 | R27: 12.970787 | S27: 13.004401 | T27: 13.036154 | U27: 13.066003 | V27: 13.093907 | W27: 13.119826 | X27: 14.288423 | Y27: 13.982703 | Z27: 13.67684 | AA27: 13.370967 | AB27: 13.065221 | AC27: 12.759739 | AD27: 12.454666 | AE27: 12.150146 | AF27: 11.846328 | AG27: 11.543362 | AH27: 11.241404 | AI27: 10.940608 | AJ27: 10.641135 | AK27: 10.343146 | AL27: 10.046804 | AM27: 9.7522739 | AN27: 9.4597232 | AO27: 9.1693202 | AP27: 8.8812344 | AQ27: 8.5956364 | AR27: 64.127509 | AS27: 64.124548 | AT27: 64.121536 | AU27: 64.118473 | AV27: 64.115359 | AW27: 64.112192 | AX27: 64.108972 | AY27: 64.105699 | AZ27: 64.102372 | BA27: 64.098991 | BB27: 64.095554 | BC27: 64.092063 | BD27: 64.088515 | BE27: 64.08491 | BF27: 64.081248 | BG27: 64.077527 | BH27: 64.073748 | BI27: 64.06991 | BJ27: 64.066011 | BK27: 64.062051 | BL27: 65.516569 | BM27: 65.515305 | BN27: 65.513998 | BO27: 65.512647 | BP27: 65.511251 | BQ27: 65.509807 | BR27: 65.508315 | BS27: 65.506774 | BT27: 65.50518 | BU27: 65.503534 | BV27: 65.501833 | BW27: 65.500075 | BX27: 65.498258 | BY27: 65.496382 | BZ27: 65.494442 | CA27: 65.492439 | CB27: 65.490368 | CC27: 65.488229 | CD27: 65.486018 | CE27: 65.483733 | CF27: 43.13417 | CG27: 42.785936 | CH27: 42.423103 | CI27: 42.045096 | CJ27: 41.651323 | CK27: 41.241181 | CL27: 40.814053 | CM27: 40.369309 | CN27: 39.906311 | CO27: 39.424414 | CP27: 38.922966 | CQ27: 38.401314 | CR27: 37.858808 | CS27: 37.294802 | CT27: 36.708661 | CU27: 36.099766 | CV27: 35.467522 | CW27: 34.811364 | CX27: 34.130765 | CY27: 33.425246 | CZ27: 6.6233529 | DA27: 5.5934126 | DB27: 4.6450586 | DC27: 3.7861739 | DD27: 3.0226307 | DE27: 2.3578335 | DF27: 1.7923687 | DG27: 1.323821 | DH27: 0.94680861 | DI27: 0.65326964 | DJ27: 0.43300161 | DK27: 0.2744137 | DL27: 0.16540941 | DM27: 0.094283044 | DN27: 0.050501138 | DO27: 0.025256507 | DP27: 0.011729008 | DQ27: 0.0050518673 | DR27: 0.0020459537 | DS27: 0.00082542745
A28: Poverty | B28: Projected to 2040 | C28: Poverty Headcount Rate ($6.85) - Share of total population living below the poverty line | D28: 31.99797 | E28: 32.039063 | F28: 32.079058 | G28: 32.117939 | H28: 32.155689 | I28: 32.192292 | J28: 32.227729 | K28: 32.261984 | L28: 32.295038 | M28: 32.326872 | N28: 32.357466 | O28: 32.386801 | P28: 32.414856 | Q28: 32.441611 | R28: 32.467043 | S28: 32.491131 | T28: 32.513851 | U28: 32.535181 | V28: 32.555096 | W28: 32.573571 | X28: 39.779017 | Y28: 39.643681 | Z28: 39.506381 | AA28: 39.367094 | AB28: 39.225797 | AC28: 39.082466 | AD28: 38.937077 | AE28: 38.789605 | AF28: 38.640025 | AG28: 38.488313 | AH28: 38.334443 | AI28: 38.178388 | AJ28: 38.020124 | AK28: 37.859624 | AL28: 37.69686 | AM28: 37.531806 | AN28: 37.364435 | AO28: 37.194718 | AP28: 37.022628 | AQ28: 36.848136 | AR28: 88.509867 | AS28: 88.506906 | AT28: 88.503894 | AU28: 88.500831 | AV28: 88.497716 | AW28: 88.494549 | AX28: 88.49133 | AY28: 88.488056 | AZ28: 88.48473 | BA28: 88.481348 | BB28: 88.477912 | BC28: 88.47442 | BD28: 88.470872 | BE28: 88.467267 | BF28: 88.463605 | BG28: 88.459885 | BH28: 88.456106 | BI28: 88.452267 | BJ28: 88.448368 | BK28: 88.444408 | BL28: 87.43947 | BM28: 87.438206 | BN28: 87.4369 | BO28: 87.435549 | BP28: 87.434152 | BQ28: 87.432709 | BR28: 87.431217 | BS28: 87.429675 | BT28: 87.428082 | BU28: 87.426435 | BV28: 87.424734 | BW28: 87.422976 | BX28: 87.42116 | BY28: 87.419283 | BZ28: 87.417344 | CA28: 87.41534 | CB28: 87.413269 | CC28: 87.41113 | CD28: 87.408919 | CE28: 87.406634 | CF28: 80.974435 | CG28: 80.959243 | CH28: 80.943388 | CI28: 80.92684 | CJ28: 80.909568 | CK28: 80.891539 | CL28: 80.872719 | CM28: 80.853071 | CN28: 80.832558 | CO28: 80.811141 | CP28: 80.788779 | CQ28: 80.765429 | CR28: 80.741045 | CS28: 80.71558 | CT28: 80.688986 | CU28: 80.66121 | CV28: 80.632198 | CW28: 80.601895 | CX28: 80.57024 | CY28: 80.537172 | CZ28: 29.55282 | DA28: 28.453081 | DB28: 27.310321 | DC28: 26.125513 | DD28: 24.900204 | DE28: 23.636605 | DF28: 22.337679 | DG28: 21.007236 | DH28: 19.650019 | DI28: 18.271781 | DJ28: 16.879345 | DK28: 15.480643 | DL28: 14.084712 | DM28: 12.701646 | DN28: 11.342485 | DO28: 10.019034 | DP28: 8.7435908 | DQ28: 7.528593 | DR28: 6.3861649 | DS28: 5.327589
A29: Poverty | B29: Projected to 2040 | C29: Agrifood System Jobs (incl. subsistence farming and informal sector) - millions of workers | D29: 79.453806 | E29: 81.086566 | F29: 82.7612 | G29: 84.478933 | H29: 86.241033 | I29: 88.048807 | J29: 89.903606 | K29: 91.806824 | L29: 93.759905 | M29: 95.764336 | N29: 97.821657 | O29: 99.933458 | P29: 102.10138 | Q29: 104.32713 | R29: 106.61247 | S29: 108.95919 | T29: 111.3692 | U29: 113.84443 | V29: 116.3869 | W29: 118.99868 | X29: 50.377779 | Y29: 51.475884 | Z29: 52.606947 | AA29: 53.772164 | AB29: 54.972781 | AC29: 56.210098 | AD29: 57.485472 | AE29: 58.800317 | AF29: 60.156109 | AG29: 61.554391 | AH29: 62.996771 | AI29: 64.48493 | AJ29: 66.020625 | AK29: 67.605691 | AL29: 69.242045 | AM29: 70.931693 | AN29: 72.676732 | AO29: 74.479356 | AP29: 76.341859 | AQ29: 78.266643 | AR29: 118.18601 | AS29: 122.23843 | AT29: 126.45317 | AU29: 130.8372 | AV29: 135.39785 | AW29: 140.14274 | AX29: 145.07984 | AY29: 150.21751 | AZ29: 155.56444 | BA29: 161.12976 | BB29: 166.92299 | BC29: 172.9541 | BD29: 179.23348 | BE29: 185.77203 | BF29: 192.58113 | BG29: 199.67268 | BH29: 207.05915 | BI29: 214.75354 | BJ29: 222.76947 | BK29: 231.1212 | BL29: 152.33566 | BM29: 158.07421 | BN29: 164.07237 | BO29: 170.34342 | BP29: 176.90137 | BQ29: 183.76104 | BR29: 190.93808 | BS29: 198.44902 | BT29: 206.31135 | BU29: 214.54355 | BV29: 223.16518 | BW29: 232.19692 | BX29: 241.66066 | BY29: 251.57954 | BZ29: 261.9781 | CA29: 272.88229 | CB29: 284.3196 | CC29: 296.31915 | CD29: 308.91182 | CE29: 322.1303 | CF29: 335.11902 | CG29: 345.66882 | CH29: 356.63814 | CI29: 368.04754 | CJ29: 379.91877 | CK29: 392.27487 | CL29: 405.14024 | CM29: 418.54076 | CN29: 432.50383 | CO29: 447.05854 | CP29: 462.23575 | CQ29: 478.06821 | CR29: 494.5907 | CS29: 511.84016 | CT29: 529.85585 | CU29: 548.6795 | CV29: 568.3555 | CW29: 588.93105 | CX29: 610.45641 | CY29: 632.98506 | CZ29: 430.51747 | DA29: 439.33041 | DB29: 448.38064 | DC29: 457.67536 | DD29: 467.22202 | DE29: 477.02828 | DF29: 487.10209 | DG29: 497.45165 | DH29: 508.08544 | DI29: 519.0122 | DJ29: 530.24097 | DK29: 541.7811 | DL29: 553.64225 | DM29: 565.8344 | DN29: 578.36786 | DO29: 591.25328 | DP29: 604.5017 | DQ29: 618.12449 | DR29: 632.13342 | DS29: 646.54069
A30: Poverty | B30: Projected to 2040 | C30: Agrifood System GDP Per Worker - US$ per worker | D30: 9757.9382 | E30: 9757.9382 | F30: 9757.9382 | G30: 9757.9382 | H30: 9757.9382 | I30: 9757.9382 | J30: 9757.9382 | K30: 9757.9382 | L30: 9757.9382 | M30: 9757.9382 | N30: 9757.9382 | O30: 9757.9382 | P30: 9757.9382 | Q30: 9757.9382 | R30: 9757.9382 | S30: 9757.9382 | T30: 9757.9382 | U30: 9757.9382 | V30: 9757.9382 | W30: 9757.9382 | X30: 11320.812 | Y30: 11320.812 | Z30: 11320.812 | AA30: 11320.812 | AB30: 11320.812 | AC30: 11320.812 | AD30: 11320.812 | AE30: 11320.812 | AF30: 11320.812 | AG30: 11320.812 | AH30: 11320.812 | AI30: 11320.812 | AJ30: 11320.812 | AK30: 11320.812 | AL30: 11320.812 | AM30: 11320.812 | AN30: 11320.812 | AO30: 11320.812 | AP30: 11320.812 | AQ30: 11320.812 | AR30: 2860.2434 | AS30: 2860.2434 | AT30: 2860.2434 | AU30: 2860.2434 | AV30: 2860.2434 | AW30: 2860.2434 | AX30: 2860.2434 | AY30: 2860.2434 | AZ30: 2860.2434 | BA30: 2860.2434 | BB30: 2860.2434 | BC30: 2860.2434 | BD30: 2860.2434 | BE30: 2860.2434 | BF30: 2860.2434 | BG30: 2860.2434 | BH30: 2860.2434 | BI30: 2860.2434 | BJ30: 2860.2434 | BK30: 2860.2434 | BL30: 1686.5692 | BM30: 1686.5692 | BN30: 1686.5692 | BO30: 1686.5692 | BP30: 1686.5692 | BQ30: 1686.5692 | BR30: 1686.5692 | BS30: 1686.5692 | BT30: 1686.5692 | BU30: 1686.5692 | BV30: 1686.5692 | BW30: 1686.5692 | BX30: 1686.5692 | BY30: 1686.5692 | BZ30: 1686.5692 | CA30: 1686.5692 | CB30: 1686.5692 | CC30: 1686.5692 | CD30: 1686.5692 | CE30: 1686.5692 | CF30: 2772.7337 | CG30: 2772.7337 | CH30: 2772.7337 | CI30: 2772.7337 | CJ30: 2772.7337 | CK30: 2772.7337 | CL30: 2772.7337 | CM30: 2772.7337 | CN30: 2772.7337 | CO30: 2772.7337 | CP30: 2772.7337 | CQ30: 2772.7337 | CR30: 2772.7337 | CS30: 2772.7337 | CT30: 2772.7337 | CU30: 2772.7337 | CV30: 2772.7337 | CW30: 2772.7337 | CX30: 2772.7337 | CY30: 2772.7337 | CZ30: 8556.862 | DA30: 8556.862 | DB30: 8556.862 | DC30: 8556.862 | DD30: 8556.862 | DE30: 8556.862 | DF30: 8556.862 | DG30: 8556.862 | DH30: 8556.862 | DI30: 8556.862 | DJ30: 8556.862 | DK30: 8556.862 | DL30: 8556.862 | DM30: 8556.862 | DN30: 8556.862 | DO30: 8556.862 | DP30: 8556.862 | DQ30: 8556.862 | DR30: 8556.862 | DS30: 8556.862
A31: Climate | B31: Projected to 2040 | C31: Agrifood System Greenhouse Gas (GHG) Emissions | D31: 1290.6349 | E31: 1299.4607 | F31: 1308.4565 | G31: 1317.627 | H31: 1326.977 | I31: 1336.5113 | J31: 1346.2348 | K31: 1356.1529 | L31: 1366.2709 | M31: 1376.5942 | N31: 1387.1287 | O31: 1397.8802 | P31: 1408.8548 | Q31: 1420.0587 | R31: 1431.4986 | S31: 1443.181 | T31: 1455.113 | U31: 1467.3017 | V31: 1479.7545 | W31: 1492.4791 | X31: 521.24598 | Y31: 532.37733 | Z31: 543.82156 | AA31: 555.58869 | AB31: 567.68908 | AC31: 580.13348 | AD31: 592.93304 | AE31: 606.09934 | AF31: 619.64439 | AG31: 633.58065 | AH31: 647.92106 | AI31: 662.67905 | AJ31: 677.86859 | AK31: 693.50417 | AL31: 709.60086 | AM31: 726.17432 | AN31: 743.24082 | AO31: 760.81729 | AP31: 778.92133 | AQ31: 797.57126 | AR31: 420.59141 | AS31: 431.825 | AT31: 443.40263 | AU31: 455.3357 | AV31: 467.63605 | AW31: 480.31594 | AX31: 493.38808 | AY31: 506.86563 | AZ31: 520.76222 | BA31: 535.09201 | BB31: 549.86963 | BC31: 565.11028 | BD31: 580.82972 | BE31: 597.04426 | BF31: 613.77085 | BG31: 631.02704 | BH31: 648.83104 | BI31: 667.20175 | BJ31: 686.15877 | BK31: 705.72241 | BL31: 552.78648 | BM31: 575.08538 | BN31: 598.466 | BO31: 622.98755 | BP31: 648.71274 | BQ31: 675.70795 | BR31: 704.0435 | BS31: 733.79384 | BT31: 765.03783 | BU31: 797.85902 | BV31: 832.34591 | BW31: 868.59228 | BX31: 906.69748 | BY31: 946.76683 | BZ31: 988.91191 | CA31: 1033.251 | CB31: 1079.9095 | CC31: 1129.0204 | CD31: 1180.7245 | CE31: 1235.1714 | CF31: 1337.1419 | CG31: 1368.6614 | CH31: 1401.2786 | CI31: 1435.0419 | CJ31: 1470.0024 | CK31: 1506.2136 | CL31: 1543.732 | CM31: 1582.6166 | CN31: 1622.9297 | CO31: 1664.7367 | CP31: 1708.1063 | CQ31: 1753.1111 | CR31: 1799.8271 | CS31: 1848.3343 | CT31: 1898.7173 | CU31: 1951.0646 | CV31: 2005.4699 | CW31: 2062.0314 | CX31: 2120.8529 | CY31: 2182.0435 | CZ31: 2408.5001 | DA31: 2440.4414 | DB31: 2473.2397 | DC31: 2506.9196 | DD31: 2541.5063 | DE31: 2577.0259 | DF31: 2613.5052 | DG31: 2650.9722 | DH31: 2689.4553 | DI31: 2728.9842 | DJ31: 2769.5894 | DK31: 2811.3024 | DL31: 2854.1556 | DM31: 2898.1827 | DN31: 2943.4182 | DO31: 2989.8979 | DP31: 3037.6588 | DQ31: 3086.7389 | DR31: 3137.1777 | DS31: 3189.0156
A34: Prevalence of Undernourishment
A52: Undernourished Population
A69: Poverty Headcount Rate ($2.15)
A85: Poverty Headcount Rate ($3.65)
A102: Poverty Headcount Rate ($6.85)
A119: Agrifood System Jobs (incl. subsistence farming and informal sector)
A137: Agricultural Jobs (incl. subsistence farming and informal sector)
A154: Agricultural Greenhouse Gas (GHG) Emissions

Sheet 1.Food_security
C1: FS Indicators
A2: VH | B2: 5 | D2: LAC | E2: CWANA | F2: WCA | G2: ESA | H2: SA | I2: SEA
A3: H | B3: 4 | C3: Total score by column | D3: =SUM(D11:D61) -> 104 | E3: =SUM(E11:E61) -> 104 | F3: =SUM(F11:F61) -> 104 | G3: =SUM(G11:G61) -> 104 | H3: =SUM(H11:H61) -> 104 | I3: =SUM(I11:I61) -> 104
A4: MH | B4: 3 | C4: VH count by column | D4: =COUNTIF(D$11:D$61, 5) -> 5 | E4: =COUNTIF(E$11:E$61, 5) -> 7 | F4: =COUNTIF(F$11:F$61, 5) -> 5 | G4: =COUNTIF(G$11:G$61, 5) -> 7 | H4: =COUNTIF(H$11:H$61, 5) -> 4 | I4: =COUNTIF(I$11:I$61, 5) -> 6
A5: M | B5: 2 | C5: H count by column | D5: =COUNTIF(D$11:D$61, 4) -> 10 | E5: =COUNTIF(E$11:E$61, 4) -> 7 | F5: =COUNTIF(F$11:F$61, 4) -> 7 | G5: =COUNTIF(G$11:G$61, 4) -> 8 | H5: =COUNTIF(H$11:H$61, 4) -> 12 | I5: =COUNTIF(I$11:I$61, 4) -> 9
A6: L | B6: 1 | C6: MH count by column | D6: =COUNTIF(D$11:D$61, 3) -> 6 | E6: =COUNTIF(E$11:E$61, 3) -> 5 | F6: =COUNTIF(F$11:F$61, 3) -> 10 | G6: =COUNTIF(G$11:G$61, 3) -> 6 | H6: =COUNTIF(H$11:H$61, 3) -> 4 | I6: =COUNTIF(I$11:I$61, 3) -> 5
C7: M count by column | D7: =COUNTIF(D$11:D$61, 2) -> 8 | E7: =COUNTIF(E$11:E$61, 2) -> 11 | F7: =COUNTIF(F$11:F$61, 2) -> 9 | G7: =COUNTIF(G$11:G$61, 2) -> 6 | H7: =COUNTIF(H$11:H$61, 2) -> 10 | I7: =COUNTIF(I$11:I$61, 2) -> 9
C8: L count by column | D8: =COUNTIF(D$11:D$61, 1) -> 5 | E8: =COUNTIF(E$11:E$61, 1) -> 4 | F8: =COUNTIF(F$11:F$61, 1) -> 3 | G8: =COUNTIF(G$11:G$61, 1) -> 7 | H8: =COUNTIF(H$11:H$61, 1) -> 4 | I8: =COUNTIF(I$11:I$61, 1) -> 5 | K8: Current state (across the Global South) | L8: Ideal state (across the Global South) | M8: Assumptions (for region-specific scores) | N8: Requirements for success (internal to P/A) | O8: Requirements for success (from other P/As)
C10: HLO | D10: LAC | E10: CWANA | F10: WCA | G10: ESA | H10: SA | I10: SEA
A11: HLO count: | B11: =COUNTA(C11:C61) -> 34 | C11: HLO 1.1: Quantified climate change-related hazards that affect the delivery of agronomic gain | D11: 4 | E11: 4 | F11: 3 | G11: 3 | H11: 4 | I11: 4 | K11: Limited understanding of how climate hazards specifically impact food production and nutritional outcomes in vulnerable regions. | L11: Comprehensive mapping of climate-nutrition pathways enabling targeted interventions to protect food security in changing conditions. | M11: Regional variations in climate-nutrition vulnerability, food system resilience, and nutritional baseline status. | N11: Integrated climate-nutrition modeling, food security impact assessments, and nutritional risk mapping. | O11: Collaboration with Nutrition Program for impact pathways; Food Systems Program for systemic integration.
A12: Sets of 5: | B12: =_xlfn.FLOOR.MATH(B11/5) -> 6 | C12: HLO 1.2: Climate hazard-specific inclusive sustainable farming system innovations | D12: 4 | E12: 4 | F12: 3 | G12: 3 | H12: 4 | I12: 4 | K12: Current adaptation practices rarely prioritize nutritional outcomes, focusing primarily on yield maintenance rather than dietary quality. | L12: Climate-adaptive farming systems optimized for nutritional security, dietary diversity, and stable food access across changing conditions. | M12: Regional differences in dietary patterns, nutritional challenges, and climate-sensitive food production systems. | N12: Nutrition-sensitive adaptation research, food system resilience metrics, and dietary outcome monitoring. | O12: Integration with Nutrition Program for diet-sensitive design; Gender Program for household food security impacts.
A13: Remainder: | B13: =MOD(B11,5) -> 4 | C13: HLO 1.3: Training materials for climate adaptation and mitigation | D13: 4 | E13: 2 | F13: 3 | G13: 3 | H13: 4 | I13: 4 | K13: Extension materials rarely integrate nutrition-sensitive adaptation, limiting impact on dietary outcomes under climate stress. | L13: Capacity development resources enabling implementers to optimize both climate resilience and nutritional outcomes across food systems. | M13: Variations in extension capacity, nutrition awareness, and prioritization of dietary outcomes in agricultural training. | N13: Nutrition-sensitive adaptation curricula, dietary impact training modules, and household food security assessment tools. | O13: Partnership with Capacity Sharing Accelerator; Nutrition Program for technical content.
A14: Max score: | B14: =(B12*SUM($B$2:$B$6))+IF(B11=0,0,SUM($B$2:INDEX(B:B,$B$13+1))) -> 104 | C14: HLO 1.4: Policy and investment-ready information on sustainable farming solutions | D14: 4 | E14: 4 | F14: 3 | G14: 2 | H14: 4 | I14: 4 | K14: Climate policy frameworks rarely prioritize nutritional outcomes, missing opportunities to protect dietary quality under changing conditions. | L14: Integrated climate-nutrition policies guiding investments toward farming systems that maintain food security while building resilience. | M14: Differences in policy integration, nutrition prioritization in climate agendas, and food security governance. | N14: Climate-nutrition policy analysis, investment case development for nutrition-sensitive adaptation, and stakeholder engagement. | O14: Collaboration with Policy Program; Nutrition Program for technical framing.
C15: HLO 2.1: Spatially-explicit recommendation decision support models for soil nutrient constraints | D15: 5 | E15: 5 | F15: 3 | G15: 5 | H15: 5 | I15: 5 | K15: Nutrient recommendations are largely blanket and disconnected from localized soil and crop needs, limiting their effectiveness in addressing food insecurity and micronutrient deficiencies. | L15: Spatially-explicit, data-driven nutrient recommendation models are widely adopted and tailored to local agroecological and socio-economic conditions, enabling farmers to optimize yield, improve soil health, and contribute to food and nutrition security. | M15: It is assumed that agroecological diversity, data availability, institutional capacity, and farmer adoption potential vary significantly across regions, influencing impact. | N15: High-resolution, geo-referenced soil and crop data, robust spatial modeling tools, and integration with climate and agronomic datasets are essential for accurate and actionable recommendations. | O15: Strong extension systems, multi-stakeholder engagement, enabling policies, and farmer-centric delivery platforms are critical to ensure adoption and scalability of nutrient management advisories.
C16: HLO 2.2: Expanded data-driven agronomic recommendations for site-specific nutrient management | D16: 5 | E16: 4 | F16: 3 | G16: 5 | H16: 5 | I16: 4 | K16: Agronomic recommendations are often generalized and not data-driven, resulting in suboptimal nutrient use, low productivity, and limited progress toward food and nutrition security goals. | L16: Site-specific, data-driven agronomic recommendation systems are operational at scale, enabling tailored nutrient management that enhances yield, profitability, resource efficiency, and nutritional outcomes. | M16: Assumes variable quality and availability of agronomic, soil, and weather data; differences in digital infrastructure; and diverse levels of institutional support and farmer digital literacy across regions. | N16: Robust decision support tools, integration of multi-source datasets (e.g., soil, crop, climate, socioeconomic), and continuous feedback mechanisms to refine nutrient recommendations. | O16: Collaborative research-extension systems, policy incentives, digital access for smallholders, and inclusive capacity development are essential to scale and sustain adoption of site-specific nutrient management practices.
C17: HLO 2.3: Training materials for site-specific nutrient management | D17: 5 | E17: 2 | F17: 3 | G17: 3 | H17: 5 | I17: 4 | K17: Training materials on nutrient management are often generic, outdated, or disconnected from local conditions, limiting their effectiveness in promoting site-specific and sustainable practices among farmers and extension agents. | L17: Localized, user-friendly, and digitally accessible training materials are widely available and regularly updated, equipping farmers, extension workers, and advisors with practical guidance for implementing site-specific nutrient management. | M17: Assumes varying levels of literacy, digital access, language needs, and agronomic knowledge across regions, affecting how training content is designed, delivered, and absorbed. | N17: Development of modular, multimedia content co-designed with users, based on local data and decision tools, and adaptable to different delivery formats (print, app, video, radio). | O17: Strong partnerships with NARES, NGOs, and private sector actors; capacity building for trainers; and sustained investment in outreach mechanisms that ensure inclusive access and adoption.
C18: HLO 2.4: Evidence for policy recommendations for precision nutrient management | D18: 4 | E18: 4 | F18: 2 | G18: 5 | H18: 4 | I18: 4 | K18: Policy frameworks often lack robust, localized evidence to support precision nutrient management, resulting in limited policy alignment with sustainable intensification and food security goals. | L18: Policies are informed by strong scientific evidence and field-based outcomes, enabling support for precision nutrient management through targeted subsidies, regulatory frameworks, and national extension strategies. | M18: Assumes variation in policy responsiveness, availability of empirical data, institutional coordination, and political will across countries and regions. | N18: Rigorous multi-location field trials, impact assessments, and harmonized data systems that generate credible evidence on productivity, economic returns, and environmental outcomes. | O18: Close collaboration with policymakers, think tanks, and national research systems; strategic communication of evidence; and alignment with broader agricultural, environmental, and nutrition policy agendas.
C19: HLO 3.1: Soil health monitoring and assessment framework operationalized | D19: 5 | E19: 5 | F19: 2 | G19: 2 | H19: 4 | I19: 5 | K19: Soil health monitoring rarely includes indicators relevant to nutritional security or dietary quality outcomes. | L19: Comprehensive soil monitoring systems tracking both agricultural productivity and nutritional quality determinants. | M19: Regional differences in soil monitoring capacity, nutrition-soil linkage awareness, and monitoring priorities. | N19: Nutrition-relevant soil indicator development, integrated monitoring system design, and outcome tracking methodologies. | O19: Collaboration with Digital Accelerator for systems; Nutrition Program for indicator framework.
C20: HLO 3.2: Network of long-term monitoring sites for carbon storage assessment | D20: 4 | E20: 5 | F20: 2 | G20: 2 | H20: 2 | I20: 4 | K20: Long-term agricultural monitoring rarely tracks nutritional outcomes alongside environmental parameters. | L20: Monitoring networks documenting interactions between soil health, environmental parameters, and nutritional outcomes over time. | M20: Variations in research infrastructure, nutrition-environment research traditions, and monitoring priorities. | N20: Nutrition-sensitive monitoring design, long-term experimental protocols, and integrated outcome assessment methodologies. | O20: Partnership with Environmental Health Program; Nutrition Program for dietary indicators.
C21: HLO 3.3: Impacts of agricultural practices quantified and catalogued | D21: 4 | E21: 2 | F21: 2 | G21: 2 | H21: 2 | I21: 2 | K21: Limited evidence on how soil management practices impact nutritional outcomes hinders nutrition-sensitive agriculture. | L21: Comprehensive evidence base linking soil management practices to both productivity and nutritional outcomes across contexts. | M21: Regional differences in research coverage, nutrition-soil linkage understanding, and evidence synthesis capacity. | N21: Nutrition impact assessment methodologies, evidence synthesis protocols, and knowledge management systems. | O21: Integration with Nutrition Program for outcome framework; Digital Accelerator for knowledge systems.
C22: HLO 3.4: Evidence for policy makers on soil health translated to accessible formats | D22: 4 | E22: 2 | F22: 2 | G22: 2 | H22: 2 | I22: 2 | K22: Soil health policy rarely incorporates nutritional considerations, missing critical soil-diet-health connections. | L22: Soil policies explicitly addressing nutritional security through maintenance of nutrient-supporting soil functions. | M22: Differences in policy environments, nutrition-soil linkage awareness, and policy integration capacity. | N22: Nutrition-soil policy analysis, evidence translation methodologies, and stakeholder engagement strategies. | O22: Partnership with Policy Program; Nutrition Program for framing and messaging.
C23: HLO 4.1: Capacity and networks of plant health practitioners improved | D23: 2 | E23: 2 | F23: 2 | G23: 2 | H23: 2 | I23: 4 | K23: Plant health systems rarely prioritize nutrition-sensitive crop protection, focusing primarily on yield protection. | L23: Practitioner networks optimizing plant health management for both yield stability and nutritional quality maintenance. | M23: Regional variations in plant health system capacity, nutrition awareness, and crop protection priorities. | N23: Nutrition-sensitive plant health training, network development methodologies, and integrated impact assessment tools. | O23: Collaboration with Capacity Sharing Accelerator; Nutrition Program for dietary quality parameters.
C24: HLO 4.2: Improved pest and disease monitoring and modeling tools | D24: 3 | E24: 3 | F24: 3 | G24: 3 | H24: 3 | I24: 3 | K24: Pest monitoring systems rarely consider nutritional consequences, potentially sacrificing dietary quality for yield protection. | L24: Advanced surveillance systems protecting both yield and nutritional quality through targeted monitoring of nutrition-critical crops. | M24: Differences in monitoring infrastructure, nutrition-pest impact understanding, and surveillance priorities. | N24: Nutrition-sensitive pest monitoring design, impact modeling methodologies, and outcome tracking protocols. | O24: Partnership with Digital Accelerator for systems; Nutrition Program for crop prioritization.
C25: HLO 4.3: Surveillance data and prevention strategies available | D25: 3 | E25: 2 | F25: 4 | G25: 4 | H25: 2 | I25: 3 | K25: Prevention strategies rarely differentiate nutritional importance of crops, potentially underprotecting dietary diversity contributors. | L25: Evidence-based prevention strategies prioritizing nutritionally important crops and protecting dietary quality. | M25: Regional variations in prevention capacity, nutrition-pest relationship awareness, and strategic priorities. | N25: Nutrition-sensitive prioritization frameworks, prevention strategy design methodologies, and impact assessment tools. | O25: Integration with Nutrition Program for dietary importance mapping; Scaling Program for deployment.
C26: HLO 4.4: Eco-friendly options for integrated pest management developed | D26: 4 | E26: 4 | F26: 5 | G26: 5 | H26: 4 | I26: 5 | K26: Ecological management approaches rarely optimize for both environmental and nutritional outcomes simultaneously. | L26: Integrated management systems protecting dietary diversity while maintaining environmental sustainability across farm systems. | M26: Differences in ecological management capacity, nutrition awareness, and implementation priorities. | N26: Nutrition-sensitive IPM design, participatory testing methodologies, and multi-objective assessment tools. | O26: Collaboration with Biodiversity Program for approaches; Nutrition Program for outcome assessment.
... C44: HLO 8.5: Policy-related information for sustainable farming systems | D44: 2 | E44: 2 | F44: 1 | G44: 1 | H44: 2 | I44: 2 | K44: Limited policy coherence between agriculture and nutrition sectors undermines food security outcomes. | L44: Systematic integration of farming systems evidence into nutrition-sensitive agricultural policy across governance scales. | M44: Regional variations in policy-science interfaces, cross-sectoral coordination capacity, and governance approaches. | N44: Nutrition-agriculture policy analysis, evidence synthesis methodologies, and cross-sectoral communication protocols. | O44: Strong integration with Policy Program; Nutrition Program for framing and priorities.

Sheet 2.Poverty_reduction
C1: Poverty Indicators
A2: VH | B2: 5 | D2: LAC | E2: CWANA | F2: WCA | G2: ESA | H2: SA | I2: SEA
A3: H | B3: 4 | C3: total score by column | D3: =SUM(D11:D61) -> 104 | E3: =SUM(E11:E61) -> 104 | F3: =SUM(F11:F61) -> 104 | G3: =SUM(G11:G61) -> 104 | H3: =SUM(H11:H61) -> 104 | I3: =SUM(I11:I61) -> 103
A4: MH | B4: 3 | C4: VH count by column | D4: =COUNTIF(D$11:D$61, 5) -> 6 | E4: =COUNTIF(E$11:E$61, 5) -> 5 | F4: =COUNTIF(F$11:F$61, 5) -> 5 | G4: =COUNTIF(G$11:G$61, 5) -> 7 | H4: =COUNTIF(H$11:H$61, 5) -> 3 | I4: =COUNTIF(I$11:I$61, 5) -> 7
A5: M | B5: 2 | C5: H count by column | D5: =COUNTIF(D$11:D$61, 4) -> 9 | E5: =COUNTIF(E$11:E$61, 4) -> 11 | F5: =COUNTIF(F$11:F$61, 4) -> 9 | G5: =COUNTIF(G$11:G$61, 4) -> 5 | H5: =COUNTIF(H$11:H$61, 4) -> 13 | I5: =COUNTIF(I$11:I$61, 4) -> 7
A6: L | B6: 1 | C6: MH count by column | D6: =COUNTIF(D$11:D$61, 3) -> 5 | E6: =COUNTIF(E$11:E$61, 3) -> 3 | F6: =COUNTIF(F$11:F$61, 3) -> 8 | G6: =COUNTIF(G$11:G$61, 3) -> 10 | H6: =COUNTIF(H$11:H$61, 3) -> 3 | I6: =COUNTIF(I$11:I$61, 3) -> 5
C7: M count by column | D7: =COUNTIF(D$11:D$61, 2) -> 9 | E7: =COUNTIF(E$11:E$61, 2) -> 11 | F7: =COUNTIF(F$11:F$61, 2) -> 7 | G7: =COUNTIF(G$11:G$61, 2) -> 7 | H7: =COUNTIF(H$11:H$61, 2) -> 13 | I7: =COUNTIF(I$11:I$61, 2) -> 10
C8: L count by column | D8: =COUNTIF(D$11:D$61, 1) -> 5 | E8: =COUNTIF(E$11:E$61, 1) -> 4 | F8: =COUNTIF(F$11:F$61, 1) -> 5 | G8: =COUNTIF(G$11:G$61, 1) -> 5 | H8: =COUNTIF(H$11:H$61, 1) -> 2 | I8: =COUNTIF(I$11:I$61, 1) -> 5 | K8: Current state (across the Global South) | L8: Ideal state (across the Global South) | M8: Assumptions (for region-specific scores) | N8: Requirements for success (internal to P/A) | O8: Requirements for success (from other P/As)
C10: HLO | D10: LAC | E10: CWANA | F10: WCA | G10: ESA | H10: SA | I10: SEA
A11: HLO count: | B11: =COUNTA(C11:C61) -> 34 | C11: HLO 1.1: Quantified climate change-related hazards that affect the delivery of agronomic gain | D11: 4 | E11: 4 | F11: 3 | G11: 3 | H11: 4 | I11: 4 | K11: Limited understanding of how climate hazards specifically impact income stability, rural employment, and poverty trajectories. | L11: Comprehensive mapping of climate-livelihood pathways enabling targeted interventions to protect economic wellbeing under changing conditions. | M11: Regional variations in climate-livelihood vulnerability, economic diversification, and poverty baseline status. | N11: Integrated climate-poverty modeling, livelihood impact assessments, and economic vulnerability mapping. | O11: Collaboration with Foresight services for socioeconomic projections; Markets Program for value chain impacts.
A12: Sets of 5: | B12: =_xlfn.FLOOR.MATH(B11/5) -> 6 | C12: HLO 1.2: Climate hazard-specific inclusive sustainable farming system innovations | D12: 4 | E12: 4 | F12: 3 | G12: 3 | H12: 4 | I12: 5 | K12: Adaptation technologies often fail to explicitly consider livelihood impacts, employment effects, or poverty reduction potential. | L12: Climate-adaptive farming systems optimized for stable incomes, job creation, and poverty reduction across changing environmental conditions. | M12: Differences in economic vulnerability, livelihood diversification opportunities, and labor market dynamics across regions. | N12: Income-sensitive adaptation research, employment impact assessment methodologies, and poverty reduction metrics. | O12: Integration with Markets Program for value chain evaluation; Policy Program for enabling environment analysis.
A13: Remainder: | B13: =MOD(B11,5) -> 4 | C13: HLO 1.3: Training materials for climate adaptation and mitigation | D13: 4 | E13: 4 | F13: 3 | G13: 3 | H13: 4 | I13: 4 | K13: Extension materials rarely highlight economic implications, business model adaptation, or livelihood diversification opportunities. | L13: Capacity development resources enabling implementers to optimize economic outcomes alongside environmental resilience in adaptation strategies. | M13: Variations in extension capacity, enterprise development support, and prioritization of economic dimensions in training. | N13: Economic impact training modules, business adaptation curricula, and income diversification assessment tools. | O13: Partnership with Capacity Sharing Accelerator; Markets Program for enterprise content.
A14: Max score: | B14: =(B12*SUM($B$2:$B$6))+IF(B11=0,0,SUM($B$2:INDEX(B:B,$B$13+1))) -> 104 | C14: HLO 1.4: Policy and investment-ready information on sustainable farming solutions | D14: 4 | E14: 4 | F14: 3 | G14: 3 | H14: 4 | I14: 4 | K14: Climate policy frameworks rarely prioritize employment protection, income stability, or poverty reduction potential of interventions. | L14: Integrated climate-economic policies guiding investments toward farming systems that maintain livelihoods while building resilience. | M14: Differences in policy integration, economic prioritization in climate agendas, and poverty reduction governance. | N14: Climate-economic policy analysis, livelihood-focused investment case development, and poverty impact assessment. | O14: Collaboration with Policy Program; Markets Program for value chain frameworks.
C15: HLO 2.1: Spatially-explicit recommendation decision support models for soil nutrient constraints | D15: 5 | E15: 5 | F15: 5 | G15: 3 | H15: 5 | I15: 5 | K15: Nutrient management technologies rarely optimize for economic returns, labor implications, or poverty reduction impact. | L15: Precision nutrient systems enhancing both agricultural productivity and economic returns across diverse socioeconomic contexts. | M15: Regional variations in input markets, labor costs, and poverty-nutrient management relationships. | N15: Economic return modeling capacity, poverty impact assessment methodologies, and livelihood-oriented spatial analysis. | O15: Integration with Digital Accelerator for systems; Markets Program for economic analysis.
C16: HLO 2.2: Expanded data-driven agronomic recommendations for site-specific nutrient management | D16: 5 | E16: 4 | F16: 3 | G16: 3 | H16: 5 | I16: 2 | K16: Advisory services rarely incorporate economic optimization, return-on-investment analysis, or poverty impact considerations. | L16: Integrated nutrient recommendations explicitly balancing agronomic, environmental, and economic outcomes for livelihood enhancement. | M16: Differences in advisory system economic capacity, business model integration, and poverty-sensitive recommendation approaches. | N16: Economic return algorithms, cost-benefit modeling tools, and poverty-sensitive recommendation frameworks. | O16: Collaboration with Markets Program; Digital Accelerator for delivery systems.
C17: HLO 2.3: Training materials for site-specific nutrient management | D17: 5 | E17: 5 | F17: 3 | G17: 3 | H17: 5 | I17: 4 | K17: Extension resources rarely emphasize business case development, economic analysis, or livelihood enhancement strategies. | L17: Capacity building materials enabling practitioners to optimize nutrient management for economic returns and poverty reduction. | M17: Regional differences in business extension capacity, economic training infrastructure, and poverty-focused advisory services. | N17: Economic analysis training curricula, business case development tools, and poverty-sensitive advisory methodologies. | O17: Partnership with Capacity Sharing Accelerator; Markets Program for business content.
C18: HLO 2.4: Evidence for policy recommendations for precision nutrient management | D18: 4 | E18: 4 | F18: 2 | G18: 2 | H18: 2 | I18: 2 | K18: Policy frameworks rarely optimize fertilizer programs for income generation, job creation, or poverty reduction outcomes. | L18: Evidence-based policies balancing productivity, sustainability, and economic returns from nutrient management investments. | M18: Variations in policy environments, subsidy economic efficiency, and poverty-reduction focus in input systems. | N18: Economic policy analysis, poverty impact evidence synthesis, and subsidy optimization methodologies. | O18: Strong integration with Policy Program; Markets Program for value chain analysis.
C19: HLO 3.1: Soil health monitoring and assessment framework operationalized | D19: 5 | E19: 5 | F19: 2 | G19: 2 | H19: 2 | I19: 5 | K19: Soil monitoring systems rarely track economic indicators, livelihood impacts, or poverty reduction contributions. | L19: Comprehensive soil frameworks connecting soil health improvements to measurable economic benefits across diverse contexts. | M19: Regional differences in soil-livelihood connections, economic monitoring capacity, and poverty-soil health relationships. | N19: Economic indicator development, livelihood impact tracking methodologies, and poverty-soil relationships analysis. | O19: Collaboration with Digital Accelerator for systems; Markets Program for economic frameworks.
C20: HLO 3.2: Network of long-term monitoring sites for carbon storage assessment | D20: 4 | E20: 2 | F20: 2 | G20: 2 | H20: 2 | I20: 2 | K20: Long-term research rarely quantifies economic returns, livelihood enhancement, or poverty reduction from soil investments. | L20: Monitoring networks documenting long-term economic benefits of soil health investments across diverse socioeconomic contexts. | M20: Variations in research economic capacity, livelihood impact metrics, and poverty reduction monitoring approaches. | N20: Economic return assessment methodologies, long-term livelihood tracking, and poverty impact monitoring protocols. | O20: Partnership with Foresight services for projections; Markets Program for economic analysis.
C21: HLO 3.3: Impacts of agricultural practices quantified and catalogued | D21: 4 | E21: 2 | F21: 2 | G21: 2 | H21: 2 | I21: 2 | K21: Limited evidence on economic returns, employment effects, or poverty reduction impacts of soil management practices. | L21: Comprehensive evidence base linking soil management practices to quantified economic benefits across diverse contexts. | M21: Regional differences in economic research coverage, livelihood impact methodologies, and poverty-soil evidence synthesis. | N21: Economic impact assessment tools, livelihood benefit quantification methods, and poverty reduction evidence frameworks. | O21: Integration with Markets Program for economic analysis; Scaling Program for business models.
C22: HLO 3.4: Evidence for policy makers on soil health translated to accessible formats | D22: 4 | E22: 2 | F22: 2 | G22: 2 | H22: 2 | I22: 2 | K22: Soil health policy communication rarely emphasizes economic returns, employment creation, or poverty reduction potential. | L22: Soil policies explicitly connecting soil health to economic prosperity and poverty reduction through accessible evidence. | M22: Differences in policy economic framing, livelihood emphasis in governance, and poverty reduction orientation in soil health. | N22: Economic policy analysis, poverty impact communication strategies, and livelihood-focused stakeholder engagement. | O22: Partnership with Policy Program; Communications for economic messaging.
C23: HLO 4.1: Capacity and networks of plant health practitioners improved | D23: 2 | E23: 2 | F23: 2 | G23: 2 | H23: 2 | I23: 4 | K23: Plant health systems rarely optimize for economic outcomes, livelihood protection, or poverty reduction potential. | L23: Practitioner networks balancing plant protection with explicit livelihood preservation and economic optimization objectives. | M23: Regional variations in pest economic impacts, plant health business models, and poverty-pest management relationships. | N23: Economic impact training, livelihood-centered plant health approaches, and poverty-sensitive management strategies. | O23: Collaboration with Capacity Sharing Accelerator; Markets Program for business models.
C24: HLO 4.2: Improved pest and disease monitoring and modeling tools | D24: 3 | E24: 3 | F24: 3 | G24: 3 | H24: 3 | I24: 3 | K24: Monitoring systems rarely prioritize economic threats, livelihood impacts, or poverty implications of pest outbreaks. | L24: Advanced surveillance systems enabling economically-optimized pest management decisions that protect critical livelihood sources. | M24: Differences in monitoring economic integration, livelihood-threat assessment, and poverty-sensitive prioritization approaches. | N24: Economic impact modeling, livelihood vulnerability assessment, and poverty-sensitive prioritization frameworks. | O24: Partnership with Digital Accelerator for systems; Markets Program for value chain analysis.
C25: HLO 4.3: Surveillance data and prevention strategies available | D25: 3 | E25: 2 | F25: 4 | G25: 4 | H25: 2 | I25: 3 | K25: Prevention strategies rarely differentiate economic importance of crops, livelihood significance, or poverty reduction potential. | L25: Evidence-based prevention approaches explicitly prioritizing economic high-leverage points in agricultural systems. | M25: Regional variations in pest economic impacts, prevention return-on-investment potential, and poverty-sensitive prioritization. | N25: Economic prioritization frameworks, livelihood impact assessment tools, and poverty-focused prevention strategies. | O25: Integration with Markets Program for value chain analysis; Policy Program for implementation frameworks.
C26: HLO 4.4: Eco-friendly options for integrated pest management developed | D26: 4 | E26: 4 | F26: 5 | G26: 5 | H26: 4 | I26: 5 | K26: Ecological approaches rarely optimize for economic returns, labor requirements, or poverty reduction potential. | L26: Integrated management systems balancing environmental sustainability with explicit economic optimization across farm types. | M26: Differences in ecological-economic integration, green market development, and poverty-sensitive IPM implementation. | N26: Economic return analysis for ecological approaches, livelihood impact assessment tools, and poverty reduction metrics. | O26: Collaboration with Biodiversity Program for approaches; Markets Program for economic analysis.
... C44: HLO 8.5: Policy-related information for sustainable farming systems | D44: 2 | E44: 2 | F44: 4 | G44: 1 | H44: 2 | I44: 2 | K44: Policy engagement often separates technical and economic evidence, limiting integrated approaches to agricultural development. | L44: Systematic integration of farming systems evidence into economically-optimized agricultural policy across governance scales. | M44: Regional variations in policy-market interfaces, economic-technical integration, and poverty-focused governance approaches. | N44: Economic-technical policy analysis, integrated evidence synthesis, and poverty-focused communication strategies. | O44: Strong integration with Policy Program; Markets Program for economic frameworks.

Sheet 3.Social_inclusion
C1: Social inclusion Indicator
A2: VH | B2: 5 | D2: LAC | E2: CWANA | F2: WCA | G2: ESA | H2: SA | I2: SEA
A3: H | B3: 4 | C3: Total score by column | D3: =SUM(D11:D61) -> 104 | E3: =SUM(E11:E61) -> 104 | F3: =SUM(F11:F61) -> 104 | G3: =SUM(G11:G61) -> 104 | H3: =SUM(H11:H61) -> 104 | I3: =SUM(I11:I61) -> 104
A4: MH | B4: 3 | C4: VH count by column | D4: =COUNTIF(D$11:D$61, 5) -> 5 | E4: =COUNTIF(E$11:E$61, 5) -> 3 | F4: =COUNTIF(F$11:F$61, 5) -> 3 | G4: =COUNTIF(G$11:G$61, 5) -> 4 | H4: =COUNTIF(H$11:H$61, 5) -> 7 | I4: =COUNTIF(I$11:I$61, 5) -> 8
A5: M | B5: 2 | C5: H count by column | D5: =COUNTIF(D$11:D$61, 4) -> 10 | E5: =COUNTIF(E$11:E$61, 4) -> 12 | F5: =COUNTIF(F$11:F$61, 4) -> 11 | G5: =COUNTIF(G$11:G$61, 4) -> 8 | H5: =COUNTIF(H$11:H$61, 4) -> 3 | I5: =COUNTIF(I$11:I$61, 4) -> 6
A6: L | B6: 1 | C6: MH count by column | D6: =COUNTIF(D$11:D$61, 3) -> 6 | E6: =COUNTIF(E$11:E$61, 3) -> 5 | F6: =COUNTIF(F$11:F$61, 3) -> 11 | G6: =COUNTIF(G$11:G$61, 3) -> 14 | H6: =COUNTIF(H$11:H$61, 3) -> 13 | I6: =COUNTIF(I$11:I$61, 3) -> 5
C7: M count by column | D7: =COUNTIF(D$11:D$61, 2) -> 8 | E7: =COUNTIF(E$11:E$61, 2) -> 12 | F7: =COUNTIF(F$11:F$61, 2) -> 3 | G7: =COUNTIF(G$11:G$61, 2) -> 2 | H7: =COUNTIF(H$11:H$61, 2) -> 7 | I7: =COUNTIF(I$11:I$61, 2) -> 10
C8: L count by column | D8: =COUNTIF(D$11:D$61, 1) -> 5 | E8: =COUNTIF(E$11:E$61, 1) -> 2 | F8: =COUNTIF(F$11:F$61, 1) -> 6 | G8: =COUNTIF(G$11:G$61, 1) -> 6 | H8: =COUNTIF(H$11:H$61, 1) -> 4 | I8: =COUNTIF(I$11:I$61, 1) -> 5 | K8: Current state (across the Global South) | L8: Ideal state (across the Global South) | M8: Assumptions (for region-specific scores) | N8: Requirements for success (internal to P/A) | O8: Requirements for success (from other P/As)
C10: HLO | D10: LAC | E10: CWANA | F10: WCA | G10: ESA | H10: SA | I10: SEA
A11: HLO count: | B11: =COUNTA(C11:C61) -> 34 | C11: HLO 1.1: Quantified climate change-related hazards that affect the delivery of agronomic gain | D11: 4 | E11: 4 | F11: 4 | G11: 4 | H11: 3 | I11: 4 | K11: Climate hazard research rarely differentiates impacts by gender, age, or social group, leading to exclusionary adaptation responses. | L11: Climate hazard analysis that explicitly captures differential vulnerability across gender, youth, and social groups enabling inclusive adaptation. | M11: Regional variations in gender norms, youth engagement in agriculture, and social stratification affecting hazard impacts. | N11: Gender-disaggregated hazard assessment methodologies, social inclusion frameworks, and differential vulnerability mapping. | O11: Collaboration with Gender Program for analytical frameworks; Nutrition Program for household impacts.
A12: Sets of 5: | B12: =_xlfn.FLOOR.MATH(B11/5) -> 6 | C12: HLO 1.2: Climate hazard-specific inclusive sustainable farming system innovations | D12: 4 | E12: 4 | F12: 4 | G12: 4 | H12: 3 | I12: 4 | K12: Adaptation innovations often reinforce gender inequalities by focusing on male-dominated crops and practices while overlooking female priorities. | L12: Inclusive innovation portfolios addressing gender-specific vulnerabilities and strengthening agency of women, youth, and marginalized groups in adaptation. | M12: Differences in gender roles in agriculture, youth engagement patterns, and social exclusion dynamics across regions. | N12: Gender-transformative innovation design methodologies, youth engagement strategies, and social inclusion testing protocols. | O12: Integration with Gender Program for inclusive innovation; Youth Program for targeted approaches.
A13: Remainder: | B13: =MOD(B11,5) -> 4 | C13: HLO 1.3: Training materials for climate adaptation and mitigation | D13: 4 | E13: 4 | F13: 4 | G13: 4 | H13: 3 | I13: 4 | K13: Climate extension materials often fail to address differentiated learning needs or access constraints across gender and social groups. | L13: Inclusive training resources addressing diverse learning needs and enabling equitable participation in climate adaptation implementation. | M13: Regional variations in literacy rates, gender-based mobility restrictions, and youth engagement in agricultural learning. | N13: Gender-responsive training design, youth-focused content development, and accessible material creation methodologies. | O13: Partnership with Capacity Sharing Accelerator; Gender Program for inclusive methodologies.
A14: Max score: | B14: =(B12*SUM($B$2:$B$6))+IF(B11=0,0,SUM($B$2:INDEX(B:B,$B$13+1))) -> 104 | C14: HLO 1.4: Policy and investment-ready information on sustainable farming solutions | D14: 4 | E14: 4 | F14: 4 | G14: 4 | H14: 3 | I14: 4 | K14: Climate policy frameworks rarely address gender inequality, youth exclusion, or social marginalization in adaptation planning. | L14: Evidence-based climate policies explicitly addressing gender transformation, youth opportunity, and social inclusion in agricultural adaptation. | M14: Differences in policy environments, gender integration in governance, and youth representation in decision-making. | N14: Gender-responsive policy analysis, youth opportunity assessment, and social inclusion evidence synthesis methodologies. | O14: Strong integration with Policy Program; Gender Program for analytical frameworks.
C15: HLO 2.1: Spatially-explicit recommendation decision support models for soil nutrient constraints | D15: 5 | E15: 3 | F15: 4 | G15: 5 | H15: 5 | I15: 5 | K15: Nutrient management technologies often reflect and reinforce gender divides in resource access and decision-making power. | L15: Gender-transformative, youth-inclusive recommendation systems that address differentiated constraints and strengthen agency in soil management. | M15: Regional variations in gender roles in soil management, youth engagement in technology, and social stratification in resource access. | N15: Gender-responsive modeling approaches, youth engagement methodologies, and social inclusion assessment frameworks. | O15: Integration with Digital Accelerator for gender-inclusive design; Gender Program for analytical frameworks.
C16: HLO 2.2: Expanded data-driven agronomic recommendations for site-specific nutrient management | D16: 5 | E16: 2 | F16: 3 | G16: 3 | H16: 3 | I16: 5 | K16: Digital advisory services often exacerbate gender and social divides through design and delivery approaches that favor privileged groups. | L16: Inclusive advisory systems that bridge rather than widen digital divides and enable equitable participation in precision agriculture. | M16: Differences in digital access patterns, gender technology gaps, and youth engagement in digital agriculture across regions. | N16: Gender-responsive digital design, youth engagement strategies, and social inclusion testing methodologies. | O16: Collaboration with Digital Accelerator for inclusive interfaces; Gender Program for analytical frameworks.
C17: HLO 2.3: Training materials for site-specific nutrient management | D17: 5 | E17: 2 | F17: 3 | G17: 3 | H17: 2 | I17: 5 | K17: Nutrient management training often reinforces gender inequalities through content and delivery approaches that exclude women and marginalized groups. | L17: Inclusive capacity development resources that transform rather than reinforce gender inequalities in agricultural knowledge and practice. | M17: Regional variations in literacy rates, gender-based mobility restrictions, and youth engagement in agricultural training. | N17: Gender-transformative training design, youth-focused content development, and socially inclusive delivery methodologies. | O17: Partnership with Capacity Sharing Accelerator; Gender Program for inclusive approaches.
C18: HLO 2.4: Evidence for policy recommendations for precision nutrient management | D18: 4 | E18: 2 | F18: 3 | G18: 3 | H18: 2 | I18: 4 | K18: Fertilizer policy frameworks rarely address gender inequality or social exclusion in input access and usage. | L18: Evidence-based input policies explicitly addressing gender transformation and social inclusion in agricultural resource distribution. | M18: Differences in policy environments, gender integration in agricultural governance, and social equity in input distribution. | N18: Gender-responsive policy analysis, equity assessment methodologies, and inclusion-focused evidence synthesis. | O18: Strong integration with Policy Program; Gender Program for analytical frameworks.
C19: HLO 3.1: Soil health monitoring and assessment framework operationalized | D19: 5 | E19: 2 | F19: 3 | G19: 3 | H19: 5 | I19: 5 | K19: Soil monitoring approaches often reflect and reinforce gender divides in knowledge systems and decision-making authority. | L19: Inclusive soil health frameworks that integrate diverse knowledge systems and enable equitable participation in soil management. | M19: Regional variations in gender roles in soil knowledge, youth engagement in monitoring, and social stratification in land management. | N19: Gender-responsive monitoring design, youth engagement strategies, and social inclusion assessment methodologies. | O19: Collaboration with Digital Accelerator for inclusive systems; Gender Program for analytical frameworks.
C20: HLO 3.2: Network of long-term monitoring sites for carbon storage assessment | D20: 4 | E20: 2 | F20: 3 | G20: 3 | H20: 2 | I20: 2 | K20: Research networks often marginalize female researchers, indigenous knowledge systems, and youth engagement in scientific processes. | L20: Inclusive research networks that transform rather than reinforce gender and social inequalities in agricultural science and knowledge creation. | M20: Differences in gender representation in agricultural science, youth engagement in research, and validation of indigenous knowledge. | N20: Gender-balanced research design, youth scientist development, and inclusive knowledge co-creation methodologies. | O20: Partnership with Capacity Sharing Accelerator for inclusive science; Gender Program for frameworks.
C21: HLO 3.3: Impacts of agricultural practices quantified and catalogued | D21: 4 | E21: 2 | F21: 3 | G21: 3 | H21: 2 | I21: 2 | K21: Impact assessment rarely disaggregates by gender, age, or social group, obscuring differentiated effects of agricultural interventions. | L21: Comprehensive evidence base explicitly documenting differentiated impacts across gender, age, and social groups to guide inclusive agriculture. | M21: Regional variations in gender impact patterns, youth engagement effects, and social differentiation in agricultural outcomes. | N21: Gender-disaggregated impact assessment, youth-specific indicators, and social inclusion measurement methodologies. | O21: Integration with MELIA systems across Programs; Gender Program for analytical frameworks.
C22: HLO 3.4: Evidence for policy makers on soil health translated to accessible formats | D22: 4 | E22: 1 | F22: 3 | G22: 2 | H22: 2 | I22: 2 | K22: Policy communication often fails to reach female policymakers, youth advocates, or representatives of marginalized groups. | L22: Inclusive policy engagement explicitly addressing diversity in policy audiences and enabling equitable participation in evidence-based governance. | M22: Differences in gender representation in agricultural governance, youth leadership in policy, and social diversity in decision-making. | N22: Gender-responsive communication strategies, youth engagement approaches, and inclusive policy dialogue methodologies. | O22: Partnership with Policy Program; Communications for inclusive strategies.
C23: HLO 4.1: Capacity and networks of plant health practitioners improved | D23: 4 | E23: 4 | F23: 4 | G23: 4 | H23: 3 | I23: 3 | K23: Plant health systems often marginalize female practitioners, traditional knowledge holders, and youth engagement in pest management. | L23: Inclusive practitioner networks that value diverse knowledge systems and enable equitable participation across gender, age, and social groups. | M23: Regional variations in gender roles in pest management, youth engagement in plant health, and social validation of knowledge systems. | N23: Gender-balanced network development, youth engagement strategies, and inclusive knowledge validation methodologies. | O23: Collaboration with Capacity Sharing Accelerator; Gender Program for inclusive frameworks.
C24: HLO 4.2: Improved pest and disease monitoring and modeling tools | D24: 3 | E24: 3 | F24: 3 | G24: 3 | H24: 3 | I24: 3 | K24: Digital pest monitoring tools often reflect and reinforce gender divides in technology access and information control. | L24: Inclusive monitoring systems that bridge rather than widen digital divides and enable equitable participation in plant health management. | M24: Differences in digital access patterns, gender technology gaps, and youth engagement in digital agriculture across regions. | N24: Gender-responsive digital design, youth engagement strategies, and social inclusion testing methodologies. | O24: Partnership with Digital Accelerator for inclusive interfaces; Gender Program for frameworks.
C25: HLO 4.3: Surveillance data and prevention strategies available | D25: 3 | E25: 2 | F25: 3 | G25: 3 | H25: 2 | I25: 3 | K25: Pest management strategies often overlook differentiated impacts and implementation constraints across gender and social groups. | L25: Inclusive prevention approaches explicitly addressing diversity in pest management roles, constraints, and priorities across social boundaries. | M25: Regional variations in gender roles in pest control, youth engagement in surveillance, and social differentiation in management capacity. | N25: Gender-responsive strategy design, youth engagement approaches, and social inclusion assessment methodologies. | O25: Integration with Scaling Program for inclusive deployment; Gender Program for frameworks.
C26: HLO 4.4: Eco-friendly options for integrated pest management developed | D26: 4 | E26: 4 | F26: 4 | G26: 4 | H26: 3 | I26: 5 | K26: Ecological pest management approaches often fail to address gender-specific constraints, priorities, and knowledge systems. | L26: Gender-transformative IPM approaches that build on diverse knowledge systems and enable equitable participation in implementation. | M26: Differences in gender roles in pest management, youth engagement in ecological approaches, and social differentiation in knowledge validation. | N26: Gender-responsive IPM design, youth engagement strategies, and inclusive knowledge co-creation methodologies. | O26: Collaboration with Biodiversity Program for ecological approaches; Gender Program for frameworks.
... C44: HLO 8.5: Policy-related information for sustainable farming systems | D44: 2 | E44: 2 | F44: 4 | G44: 3 | H44: 3 | I44: 2 | K44: Policy processes often exclude female perspectives, youth priorities, and marginalized voices from agricultural evidence and decision-making. | L44: Inclusive policy engagement explicitly addressing power dynamics and enabling equitable participation in evidence-based agricultural governance. | M44: Regional variations in gender representation in policy, youth voice in governance, and social diversity in decision-making. | N44: Gender-responsive policy communication, youth engagement strategies, and inclusive dialogue methodologies. | O44: Strong integration with Policy Program; Gender Program for inclusive frameworks.

Sheet 4.Climate_adaptation
C1: Climate adaptation Indicator
A2: VH | B2: 5 | D2: LAC | E2: CWANA | F2: WCA | G2: ESA | H2: SA | I2: SEA
A3: H | B3: 4 | C3: Total score by column | D3: =SUM(D11:D61) -> 104 | E3: =SUM(E11:E61) -> 104 | F3: =SUM(F11:F61) -> 104 | G3: =SUM(G11:G61) -> 104 | H3: =SUM(H11:H61) -> 104 | I3: =SUM(I11:I61) -> 104
A4: MH | B4: 3 | C4: VH count by column | D4: =COUNTIF(D$11:D$61, 5) -> 8 | E4: =COUNTIF(E$11:E$61, 5) -> 8 | F4: =COUNTIF(F$11:F$61, 5) -> 3 | G4: =COUNTIF(G$11:G$61, 5) -> 8 | H4: =COUNTIF(H$11:H$61, 5) -> 7 | I4: =COUNTIF(I$11:I$61, 5) -> 7
A5: M | B5: 2 | C5: H count by column | D5: =COUNTIF(D$11:D$61, 4) -> 7 | E5: =COUNTIF(E$11:E$61, 4) -> 8 | F5: =COUNTIF(F$11:F$61, 4) -> 10 | G5: =COUNTIF(G$11:G$61, 4) -> 4 | H5: =COUNTIF(H$11:H$61, 4) -> 8 | I5: =COUNTIF(I$11:I$61, 4) -> 7
A6: L | B6: 1 | C6: MH count by column | D6: =COUNTIF(D$11:D$61, 3) -> 6 | E6: =COUNTIF(E$11:E$61, 3) -> 5 | F6: =COUNTIF(F$11:F$61, 3) -> 10 | G6: =COUNTIF(G$11:G$61, 3) -> 11 | H6: =COUNTIF(H$11:H$61, 3) -> 5 | I6: =COUNTIF(I$11:I$61, 3) -> 6
C7: M count by column | D7: =COUNTIF(D$11:D$61, 2) -> 5 | E7: =COUNTIF(E$11:E$61, 2) -> 4 | F7: =COUNTIF(F$11:F$61, 2) -> 8 | G7: =COUNTIF(G$11:G$61, 2) -> 4 | H7: =COUNTIF(H$11:H$61, 2) -> 8 | I7: =COUNTIF(I$11:I$61, 2) -> 9
C8: L count by column | D8: =COUNTIF(D$11:D$61, 1) -> 8 | E8: =COUNTIF(E$11:E$61, 1) -> 9 | F8: =COUNTIF(F$11:F$61, 1) -> 3 | G8: =COUNTIF(G$11:G$61, 1) -> 7 | H8: =COUNTIF(H$11:H$61, 1) -> 6 | I8: =COUNTIF(I$11:I$61, 1) -> 5 | K8: Current state (across the Global South) | L8: Ideal state (across the Global South) | M8: Assumptions (for region-specific scores) | N8: Requirements for success (internal to P/A) | O8: Requirements for success (from other P/As)
C10: HLO | D10: LAC | E10: CWANA | F10: WCA | G10: ESA | H10: SA | I10: SEA
A11: HLO count: | B11: =COUNTA(C11:C61) -> 34 | C11: HLO 1.1: Quantified climate change-related hazards that affect the delivery of agronomic gain | D11: 4 | E11: 5 | F11: 3 | G11: 5 | H11: 5 | I11: 5 | K11: Climate hazards are poorly quantified at local scales, with limited connection to agronomic impacts, resulting in ineffective adaptation strategies. | L11: Locally-relevant climate hazard data integrated with agronomic systems for evidence-based adaptation planning and implementation across diverse farming systems. | M11: Regions differ in climate data availability, monitoring infrastructure, and severity of climate hazards. | N11: Advanced climate modeling capacity, downscaling expertise, and agronomic impact assessment methodologies. | O11: Coordination with Digital Accelerator for data infrastructure; collaboration with Policies Program for implementation frameworks.
A12: Sets of 5: | B12: =_xlfn.FLOOR.MATH(B11/5) -> 6 | C12: HLO 1.2: Climate hazard-specific inclusive sustainable farming system innovations | D12: 5 | E12: 5 | F12: 3 | G12: 5 | H12: 5 | I12: 4 | K12: Current adaptation practices are fragmented, often not inclusive, and lack evidence of effectiveness at scale for specific climate hazards. | L12: Comprehensive portfolio of proven, gender-inclusive adaptation innovations tailored to specific climate hazards and farming systems with quantified mitigation co-benefits. | M12: Regional differences in farming systems vulnerability, institutional support, and current adaptation practices. | N12: Participatory innovation testing frameworks, mitigation measurement tools, and inclusive research approaches. | O12: Integration with Scaling Program for deployment; Gender Program for inclusive innovation design; Digital Accelerator for monitoring systems.
A13: Remainder: | B13: =MOD(B11,5) -> 4 | C13: HLO 1.3: Training materials for climate adaptation and mitigation | D13: 4 | E13: 5 | F13: 3 | G13: 3 | H13: 5 | I13: 5 | K13: Training resources on climate-smart agriculture are generic, not context-specific, and often fail to reach the most vulnerable farmers. | L13: Comprehensive, accessible, and locally-relevant training materials enabling diverse stakeholders to implement effective climate solutions. | M13: Differences in educational access, extension system capacity, and existing training infrastructure. | N13: Adult education expertise, multimedia content development skills, and knowledge of local contexts and languages. | O13: Collaboration with Capacity Sharing Accelerator for delivery systems; Scaling Program for distribution channels.
A14: Max score: | B14: =(B12*SUM($B$2:$B$6))+IF(B11=0,0,SUM($B$2:INDEX(B:B,$B$13+1))) -> 104 | C14: HLO 1.4: Policy and investment-ready information on sustainable farming solutions | D14: 5 | E14: 4 | F14: 3 | G14: 3 | H14: 5 | I14: 5 | K14: Climate policy frameworks often lack specific, evidence-based agricultural adaptation guidance, leading to poor investment allocation. | L14: Robust, implementable policy frameworks guiding climate-smart agricultural investments based on quantified adaptation and mitigation impacts. | M14: Variations in policy environments, institutional capacity, and climate finance readiness across regions. | N14: Policy analysis capabilities, economic modeling expertise, and investment case development skills. | O14: Strong linkage with Policies Program for analysis; Foresight services for scenario planning.
C15: HLO 2.1: Spatially-explicit recommendation decision support models for soil nutrient constraints | D15: 5 | E15: 5 | F15: 3 | G15: 3 | H15: 5 | I15: 5 | K15: Limited site-specific nutrient management leads to inefficient fertilizer use, contributing to emissions and reduced climate resilience. | L15: Precision nutrient management systems optimizing fertilizer use for productivity while minimizing N‚ÇÇO emissions and building system resilience. | M15: Regional differences in fertilizer access, soil mapping capacity, and nutrient-specific climate vulnerabilities. | N15: Advanced modeling capacity, soil mapping expertise, and ROI analysis capabilities. | O15: Integration with Digital Accelerator for data systems; Scaling Program for advisory service delivery.
C16: HLO 2.2: Expanded data-driven agronomic recommendations for site-specific nutrient management | D16: 4 | E16: 2 | F16: 3 | G16: 2 | H16: 5 | I16: 4 | K16: Current nutrient recommendations rarely incorporate climate factors, soil health, or long-term sustainability considerations. | L16: Integrated nutrient advisory systems optimizing productivity, climate resilience, and environmental health across diverse farming contexts. | M16: Differences in data availability, advisory service capacity, and climate-specific nutrient dynamics. | N16: Climate-nutrient interaction models, soil health assessment tools, and advisory system algorithms. | O16: Collaboration with Soil Health AoW for integration; Digital Accelerator for data systems.
C17: HLO 2.3: Training materials for site-specific nutrient management | D17: 5 | E17: 2 | F17: 2 | G17: 3 | H17: 5 | I17: 2 | K17: Generic nutrient management training fails to address climate-specific challenges or mitigation opportunities through precision approaches. | L17: Capacity development resources enabling context-specific implementation of climate-smart nutrient management across stakeholder groups. | M17: Regional variations in extension systems, educational levels, and private sector engagement in nutrient management. | N17: Adult education expertise, technical training development skills, and knowledge translation capabilities. | O17: Partnership with Capacity Sharing Accelerator for delivery; Private sector for implementation.
C18: HLO 2.4: Evidence for policy recommendations for precision nutrient management | D18: 5 | E18: 2 | F18: 2 | G18: 3 | H18: 2 | I18: 2 | K18: Policy frameworks rarely incentivize climate-smart nutrient practices, missing mitigation and adaptation opportunities. | L18: Evidence-based policies that promote climate-optimized nutrient management through appropriate incentives, regulations, and support programs. | M18: Differences in policy environments, subsidy systems, and climate policy integration across regions. | N18: Policy analysis expertise, economic assessment capabilities, and stakeholder engagement skills. | O18: Strong integration with Policies Program for analysis and recommendations.
C19: HLO 3.1: Soil health monitoring and assessment framework operationalized | D19: 5 | E19: 4 | F19: 4 | G19: 2 | H19: 2 | I19: 5 | K19: Soil health monitoring systems rarely include climate-relevant indicators or support adaptation/mitigation decision-making. | L19: Comprehensive soil monitoring systems tracking climate-relevant indicators and supporting data-driven decisions for adaptation and carbon sequestration. | M19: Regional variations in soil monitoring infrastructure, technical capacity, and climate-soil interaction priorities. | N19: Soil health indicator expertise, digital monitoring systems, and advanced analytical capabilities. | O19: Collaboration with Digital Accelerator for data architecture; Scaling Program for implementation.
C20: HLO 3.2: Network of long-term monitoring sites for carbon storage assessment | D20: 4 | E20: 4 | F20: 2 | G20: 5 | H20: 2 | I20: 5 | K20: Insufficient long-term data on agricultural carbon sequestration potential limits climate mitigation planning and implementation. | L20: Robust network providing verified data on carbon sequestration potential across diverse agricultural systems to guide climate investments. | M20: Differences in existing research infrastructure, agroecological diversity, and carbon sequestration priorities. | N20: Site selection expertise, standardized monitoring protocols, and long-term experimental design capabilities. | O20: Partnership with Environmental Health Program for monitoring; Climate Change Program for integration.
C21: HLO 3.3: Impacts of agricultural practices quantified and catalogued | D21: 4 | E21: 4 | F21: 2 | G21: 5 | H21: 2 | I21: 4 | K21: Limited systematic evidence on climate impacts of agricultural practices hinders effective adaptation and mitigation investments. | L21: Comprehensive evidence base quantifying adaptation and mitigation impacts of practices across contexts to guide climate-smart agriculture scaling. | M21: Regional differences in research coverage, practice adoption patterns, and climate-specific priorities. | N21: Meta-analysis capabilities, impact assessment methodologies, and systematic review expertise. | O21: Integration with Foresight services for scenario modeling; Scaling Program for implementation pathways.
C22: HLO 3.4: Evidence for policy makers on soil health translated to accessible formats | D22: 5 | E22: 4 | F22: 4 | G22: 2 | H22: 2 | I22: 2 | K22: Policy frameworks rarely prioritize soil health for climate resilience or mitigation due to knowledge translation gaps. | L22: Soil health integrated into climate policy frameworks based on accessible evidence demonstrating adaptation and mitigation benefits. | M22: Variations in policy environments, knowledge transmission systems, and prioritization of soil health in climate agendas. | N22: Science communication expertise, policy analysis skills, and stakeholder engagement capabilities. | O22: Partnership with Policy Program for translation; Communications for dissemination strategies.
C23: HLO 4.1: Capacity and networks of plant health practitioners improved | D23: 4 | E23: 4 | F23: 4 | G23: 4 | H23: 3 | I23: 3 | K23: Insufficient capacity to address emerging climate-driven pest and disease threats undermines agricultural resilience. | L23: Robust practitioner networks equipped to monitor, predict, and manage climate-induced shifts in pest and disease pressure. | M23: Regional differences in existing plant health systems, emerging climate-driven threats, and surveillance capacity. | N23: Network development expertise, capacity assessment methodologies, and training program design skills. | O23: Collaboration with Capacity Development Accelerator; Digital Accelerator for surveillance tools.
C24: HLO 4.2: Improved pest and disease monitoring and modeling tools | D24: 5 | E24: 4 | F24: 5 | G24: 5 | H24: 4 | I24: 4 | K24: Early warning systems for climate-driven pest and disease outbreaks are underdeveloped, limiting adaptive response capacity. | L24: Advanced surveillance systems predicting climate-influenced pest and disease dynamics to enable proactive adaptation responses. | M24: Differences in monitoring infrastructure, data availability, and climate-pest modeling capacity. | N24: AI/ML expertise, surveillance technology development capabilities, and predictive modeling skills. | O24: Partnership with Digital Accelerator for technology; Climate Change Program for climate projections.
C25: HLO 4.3: Surveillance data and prevention strategies available | D25: 3 | E25: 3 | F25: 3 | G25: 3 | H25: 2 | I25: 3 | K25: Limited translation of pest/disease intelligence into climate-adaptive prevention strategies undermines resilience. | L25: Evidence-based prevention strategies informed by climate-pest dynamics data enabling proactive adaptation at multiple scales. | M25: Regional variations in data utilization capacity, prevention infrastructure, and climate-pest policy priorities. | N25: Data synthesis expertise, prevention strategy design skills, and policy brief development capabilities. | O25: Integration with Scaling Program for deployment; Policy Program for implementation frameworks.
C26: HLO 4.4: Eco-friendly options for integrated pest management developed | D26: 3 | E26: 3 | F26: 4 | G26: 3 | H26: 3 | I26: 3 | K26: Chemical-intensive pest management approaches increase vulnerability to climate disruptions and undermine ecosystem resilience. | L26: Ecological pest management approaches that build system resilience to climate stresses while reducing environmental impacts. | M26: Differences in current management approaches, agroecological contexts, and climate-specific pest challenges. | N26: Agroecological expertise, participatory testing methodologies, and integrated management design skills. | O26: Collaboration with Biodiversity Program for ecological approaches; Scaling Program for deployment.
... C44: HLO 8.5: Policy-related information for sustainable farming systems | D44: 1 | E44: 1 | F44: 2 | G44: 1 | H44: 1 | I44: 2 | K44: Limited integration of technical evidence into climate policy constrains effective adaptation and mitigation governance. | L44: Systematic translation of farming systems evidence into implementable climate policy across governance scales. | M44: Regional differences in policy-science interfaces, evidence utilization capacity, and climate governance approaches. | N44: Science-policy translation expertise, evidence synthesis methodologies, and policy communication skills. | O44: Strong integration with Policy Program; partnerships with governance institutions.

Sheet 5.Environmental_health
C1: Environmental Indicators
A2: VH | B2: 5 | D2: LAC | E2: CWANA | F2: WCA | G2: ESA | H2: SA | I2: SEA
A3: H | B3: 4 | C3: Total score by column | D3: =SUM(D11:D61) -> 104 | E3: =SUM(E11:E61) -> 104 | F3: =SUM(F11:F61) -> 104 | G3: =SUM(G11:G61) -> 104 | H3: =SUM(H11:H61) -> 104 | I3: =SUM(I11:I61) -> 104
A4: MH | B4: 3 | C4: VH count by column | D4: =COUNTIF(D$11:D$61, 5) -> 7 | E4: =COUNTIF(E$11:E$61, 5) -> 9 | F4: =COUNTIF(F$11:F$61, 5) -> 6 | G4: =COUNTIF(G$11:G$61, 5) -> 8 | H4: =COUNTIF(H$11:H$61, 5) -> 6 | I4: =COUNTIF(I$11:I$61, 5) -> 8
A5: M | B5: 2 | C5: H count by column | D5: =COUNTIF(D$11:D$61, 4) -> 9 | E5: =COUNTIF(E$11:E$61, 4) -> 6 | F5: =COUNTIF(F$11:F$61, 4) -> 6 | G5: =COUNTIF(G$11:G$61, 4) -> 4 | H5: =COUNTIF(H$11:H$61, 4) -> 10 | I5: =COUNTIF(I$11:I$61, 4) -> 2
A6: L | B6: 1 | C6: MH count by column | D6: =COUNTIF(D$11:D$61, 3) -> 2 | E6: =COUNTIF(E$11:E$61, 3) -> 2 | F6: =COUNTIF(F$11:F$61, 3) -> 11 | G6: =COUNTIF(G$11:G$61, 3) -> 10 | H6: =COUNTIF(H$11:H$61, 3) -> 2 | I6: =COUNTIF(I$11:I$61, 3) -> 11
C7: M count by column | D7: =COUNTIF(D$11:D$61, 2) -> 11 | E7: =COUNTIF(E$11:E$61, 2) -> 12 | F7: =COUNTIF(F$11:F$61, 2) -> 6 | G7: =COUNTIF(G$11:G$61, 2) -> 6 | H7: =COUNTIF(H$11:H$61, 2) -> 12 | I7: =COUNTIF(I$11:I$61, 2) -> 10
C8: L count by column | D8: =COUNTIF(D$11:D$61, 1) -> 5 | E8: =COUNTIF(E$11:E$61, 1) -> 5 | F8: =COUNTIF(F$11:F$61, 1) -> 5 | G8: =COUNTIF(G$11:G$61, 1) -> 6 | H8: =COUNTIF(H$11:H$61, 1) -> 4 | I8: =COUNTIF(I$11:I$61, 1) -> 3 | K8: Current state (across the Global South) | L8: Ideal state (across the Global South) | M8: Assumptions (for region-specific scores) | N8: Requirements for success (internal to P/A) | O8: Requirements for success (from other P/As)
C10: HLO | D10: LAC | E10: CWANA | F10: WCA | G10: ESA | H10: SA | I10: SEA
A11: HLO count: | B11: =COUNTA(C11:C61) -> 34 | C11: HLO 1.1: Quantified climate change-related hazards that affect the delivery of agronomic gain | D11: 4 | E11: 4 | F11: 4 | G11: 3 | H11: 4 | I11: 2 | K11: Limited understanding of how climate hazards impact biodiversity, ecosystem services, and overall environmental health in agricultural landscapes. | L11: Comprehensive mapping of climate-biodiversity-agriculture relationships enabling interventions that enhance productivity while protecting ecosystems. | M11: Regional variations in biodiversity hotspots, ecosystem vulnerability to climate change, and environmentally sensitive agricultural systems. | N11: Integrated climate-biodiversity assessment methodologies, ecosystem service mapping, and environmental risk analysis frameworks. | O11: Collaboration with Biodiversity Program for analytical frameworks; Environmental Health Program for monitoring systems.
A12: Sets of 5: | B12: =_xlfn.FLOOR.MATH(B11/5) -> 6 | C12: HLO 1.2: Climate hazard-specific inclusive sustainable farming system innovations | D12: 4 | E12: 4 | F12: 4 | G12: 3 | H12: 4 | I12: 2 | K12: Adaptation approaches often increase environmental pressure through intensification, land expansion, or resource extraction. | L12: Climate-adaptive farming systems explicitly designed to enhance ecosystem services, conserve biodiversity, and reduce land pressure. | M12: Differences in ecosystem-climate dynamics, agrobiodiversity potential, and land pressure patterns across regions. | N12: Ecosystem service-enhancing adaptation research, biodiversity-friendly innovation design, and land footprint assessment methodologies. | O12: Integration with Biodiversity Program for design frameworks; Landscape Program for spatial optimization.
A13: Remainder: | B13: =MOD(B11,5) -> 4 | C13: HLO 1.3: Training materials for climate adaptation and mitigation | D13: 4 | E13: 4 | F13: 4 | G13: 3 | H13: 4 | I13: 2 | K13: Extension materials rarely emphasize ecosystem conservation, biodiversity protection, or environmental stewardship within adaptation strategies. | L13: Capacity development resources enabling implementers to optimize both climate resilience and biodiversity conservation in agricultural landscapes. | M13: Variations in environmental extension capacity, ecosystem stewardship awareness, and prioritization of biodiversity in agricultural training. | N13: Biodiversity-sensitive adaptation curricula, ecosystem service protection modules, and environmental impact minimization tools. | O13: Partnership with Capacity Sharing Accelerator; Biodiversity Program for technical content.
A14: Max score: | B14: =(B12*SUM($B$2:$B$6))+IF(B11=0,0,SUM($B$2:INDEX(B:B,$B$13+1))) -> 104 | C14: HLO 1.4: Policy and investment-ready information on sustainable farming solutions | D14: 4 | E14: 4 | F14: 3 | G14: 3 | H14: 4 | I14: 2 | K14: Climate policy frameworks rarely prioritize biodiversity co-benefits, ecosystem service protection, or land-sparing productivity. | L14: Integrated climate-biodiversity policies guiding investments toward farming systems that enhance environmental health while building resilience. | M14: Differences in policy integration, biodiversity prioritization in climate agendas, and ecosystem service governance. | N14: Climate-biodiversity policy analysis, ecological investment case development, and ecosystem service valuation methodologies. | O14: Collaboration with Policy Program; Biodiversity Program for technical framing.
C15: HLO 2.1: Spatially-explicit recommendation decision support models for soil nutrient constraints | D15: 5 | E15: 5 | F15: 5 | G15: 5 | H15: 5 | I15: 5 | K15: Nutrient recommendations rarely optimize for ecosystem impacts, biodiversity protection, or land-sparing productivity enhancement. | L15: Precision nutrient management systems enhancing productivity while minimizing environmental footprint across diverse landscapes. | M15: Regional variations in ecosystem sensitivity to nutrients, biodiversity-agriculture interactions, and land pressure dynamics. | N15: Ecosystem impact modeling capacity, biodiversity-sensitive recommendation frameworks, and land-sparing productivity assessment tools. | O15: Integration with Digital Accelerator for systems; Biodiversity Program for environmental frameworks.
C16: HLO 2.2: Expanded data-driven agronomic recommendations for site-specific nutrient management | D16: 5 | E16: 5 | F16: 3 | G16: 3 | H16: 5 | I16: 2 | K16: Advisory systems rarely incorporate ecosystem health indicators, biodiversity considerations, or environmental impact minimization. | L16: Integrated nutrient recommendations explicitly balancing productivity enhancement with ecosystem protection and biodiversity conservation. | M16: Differences in ecosystem-nutrient relationships, environmental advisory capacity, and biodiversity-sensitive management approaches. | N16: Ecosystem impact assessment algorithms, biodiversity-sensitive recommendation frameworks, and environmental outcome monitoring tools. | O16: Collaboration with Biodiversity Program; Digital Accelerator for systems development.
C17: HLO 2.3: Training materials for site-specific nutrient management | D17: 5 | E17: 5 | F17: 3 | G17: 2 | H17: 2 | I17: 3 | K17: Extension resources rarely connect soil nutrient management to biodiversity conservation, ecosystem services, or environmental health. | L17: Capacity building materials enabling practitioners to optimize nutrient management for both productivity and environmental objectives. | M17: Regional differences in environmental extension awareness, ecosystem impact training, and biodiversity-nutrient management education. | N17: Ecosystem-sensitive nutrient management curricula, biodiversity impact training modules, and environmental assessment tools. | O17: Partnership with Capacity Sharing Accelerator; Biodiversity Program for content frameworks.
C18: HLO 2.4: Evidence for policy recommendations for precision nutrient management | D18: 2 | E18: 4 | F18: 3 | G18: 2 | H18: 5 | I18: 2 | K18: Policy frameworks rarely optimize fertilizer programs for ecosystem protection, biodiversity conservation, or land-sparing productivity. | L18: Evidence-based policies balancing productivity, economic returns, and environmental health from nutrient management investments. | M18: Variations in policy environments, environmental regulation of inputs, and ecosystem-service valuation in fertilizer governance. | N18: Environmental policy analysis, biodiversity impact evidence synthesis, and ecosystem service valuation methodologies. | O18: Strong integration with Policy Program; Biodiversity Program for analytical frameworks.
C19: HLO 3.1: Soil health monitoring and assessment framework operationalized | D19: 5 | E19: 5 | F19: 4 | G19: 5 | H19: 5 | I19: 5 | K19: Soil monitoring systems rarely track biodiversity indicators, ecosystem service provision, or environmental health outcomes. | L19: Comprehensive soil frameworks connecting soil health to measurable environmental benefits across diverse landscapes. | M19: Regional differences in soil-biodiversity connections, ecosystem service monitoring capacity, and environmental health assessment. | N19: Biodiversity indicator development, ecosystem service tracking methodologies, and environmental health assessment protocols. | O19: Collaboration with Digital Accelerator for systems; Biodiversity Program for indicator frameworks.
C20: HLO 3.2: Network of long-term monitoring sites for carbon storage assessment | D20: 2 | E20: 4 | F20: 3 | G20: 2 | H20: 2 | I20: 1 | K20: Insufficient long-term data on agricultural management impacts on biodiversity, ecosystem services, and environmental health. | L20: Robust network providing verified data on biodiversity impacts of agricultural practices to guide environmental investment. | M20: Differences in existing research infrastructure, agroecological diversity, and biodiversity conservation priorities. | N20: Biodiversity monitoring protocols, ecosystem service assessment methodologies, and environmental impact tracking systems. | O20: Partnership with Biodiversity Program for frameworks; Environmental Health Program for integration.
C21: HLO 3.3: Impacts of agricultural practices quantified and catalogued | D21: 4 | E21: 2 | F21: 2 | G21: 2 | H21: 2 | I21: 5 | K21: Limited systematic evidence on biodiversity impacts, ecosystem service enhancements, or environmental benefits of agricultural practices. | L21: Comprehensive evidence base quantifying ecological outcomes of practices across contexts to guide biodiversity-enhancing agriculture. | M21: Regional differences in ecosystem-agriculture research coverage, biodiversity impact methodologies, and environmental evidence synthesis. | N21: Biodiversity impact assessment methodologies, ecosystem service quantification tools, and environmental meta-analysis frameworks. | O21: Integration with Biodiversity Program for frameworks; Scaling Program for implementation pathways.
C22: HLO 3.4: Evidence for policy makers on soil health translated to accessible formats | D22: 4 | E22: 2 | F22: 2 | G22: 5 | H22: 4 | I22: 5 | K22: Soil health policy communication rarely emphasizes biodiversity benefits, ecosystem service provision, or environmental health enhancement. | L22: Soil policies explicitly connecting soil health to biodiversity conservation and ecosystem service provision through accessible evidence. | M22: Differences in policy environmental framing, ecosystem service emphasis in governance, and biodiversity orientation in soil health. | N22: Biodiversity policy analysis, ecosystem service communication strategies, and environmental stakeholder engagement methodologies. | O22: Partnership with Policy Program; Communications for environmental messaging.
C23: HLO 4.1: Capacity and networks of plant health practitioners improved | D23: 2 | E23: 2 | F23: 2 | G23: 2 | H23: 2 | I23: 2 | K23: Plant health systems rarely optimize for ecological outcomes, biodiversity conservation, or environmental health enhancement. | L23: Practitioner networks balancing plant protection with explicit ecosystem enhancement and biodiversity conservation objectives. | M23: Regional variations in agroecological approaches, biodiversity-sensitive pest management, and ecosystem-based plant health traditions. | N23: Ecological plant health training, biodiversity-centered management approaches, and ecosystem-based intervention strategies. | O23: Collaboration with Capacity Sharing Accelerator; Biodiversity Program for ecological frameworks.
C24: HLO 4.2: Improved pest and disease monitoring and modeling tools | D24: 2 | E24: 2 | F24: 2 | G24: 2 | H24: 2 | I24: 2 | K24: Monitoring systems rarely prioritize non-target impacts, biodiversity protection, or ecosystem service preservation. | L24: Advanced surveillance systems enabling ecologically-optimized pest management decisions that protect biodiversity and ecosystem health. | M24: Differences in monitoring ecological integration, biodiversity impact assessment, and ecosystem-service preservation approaches. | N24: Ecological impact modeling, biodiversity risk assessment, and ecosystem service preservation prioritization frameworks. | O24: Partnership with Digital Accelerator for systems; Biodiversity Program for ecological frameworks.
C25: HLO 4.3: Surveillance data and prevention strategies available | D25: 2 | E25: 2 | F25: 2 | G25: 1 | H25: 2 | I25: 2 | K25: Prevention strategies rarely differentiate ecological sensitivity of interventions, biodiversity impacts, or ecosystem service effects. | L25: Evidence-based prevention approaches explicitly prioritizing biodiversity conservation and ecosystem service protection. | M25: Regional variations in ecosystem-pest relationships, biodiversity-sensitive prevention capacity, and ecological prevention traditions. | N25: Ecological prioritization frameworks, biodiversity impact assessment tools, and ecosystem-based prevention strategies. | O25: Integration with Biodiversity Program for frameworks; Environmental Health Program for indicators.
C26: HLO 4.4: Eco-friendly options for integrated pest management developed | D26: 5 | E26: 5 | F26: 5 | G26: 5 | H26: 5 | I26: 5 | K26: Ecological approaches represent a fundamental pathway to biodiversity conservation and environmental health enhancement in agriculture. | L26: Agroecological pest management systems enhancing both production sustainability and ecosystem health across farm types. | M26: Differences in agroecological potential, biodiversity conservation opportunity, and ecosystem restoration capacity across regions. | N26: Biodiversity-enhancing IPM design, ecosystem service assessment tools, and environmental impact measurement methodologies. | O26: Collaboration with Biodiversity Program for frameworks; Environmental Health Program for monitoring.
... C44: HLO 8.5: Policy-related information for sustainable farming systems | D44: 2 | E44: 2 | F44: 3 | G44: 3 | H44: 2 | I44: 3 | K44: Policy engagement often separates agricultural production and environmental conservation evidence, limiting integrated approaches. | L44: Systematic integration of farming systems evidence into biodiversity-sensitive agricultural policy across governance scales. | M44: Regional variations in environment-agriculture policy interfaces, conservation-production integration, and ecosystem service governance approaches. | N44: Environmental-agricultural policy analysis, integrated evidence synthesis, and conservation-focused communication strategies. | O44: Strong integration with Policy Program; Biodiversity Program for conservation frameworks.

Sheet Step B - Weight by Scl Impact
A1: Potential Scale of Impact - this tab automatically populates your scores from your Step A Impact Area tabs, automatically weighting them by the regional Potential Scale of Impact Scores - You do not have to do anything in this tab, the excel formulas do the weighting for you.
A2: VH
A3: H
A4: MH
A5: M
A6: L
A8: Food Security | I8: Poverty reduction | Q8: Social Inclusion | Y8: Climate Adaptation | AG8: Environmental health
A9: HLO | B9: LAC | C9: CWANA | D9: WCA | E9: ESA | F9: SA | G9: SEA | I9: HLO | J9: LAC | K9: CWANA | L9: WCA | M9: ESA | N9: SA | O9: SEA | Q9: HLO | R9: LAC | S9: CWANA | T9: WCA | U9: ESA | V9: SA | W9: SEA | Y9: HLO | Z9: LAC | AA9: CWANA | AB9: WCA | AC9: ESA | AD9: SA | AE9: SEA | AG9: HLO | AH9: LAC | AI9: CWANA | AJ9: WCA | AK9: ESA | AL9: SA | AM9: SEA
A10: =IF(NOT(ISBLANK(HLOs!D8)),HLOs!D8,"") -> HLO 1.1: Quantified climate change-related hazards that affect the delivery of agronomic gain | B10: ='1.Food_security'!D11*'Step B weights'!B$50 -> 0.25586674 | C10: ='1.Food_security'!E11*'Step B weights'!C$50 -> 0.37399436 | D10: ='1.Food_security'!F11*'Step B weights'!D$50 -> 0.60019803 | E10: ='1.Food_security'!G11*'Step B weights'!E$50 -> 0.68782695 | F10: ='1.Food_security'!H11*'Step B weights'!F$50 -> 1.3955808 | G10: ='1.Food_security'!I11*'Step B weights'!G$50 -> 0.25719153 | I10: =A10 -> HLO 1.1: Quantified climate change-related hazards that affect the delivery of agronomic gain | J10: ='2.Poverty_reduction'!D11*'Step B weights'!J$50 -> 0.18946443 | K10: ='2.Poverty_reduction'!E11*'Step B weights'!K$50 -> 0.13523516 | L10: ='2.Poverty_reduction'!F11*'Step B weights'!L$50 -> 0.97726603 | M10: ='2.Poverty_reduction'!G11*'Step B weights'!M$50 -> 1.1075948 | N10: ='2.Poverty_reduction'!H11*'Step B weights'!N$50 -> 0.86196112 | O10: ='2.Poverty_reduction'!I11*'Step B weights'!O$50 -> 0.033524789 | Q10: =A10 -> HLO 1.1: Quantified climate change-related hazards that affect the delivery of agronomic gain | R10: ='3.Social_inclusion'!D11*'Step B weights'!R$50 -> 0.57779473 | S10: ='3.Social_inclusion'!E11*'Step B weights'!S$50 -> 0.64128195 | T10: ='3.Social_inclusion'!F11*'Step B weights'!T$50 -> 0.93918352 | U10: ='3.Social_inclusion'!G11*'Step B weights'!U$50 -> 0.77832888 | V10: ='3.Social_inclusion'!H11*'Step B weights'!V$50 -> 0.51987791 | W10: ='3.Social_inclusion'!I11*'Step B weights'!W$50 -> 0.37024037 | Y10: =A10 -> HLO 1.1: Quantified climate change-related hazards that affect the delivery of agronomic gain | Z10: ='4.Climate_adaptation'!D11*'Step B weights'!Z$50 -> 0.90299439 | AA10: ='4.Climate_adaptation'!E11*'Step B weights'!AA$50 -> 0.30448259 | AB10: ='4.Climate_adaptation'!F11*'Step B weights'!AB$50 -> 0.24591744 | AC10: ='4.Climate_adaptation'!G11*'Step B weights'!AC$50 -> 0.62086281 | AD10: ='4.Climate_adaptation'!H11*'Step B weights'!AD$50 -> 1.3133688 | AE10: ='4.Climate_adaptation'!I11*'Step B weights'!AE$50 -> 1.2226804 | AG10: =A10 -> HLO 1.1: Quantified climate change-related hazards that affect the delivery of agronomic gain | AH10: ='5.Environmental_health'!D11*'Step B weights'!AH$50 -> 0.90299439 | AI10: ='5.Environmental_health'!E11*'Step B weights'!AI$50 -> 0.24358607 | AJ10: ='5.Environmental_health'!F11*'Step B weights'!AJ$50 -> 0.32788992 | AK10: ='5.Environmental_health'!G11*'Step B weights'!AK$50 -> 0.37251769 | AL10: ='5.Environmental_health'!H11*'Step B weights'!AL$50 -> 1.050695 | AM10: ='5.Environmental_health'!I11*'Step B weights'!AM$50 -> 0.48907218
A11: =IF(NOT(ISBLANK(HLOs!D9)),HLOs!D9,"") -> HLO 1.2: Climate hazard-specific inclusive sustainable farming system innovations | B11: ='1.Food_security'!D12*'Step B weights'!B$50 -> 0.25586674 | C11: ='1.Food_security'!E12*'Step B weights'!C$50 -> 0.37399436 | D11: ='1.Food_security'!F12*'Step B weights'!D$50 -> 0.60019803 | E11: ='1.Food_security'!G12*'Step B weights'!E$50 -> 0.68782695 | F11: ='1.Food_security'!H12*'Step B weights'!F$50 -> 1.3955808 | G11: ='1.Food_security'!I12*'Step B weights'!G$50 -> 0.25719153 | I11: =A11 -> HLO 1.2: Climate hazard-specific inclusive sustainable farming system innovations | J11: ='2.Poverty_reduction'!D12*'Step B weights'!J$50 -> 0.18946443 | K11: ='2.Poverty_reduction'!E12*'Step B weights'!K$50 -> 0.13523516 | L11: ='2.Poverty_reduction'!F12*'Step B weights'!L$50 -> 0.97726603 | M11: ='2.Poverty_reduction'!G12*'Step B weights'!M$50 -> 1.1075948 | N11: ='2.Poverty_reduction'!H12*'Step B weights'!N$50 -> 0.86196112 | O11: ='2.Poverty_reduction'!I12*'Step B weights'!O$50 -> 0.041905986 | Q11: =A11 -> HLO 1.2: Climate hazard-specific inclusive sustainable farming system innovations | R11: ='3.Social_inclusion'!D12*'Step B weights'!R$50 -> 0.57779473 | S11: ='3.Social_inclusion'!E12*'Step B weights'!S$50 -> 0.64128195 | T11: ='3.Social_inclusion'!F12*'Step B weights'!T$50 -> 0.93918352 | U11: ='3.Social_inclusion'!G12*'Step B weights'!U$50 -> 0.77832888 | V11: ='3.Social_inclusion'!H12*'Step B weights'!V$50 -> 0.51987791 | W11: ='3.Social_inclusion'!I12*'Step B weights'!W$50 -> 0.37024037 | Y11: =A11 -> HLO 1.2: Climate hazard-specific inclusive sustainable farming system innovations | Z11: ='4.Climate_adaptation'!D12*'Step B weights'!Z$50 -> 1.128743 | AA11: ='4.Climate_adaptation'!E12*'Step B weights'!AA$50 -> 0.30448259 | AB11: ='4.Climate_adaptation'!F12*'Step B weights'!AB$50 -> 0.24591744 | AC11: ='4.Climate_adaptation'!G12*'Step B weights'!AC$50 -> 0.62086281 | AD11: ='4.Climate_adaptation'!H12*'Step B weights'!AD$50 -> 1.3133688 | AE11: ='4.Climate_adaptation'!I12*'Step B weights'!AE$50 -> 0.97814436 | AG11: =A11 -> HLO 1.2: Climate hazard-specific inclusive sustainable farming system innovations | AH11: ='5.Environmental_health'!D12*'Step B weights'!AH$50 -> 0.90299439 | AI11: ='5.Environmental_health'!E12*'Step B weights'!AI$50 -> 0.24358607 | AJ11: ='5.Environmental_health'!F12*'Step B weights'!AJ$50 -> 0.32788992 | AK11: ='5.Environmental_health'!G12*'Step B weights'!AK$50 -> 0.37251769 | AL11: ='5.Environmental_health'!H12*'Step B weights'!AL$50 -> 1.050695 | AM11: ='5.Environmental_health'!I12*'Step B weights'!AM$50 -> 0.48907218
A12: =IF(NOT(ISBLANK(HLOs!D10)),HLOs!D10,"") -> HLO 1.3: Training materials for climate adaptation and mitigation | B12: ='1.Food_security'!D13*'Step B weights'!B$50 -> 0.25586674 | C12: ='1.Food_security'!E13*'Step B weights'!C$50 -> 0.18699718 | D12: ='1.Food_security'!F13*'Step B weights'!D$50 -> 0.60019803 | E12: ='1.Food_security'!G13*'Step B weights'!E$50 -> 0.68782695 | F12: ='1.Food_security'!H13*'Step B weights'!F$50 -> 1.3955808 | G12: ='1.Food_security'!I13*'Step B weights'!G$50 -> 0.25719153 | I12: =A12 -> HLO 1.3: Training materials for climate adaptation and mitigation | J12: ='2.Poverty_reduction'!D13*'Step B weights'!J$50 -> 0.18946443 | K12: ='2.Poverty_reduction'!E13*'Step B weights'!K$50 -> 0.13523516 | L12: ='2.Poverty_reduction'!F13*'Step B weights'!L$50 -> 0.97726603 | M12: ='2.Poverty_reduction'!G13*'Step B weights'!M$50 -> 1.1075948 | N12: ='2.Poverty_reduction'!H13*'Step B weights'!N$50 -> 0.86196112 | O12: ='2.Poverty_reduction'!I13*'Step B weights'!O$50 -> 0.033524789 | Q12: =A12 -> HLO 1.3: Training materials for climate adaptation and mitigation | R12: ='3.Social_inclusion'!D13*'Step B weights'!R$50 -> 0.57779473 | S12: ='3.Social_inclusion'!E13*'Step B weights'!S$50 -> 0.64128195 | T12: ='3.Social_inclusion'!F13*'Step B weights'!T$50 -> 0.93918352 | U12: ='3.Social_inclusion'!G13*'Step B weights'!U$50 -> 0.77832888 | V12: ='3.Social_inclusion'!H13*'Step B weights'!V$50 -> 0.51987791 | W12: ='3.Social_inclusion'!I13*'Step B weights'!W$50 -> 0.37024037 | Y12: =A12 -> HLO 1.3: Training materials for climate adaptation and mitigation | Z12: ='4.Climate_adaptation'!D13*'Step B weights'!Z$50 -> 0.90299439 | AA12: ='4.Climate_adaptation'!E13*'Step B weights'!AA$50 -> 0.30448259 | AB12: ='4.Climate_adaptation'!F13*'Step B weights'!AB$50 -> 0.24591744 | AC12: ='4.Climate_adaptation'!G13*'Step B weights'!AC$50 -> 0.37251769 | AD12: ='4.Climate_adaptation'!H13*'Step B weights'!AD$50 -> 1.3133688 | AE12: ='4.Climate_adaptation'!I13*'Step B weights'!AE$50 -> 1.2226804 | AG12: =A12 -> HLO 1.3: Training materials for climate adaptation and mitigation | AH12: ='5.Environmental_health'!D13*'Step B weights'!AH$50 -> 0.90299439 | AI12: ='5.Environmental_health'!E13*'Step B weights'!AI$50 -> 0.24358607 | AJ12: ='5.Environmental_health'!F13*'Step B weights'!AJ$50 -> 0.32788992 | AK12: ='5.Environmental_health'!G13*'Step B weights'!AK$50 -> 0.37251769 | AL12: ='5.Environmental_health'!H13*'Step B weights'!AL$50 -> 1.050695 | AM12: ='5.Environmental_health'!I13*'Step B weights'!AM$50 -> 0.48907218
A13: =IF(NOT(ISBLANK(HLOs!D11)),HLOs!D11,"") -> HLO 1.4: Policy and investment-ready information on sustainable farming solutions | B13: ='1.Food_security'!D14*'Step B weights'!B$50 -> 0.25586674 | C13: ='1.Food_security'!E14*'Step B weights'!C$50 -> 0.37399436 | D13: ='1.Food_security'!F14*'Step B weights'!D$50 -> 0.60019803 | E13: ='1.Food_security'!G14*'Step B weights'!E$50 -> 0.4585513 | F13: ='1.Food_security'!H14*'Step B weights'!F$50 -> 1.3955808 | G13: ='1.Food_security'!I14*'Step B weights'!G$50 -> 0.25719153 | I13: =A13 -> HLO 1.4: Policy and investment-ready information on sustainable farming solutions | J13: ='2.Poverty_reduction'!D14*'Step B weights'!J$50 -> 0.18946443 | K13: ='2.Poverty_reduction'!E14*'Step B weights'!K$50 -> 0.13523516 | L13: ='2.Poverty_reduction'!F14*'Step B weights'!L$50 -> 0.97726603 | M13: ='2.Poverty_reduction'!G14*'Step B weights'!M$50 -> 1.1075948 | N13: ='2.Poverty_reduction'!H14*'Step B weights'!N$50 -> 0.86196112 | O13: ='2.Poverty_reduction'!I14*'Step B weights'!O$50 -> 0.033524789 | Q13: =A13 -> HLO 1.4: Policy and investment-ready information on sustainable farming solutions | R13: ='3.Social_inclusion'!D14*'Step B weights'!R$50 -> 0.57779473 | S13: ='3.Social_inclusion'!E14*'Step B weights'!S$50 -> 0.64128195 | T13: ='3.Social_inclusion'!F14*'Step B weights'!T$50 -> 0.93918352 | U13: ='3.Social_inclusion'!G14*'Step B weights'!U$50 -> 0.77832888 | V13: ='3.Social_inclusion'!H14*'Step B weights'!V$50 -> 0.51987791 | W13: ='3.Social_inclusion'!I14*'Step B weights'!W$50 -> 0.37024037 | Y13: =A13 -> HLO 1.4: Policy and investment-ready information on sustainable farming solutions | Z13: ='4.Climate_adaptation'!D14*'Step B weights'!Z$50 -> 1.128743 | AA13: ='4.Climate_adaptation'!E14*'Step B weights'!AA$50 -> 0.24358607 | AB13: ='4.Climate_adaptation'!F14*'Step B weights'!AB$50 -> 0.24591744 | AC13: ='4.Climate_adaptation'!G14*'Step B weights'!AC$50 -> 0.37251769 | AD13: ='4.Climate_adaptation'!H14*'Step B weights'!AD$50 -> 1.3133688 | AE13: ='4.Climate_adaptation'!I14*'Step B weights'!AE$50 -> 1.2226804 | AG13: =A13 -> HLO 1.4: Policy and investment-ready information on sustainable farming solutions | AH13: ='5.Environmental_health'!D14*'Step B weights'!AH$50 -> 0.90299439 | AI13: ='5.Environmental_health'!E14*'Step B weights'!AI$50 -> 0.24358607 | AJ13: ='5.Environmental_health'!F14*'Step B weights'!AJ$50 -> 0.24591744 | AK13: ='5.Environmental_health'!G14*'Step B weights'!AK$50 -> 0.37251769 | AL13: ='5.Environmental_health'!H14*'Step B weights'!AL$50 -> 1.050695 | AM13: ='5.Environmental_health'!I14*'Step B weights'!AM$50 -> 0.48907218
A14: =IF(NOT(ISBLANK(HLOs!D12)),HLOs!D12,"") -> HLO 2.1: Spatially-explicit recommendation decision support models for soil nutrient constraints | B14: ='1.Food_security'!D15*'Step B weights'!B$50 -> 0.31983342 | C14: ='1.Food_security'!E15*'Step B weights'!C$50 -> 0.46749294 | D14: ='1.Food_security'!F15*'Step B weights'!D$50 -> 0.60019803 | E14: ='1.Food_security'!G15*'Step B weights'!E$50 -> 1.1463782 | F14: ='1.Food_security'!H15*'Step B weights'!F$50 -> 1.7444759 | G14: ='1.Food_security'!I15*'Step B weights'!G$50 -> 0.32148941 | I14: =A14 -> HLO 2.1: Spatially-explicit recommendation decision support models for soil nutrient constraints | J14: ='2.Poverty_reduction'!D15*'Step B weights'!J$50 -> 0.23683054 | K14: ='2.Poverty_reduction'!E15*'Step B weights'!K$50 -> 0.16904395 | L14: ='2.Poverty_reduction'!F15*'Step B weights'!L$50 -> 1.6287767 | M14: ='2.Poverty_reduction'!G15*'Step B weights'!M$50 -> 1.1075948 | N14: ='2.Poverty_reduction'!H15*'Step B weights'!N$50 -> 1.0774514 | O14: ='2.Poverty_reduction'!I15*'Step B weights'!O$50 -> 0.041905986 | Q14: =A14 -> HLO 2.1: Spatially-explicit recommendation decision support models for soil nutrient constraints | R14: ='3.Social_inclusion'!D15*'Step B weights'!R$50 -> 0.72224342 | S14: ='3.Social_inclusion'!E15*'Step B weights'!S$50 -> 0.48096147 | T14: ='3.Social_inclusion'!F15*'Step B weights'!T$50 -> 0.93918352 | U14: ='3.Social_inclusion'!G15*'Step B weights'!U$50 -> 0.9729111 | V14: ='3.Social_inclusion'!H15*'Step B weights'!V$50 -> 0.86646318 | W14: ='3.Social_inclusion'!I15*'Step B weights'!W$50 -> 0.46280046 | Y14: =A14 -> HLO 2.1: Spatially-explicit recommendation decision support models for soil nutrient constraints | Z14: ='4.Climate_adaptation'!D15*'Step B weights'!Z$50 -> 1.128743 | AA14: ='4.Climate_adaptation'!E15*'Step B weights'!AA$50 -> 0.30448259 | AB14: ='4.Climate_adaptation'!F15*'Step B weights'!AB$50 -> 0.24591744 | AC14: ='4.Climate_adaptation'!G15*'Step B weights'!AC$50 -> 0.37251769 | AD14: ='4.Climate_adaptation'!H15*'Step B weights'!AD$50 -> 1.3133688 | AE14: ='4.Climate_adaptation'!I15*'Step B weights'!AE$50 -> 1.2226804 | AG14: =A14 -> HLO 2.1: Spatially-explicit recommendation decision support models for soil nutrient constraints | AH14: ='5.Environmental_health'!D15*'Step B weights'!AH$50 -> 1.128743 | AI14: ='5.Environmental_health'!E15*'Step B weights'!AI$50 -> 0.30448259 | AJ14: ='5.Environmental_health'!F15*'Step B weights'!AJ$50 -> 0.4098624 | AK14: ='5.Environmental_health'!G15*'Step B weights'!AK$50 -> 0.62086281 | AL14: ='5.Environmental_health'!H15*'Step B weights'!AL$50 -> 1.3133688 | AM14: ='5.Environmental_health'!I15*'Step B weights'!AM$50 -> 1.2226804
A15: =IF(NOT(ISBLANK(HLOs!D13)),HLOs!D13,"") -> HLO 2.2: Expanded data-driven agronomic recommendations for site-specific nutrient management | B15: ='1.Food_security'!D16*'Step B weights'!B$50 -> 0.31983342 | C15: ='1.Food_security'!E16*'Step B weights'!C$50 -> 0.37399436 | D15: ='1.Food_security'!F16*'Step B weights'!D$50 -> 0.60019803 | E15: ='1.Food_security'!G16*'Step B weights'!E$50 -> 1.1463782 | F15: ='1.Food_security'!H16*'Step B weights'!F$50 -> 1.7444759 | G15: ='1.Food_security'!I16*'Step B weights'!G$50 -> 0.25719153 | I15: =A15 -> HLO 2.2: Expanded data-driven agronomic recommendations for site-specific nutrient management | J15: ='2.Poverty_reduction'!D16*'Step B weights'!J$50 -> 0.23683054 | K15: ='2.Poverty_reduction'!E16*'Step B weights'!K$50 -> 0.13523516 | L15: ='2.Poverty_reduction'!F16*'Step B weights'!L$50 -> 0.97726603 | M15: ='2.Poverty_reduction'!G16*'Step B weights'!M$50 -> 1.1075948 | N15: ='2.Poverty_reduction'!H16*'Step B weights'!N$50 -> 1.0774514 | O15: ='2.Poverty_reduction'!I16*'Step B weights'!O$50 -> 0.016762394 | Q15: =A15 -> HLO 2.2: Expanded data-driven agronomic recommendations for site-specific nutrient management | R15: ='3.Social_inclusion'!D16*'Step B weights'!R$50 -> 0.72224342 | S15: ='3.Social_inclusion'!E16*'Step B weights'!S$50 -> 0.32064098 | T15: ='3.Social_inclusion'!F16*'Step B weights'!T$50 -> 0.70438764 | U15: ='3.Social_inclusion'!G16*'Step B weights'!U$50 -> 0.58374666 | V15: ='3.Social_inclusion'!H16*'Step B weights'!V$50 -> 0.51987791 | W15: ='3.Social_inclusion'!I16*'Step B weights'!W$50 -> 0.46280046 | Y15: =A15 -> HLO 2.2: Expanded data-driven agronomic recommendations for site-specific nutrient management | Z15: ='4.Climate_adaptation'!D16*'Step B weights'!Z$50 -> 0.90299439 | AA15: ='4.Climate_adaptation'!E16*'Step B weights'!AA$50 -> 0.12179304 | AB15: ='4.Climate_adaptation'!F16*'Step B weights'!AB$50 -> 0.24591744 | AC15: ='4.Climate_adaptation'!G16*'Step B weights'!AC$50 -> 0.24834513 | AD15: ='4.Climate_adaptation'!H16*'Step B weights'!AD$50 -> 1.3133688 | AE15: ='4.Climate_adaptation'!I16*'Step B weights'!AE$50 -> 0.97814436 | AG15: =A15 -> HLO 2.2: Expanded data-driven agronomic recommendations for site-specific nutrient management | AH15: ='5.Environmental_health'!D16*'Step B weights'!AH$50 -> 1.128743 | AI15: ='5.Environmental_health'!E16*'Step B weights'!AI$50 -> 0.30448259 | AJ15: ='5.Environmental_health'!F16*'Step B weights'!AJ$50 -> 0.24591744 | AK15: ='5.Environmental_health'!G16*'Step B weights'!AK$50 -> 0.37251769 | AL15: ='5.Environmental_health'!H16*'Step B weights'!AL$50 -> 1.3133688 | AM15: ='5.Environmental_health'!I16*'Step B weights'!AM$50 -> 0.48907218
A16: =IF(NOT(ISBLANK(HLOs!D14)),HLOs!D14,"") -> HLO 2.3: Training materials for site-specific nutrient management | B16: ='1.Food_security'!D17*'Step B weights'!B$50 -> 0.31983342 | C16: ='1.Food_security'!E17*'Step B weights'!C$50 -> 0.18699718 | D16: ='1.Food_security'!F17*'Step B weights'!D$50 -> 0.60019803 | E16: ='1.Food_security'!G17*'Step B weights'!E$50 -> 0.68782695 | F16: ='1.Food_security'!H17*'Step B weights'!F$50 -> 1.7444759 | G16: ='1.Food_security'!I17*'Step B weights'!G$50 -> 0.25719153 | I16: =A16 -> HLO 2.3: Training materials for site-specific nutrient management | J16: ='2.Poverty_reduction'!D17*'Step B weights'!J$50 -> 0.23683054 | K16: ='2.Poverty_reduction'!E17*'Step B weights'!K$50 -> 0.16904395 | L16: ='2.Poverty_reduction'!F17*'Step B weights'!L$50 -> 0.97726603 | M16: ='2.Poverty_reduction'!G17*'Step B weights'!M$50 -> 1.1075948 | N16: ='2.Poverty_reduction'!H17*'Step B weights'!N$50 -> 1.0774514 | O16: ='2.Poverty_reduction'!I17*'Step B weights'!O$50 -> 0.033524789 | Q16: =A16 -> HLO 2.3: Training materials for site-specific nutrient management | R16: ='3.Social_inclusion'!D17*'Step B weights'!R$50 -> 0.72224342 | S16: ='3.Social_inclusion'!E17*'Step B weights'!S$50 -> 0.32064098 | T16: ='3.Social_inclusion'!F17*'Step B weights'!T$50 -> 0.70438764 | U16: ='3.Social_inclusion'!G17*'Step B weights'!U$50 -> 0.58374666 | V16: ='3.Social_inclusion'!H17*'Step B weights'!V$50 -> 0.34658527 | W16: ='3.Social_inclusion'!I17*'Step B weights'!W$50 -> 0.46280046 | Y16: =A16 -> HLO 2.3: Training materials for site-specific nutrient management | Z16: ='4.Climate_adaptation'!D17*'Step B weights'!Z$50 -> 1.128743 | AA16: ='4.Climate_adaptation'!E17*'Step B weights'!AA$50 -> 0.12179304 | AB16: ='4.Climate_adaptation'!F17*'Step B weights'!AB$50 -> 0.16394496 | AC16: ='4.Climate_adaptation'!G17*'Step B weights'!AC$50 -> 0.37251769 | AD16: ='4.Climate_adaptation'!H17*'Step B weights'!AD$50 -> 1.3133688 | AE16: ='4.Climate_adaptation'!I17*'Step B weights'!AE$50 -> 0.48907218 | AG16: =A16 -> HLO 2.3: Training materials for site-specific nutrient management | AH16: ='5.Environmental_health'!D17*'Step B weights'!AH$50 -> 1.128743 | AI16: ='5.Environmental_health'!E17*'Step B weights'!AI$50 -> 0.30448259 | AJ16: ='5.Environmental_health'!F17*'Step B weights'!AJ$50 -> 0.24591744 | AK16: ='5.Environmental_health'!G17*'Step B weights'!AK$50 -> 0.24834513 | AL16: ='5.Environmental_health'!H17*'Step B weights'!AL$50 -> 0.5253475 | AM16: ='5.Environmental_health'!I17*'Step B weights'!AM$50 -> 0.73360827
A17: =IF(NOT(ISBLANK(HLOs!D15)),HLOs!D15,"") -> HLO 2.4: Evidence for policy recommendations for precision nutrient management | B17: ='1.Food_security'!D18*'Step B weights'!B$50 -> 0.25586674 | C17: ='1.Food_security'!E18*'Step B weights'!C$50 -> 0.37399436 | D17: ='1.Food_security'!F18*'Step B weights'!D$50 -> 0.40013202 | E17: ='1.Food_security'!G18*'Step B weights'!E$50 -> 1.1463782 | F17: ='1.Food_security'!H18*'Step B weights'!F$50 -> 1.3955808 | G17: ='1.Food_security'!I18*'Step B weights'!G$50 -> 0.25719153 | I17: =A17 -> HLO 2.4: Evidence for policy recommendations for precision nutrient management | J17: ='2.Poverty_reduction'!D18*'Step B weights'!J$50 -> 0.18946443 | K17: ='2.Poverty_reduction'!E18*'Step B weights'!K$50 -> 0.13523516 | L17: ='2.Poverty_reduction'!F18*'Step B weights'!L$50 -> 0.65151069 | M17: ='2.Poverty_reduction'!G18*'Step B weights'!M$50 -> 0.73839656 | N17: ='2.Poverty_reduction'!H18*'Step B weights'!N$50 -> 0.43098056 | O17: ='2.Poverty_reduction'!I18*'Step B weights'!O$50 -> 0.016762394 | Q17: =A17 -> HLO 2.4: Evidence for policy recommendations for precision nutrient management | R17: ='3.Social_inclusion'!D18*'Step B weights'!R$50 -> 0.57779473 | S17: ='3.Social_inclusion'!E18*'Step B weights'!S$50 -> 0.32064098 | T17: ='3.Social_inclusion'!F18*'Step B weights'!T$50 -> 0.70438764 | U17: ='3.Social_inclusion'!G18*'Step B weights'!U$50 -> 0.58374666 | V17: ='3.Social_inclusion'!H18*'Step B weights'!V$50 -> 0.34658527 | W17: ='3.Social_inclusion'!I18*'Step B weights'!W$50 -> 0.37024037 | Y17: =A17 -> HLO 2.4: Evidence for policy recommendations for precision nutrient management | Z17: ='4.Climate_adaptation'!D18*'Step B weights'!Z$50 -> 1.128743 | AA17: ='4.Climate_adaptation'!E18*'Step B weights'!AA$50 -> 0.12179304 | AB17: ='4.Climate_adaptation'!F18*'Step B weights'!AB$50 -> 0.16394496 | AC17: ='4.Climate_adaptation'!G18*'Step B weights'!AC$50 -> 0.37251769 | AD17: ='4.Climate_adaptation'!H18*'Step B weights'!AD$50 -> 0.5253475 | AE17: ='4.Climate_adaptation'!I18*'Step B weights'!AE$50 -> 0.48907218 | AG17: =A17 -> HLO 2.4: Evidence for policy recommendations for precision nutrient management | AH17: ='5.Environmental_health'!D18*'Step B weights'!AH$50 -> 0.4514972 | AI17: ='5.Environmental_health'!E18*'Step B weights'!AI$50 -> 0.24358607 | AJ17: ='5.Environmental_health'!F18*'Step B weights'!AJ$50 -> 0.24591744 | AK17: ='5.Environmental_health'!G18*'Step B weights'!AK$50 -> 0.24834513 | AL17: ='5.Environmental_health'!H18*'Step B weights'!AL$50 -> 1.3133688 | AM17: ='5.Environmental_health'!I18*'Step B weights'!AM$50 -> 0.48907218
A18: =IF(NOT(ISBLANK(HLOs!D16)),HLOs!D16,"") -> HLO 3.1: Soil health monitoring and assessment framework operationalized | B18: ='1.Food_security'!D19*'Step B weights'!B$50 -> 0.31983342 | C18: ='1.Food_security'!E19*'Step B weights'!C$50 -> 0.46749294 | D18: ='1.Food_security'!F19*'Step B weights'!D$50 -> 0.40013202 | E18: ='1.Food_security'!G19*'Step B weights'!E$50 -> 0.4585513 | F18: ='1.Food_security'!H19*'Step B weights'!F$50 -> 1.3955808 | G18: ='1.Food_security'!I19*'Step B weights'!G$50 -> 0.32148941 | I18: =A18 -> HLO 3.1: Soil health monitoring and assessment framework operationalized | J18: ='2.Poverty_reduction'!D19*'Step B weights'!J$50 -> 0.23683054 | K18: ='2.Poverty_reduction'!E19*'Step B weights'!K$50 -> 0.16904395 | L18: ='2.Poverty_reduction'!F19*'Step B weights'!L$50 -> 0.65151069 | M18: ='2.Poverty_reduction'!G19*'Step B weights'!M$50 -> 0.73839656 | N18: ='2.Poverty_reduction'!H19*'Step B weights'!N$50 -> 0.43098056 | O18: ='2.Poverty_reduction'!I19*'Step B weights'!O$50 -> 0.041905986 | Q18: =A18 -> HLO 3.1: Soil health monitoring and assessment framework operationalized | R18: ='3.Social_inclusion'!D19*'Step B weights'!R$50 -> 0.72224342 | S18: ='3.Social_inclusion'!E19*'Step B weights'!S$50 -> 0.32064098 | T18: ='3.Social_inclusion'!F19*'Step B weights'!T$50 -> 0.70438764 | U18: ='3.Social_inclusion'!G19*'Step B weights'!U$50 -> 0.58374666 | V18: ='3.Social_inclusion'!H19*'Step B weights'!V$50 -> 0.86646318 | W18: ='3.Social_inclusion'!I19*'Step B weights'!W$50 -> 0.46280046 | Y18: =A18 -> HLO 3.1: Soil health monitoring and assessment framework operationalized | Z18: ='4.Climate_adaptation'!D19*'Step B weights'!Z$50 -> 1.128743 | AA18: ='4.Climate_adaptation'!E19*'Step B weights'!AA$50 -> 0.24358607 | AB18: ='4.Climate_adaptation'!F19*'Step B weights'!AB$50 -> 0.32788992 | AC18: ='4.Climate_adaptation'!G19*'Step B weights'!AC$50 -> 0.24834513 | AD18: ='4.Climate_adaptation'!H19*'Step B weights'!AD$50 -> 0.5253475 | AE18: ='4.Climate_adaptation'!I19*'Step B weights'!AE$50 -> 1.2226804 | AG18: =A18 -> HLO 3.1: Soil health monitoring and assessment framework operationalized | AH18: ='5.Environmental_health'!D19*'Step B weights'!AH$50 -> 1.128743 | AI18: ='5.Environmental_health'!E19*'Step B weights'!AI$50 -> 0.30448259 | AJ18: ='5.Environmental_health'!F19*'Step B weights'!AJ$50 -> 0.32788992 | AK18: ='5.Environmental_health'!G19*'Step B weights'!AK$50 -> 0.62086281 | AL18: ='5.Environmental_health'!H19*'Step B weights'!AL$50 -> 1.3133688 | AM18: ='5.Environmental_health'!I19*'Step B weights'!AM$50 -> 1.2226804
A19: =IF(NOT(ISBLANK(HLOs!D17)),HLOs!D17,"") -> HLO 3.2: Network of long-term monitoring sites for carbon storage assessment | B19: ='1.Food_security'!D20*'Step B weights'!B$50 -> 0.25586674 | C19: ='1.Food_security'!E20*'Step B weights'!C$50 -> 0.46749294 | D19: ='1.Food_security'!F20*'Step B weights'!D$50 -> 0.40013202 | E19: ='1.Food_security'!G20*'Step B weights'!E$50 -> 0.4585513 | F19: ='1.Food_security'!H20*'Step B weights'!F$50 -> 0.69779038 | G19: ='1.Food_security'!I20*'Step B weights'!G$50 -> 0.25719153 | I19: =A19 -> HLO 3.2: Network of long-term monitoring sites for carbon storage assessment | J19: ='2.Poverty_reduction'!D20*'Step B weights'!J$50 -> 0.18946443 | K19: ='2.Poverty_reduction'!E20*'Step B weights'!K$50 -> 0.067617579 | L19: ='2.Poverty_reduction'!F20*'Step B weights'!L$50 -> 0.65151069 | M19: ='2.Poverty_reduction'!G20*'Step B weights'!M$50 -> 0.73839656 | N19: ='2.Poverty_reduction'!H20*'Step B weights'!N$50 -> 0.43098056 | O19: ='2.Poverty_reduction'!I20*'Step B weights'!O$50 -> 0.016762394 | Q19: =A19 -> HLO 3.2: Network of long-term monitoring sites for carbon storage assessment | R19: ='3.Social_inclusion'!D20*'Step B weights'!R$50 -> 0.57779473 | S19: ='3.Social_inclusion'!E20*'Step B weights'!S$50 -> 0.32064098 | T19: ='3.Social_inclusion'!F20*'Step B weights'!T$50 -> 0.70438764 | U19: ='3.Social_inclusion'!G20*'Step B weights'!U$50 -> 0.58374666 | V19: ='3.Social_inclusion'!H20*'Step B weights'!V$50 -> 0.34658527 | W19: ='3.Social_inclusion'!I20*'Step B weights'!W$50 -> 0.18512018 | Y19: =A19 -> HLO 3.2: Network of long-term monitoring sites for carbon storage assessment | Z19: ='4.Climate_adaptation'!D20*'Step B weights'!Z$50 -> 0.90299439 | AA19: ='4.Climate_adaptation'!E20*'Step B weights'!AA$50 -> 0.24358607 | AB19: ='4.Climate_adaptation'!F20*'Step B weights'!AB$50 -> 0.16394496 | AC19: ='4.Climate_adaptation'!G20*'Step B weights'!AC$50 -> 0.62086281 | AD19: ='4.Climate_adaptation'!H20*'Step B weights'!AD$50 -> 0.5253475 | AE19: ='4.Climate_adaptation'!I20*'Step B weights'!AE$50 -> 1.2226804 | AG19: =A19 -> HLO 3.2: Network of long-term monitoring sites for carbon storage assessment | AH19: ='5.Environmental_health'!D20*'Step B weights'!AH$50 -> 0.4514972 | AI19: ='5.Environmental_health'!E20*'Step B weights'!AI$50 -> 0.24358607 | AJ19: ='5.Environmental_health'!F20*'Step B weights'!AJ$50 -> 0.24591744 | AK19: ='5.Environmental_health'!G20*'Step B weights'!AK$50 -> 0.24834513 | AL19: ='5.Environmental_health'!H20*'Step B weights'!AL$50 -> 0.5253475 | AM19: ='5.Environmental_health'!I20*'Step B weights'!AM$50 -> 0.24453609
A20: =IF(NOT(ISBLANK(HLOs!D18)),HLOs!D18,"") -> HLO 3.3: Impacts of agricultural practices quantified and catalogued | B20: ='1.Food_security'!D21*'Step B weights'!B$50 -> 0.25586674 | C20: ='1.Food_security'!E21*'Step B weights'!C$50 -> 0.18699718 | D20: ='1.Food_security'!F21*'Step B weights'!D$50 -> 0.40013202 | E20: ='1.Food_security'!G21*'Step B weights'!E$50 -> 0.4585513 | F20: ='1.Food_security'!H21*'Step B weights'!F$50 -> 0.69779038 | G20: ='1.Food_security'!I21*'Step B weights'!G$50 -> 0.12859576 | I20: =A20 -> HLO 3.3: Impacts of agricultural practices quantified and catalogued | J20: ='2.Poverty_reduction'!D21*'Step B weights'!J$50 -> 0.18946443 | K20: ='2.Poverty_reduction'!E21*'Step B weights'!K$50 -> 0.067617579 | L20: ='2.Poverty_reduction'!F21*'Step B weights'!L$50 -> 0.65151069 | M20: ='2.Poverty_reduction'!G21*'Step B weights'!M$50 -> 0.73839656 | N20: ='2.Poverty_reduction'!H21*'Step B weights'!N$50 -> 0.43098056 | O20: ='2.Poverty_reduction'!I21*'Step B weights'!O$50 -> 0.016762394 | Q20: =A20 -> HLO 3.3: Impacts of agricultural practices quantified and catalogued | R20: ='3.Social_inclusion'!D21*'Step B weights'!R$50 -> 0.57779473 | S20: ='3.Social_inclusion'!E21*'Step B weights'!S$50 -> 0.32064098 | T20: ='3.Social_inclusion'!F21*'Step B weights'!T$50 -> 0.70438764 | U20: ='3.Social_inclusion'!G21*'Step B weights'!U$50 -> 0.58374666 | V20: ='3.Social_inclusion'!H21*'Step B weights'!V$50 -> 0.34658527 | W20: ='3.Social_inclusion'!I21*'Step B weights'!W$50 -> 0.18512018 | Y20: =A20 -> HLO 3.3: Impacts of agricultural practices quantified and catalogued | Z20: ='4.Climate_adaptation'!D21*'Step B weights'!Z$50 -> 0.90299439 | AA20: ='4.Climate_adaptation'!E21*'Step B weights'!AA$50 -> 0.24358607 | AB20: ='4.Climate_adaptation'!F21*'Step B weights'!AB$50 -> 0.16394496 | AC20: ='4.Climate_adaptation'!G21*'Step B weights'!AC$50 -> 0.62086281 | AD20: ='4.Climate_adaptation'!H21*'Step B weights'!AD$50 -> 0.5253475 | AE20: ='4.Climate_adaptation'!I21*'Step B weights'!AE$50 -> 0.97814436 | AG20: =A20 -> HLO 3.3: Impacts of agricultural practices quantified and catalogued | AH20: ='5.Environmental_health'!D21*'Step B weights'!AH$50 -> 0.90299439 | AI20: ='5.Environmental_health'!E21*'Step B weights'!AI$50 -> 0.12179304 | AJ20: ='5.Environmental_health'!F21*'Step B weights'!AJ$50 -> 0.16394496 | AK20: ='5.Environmental_health'!G21*'Step B weights'!AK$50 -> 0.24834513 | AL20: ='5.Environmental_health'!H21*'Step B weights'!AL$50 -> 0.5253475 | AM20: ='5.Environmental_health'!I21*'Step B weights'!AM$50 -> 1.2226804
A21: =IF(NOT(ISBLANK(HLOs!D19)),HLOs!D19,"") -> HLO 3.4: Evidence for policy makers on soil health translated to accessible formats | B21: ='1.Food_security'!D22*'Step B weights'!B$50 -> 0.25586674 | C21: ='1.Food_security'!E22*'Step B weights'!C$50 -> 0.18699718 | D21: ='1.Food_security'!F22*'Step B weights'!D$50 -> 0.40013202 | E21: ='1.Food_security'!G22*'Step B weights'!E$50 -> 0.4585513 | F21: ='1.Food_security'!H22*'Step B weights'!F$50 -> 0.69779038 | G21: ='1.Food_security'!I22*'Step B weights'!G$50 -> 0.12859576 | I21: =A21 -> HLO 3.4: Evidence for policy makers on soil health translated to accessible formats | J21: ='2.Poverty_reduction'!D22*'Step B weights'!J$50 -> 0.18946443 | K21: ='2.Poverty_reduction'!E22*'Step B weights'!K$50 -> 0.067617579 | L21: ='2.Poverty_reduction'!F22*'Step B weights'!L$50 -> 0.65151069 | M21: ='2.Poverty_reduction'!G22*'Step B weights'!M$50 -> 0.73839656 | N21: ='2.Poverty_reduction'!H22*'Step B weights'!N$50 -> 0.43098056 | O21: ='2.Poverty_reduction'!I22*'Step B weights'!O$50 -> 0.016762394 | Q21: =A21 -> HLO 3.4: Evidence for policy makers on soil health translated to accessible formats | R21: ='3.Social_inclusion'!D22*'Step B weights'!R$50 -> 0.57779473 | S21: ='3.Social_inclusion'!E22*'Step B weights'!S$50 -> 0.16032049 | T21: ='3.Social_inclusion'!F22*'Step B weights'!T$50 -> 0.70438764 | U21: ='3.Social_inclusion'!G22*'Step B weights'!U$50 -> 0.38916444 | V21: ='3.Social_inclusion'!H22*'Step B weights'!V$50 -> 0.34658527 | W21: ='3.Social_inclusion'!I22*'Step B weights'!W$50 -> 0.18512018 | Y21: =A21 -> HLO 3.4: Evidence for policy makers on soil health translated to accessible formats | Z21: ='4.Climate_adaptation'!D22*'Step B weights'!Z$50 -> 1.128743 | AA21: ='4.Climate_adaptation'!E22*'Step B weights'!AA$50 -> 0.24358607 | AB21: ='4.Climate_adaptation'!F22*'Step B weights'!AB$50 -> 0.32788992 | AC21: ='4.Climate_adaptation'!G22*'Step B weights'!AC$50 -> 0.24834513 | AD21: ='4.Climate_adaptation'!H22*'Step B weights'!AD$50 -> 0.5253475 | AE21: ='4.Climate_adaptation'!I22*'Step B weights'!AE$50 -> 0.48907218 | AG21: =A21 -> HLO 3.4: Evidence for policy makers on soil health translated to accessible formats | AH21: ='5.Environmental_health'!D22*'Step B weights'!AH$50 -> 0.90299439 | AI21: ='5.Environmental_health'!E22*'Step B weights'!AI$50 -> 0.12179304 | AJ21: ='5.Environmental_health'!F22*'Step B weights'!AJ$50 -> 0.16394496 | AK21: ='5.Environmental_health'!G22*'Step B weights'!AK$50 -> 0.62086281 | AL21: ='5.Environmental_health'!H22*'Step B weights'!AL$50 -> 1.050695 | AM21: ='5.Environmental_health'!I22*'Step B weights'!AM$50 -> 1.2226804
... A43: =IF(NOT(ISBLANK(HLOs!D41)),HLOs!D41,"") -> HLO 8.5: Policy-related information for sustainable farming systems | B43: ='1.Food_security'!D44*'Step B weights'!B$50 -> 0.12793337 | C43: ='1.Food_security'!E44*'Step B weights'!C$50 -> 0.18699718 | D43: ='1.Food_security'!F44*'Step B weights'!D$50 -> 0.20006601 | E43: ='1.Food_security'!G44*'Step B weights'!E$50 -> 0.22927565 | F43: ='1.Food_security'!H44*'Step B weights'!F$50 -> 0.69779038 | G43: ='1.Food_security'!I44*'Step B weights'!G$50 -> 0.12859576 | I43: =A43 -> HLO 8.5: Policy-related information for sustainable farming systems | J43: ='2.Poverty_reduction'!D44*'Step B weights'!J$50 -> 0.094732217 | K43: ='2.Poverty_reduction'!E44*'Step B weights'!K$50 -> 0.067617579 | L43: ='2.Poverty_reduction'!F44*'Step B weights'!L$50 -> 1.3030214 | M43: ='2.Poverty_reduction'!G44*'Step B weights'!M$50 -> 0.36919828 | N43: ='2.Poverty_reduction'!H44*'Step B weights'!N$50 -> 0.43098056 | O43: ='2.Poverty_reduction'!I44*'Step B weights'!O$50 -> 0.016762394 | Q43: =A43 -> HLO 8.5: Policy-related information for sustainable farming systems | R43: ='3.Social_inclusion'!D44*'Step B weights'!R$50 -> 0.28889737 | S43: ='3.Social_inclusion'!E44*'Step B weights'!S$50 -> 0.32064098 | T43: ='3.Social_inclusion'!F44*'Step B weights'!T$50 -> 0.93918352 | U43: ='3.Social_inclusion'!G44*'Step B weights'!U$50 -> 0.58374666 | V43: ='3.Social_inclusion'!H44*'Step B weights'!V$50 -> 0.51987791 | W43: ='3.Social_inclusion'!I44*'Step B weights'!W$50 -> 0.18512018 | Y43: =A43 -> HLO 8.5: Policy-related information for sustainable farming systems | Z43: ='4.Climate_adaptation'!D44*'Step B weights'!Z$50 -> 0.2257486 | AA43: ='4.Climate_adaptation'!E44*'Step B weights'!AA$50 -> 0.060896518 | AB43: ='4.Climate_adaptation'!F44*'Step B weights'!AB$50 -> 0.16394496 | AC43: ='4.Climate_adaptation'!G44*'Step B weights'!AC$50 -> 0.12417256 | AD43: ='4.Climate_adaptation'!H44*'Step B weights'!AD$50 -> 0.26267375 | AE43: ='4.Climate_adaptation'!I44*'Step B weights'!AE$50 -> 0.48907218 | AG43: =A43 -> HLO 8.5: Policy-related information for sustainable farming systems | AH43: ='5.Environmental_health'!D44*'Step B weights'!AH$50 -> 0.4514972 | AI43: ='5.Environmental_health'!E44*'Step B weights'!AI$50 -> 0.12179304 | AJ43: ='5.Environmental_health'!F44*'Step B weights'!AJ$50 -> 0.24591744 | AK43: ='5.Environmental_health'!G44*'Step B weights'!AK$50 -> 0.37251769 | AL43: ='5.Environmental_health'!H44*'Step B weights'!AL$50 -> 0.5253475 | AM43: ='5.Environmental_health'!I44*'Step B weights'!AM$50 -> 0.73360827

Sheet Step B weights
A1: Link to spreadsheet with raw data: Projected Benefits Data (Nov 2024) - With Analysis.xlsx
A2: Food Security | I2: Poverty reduction | Q2: Social Inclusion | Y2: Climate Adaptation | AG2: Environmental health
A3: Prevalence of Undernourishment | I3: Poor Population ($2.15) | Q3: Gender Inclusivity Index | Y3: Agricultural Greenhouse Gas (GHG) Emissions | AG3: Agricultural Greenhouse Gas (GHG) Emissions
A4: Coverage | B4: Region totals | I4: Coverage | J4: Region totals | Q4: Coverage | R4: Region totals | Y4: Coverage | Z4: Region totals | AG4: Coverage | AH4: Region totals
A5: Units | B5: Share of total population living below the minimum calorie daily threshold | I5: Units | J5: Millions of people living below the poverty line | Q5: Units | Y5: Units | Z5: Millions of tons of CO2eq emissions | AG5: Units | AH5: Millions of tons of CO2eq emissions
A6: Region | B6: 2021 | C6: 2022 | D6: 2023 | E6: 2024 | F6: 2025 | I6: Region | J6: 2021 | K6: 2022 | L6: 2023 | M6: 2024 | N6: 2025 | Q6: Region | V6: 2022 | Y6: Region | Z6: 2021 | AA6: 2022 | AB6: 2023 | AC6: 2024 | AD6: 2025 | AG6: Region | AH6: 2021 | AI6: 2022 | AJ6: 2023 | AK6: 2024 | AL6: 2025
A7: r_wld | B7: 8.8427009 | C7: 8.2286613 | D7: 7.6489309 | E7: 7.1031772 | F7: 6.5908679 | I7: r_wld | J7: 751.13725 | K7: 737.74175 | L7: 726.16698 | M7: 716.37814 | N7: 708.31417
A8: LAC | B8: 7.1892578 | C8: 6.68889 | D8: 6.2115266 | E8: 5.7570393 | F8: 5.3252329 | H8: LAC | I8: r_lac | J8: 31.202645 | K8: 31.753595 | L8: 32.307095 | M8: 32.862885 | N8: 33.420694 | P8: LAC | Q8: r_lac | V8: 0.3786 | X8: LAC | Y8: r_lac | Z8: 1062.158 | AA8: 1066.2886 | AB8: 1070.4689 | AC8: 1074.6999 | AD8: 1078.9828 | AF8: LAC | AG8: r_lac | AH8: 1062.158 | AI8: 1066.2886 | AJ8: 1070.4689 | AK8: 1074.6999 | AL8: 1078.9828
A9: CWANA | B9: 9.1504665 | C9: 8.9091662 | D9: 8.6634743 | E9: 8.4138444 | F9: 8.160744 | H9: CWANA | I9: r_cwana | J9: 26.653279 | K9: 25.965677 | L9: 25.26942 | M9: 24.565485 | N9: 23.854888 | P9: CWANA | Q9: r_cwana | V9: 0.4202 | X9: CWANA | Y9: r_cwana | Z9: 267.73908 | AA9: 273.34463 | AB9: 279.09723 | AC9: 285.00085 | AD9: 291.05959 | AF9: CWANA | AG9: r_cwana | AH9: 267.73908 | AI9: 273.34463 | AJ9: 279.09723 | AK9: 285.00085 | AL9: 291.05959
A10: WCA | B10: 18.91209 | C10: 18.415278 | D10: 17.911492 | E10: 17.401678 | F10: 16.886799 | H10: WCA | I10: r_wca | J10: 208.51838 | K10: 213.67868 | L10: 218.95234 | M10: 224.34123 | N10: 229.84725 | P10: WCA | Q10: r_wca | V10: 0.6154 | X10: WCA | Y10: r_wca | Z10: 354.39024 | AA10: 363.3539 | AB10: 372.57066 | AC10: 382.04804 | AD10: 391.79377 | AF10: WCA | AG10: r_wca | AH10: 354.39024 | AI10: 363.3539 | AJ10: 372.57066 | AK10: 382.04804 | AL10: 391.79377
A11: ESA | B11: 22.510157 | C11: 21.490211 | D11: 20.474437 | E11: 19.465188 | F11: 18.464847 | H11: ESA | I11: r_esa | J11: 236.00367 | K11: 241.91652 | L11: 247.96834 | M11: 254.16186 | N11: 260.49982 | P11: ESA | Q11: r_esa | V11: 0.51 | X11: ESA | Y11: r_esa | Z11: 505.23434 | AA11: 525.74193 | AB11: 547.2502 | AC11: 569.81422 | AD11: 593.49232 | AF11: ESA | AG11: r_esa | AH11: 505.23434 | AI11: 525.74193 | AJ11: 547.2502 | AK11: 569.81422 | AL11: 593.49232
A12: SA | B12: 15.036352 | C12: 13.50078 | D12: 12.058387 | E12: 10.711231 | F12: 9.460449 | H12: SA | I12: r_sa | J12: 218.39156 | K12: 201.58977 | L12: 184.85464 | M12: 168.30042 | N12: 152.04616 | P12: SA | Q12: r_sa | V12: 0.4542 | X12: SA | Y12: r_sa | Z12: 1147.9065 | AA12: 1173.4687 | AB12: 1199.8917 | AC12: 1227.2124 | AD12: 1255.4694 | AF12: SA | AG12: r_sa | AH12: 1147.9065 | AI12: 1173.4687 | AJ12: 1199.8917 | AK12: 1227.2124 | AL12: 1255.4694
A13: SEA | B13: 2.9870488 | C13: 2.5739841 | D13: 2.2066181 | E13: 1.8817105 | F13: 1.5959854 | H13: SEA | I13: r_sea | J13: 26.133491 | K13: 19.027453 | L13: 13.395783 | M13: 9.0857768 | N13: 5.9136254 | P13: SEA | Q13: r_sea | V13: 0.2426 | X13: SEA | Y13: r_sea | Z13: 1143.6131 | AA13: 1149.6615 | AB13: 1155.8696 | AC13: 1162.241 | AD13: 1168.7791 | AF13: SEA | AG13: r_sea | AH13: 1143.6131 | AI13: 1149.6615 | AJ13: 1155.8696 | AK13: 1162.241 | AL13: 1168.7791
A14: r_dev | B14: 0.19396868 | C14: 0.16222959 | D14: 0.13500924 | E14: 0.11178665 | F14: 0.092080432 | I14: r_dev | J14: 4.2342174 | K14: 3.8100482 | L14: 3.4193654 | M14: 3.0604921 | N14: 2.7317471 | Y14: r_dev | Z14: 1235.344 | AA14: 1232.4028 | AB14: 1229.5572 | AC14: 1226.808 | AD14: 1224.1558 | AG14: r_dev | AH14: 1235.344 | AI14: 1232.4028 | AJ14: 1229.5572 | AK14: 1226.808 | AL14: 1224.1558
A16: Population
A17: Coverage | B17: Region totals
A18: Units | B18: Billions of people
A19: Region | B19: 2021 | C19: 2022 | D19: 2023 | E19: 2024 | F19: 2025
A20: r_lac | B20: 0.62585913 | C20: 0.63200593 | D20: 0.63821309 | E20: 0.64448122 | F20: 0.65081092 | H20: LAC | P20: LAC | X20: LAC | AF20: LAC
A21: r_cwana | B21: 0.57952241 | C21: 0.5895646 | D21: 0.59978081 | E21: 0.61017405 | F21: 0.62074738 | H21: CWANA | P21: CWANA | X21: CWANA | AF21: CWANA
A22: r_wca | B22: 0.57430313 | C22: 0.59050323 | D22: 0.60716031 | E22: 0.62428725 | F22: 0.64189732 | H22: WCA | P22: WCA | X22: WCA | AF22: WCA
A23: r_esa | B23: 0.60676063 | C23: 0.6226242 | D23: 0.63890252 | E23: 0.65560643 | F23: 0.67274706 | H23: ESA | P23: ESA | X23: ESA | AF23: ESA
A24: r_sa | B24: 1.9019116 | C24: 1.9255219 | D24: 1.9494252 | E24: 1.9736253 | F24: 1.9981258 | H24: SA | P24: SA | X24: SA | AF24: SA
A25: r_sea | B25: 2.1236554 | C25: 2.1382815 | D25: 2.1530083 | E25: 2.1678365 | F25: 2.1827669 | H25: SEA | P25: SEA | X25: SEA | AF25: SEA
A26: r_dev | B26: 1.4526614 | C26: 1.4579604 | D26: 1.4632788 | E26: 1.4686166 | F26: 1.4739738
A28: Number of undernourished | I28: Number of poor | Q28: GII | Y28: GHG emssions | AG28: GHG emssions
F29: 2025 | N29: 2025 | V29: 2022 | AD29: 2025 | AL29: 2025
A30: LAC | F30: =F20*F8 -> 3.4657197 | H30: LAC | N30: =N8 -> 33.420694 | P30: LAC | V30: =V8 -> 0.3786 | X30: LAC | AD30: =AD8 -> 1078.9828 | AF30: LAC | AL30: =AL8 -> 1078.9828
A31: CWANA | F31: =F21*F9 -> 5.0657605 | H31: CWANA | N31: =N9 -> 23.854888 | P31: CWANA | V31: =V9 -> 0.4202 | X31: CWANA | AD31: =AD9 -> 291.05959 | AF31: CWANA | AL31: =AL9 -> 291.05959
A32: WCA | F32: =F22*F10 -> 10.839591 | H32: WCA | N32: =N10 -> 229.84725 | P32: WCA | V32: =V10 -> 0.6154 | X32: WCA | AD32: =AD10 -> 391.79377 | AF32: WCA | AL32: =AL10 -> 391.79377
A33: ESA | F33: =F23*F11 -> 12.422172 | H33: ESA | N33: =N11 -> 260.49982 | P33: ESA | V33: =V11 -> 0.51 | X33: ESA | AD33: =AD11 -> 593.49232 | AF33: ESA | AL33: =AL11 -> 593.49232
A34: SA | F34: =F24*F12 -> 18.903167 | H34: SA | N34: =N12 -> 152.04616 | P34: SA | V34: =V12 -> 0.4542 | X34: SA | AD34: =AD12 -> 1255.4694 | AF34: SA | AL34: =AL12 -> 1255.4694
A35: SEA | F35: =F25*F13 -> 3.483664 | H35: SEA | N35: =N13 -> 5.9136254 | P35: SEA | V35: =V13 -> 0.2426 | X35: SEA | AD35: =AD13 -> 1168.7791 | AF35: SEA | AL35: =AL13 -> 1168.7791
A37: Weights for Food Security scale of impact
F38: 2025 | N38: 2025 | V38: 2022 | AD38: 2025 | AL38: 2025
A39: LAC | F39: =F30/SUM($F$30:$F$35) -> 0.063966684 | H39: LAC | N39: =N30/SUM($N$30:$N$35) -> 0.047366108 | P39: LAC | V39: =V30/SUM($V$30:$V$35) -> 0.14444868 | X39: LAC | AD39: =AD30/SUM($AD$30:$AD$35) -> 0.2257486 | AF39: LAC | AL39: =AL30/SUM($AL$30:$AL$35) -> 0.2257486
A40: CWANA | F40: =F31/SUM($F$30:$F$35) -> 0.093498589 | H40: CWANA | N40: =N31/SUM($N$30:$N$35) -> 0.033808789 | P40: CWANA | V40: =V31/SUM($V$30:$V$35) -> 0.16032049 | X40: CWANA | AD40: =AD31/SUM($AD$30:$AD$35) -> 0.060896518 | AF40: CWANA | AL40: =AL31/SUM($AL$30:$AL$35) -> 0.060896518
A41: WCA | F41: =F32/SUM($F$30:$F$35) -> 0.20006601 | H41: WCA | N41: =N32/SUM($N$30:$N$35) -> 0.32575534 | P41: WCA | V41: =V32/SUM($V$30:$V$35) -> 0.23479588 | X41: WCA | AD41: =AD32/SUM($AD$30:$AD$35) -> 0.081972479 | AF41: WCA | AL41: =AL32/SUM($AL$30:$AL$35) -> 0.081972479
A42: ESA | F42: =F33/SUM($F$30:$F$35) -> 0.22927565 | H42: ESA | N42: =N33/SUM($N$30:$N$35) -> 0.36919828 | P42: ESA | V42: =V33/SUM($V$30:$V$35) -> 0.19458222 | X42: ESA | AD42: =AD33/SUM($AD$30:$AD$35) -> 0.12417256 | AF42: ESA | AL42: =AL33/SUM($AL$30:$AL$35) -> 0.12417256
A43: SA | F43: =F34/SUM($F$30:$F$35) -> 0.34889519 | H43: SA | N43: =N34/SUM($N$30:$N$35) -> 0.21549028 | P43: SA | V43: =V34/SUM($V$30:$V$35) -> 0.17329264 | X43: SA | AD43: =AD34/SUM($AD$30:$AD$35) -> 0.26267375 | AF43: SA | AL43: =AL34/SUM($AL$30:$AL$35) -> 0.26267375
A44: SEA | F44: =F35/SUM($F$30:$F$35) -> 0.064297882 | H44: SEA | N44: =N35/SUM($N$30:$N$35) -> 0.0083811972 | P44: SEA | V44: =V35/SUM($V$30:$V$35) -> 0.092560092 | X44: SEA | AD44: =AD35/SUM($AD$30:$AD$35) -> 0.24453609 | AF44: SEA | AL44: =AL35/SUM($AL$30:$AL$35) -> 0.24453609
A46: Transposed weights
A47: Food Security | I47: Poverty reduction | Q47: Social Inclusion | Y47: Climate Adaptation | AG47: Environmental health
B49: LAC | C49: CWANA | D49: WCA | E49: ESA | F49: SA | G49: SEA | J49: LAC | K49: CWANA | L49: WCA | M49: ESA | N49: SA | O49: SEA | R49: LAC | S49: CWANA | T49: WCA | U49: ESA | V49: SA | W49: SEA | Z49: LAC | AA49: CWANA | AB49: WCA | AC49: ESA | AD49: SA | AE49: SEA | AH49: LAC | AI49: CWANA | AJ49: WCA | AK49: ESA | AL49: SA | AM49: SEA
B50: =F39 -> 0.063966684 | C50: =F40 -> 0.093498589 | D50: =F41 -> 0.20006601 | E50: =F42 -> 0.22927565 | F50: =F43 -> 0.34889519 | G50: =F44 -> 0.064297882 | J50: =N39 -> 0.047366108 | K50: =N40 -> 0.033808789 | L50: =N41 -> 0.32575534 | M50: =N42 -> 0.36919828 | N50: =N43 -> 0.21549028 | O50: =N44 -> 0.0083811972 | R50: =V39 -> 0.14444868 | S50: =V40 -> 0.16032049 | T50: =V41 -> 0.23479588 | U50: =V42 -> 0.19458222 | V50: =V43 -> 0.17329264 | W50: =V44 -> 0.092560092 | Z50: =AD39 -> 0.2257486 | AA50: =AD40 -> 0.060896518 | AB50: =AD41 -> 0.081972479 | AC50: =AD42 -> 0.12417256 | AD50: =AD43 -> 0.26267375 | AE50: =AD44 -> 0.24453609 | AH50: =AL39 -> 0.2257486 | AI50: =AL40 -> 0.060896518 | AJ50: =AL41 -> 0.081972479 | AK50: =AL42 -> 0.12417256 | AL50: =AL43 -> 0.26267375 | AM50: =AL44 -> 0.24453609

Sheet Step C weights
A4: Index components
C5: low better | D5: high better | E5: high better | F5: high better | G5: low better
B6: Region | C6: conflixt_index | D6: CPI | E6: EoDB | F6: EMPINX | G6: FSI
A7: LAC | B7: Latin America and the Caribbean | C7: 0.54302381 | D7: 34.420755 | E7: 62.024684 | F7: 10.480365 | G7: 70.558656 | H7: LAC
A8: CWANA | B8: Central and West Asia and North Africa | C8: 0.12588317 | D8: 31.026147 | E8: 59.673664 | F8: 3.0737838 | G8: 81.957032 | H8: CWANA
A9: WCA | B9: West and Central Africa | C9: 0.32215883 | D9: 28.548207 | E9: 51.795414 | F9: 5.433525 | G9: 94.133003 | H9: WCA
A10: ESA | B10: East and Southern Africa | C10: 0.11785058 | D10: 32.889928 | E10: 54.702176 | F10: 5.9487617 | G10: 88.468946 | H10: ESA
A11: SA | B11: South Asia | C11: 0.40586822 | D11: 36.281216 | E11: 67.183583 | F11: 6.4953468 | G11: 77.355629 | H11: SA
A12: SEA | B12: South East Asia and the Pacific | C12: 0.069992243 | D12: 42.533784 | E12: 74.722296 | F12: 2.6347802 | G12: 63.410873 | H12: SEA
B13: Europe | C13: 0.10802819 | D13: 55.44159 | E13: 77.120726 | F13: 9.1956478 | G13: 49.207111
B14: North America | C14: 0.019863877 | D14: 69.711937 | E14: 83.553626 | F14: 11.101705 | G14: 42.61498
B18: Region | C18: high better | D18: high better | E18: high better | F18: high better | G18: high better
A19: LAC | B19: Latin America and the Caribbean | C19: =1-(C7-0) -> 0.45697619 | D19: =D7/100 -> 0.34420755 | E19: =E7/100 -> 0.62024684 | F19: =(F7/14) -> 0.74859748 | G19: =1-(G7/100) -> 0.29441344 | H19: LAC
A20: CWANA | B20: Central and West Asia and North Africa | C20: =1-(C8-0) -> 0.87411683 | D20: =D8/100 -> 0.31026147 | E20: =E8/100 -> 0.59673664 | F20: =(F8/14) -> 0.21955598 | G20: =1-(G8/100) -> 0.18042968 | H20: CWANA
A21: WCA | B21: West and Central Africa | C21: =1-(C9-0) -> 0.67784117 | D21: =D9/100 -> 0.28548207 | E21: =E9/100 -> 0.51795414 | F21: =(F9/14) -> 0.38810893 | G21: =1-(G9/100) -> 0.058669971 | H21: WCA
A22: ESA | B22: East and Southern Africa | C22: =1-(C10-0) -> 0.88214942 | D22: =D10/100 -> 0.32889928 | E22: =E10/100 -> 0.54702176 | F22: =(F10/14) -> 0.42491155 | G22: =1-(G10/100) -> 0.11531054 | H22: ESA
A23: SA | B23: South Asia | C23: =1-(C11-0) -> 0.59413178 | D23: =D11/100 -> 0.36281216 | E23: =E11/100 -> 0.67183583 | F23: =(F11/14) -> 0.46395334 | G23: =1-(G11/100) -> 0.22644371 | H23: SA
A24: SEA | B24: South East Asia and the Pacific | C24: =1-(C12-0) -> 0.93000776 | D24: =D12/100 -> 0.42533784 | E24: =E12/100 -> 0.74722296 | F24: =(F12/14) -> 0.18819859 | G24: =1-(G12/100) -> 0.36589127 | H24: SEA
A27: Enabling environment weights
C28: Aggregate (equal weighting of component indices)
A29: LAC | C29: =AVERAGE(C19:G19) -> 0.4928883 | H29: LAC
A30: CWANA | C30: =AVERAGE(C20:G20) -> 0.43622012 | H30: CWANA
A31: WCA | C31: =AVERAGE(C21:G21) -> 0.38561126 | H31: WCA
A32: ESA | C32: =AVERAGE(C22:G22) -> 0.45965851 | H32: ESA
A33: SA | C33: =AVERAGE(C23:G23) -> 0.46383536 | H33: SA
A34: SEA | C34: =AVERAGE(C24:G24) -> 0.53133168 | H34: SEA
A37: Transposed weights
B39: LAC | C39: CWANA | D39: WCA | E39: ESA | F39: SA | G39: SEA
B40: =C29 -> 0.4928883 | C40: =C30 -> 0.43622012 | D40: =C31 -> 0.38561126 | E40: =C32 -> 0.45965851 | F40: =C33 -> 0.46383536 | G40: =C34 -> 0.53133168

Sheet Step C - Weight by Enable Env
A1: Enabling Environment - This tab automatically populates your scores from your Step B tab (that is, the Impact Area tabs*Potential Scale for Impact). It automatically weights your Step B scores by the regional Enabling Environment - You do not have to do anything in this tab, the excel formulas do the weighting for you. THESE ARE YOUR FINAL SCORES
A2: VH
A3: H
A4: MH
A5: M
A6: L
A7: Food Security | I7: Poverty reduction | Q7: Social Inclusion | Y7: Climate Adaptation | AG7: Environmental health
A8: HLO | B8: LAC | C8: CWANA | D8: WCA | E8: ESA | F8: SA | G8: SEA | I8: HLO | J8: LAC | K8: CWANA | L8: WCA | M8: ESA | N8: SA | O8: SEA | Q8: HLO | R8: LAC | S8: CWANA | T8: WCA | U8: ESA | V8: SA | W8: SEA | Y8: HLO | Z8: LAC | AA8: CWANA | AB8: WCA | AC8: ESA | AD8: SA | AE8: SEA | AG8: HLO | AH8: LAC | AI8: CWANA | AJ8: WCA | AK8: ESA | AL8: SA | AM8: SEA
A9: =IF(NOT(ISBLANK(HLOs!D8)),HLOs!D8,"") -> HLO 1.1: Quantified climate change-related hazards that affect the delivery of agronomic gain | B9: ='Step B - Weight by Scl Impact'!B10*'Step C weights'!B$40 -> 0.12611372 | C9: ='Step B - Weight by Scl Impact'!C10*'Step C weights'!C$40 -> 0.16314386 | D9: ='Step B - Weight by Scl Impact'!D10*'Step C weights'!D$40 -> 0.23144312 | E9: ='Step B - Weight by Scl Impact'!E10*'Step C weights'!E$40 -> 0.31616551 | F9: ='Step B - Weight by Scl Impact'!F10*'Step C weights'!F$40 -> 0.64731971 | G9: ='Step B - Weight by Scl Impact'!G10*'Step C weights'!G$40 -> 0.13665401 | I9: =A9 -> HLO 1.1: Quantified climate change-related hazards that affect the delivery of agronomic gain | J9: ='Step B - Weight by Scl Impact'!J10*'Step C weights'!B$40 -> 0.093384803 | K9: ='Step B - Weight by Scl Impact'!K10*'Step C weights'!C$40 -> 0.058992296 | L9: ='Step B - Weight by Scl Impact'!L10*'Step C weights'!D$40 -> 0.37684478 | M9: ='Step B - Weight by Scl Impact'!M10*'Step C weights'!E$40 -> 0.50911539 | N9: ='Step B - Weight by Scl Impact'!N10*'Step C weights'!F$40 -> 0.39980805 | O9: ='Step B - Weight by Scl Impact'!O10*'Step C weights'!G$40 -> 0.017812782 | Q9: =I9 -> HLO 1.1: Quantified climate change-related hazards that affect the delivery of agronomic gain | R9: ='Step B - Weight by Scl Impact'!R10*'Step C weights'!B$40 -> 0.28478827 | S9: ='Step B - Weight by Scl Impact'!S10*'Step C weights'!C$40 -> 0.27974009 | T9: ='Step B - Weight by Scl Impact'!T10*'Step C weights'!D$40 -> 0.36215974 | U9: ='Step B - Weight by Scl Impact'!U10*'Step C weights'!E$40 -> 0.35776549 | V9: ='Step B - Weight by Scl Impact'!V10*'Step C weights'!F$40 -> 0.24113776 | W9: ='Step B - Weight by Scl Impact'!W10*'Step C weights'!G$40 -> 0.19672044 | Y9: =A9 -> HLO 1.1: Quantified climate change-related hazards that affect the delivery of agronomic gain | Z9: ='Step B - Weight by Scl Impact'!Z10*'Step C weights'!B$40 -> 0.44507537 | AA9: ='Step B - Weight by Scl Impact'!AA10*'Step C weights'!C$40 -> 0.13282143 | AB9: ='Step B - Weight by Scl Impact'!AB10*'Step C weights'!D$40 -> 0.094828532 | AC9: ='Step B - Weight by Scl Impact'!AC10*'Step C weights'!E$40 -> 0.28538488 | AD9: ='Step B - Weight by Scl Impact'!AD10*'Step C weights'!F$40 -> 0.60918688 | AE9: ='Step B - Weight by Scl Impact'!AE10*'Step C weights'!G$40 -> 0.64964886 | AG9: =A9 -> HLO 1.1: Quantified climate change-related hazards that affect the delivery of agronomic gain | AH9: ='Step B - Weight by Scl Impact'!AH10*'Step C weights'!B$40 -> 0.44507537 | AI9: ='Step B - Weight by Scl Impact'!AI10*'Step C weights'!C$40 -> 0.10625714 | AJ9: ='Step B - Weight by Scl Impact'!AJ10*'Step C weights'!D$40 -> 0.12643804 | AK9: ='Step B - Weight by Scl Impact'!AK10*'Step C weights'!E$40 -> 0.17123093 | AL9: ='Step B - Weight by Scl Impact'!AL10*'Step C weights'!F$40 -> 0.4873495 | AM9: ='Step B - Weight by Scl Impact'!AM10*'Step C weights'!G$40 -> 0.25985954
A10: =IF(NOT(ISBLANK(HLOs!D9)),HLOs!D9,"") -> HLO 1.2: Climate hazard-specific inclusive sustainable farming system innovations | B10: ='Step B - Weight by Scl Impact'!B11*'Step C weights'!B$40 -> 0.12611372 | C10: ='Step B - Weight by Scl Impact'!C11*'Step C weights'!C$40 -> 0.16314386 | D10: ='Step B - Weight by Scl Impact'!D11*'Step C weights'!D$40 -> 0.23144312 | E10: ='Step B - Weight by Scl Impact'!E11*'Step C weights'!E$40 -> 0.31616551 | F10: ='Step B - Weight by Scl Impact'!F11*'Step C weights'!F$40 -> 0.64731971 | G10: ='Step B - Weight by Scl Impact'!G11*'Step C weights'!G$40 -> 0.13665401 | I10: =A10 -> HLO 1.2: Climate hazard-specific inclusive sustainable farming system innovations | J10: ='Step B - Weight by Scl Impact'!J11*'Step C weights'!B$40 -> 0.093384803 | K10: ='Step B - Weight by Scl Impact'!K11*'Step C weights'!C$40 -> 0.058992296 | L10: ='Step B - Weight by Scl Impact'!L11*'Step C weights'!D$40 -> 0.37684478 | M10: ='Step B - Weight by Scl Impact'!M11*'Step C weights'!E$40 -> 0.50911539 | N10: ='Step B - Weight by Scl Impact'!N11*'Step C weights'!F$40 -> 0.39980805 | O10: ='Step B - Weight by Scl Impact'!O11*'Step C weights'!G$40 -> 0.022265978 | Q10: =I10 -> HLO 1.2: Climate hazard-specific inclusive sustainable farming system innovations | R10: ='Step B - Weight by Scl Impact'!R11*'Step C weights'!B$40 -> 0.28478827 | S10: ='Step B - Weight by Scl Impact'!S11*'Step C weights'!C$40 -> 0.27974009 | T10: ='Step B - Weight by Scl Impact'!T11*'Step C weights'!D$40 -> 0.36215974 | U10: ='Step B - Weight by Scl Impact'!U11*'Step C weights'!E$40 -> 0.35776549 | V10: ='Step B - Weight by Scl Impact'!V11*'Step C weights'!F$40 -> 0.24113776 | W10: ='Step B - Weight by Scl Impact'!W11*'Step C weights'!G$40 -> 0.19672044 | Y10: =Q10 -> HLO 1.2: Climate hazard-specific inclusive sustainable farming system innovations | Z10: ='Step B - Weight by Scl Impact'!Z11*'Step C weights'!B$40 -> 0.55634422 | AA10: ='Step B - Weight by Scl Impact'!AA11*'Step C weights'!C$40 -> 0.13282143 | AB10: ='Step B - Weight by Scl Impact'!AB11*'Step C weights'!D$40 -> 0.094828532 | AC10: ='Step B - Weight by Scl Impact'!AC11*'Step C weights'!E$40 -> 0.28538488 | AD10: ='Step B - Weight by Scl Impact'!AD11*'Step C weights'!F$40 -> 0.60918688 | AE10: ='Step B - Weight by Scl Impact'!AE11*'Step C weights'!G$40 -> 0.51971909 | AG10: =A10 -> HLO 1.2: Climate hazard-specific inclusive sustainable farming system innovations | AH10: ='Step B - Weight by Scl Impact'!AH11*'Step C weights'!B$40 -> 0.44507537 | AI10: ='Step B - Weight by Scl Impact'!AI11*'Step C weights'!C$40 -> 0.10625714 | AJ10: ='Step B - Weight by Scl Impact'!AJ11*'Step C weights'!D$40 -> 0.12643804 | AK10: ='Step B - Weight by Scl Impact'!AK11*'Step C weights'!E$40 -> 0.17123093 | AL10: ='Step B - Weight by Scl Impact'!AL11*'Step C weights'!F$40 -> 0.4873495 | AM10: ='Step B - Weight by Scl Impact'!AM11*'Step C weights'!G$40 -> 0.25985954
A11: =IF(NOT(ISBLANK(HLOs!D10)),HLOs!D10,"") -> HLO 1.3: Training materials for climate adaptation and mitigation | B11: ='Step B - Weight by Scl Impact'!B12*'Step C weights'!B$40 -> 0.12611372 | C11: ='Step B - Weight by Scl Impact'!C12*'Step C weights'!C$40 -> 0.081571931 | D11: ='Step B - Weight by Scl Impact'!D12*'Step C weights'!D$40 -> 0.23144312 | E11: ='Step B - Weight by Scl Impact'!E12*'Step C weights'!E$40 -> 0.31616551 | F11: ='Step B - Weight by Scl Impact'!F12*'Step C weights'!F$40 -> 0.64731971 | G11: ='Step B - Weight by Scl Impact'!G12*'Step C weights'!G$40 -> 0.13665401 | I11: =A11 -> HLO 1.3: Training materials for climate adaptation and mitigation | J11: ='Step B - Weight by Scl Impact'!J12*'Step C weights'!B$40 -> 0.093384803 | K11: ='Step B - Weight by Scl Impact'!K12*'Step C weights'!C$40 -> 0.058992296 | L11: ='Step B - Weight by Scl Impact'!L12*'Step C weights'!D$40 -> 0.37684478 | M11: ='Step B - Weight by Scl Impact'!M12*'Step C weights'!E$40 -> 0.50911539 | N11: ='Step B - Weight by Scl Impact'!N12*'Step C weights'!F$40 -> 0.39980805 | O11: ='Step B - Weight by Scl Impact'!O12*'Step C weights'!G$40 -> 0.017812782 | Q11: =I11 -> HLO 1.3: Training materials for climate adaptation and mitigation | R11: ='Step B - Weight by Scl Impact'!R12*'Step C weights'!B$40 -> 0.28478827 | S11: ='Step B - Weight by Scl Impact'!S12*'Step C weights'!C$40 -> 0.27974009 | T11: ='Step B - Weight by Scl Impact'!T12*'Step C weights'!D$40 -> 0.36215974 | U11: ='Step B - Weight by Scl Impact'!U12*'Step C weights'!E$40 -> 0.35776549 | V11: ='Step B - Weight by Scl Impact'!V12*'Step C weights'!F$40 -> 0.24113776 | W11: ='Step B - Weight by Scl Impact'!W12*'Step C weights'!G$40 -> 0.19672044 | Y11: =Q11 -> HLO 1.3: Training materials for climate adaptation and mitigation | Z11: ='Step B - Weight by Scl Impact'!Z12*'Step C weights'!B$40 -> 0.44507537 | AA11: ='Step B - Weight by Scl Impact'!AA12*'Step C weights'!C$40 -> 0.13282143 | AB11: ='Step B - Weight by Scl Impact'!AB12*'Step C weights'!D$40 -> 0.094828532 | AC11: ='Step B - Weight by Scl Impact'!AC12*'Step C weights'!E$40 -> 0.17123093 | AD11: ='Step B - Weight by Scl Impact'!AD12*'Step C weights'!F$40 -> 0.60918688 | AE11: ='Step B - Weight by Scl Impact'!AE12*'Step C weights'!G$40 -> 0.64964886 | AG11: =A11 -> HLO 1.3: Training materials for climate adaptation and mitigation | AH11: ='Step B - Weight by Scl Impact'!AH12*'Step C weights'!B$40 -> 0.44507537 | AI11: ='Step B - Weight by Scl Impact'!AI12*'Step C weights'!C$40 -> 0.10625714 | AJ11: ='Step B - Weight by Scl Impact'!AJ12*'Step C weights'!D$40 -> 0.12643804 | AK11: ='Step B - Weight by Scl Impact'!AK12*'Step C weights'!E$40 -> 0.17123093 | AL11: ='Step B - Weight by Scl Impact'!AL12*'Step C weights'!F$40 -> 0.4873495 | AM11: ='Step B - Weight by Scl Impact'!AM12*'Step C weights'!G$40 -> 0.25985954
A12: =IF(NOT(ISBLANK(HLOs!D11)),HLOs!D11,"") -> HLO 1.4: Policy and investment-ready information on sustainable farming solutions | B12: ='Step B - Weight by Scl Impact'!B13*'Step C weights'!B$40 -> 0.12611372 | C12: ='Step B - Weight by Scl Impact'!C13*'Step C weights'!C$40 -> 0.16314386 | D12: ='Step B - Weight by Scl Impact'!D13*'Step C weights'!D$40 -> 0.23144312 | E12: ='Step B - Weight by Scl Impact'!E13*'Step C weights'!E$40 -> 0.21077701 | F12: ='Step B - Weight by Scl Impact'!F13*'Step C weights'!F$40 -> 0.64731971 | G12: ='Step B - Weight by Scl Impact'!G13*'Step C weights'!G$40 -> 0.13665401 | I12: =A12 -> HLO 1.4: Policy and investment-ready information on sustainable farming solutions | J12: ='Step B - Weight by Scl Impact'!J13*'Step C weights'!B$40 -> 0.093384803 | K12: ='Step B - Weight by Scl Impact'!K13*'Step C weights'!C$40 -> 0.058992296 | L12: ='Step B - Weight by Scl Impact'!L13*'Step C weights'!D$40 -> 0.37684478 | M12: ='Step B - Weight by Scl Impact'!M13*'Step C weights'!E$40 -> 0.50911539 | N12: ='Step B - Weight by Scl Impact'!N13*'Step C weights'!F$40 -> 0.39980805 | O12: ='Step B - Weight by Scl Impact'!O13*'Step C weights'!G$40 -> 0.017812782 | Q12: =I12 -> HLO 1.4: Policy and investment-ready information on sustainable farming solutions | R12: ='Step B - Weight by Scl Impact'!R13*'Step C weights'!B$40 -> 0.28478827 | S12: ='Step B - Weight by Scl Impact'!S13*'Step C weights'!C$40 -> 0.27974009 | T12: ='Step B - Weight by Scl Impact'!T13*'Step C weights'!D$40 -> 0.36215974 | U12: ='Step B - Weight by Scl Impact'!U13*'Step C weights'!E$40 -> 0.35776549 | V12: ='Step B - Weight by Scl Impact'!V13*'Step C weights'!F$40 -> 0.24113776 | W12: ='Step B - Weight by Scl Impact'!W13*'Step C weights'!G$40 -> 0.19672044 | Y12: =Q12 -> HLO 1.4: Policy and investment-ready information on sustainable farming solutions | Z12: ='Step B - Weight by Scl Impact'!Z13*'Step C weights'!B$40 -> 0.55634422 | AA12: ='Step B - Weight by Scl Impact'!AA13*'Step C weights'!C$40 -> 0.10625714 | AB12: ='Step B - Weight by Scl Impact'!AB13*'Step C weights'!D$40 -> 0.094828532 | AC12: ='Step B - Weight by Scl Impact'!AC13*'Step C weights'!E$40 -> 0.17123093 | AD12: ='Step B - Weight by Scl Impact'!AD13*'Step C weights'!F$40 -> 0.60918688 | AE12: ='Step B - Weight by Scl Impact'!AE13*'Step C weights'!G$40 -> 0.64964886 | AG12: =A12 -> HLO 1.4: Policy and investment-ready information on sustainable farming solutions | AH12: ='Step B - Weight by Scl Impact'!AH13*'Step C weights'!B$40 -> 0.44507537 | AI12: ='Step B - Weight by Scl Impact'!AI13*'Step C weights'!C$40 -> 0.10625714 | AJ12: ='Step B - Weight by Scl Impact'!AJ13*'Step C weights'!D$40 -> 0.094828532 | AK12: ='Step B - Weight by Scl Impact'!AK13*'Step C weights'!E$40 -> 0.17123093 | AL12: ='Step B - Weight by Scl Impact'!AL13*'Step C weights'!F$40 -> 0.4873495 | AM12: ='Step B - Weight by Scl Impact'!AM13*'Step C weights'!G$40 -> 0.25985954
A13: =IF(NOT(ISBLANK(HLOs!D12)),HLOs!D12,"") -> HLO 2.1: Spatially-explicit recommendation decision support models for soil nutrient constraints | B13: ='Step B - Weight by Scl Impact'!B14*'Step C weights'!B$40 -> 0.15764215 | C13: ='Step B - Weight by Scl Impact'!C14*'Step C weights'!C$40 -> 0.20392983 | D13: ='Step B - Weight by Scl Impact'!D14*'Step C weights'!D$40 -> 0.23144312 | E13: ='Step B - Weight by Scl Impact'!E14*'Step C weights'!E$40 -> 0.52694251 | F13: ='Step B - Weight by Scl Impact'!F14*'Step C weights'!F$40 -> 0.80914963 | G13: ='Step B - Weight by Scl Impact'!G14*'Step C weights'!G$40 -> 0.17081751 | I13: =A13 -> HLO 2.1: Spatially-explicit recommendation decision support models for soil nutrient constraints | J13: ='Step B - Weight by Scl Impact'!J14*'Step C weights'!B$40 -> 0.116731 | K13: ='Step B - Weight by Scl Impact'!K14*'Step C weights'!C$40 -> 0.07374037 | L13: ='Step B - Weight by Scl Impact'!L14*'Step C weights'!D$40 -> 0.62807464 | M13: ='Step B - Weight by Scl Impact'!M14*'Step C weights'!E$40 -> 0.50911539 | N13: ='Step B - Weight by Scl Impact'!N14*'Step C weights'!F$40 -> 0.49976007 | O13: ='Step B - Weight by Scl Impact'!O14*'Step C weights'!G$40 -> 0.022265978 | Q13: =I13 -> HLO 2.1: Spatially-explicit recommendation decision support models for soil nutrient constraints | R13: ='Step B - Weight by Scl Impact'!R14*'Step C weights'!B$40 -> 0.35598533 | S13: ='Step B - Weight by Scl Impact'!S14*'Step C weights'!C$40 -> 0.20980507 | T13: ='Step B - Weight by Scl Impact'!T14*'Step C weights'!D$40 -> 0.36215974 | U13: ='Step B - Weight by Scl Impact'!U14*'Step C weights'!E$40 -> 0.44720687 | V13: ='Step B - Weight by Scl Impact'!V14*'Step C weights'!F$40 -> 0.40189627 | W13: ='Step B - Weight by Scl Impact'!W14*'Step C weights'!G$40 -> 0.24590055 | Y13: =Q13 -> HLO 2.1: Spatially-explicit recommendation decision support models for soil nutrient constraints | Z13: ='Step B - Weight by Scl Impact'!Z14*'Step C weights'!B$40 -> 0.55634422 | AA13: ='Step B - Weight by Scl Impact'!AA14*'Step C weights'!C$40 -> 0.13282143 | AB13: ='Step B - Weight by Scl Impact'!AB14*'Step C weights'!D$40 -> 0.094828532 | AC13: ='Step B - Weight by Scl Impact'!AC14*'Step C weights'!E$40 -> 0.17123093 | AD13: ='Step B - Weight by Scl Impact'!AD14*'Step C weights'!F$40 -> 0.60918688 | AE13: ='Step B - Weight by Scl Impact'!AE14*'Step C weights'!G$40 -> 0.64964886 | AG13: =A13 -> HLO 2.1: Spatially-explicit recommendation decision support models for soil nutrient constraints | AH13: ='Step B - Weight by Scl Impact'!AH14*'Step C weights'!B$40 -> 0.55634422 | AI13: ='Step B - Weight by Scl Impact'!AI14*'Step C weights'!C$40 -> 0.13282143 | AJ13: ='Step B - Weight by Scl Impact'!AJ14*'Step C weights'!D$40 -> 0.15804755 | AK13: ='Step B - Weight by Scl Impact'!AK14*'Step C weights'!E$40 -> 0.28538488 | AL13: ='Step B - Weight by Scl Impact'!AL14*'Step C weights'!F$40 -> 0.60918688 | AM13: ='Step B - Weight by Scl Impact'!AM14*'Step C weights'!G$40 -> 0.64964886
A14: =IF(NOT(ISBLANK(HLOs!D13)),HLOs!D13,"") -> HLO 2.2: Expanded data-driven agronomic recommendations for site-specific nutrient management | B14: ='Step B - Weight by Scl Impact'!B15*'Step C weights'!B$40 -> 0.15764215 | C14: ='Step B - Weight by Scl Impact'!C15*'Step C weights'!C$40 -> 0.16314386 | D14: ='Step B - Weight by Scl Impact'!D15*'Step C weights'!D$40 -> 0.23144312 | E14: ='Step B - Weight by Scl Impact'!E15*'Step C weights'!E$40 -> 0.52694251 | F14: ='Step B - Weight by Scl Impact'!F15*'Step C weights'!F$40 -> 0.80914963 | G14: ='Step B - Weight by Scl Impact'!G15*'Step C weights'!G$40 -> 0.13665401 | I14: =A14 -> HLO 2.2: Expanded data-driven agronomic recommendations for site-specific nutrient management | J14: ='Step B - Weight by Scl Impact'!J15*'Step C weights'!B$40 -> 0.116731 | K14: ='Step B - Weight by Scl Impact'!K15*'Step C weights'!C$40 -> 0.058992296 | L14: ='Step B - Weight by Scl Impact'!L15*'Step C weights'!D$40 -> 0.37684478 | M14: ='Step B - Weight by Scl Impact'!M15*'Step C weights'!E$40 -> 0.50911539 | N14: ='Step B - Weight by Scl Impact'!N15*'Step C weights'!F$40 -> 0.49976007 | O14: ='Step B - Weight by Scl Impact'!O15*'Step C weights'!G$40 -> 0.0089063912 | Q14: =I14 -> HLO 2.2: Expanded data-driven agronomic recommendations for site-specific nutrient management | R14: ='Step B - Weight by Scl Impact'!R15*'Step C weights'!B$40 -> 0.35598533 | S14: ='Step B - Weight by Scl Impact'!S15*'Step C weights'!C$40 -> 0.13987004 | T14: ='Step B - Weight by Scl Impact'!T15*'Step C weights'!D$40 -> 0.2716198 | U14: ='Step B - Weight by Scl Impact'!U15*'Step C weights'!E$40 -> 0.26832412 | V14: ='Step B - Weight by Scl Impact'!V15*'Step C weights'!F$40 -> 0.24113776 | W14: ='Step B - Weight by Scl Impact'!W15*'Step C weights'!G$40 -> 0.24590055 | Y14: =Q14 -> HLO 2.2: Expanded data-driven agronomic recommendations for site-specific nutrient management | Z14: ='Step B - Weight by Scl Impact'!Z15*'Step C weights'!B$40 -> 0.44507537 | AA14: ='Step B - Weight by Scl Impact'!AA15*'Step C weights'!C$40 -> 0.053128572 | AB14: ='Step B - Weight by Scl Impact'!AB15*'Step C weights'!D$40 -> 0.094828532 | AC14: ='Step B - Weight by Scl Impact'!AC15*'Step C weights'!E$40 -> 0.11415395 | AD14: ='Step B - Weight by Scl Impact'!AD15*'Step C weights'!F$40 -> 0.60918688 | AE14: ='Step B - Weight by Scl Impact'!AE15*'Step C weights'!G$40 -> 0.51971909 | AG14: =A14 -> HLO 2.2: Expanded data-driven agronomic recommendations for site-specific nutrient management | AH14: ='Step B - Weight by Scl Impact'!AH15*'Step C weights'!B$40 -> 0.55634422 | AI14: ='Step B - Weight by Scl Impact'!AI15*'Step C weights'!C$40 -> 0.13282143 | AJ14: ='Step B - Weight by Scl Impact'!AJ15*'Step C weights'!D$40 -> 0.094828532 | AK14: ='Step B - Weight by Scl Impact'!AK15*'Step C weights'!E$40 -> 0.17123093 | AL14: ='Step B - Weight by Scl Impact'!AL15*'Step C weights'!F$40 -> 0.60918688 | AM14: ='Step B - Weight by Scl Impact'!AM15*'Step C weights'!G$40 -> 0.25985954
A15: =IF(NOT(ISBLANK(HLOs!D14)),HLOs!D14,"") -> HLO 2.3: Training materials for site-specific nutrient management | B15: ='Step B - Weight by Scl Impact'!B16*'Step C weights'!B$40 -> 0.15764215 | C15: ='Step B - Weight by Scl Impact'!C16*'Step C weights'!C$40 -> 0.081571931 | D15: ='Step B - Weight by Scl Impact'!D16*'Step C weights'!D$40 -> 0.23144312 | E15: ='Step B - Weight by Scl Impact'!E16*'Step C weights'!E$40 -> 0.31616551 | F15: ='Step B - Weight by Scl Impact'!F16*'Step C weights'!F$40 -> 0.80914963 | G15: ='Step B - Weight by Scl Impact'!G16*'Step C weights'!G$40 -> 0.13665401 | I15: =A15 -> HLO 2.3: Training materials for site-specific nutrient management | J15: ='Step B - Weight by Scl Impact'!J16*'Step C weights'!B$40 -> 0.116731 | K15: ='Step B - Weight by Scl Impact'!K16*'Step C weights'!C$40 -> 0.07374037 | L15: ='Step B - Weight by Scl Impact'!L16*'Step C weights'!D$40 -> 0.37684478 | M15: ='Step B - Weight by Scl Impact'!M16*'Step C weights'!E$40 -> 0.50911539 | N15: ='Step B - Weight by Scl Impact'!N16*'Step C weights'!F$40 -> 0.49976007 | O15: ='Step B - Weight by Scl Impact'!O16*'Step C weights'!G$40 -> 0.017812782 | Q15: =I15 -> HLO 2.3: Training materials for site-specific nutrient management | R15: ='Step B - Weight by Scl Impact'!R16*'Step C weights'!B$40 -> 0.35598533 | S15: ='Step B - Weight by Scl Impact'!S16*'Step C weights'!C$40 -> 0.13987004 | T15: ='Step B - Weight by Scl Impact'!T16*'Step C weights'!D$40 -> 0.2716198 | U15: ='Step B - Weight by Scl Impact'!U16*'Step C weights'!E$40 -> 0.26832412 | V15: ='Step B - Weight by Scl Impact'!V16*'Step C weights'!F$40 -> 0.16075851 | W15: ='Step B - Weight by Scl Impact'!W16*'Step C weights'!G$40 -> 0.24590055 | Y15: =Q15 -> HLO 2.3: Training materials for site-specific nutrient management | Z15: ='Step B - Weight by Scl Impact'!Z16*'Step C weights'!B$40 -> 0.55634422 | AA15: ='Step B - Weight by Scl Impact'!AA16*'Step C weights'!C$40 -> 0.053128572 | AB15: ='Step B - Weight by Scl Impact'!AB16*'Step C weights'!D$40 -> 0.063219022 | AC15: ='Step B - Weight by Scl Impact'!AC16*'Step C weights'!E$40 -> 0.17123093 | AD15: ='Step B - Weight by Scl Impact'!AD16*'Step C weights'!F$40 -> 0.60918688 | AE15: ='Step B - Weight by Scl Impact'!AE16*'Step C weights'!G$40 -> 0.25985954 | AG15: =A15 -> HLO 2.3: Training materials for site-specific nutrient management | AH15: ='Step B - Weight by Scl Impact'!AH16*'Step C weights'!B$40 -> 0.55634422 | AI15: ='Step B - Weight by Scl Impact'!AI16*'Step C weights'!C$40 -> 0.13282143 | AJ15: ='Step B - Weight by Scl Impact'!AJ16*'Step C weights'!D$40 -> 0.094828532 | AK15: ='Step B - Weight by Scl Impact'!AK16*'Step C weights'!E$40 -> 0.11415395 | AL15: ='Step B - Weight by Scl Impact'!AL16*'Step C weights'!F$40 -> 0.24367475 | AM15: ='Step B - Weight by Scl Impact'!AM16*'Step C weights'!G$40 -> 0.38978932
A16: =IF(NOT(ISBLANK(HLOs!D15)),HLOs!D15,"") -> HLO 2.4: Evidence for policy recommendations for precision nutrient management | B16: ='Step B - Weight by Scl Impact'!B17*'Step C weights'!B$40 -> 0.12611372 | C16: ='Step B - Weight by Scl Impact'!C17*'Step C weights'!C$40 -> 0.16314386 | D16: ='Step B - Weight by Scl Impact'!D17*'Step C weights'!D$40 -> 0.15429541 | E16: ='Step B - Weight by Scl Impact'!E17*'Step C weights'!E$40 -> 0.52694251 | F16: ='Step B - Weight by Scl Impact'!F17*'Step C weights'!F$40 -> 0.64731971 | G16: ='Step B - Weight by Scl Impact'!G17*'Step C weights'!G$40 -> 0.13665401 | I16: =A16 -> HLO 2.4: Evidence for policy recommendations for precision nutrient management | J16: ='Step B - Weight by Scl Impact'!J17*'Step C weights'!B$40 -> 0.093384803 | K16: ='Step B - Weight by Scl Impact'!K17*'Step C weights'!C$40 -> 0.058992296 | L16: ='Step B - Weight by Scl Impact'!L17*'Step C weights'!D$40 -> 0.25122985 | M16: ='Step B - Weight by Scl Impact'!M17*'Step C weights'!E$40 -> 0.33941026 | N16: ='Step B - Weight by Scl Impact'!N17*'Step C weights'!F$40 -> 0.19990403 | O16: ='Step B - Weight by Scl Impact'!O17*'Step C weights'!G$40 -> 0.0089063912 | Q16: =I16 -> HLO 2.4: Evidence for policy recommendations for precision nutrient management | R16: ='Step B - Weight by Scl Impact'!R17*'Step C weights'!B$40 -> 0.28478827 | S16: ='Step B - Weight by Scl Impact'!S17*'Step C weights'!C$40 -> 0.13987004 | T16: ='Step B - Weight by Scl Impact'!T17*'Step C weights'!D$40 -> 0.2716198 | U16: ='Step B - Weight by Scl Impact'!U17*'Step C weights'!E$40 -> 0.26832412 | V16: ='Step B - Weight by Scl Impact'!V17*'Step C weights'!F$40 -> 0.16075851 | W16: ='Step B - Weight by Scl Impact'!W17*'Step C weights'!G$40 -> 0.19672044 | Y16: =Q16 -> HLO 2.4: Evidence for policy recommendations for precision nutrient management | Z16: ='Step B - Weight by Scl Impact'!Z17*'Step C weights'!B$40 -> 0.55634422 | AA16: ='Step B - Weight by Scl Impact'!AA17*'Step C weights'!C$40 -> 0.053128572 | AB16: ='Step B - Weight by Scl Impact'!AB17*'Step C weights'!D$40 -> 0.063219022 | AC16: ='Step B - Weight by Scl Impact'!AC17*'Step C weights'!E$40 -> 0.17123093 | AD16: ='Step B - Weight by Scl Impact'!AD17*'Step C weights'!F$40 -> 0.24367475 | AE16: ='Step B - Weight by Scl Impact'!AE17*'Step C weights'!G$40 -> 0.25985954 | AG16: =A16 -> HLO 2.4: Evidence for policy recommendations for precision nutrient management | AH16: ='Step B - Weight by Scl Impact'!AH17*'Step C weights'!B$40 -> 0.22253769 | AI16: ='Step B - Weight by Scl Impact'!AI17*'Step C weights'!C$40 -> 0.10625714 | AJ16: ='Step B - Weight by Scl Impact'!AJ17*'Step C weights'!D$40 -> 0.094828532 | AK16: ='Step B - Weight by Scl Impact'!AK17*'Step C weights'!E$40 -> 0.11415395 | AL16: ='Step B - Weight by Scl Impact'!AL17*'Step C weights'!F$40 -> 0.60918688 | AM16: ='Step B - Weight by Scl Impact'!AM17*'Step C weights'!G$40 -> 0.25985954
A17: =IF(NOT(ISBLANK(HLOs!D16)),HLOs!D16,"") -> HLO 3.1: Soil health monitoring and assessment framework operationalized | B17: ='Step B - Weight by Scl Impact'!B18*'Step C weights'!B$40 -> 0.15764215 | C17: ='Step B - Weight by Scl Impact'!C18*'Step C weights'!C$40 -> 0.20392983 | D17: ='Step B - Weight by Scl Impact'!D18*'Step C weights'!D$40 -> 0.15429541 | E17: ='Step B - Weight by Scl Impact'!E18*'Step C weights'!E$40 -> 0.21077701 | F17: ='Step B - Weight by Scl Impact'!F18*'Step C weights'!F$40 -> 0.64731971 | G17: ='Step B - Weight by Scl Impact'!G18*'Step C weights'!G$40 -> 0.17081751 | I17: =A17 -> HLO 3.1: Soil health monitoring and assessment framework operationalized | J17: ='Step B - Weight by Scl Impact'!J18*'Step C weights'!B$40 -> 0.116731 | K17: ='Step B - Weight by Scl Impact'!K18*'Step C weights'!C$40 -> 0.07374037 | L17: ='Step B - Weight by Scl Impact'!L18*'Step C weights'!D$40 -> 0.25122985 | M17: ='Step B - Weight by Scl Impact'!M18*'Step C weights'!E$40 -> 0.33941026 | N17: ='Step B - Weight by Scl Impact'!N18*'Step C weights'!F$40 -> 0.19990403 | O17: ='Step B - Weight by Scl Impact'!O18*'Step C weights'!G$40 -> 0.022265978 | Q17: =I17 -> HLO 3.1: Soil health monitoring and assessment framework operationalized | R17: ='Step B - Weight by Scl Impact'!R18*'Step C weights'!B$40 -> 0.35598533 | S17: ='Step B - Weight by Scl Impact'!S18*'Step C weights'!C$40 -> 0.13987004 | T17: ='Step B - Weight by Scl Impact'!T18*'Step C weights'!D$40 -> 0.2716198 | U17: ='Step B - Weight by Scl Impact'!U18*'Step C weights'!E$40 -> 0.26832412 | V17: ='Step B - Weight by Scl Impact'!V18*'Step C weights'!F$40 -> 0.40189627 | W17: ='Step B - Weight by Scl Impact'!W18*'Step C weights'!G$40 -> 0.24590055 | Y17: =Q17 -> HLO 3.1: Soil health monitoring and assessment framework operationalized | Z17: ='Step B - Weight by Scl Impact'!Z18*'Step C weights'!B$40 -> 0.55634422 | AA17: ='Step B - Weight by Scl Impact'!AA18*'Step C weights'!C$40 -> 0.10625714 | AB17: ='Step B - Weight by Scl Impact'!AB18*'Step C weights'!D$40 -> 0.12643804 | AC17: ='Step B - Weight by Scl Impact'!AC18*'Step C weights'!E$40 -> 0.11415395 | AD17: ='Step B - Weight by Scl Impact'!AD18*'Step C weights'!F$40 -> 0.24367475 | AE17: ='Step B - Weight by Scl Impact'!AE18*'Step C weights'!G$40 -> 0.64964886 | AG17: =A17 -> HLO 3.1: Soil health monitoring and assessment framework operationalized | AH17: ='Step B - Weight by Scl Impact'!AH18*'Step C weights'!B$40 -> 0.55634422 | AI17: ='Step B - Weight by Scl Impact'!AI18*'Step C weights'!C$40 -> 0.13282143 | AJ17: ='Step B - Weight by Scl Impact'!AJ18*'Step C weights'!D$40 -> 0.12643804 | AK17: ='Step B - Weight by Scl Impact'!AK18*'Step C weights'!E$40 -> 0.28538488 | AL17: ='Step B - Weight by Scl Impact'!AL18*'Step C weights'!F$40 -> 0.60918688 | AM17: ='Step B - Weight by Scl Impact'!AM18*'Step C weights'!G$40 -> 0.64964886
A18: =IF(NOT(ISBLANK(HLOs!D17)),HLOs!D17,"") -> HLO 3.2: Network of long-term monitoring sites for carbon storage assessment | B18: ='Step B - Weight by Scl Impact'!B19*'Step C weights'!B$40 -> 0.12611372 | C18: ='Step B - Weight by Scl Impact'!C19*'Step C weights'!C$40 -> 0.20392983 | D18: ='Step B - Weight by Scl Impact'!D19*'Step C weights'!D$40 -> 0.15429541 | E18: ='Step B - Weight by Scl Impact'!E19*'Step C weights'!E$40 -> 0.21077701 | F18: ='Step B - Weight by Scl Impact'!F19*'Step C weights'!F$40 -> 0.32365985 | G18: ='Step B - Weight by Scl Impact'!G19*'Step C weights'!G$40 -> 0.13665401 | I18: =A18 -> HLO 3.2: Network of long-term monitoring sites for carbon storage assessment | J18: ='Step B - Weight by Scl Impact'!J19*'Step C weights'!B$40 -> 0.093384803 | K18: ='Step B - Weight by Scl Impact'!K19*'Step C weights'!C$40 -> 0.029496148 | L18: ='Step B - Weight by Scl Impact'!L19*'Step C weights'!D$40 -> 0.25122985 | M18: ='Step B - Weight by Scl Impact'!M19*'Step C weights'!E$40 -> 0.33941026 | N18: ='Step B - Weight by Scl Impact'!N19*'Step C weights'!F$40 -> 0.19990403 | O18: ='Step B - Weight by Scl Impact'!O19*'Step C weights'!G$40 -> 0.0089063912 | Q18: =I18 -> HLO 3.2: Network of long-term monitoring sites for carbon storage assessment | R18: ='Step B - Weight by Scl Impact'!R19*'Step C weights'!B$40 -> 0.28478827 | S18: ='Step B - Weight by Scl Impact'!S19*'Step C weights'!C$40 -> 0.13987004 | T18: ='Step B - Weight by Scl Impact'!T19*'Step C weights'!D$40 -> 0.2716198 | U18: ='Step B - Weight by Scl Impact'!U19*'Step C weights'!E$40 -> 0.26832412 | V18: ='Step B - Weight by Scl Impact'!V19*'Step C weights'!F$40 -> 0.16075851 | W18: ='Step B - Weight by Scl Impact'!W19*'Step C weights'!G$40 -> 0.098360218 | Y18: =Q18 -> HLO 3.2: Network of long-term monitoring sites for carbon storage assessment | Z18: ='Step B - Weight by Scl Impact'!Z19*'Step C weights'!B$40 -> 0.44507537 | AA18: ='Step B - Weight by Scl Impact'!AA19*'Step C weights'!C$40 -> 0.10625714 | AB18: ='Step B - Weight by Scl Impact'!AB19*'Step C weights'!D$40 -> 0.063219022 | AC18: ='Step B - Weight by Scl Impact'!AC19*'Step C weights'!E$40 -> 0.28538488 | AD18: ='Step B - Weight by Scl Impact'!AD19*'Step C weights'!F$40 -> 0.24367475 | AE18: ='Step B - Weight by Scl Impact'!AE19*'Step C weights'!G$40 -> 0.64964886 | AG18: =A18 -> HLO 3.2: Network of long-term monitoring sites for carbon storage assessment | AH18: ='Step B - Weight by Scl Impact'!AH19*'Step C weights'!B$40 -> 0.22253769 | AI18: ='Step B - Weight by Scl Impact'!AI19*'Step C weights'!C$40 -> 0.10625714 | AJ18: ='Step B - Weight by Scl Impact'!AJ19*'Step C weights'!D$40 -> 0.094828532 | AK18: ='Step B - Weight by Scl Impact'!AK19*'Step C weights'!E$40 -> 0.11415395 | AL18: ='Step B - Weight by Scl Impact'!AL19*'Step C weights'!F$40 -> 0.24367475 | AM18: ='Step B - Weight by Scl Impact'!AM19*'Step C weights'!G$40 -> 0.12992977
A19: =IF(NOT(ISBLANK(HLOs!D18)),HLOs!D18,"") -> HLO 3.3: Impacts of agricultural practices quantified and catalogued | B19: ='Step B - Weight by Scl Impact'!B20*'Step C weights'!B$40 -> 0.12611372 | C19: ='Step B - Weight by Scl Impact'!C20*'Step C weights'!C$40 -> 0.081571931 | D19: ='Step B - Weight by Scl Impact'!D20*'Step C weights'!D$40 -> 0.15429541 | E19: ='Step B - Weight by Scl Impact'!E20*'Step C weights'!E$40 -> 0.21077701 | F19: ='Step B - Weight by Scl Impact'!F20*'Step C weights'!F$40 -> 0.32365985 | G19: ='Step B - Weight by Scl Impact'!G20*'Step C weights'!G$40 -> 0.068327004 | I19: =A19 -> HLO 3.3: Impacts of agricultural practices quantified and catalogued | J19: ='Step B - Weight by Scl Impact'!J20*'Step C weights'!B$40 -> 0.093384803 | K19: ='Step B - Weight by Scl Impact'!K20*'Step C weights'!C$40 -> 0.029496148 | L19: ='Step B - Weight by Scl Impact'!L20*'Step C weights'!D$40 -> 0.25122985 | M19: ='Step B - Weight by Scl Impact'!M20*'Step C weights'!E$40 -> 0.33941026 | N19: ='Step B - Weight by Scl Impact'!N20*'Step C weights'!F$40 -> 0.19990403 | O19: ='Step B - Weight by Scl Impact'!O20*'Step C weights'!G$40 -> 0.0089063912 | Q19: =I19 -> HLO 3.3: Impacts of agricultural practices quantified and catalogued | R19: ='Step B - Weight by Scl Impact'!R20*'Step C weights'!B$40 -> 0.28478827 | S19: ='Step B - Weight by Scl Impact'!S20*'Step C weights'!C$40 -> 0.13987004 | T19: ='Step B - Weight by Scl Impact'!T20*'Step C weights'!D$40 -> 0.2716198 | U19: ='Step B - Weight by Scl Impact'!U20*'Step C weights'!E$40 -> 0.26832412 | V19: ='Step B - Weight by Scl Impact'!V20*'Step C weights'!F$40 -> 0.16075851 | W19: ='Step B - Weight by Scl Impact'!W20*'Step C weights'!G$40 -> 0.098360218 | Y19: =Q19 -> HLO 3.3: Impacts of agricultural practices quantified and catalogued | Z19: ='Step B - Weight by Scl Impact'!Z20*'Step C weights'!B$40 -> 0.44507537 | AA19: ='Step B - Weight by Scl Impact'!AA20*'Step C weights'!C$40 -> 0.10625714 | AB19: ='Step B - Weight by Scl Impact'!AB20*'Step C weights'!D$40 -> 0.063219022 | AC19: ='Step B - Weight by Scl Impact'!AC20*'Step C weights'!E$40 -> 0.28538488 | AD19: ='Step B - Weight by Scl Impact'!AD20*'Step C weights'!F$40 -> 0.24367475 | AE19: ='Step B - Weight by Scl Impact'!AE20*'Step C weights'!G$40 -> 0.51971909 | AG19: =A19 -> HLO 3.3: Impacts of agricultural practices quantified and catalogued | AH19: ='Step B - Weight by Scl Impact'!AH20*'Step C weights'!B$40 -> 0.44507537 | AI19: ='Step B - Weight by Scl Impact'!AI20*'Step C weights'!C$40 -> 0.053128572 | AJ19: ='Step B - Weight by Scl Impact'!AJ20*'Step C weights'!D$40 -> 0.063219022 | AK19: ='Step B - Weight by Scl Impact'!AK20*'Step C weights'!E$40 -> 0.11415395 | AL19: ='Step B - Weight by Scl Impact'!AL20*'Step C weights'!F$40 -> 0.24367475 | AM19: ='Step B - Weight by Scl Impact'!AM20*'Step C weights'!G$40 -> 0.64964886
A20: =IF(NOT(ISBLANK(HLOs!D19)),HLOs!D19,"") -> HLO 3.4: Evidence for policy makers on soil health translated to accessible formats | B20: ='Step B - Weight by Scl Impact'!B21*'Step C weights'!B$40 -> 0.12611372 | C20: ='Step B - Weight by Scl Impact'!C21*'Step C weights'!C$40 -> 0.081571931 | D20: ='Step B - Weight by Scl Impact'!D21*'Step C weights'!D$40 -> 0.15429541 | E20: ='Step B - Weight by Scl Impact'!E21*'Step C weights'!E$40 -> 0.21077701 | F20: ='Step B - Weight by Scl Impact'!F21*'Step C weights'!F$40 -> 0.32365985 | G20: ='Step B - Weight by Scl Impact'!G21*'Step C weights'!G$40 -> 0.068327004 | I20: =A20 -> HLO 3.4: Evidence for policy makers on soil health translated to accessible formats | J20: ='Step B - Weight by Scl Impact'!J21*'Step C weights'!B$40 -> 0.093384803 | K20: ='Step B - Weight by Scl Impact'!K21*'Step C weights'!C$40 -> 0.029496148 | L20: ='Step B - Weight by Scl Impact'!L21*'Step C weights'!D$40 -> 0.25122985 | M20: ='Step B - Weight by Scl Impact'!M21*'Step C weights'!E$40 -> 0.33941026 | N20: ='Step B - Weight by Scl Impact'!N21*'Step C weights'!F$40 -> 0.19990403 | O20: ='Step B - Weight by Scl Impact'!O21*'Step C weights'!G$40 -> 0.0089063912 | Q20: =I20 -> HLO 3.4: Evidence for policy makers on soil health translated to accessible formats | R20: ='Step B - Weight by Scl Impact'!R21*'Step C weights'!B$40 -> 0.28478827 | S20: ='Step B - Weight by Scl Impact'!S21*'Step C weights'!C$40 -> 0.069935022 | T20: ='Step B - Weight by Scl Impact'!T21*'Step C weights'!D$40 -> 0.2716198 | U20: ='Step B - Weight by Scl Impact'!U21*'Step C weights'!E$40 -> 0.17888275 | V20: ='Step B - Weight by Scl Impact'!V21*'Step C weights'!F$40 -> 0.16075851 | W20: ='Step B - Weight by Scl Impact'!W21*'Step C weights'!G$40 -> 0.098360218 | Y20: =Q20 -> HLO 3.4: Evidence for policy makers on soil health translated to accessible formats | Z20: ='Step B - Weight by Scl Impact'!Z21*'Step C weights'!B$40 -> 0.55634422 | AA20: ='Step B - Weight by Scl Impact'!AA21*'Step C weights'!C$40 -> 0.10625714 | AB20: ='Step B - Weight by Scl Impact'!AB21*'Step C weights'!D$40 -> 0.12643804 | AC20: ='Step B - Weight by Scl Impact'!AC21*'Step C weights'!E$40 -> 0.11415395 | AD20: ='Step B - Weight by Scl Impact'!AD21*'Step C weights'!F$40 -> 0.24367475 | AE20: ='Step B - Weight by Scl Impact'!AE21*'Step C weights'!G$40 -> 0.25985954 | AG20: =A20 -> HLO 3.4: Evidence for policy makers on soil health translated to accessible formats | AH20: ='Step B - Weight by Scl Impact'!AH21*'Step C weights'!B$40 -> 0.44507537 | AI20: ='Step B - Weight by Scl Impact'!AI21*'Step C weights'!C$40 -> 0.053128572 | AJ20: ='Step B - Weight by Scl Impact'!AJ21*'Step C weights'!D$40 -> 0.063219022 | AK20: ='Step B - Weight by Scl Impact'!AK21*'Step C weights'!E$40 -> 0.28538488 | AL20: ='Step B - Weight by Scl Impact'!AL21*'Step C weights'!F$40 -> 0.4873495 | AM20: ='Step B - Weight by Scl Impact'!AM21*'Step C weights'!G$40 -> 0.64964886
A21: =IF(NOT(ISBLANK(HLOs!D20)),HLOs!D20,"") -> HLO 4.1: Capacity and networks of plant health practitioners improved | B21: ='Step B - Weight by Scl Impact'!B22*'Step C weights'!B$40 -> 0.063056861 | C21: ='Step B - Weight by Scl Impact'!C22*'Step C weights'!C$40 -> 0.081571931 | D21: ='Step B - Weight by Scl Impact'!D22*'Step C weights'!D$40 -> 0.15429541 | E21: ='Step B - Weight by Scl Impact'!E22*'Step C weights'!E$40 -> 0.21077701 | F21: ='Step B - Weight by Scl Impact'!F22*'Step C weights'!F$40 -> 0.32365985 | G21: ='Step B - Weight by Scl Impact'!G22*'Step C weights'!G$40 -> 0.13665401 | I21: =A21 -> HLO 4.1: Capacity and networks of plant health practitioners improved | J21: ='Step B - Weight by Scl Impact'!J22*'Step C weights'!B$40 -> 0.046692401 | K21: ='Step B - Weight by Scl Impact'!K22*'Step C weights'!C$40 -> 0.029496148 | L21: ='Step B - Weight by Scl Impact'!L22*'Step C weights'!D$40 -> 0.25122985 | M21: ='Step B - Weight by Scl Impact'!M22*'Step C weights'!E$40 -> 0.33941026 | N21: ='Step B - Weight by Scl Impact'!N22*'Step C weights'!F$40 -> 0.19990403 | O21: ='Step B - Weight by Scl Impact'!O22*'Step C weights'!G$40 -> 0.017812782 | Q21: =I21 -> HLO 4.1: Capacity and networks of plant health practitioners improved | R21: ='Step B - Weight by Scl Impact'!R22*'Step C weights'!B$40 -> 0.28478827 | S21: ='Step B - Weight by Scl Impact'!S22*'Step C weights'!C$40 -> 0.27974009 | T21: ='Step B - Weight by Scl Impact'!T22*'Step C weights'!D$40 -> 0.36215974 | U21: ='Step B - Weight by Scl Impact'!U22*'Step C weights'!E$40 -> 0.35776549 | V21: ='Step B - Weight by Scl Impact'!V22*'Step C weights'!F$40 -> 0.24113776 | W21: ='Step B - Weight by Scl Impact'!W22*'Step C weights'!G$40 -> 0.14754033 | Y21: =Q21 -> HLO 4.1: Capacity and networks of plant health practitioners improved | Z21: ='Step B - Weight by Scl Impact'!Z22*'Step C weights'!B$40 -> 0.44507537 | AA21: ='Step B - Weight by Scl Impact'!AA22*'Step C weights'!C$40 -> 0.10625714 | AB21: ='Step B - Weight by Scl Impact'!AB22*'Step C weights'!D$40 -> 0.12643804 | AC21: ='Step B - Weight by Scl Impact'!AC22*'Step C weights'!E$40 -> 0.2283079 | AD21: ='Step B - Weight by Scl Impact'!AD22*'Step C weights'!F$40 -> 0.36551213 | AE21: ='Step B - Weight by Scl Impact'!AE22*'Step C weights'!G$40 -> 0.38978932 | AG21: =A21 -> HLO 4.1: Capacity and networks of plant health practitioners improved | AH21: ='Step B - Weight by Scl Impact'!AH22*'Step C weights'!B$40 -> 0.22253769 | AI21: ='Step B - Weight by Scl Impact'!AI22*'Step C weights'!C$40 -> 0.053128572 | AJ21: ='Step B - Weight by Scl Impact'!AJ22*'Step C weights'!D$40 -> 0.063219022 | AK21: ='Step B - Weight by Scl Impact'!AK22*'Step C weights'!E$40 -> 0.11415395 | AL21: ='Step B - Weight by Scl Impact'!AL22*'Step C weights'!F$40 -> 0.24367475 | AM21: ='Step B - Weight by Scl Impact'!AM22*'Step C weights'!G$40 -> 0.25985954
... A42: =IF(NOT(ISBLANK(HLOs!D41)),HLOs!D41,"") -> HLO 8.5: Policy-related information for sustainable farming systems | B42: ='Step B - Weight by Scl Impact'!B43*'Step C weights'!B$40 -> 0.063056861 | C42: ='Step B - Weight by Scl Impact'!C43*'Step C weights'!C$40 -> 0.081571931 | D42: ='Step B - Weight by Scl Impact'!D43*'Step C weights'!D$40 -> 0.077147705 | E42: ='Step B - Weight by Scl Impact'!E43*'Step C weights'!E$40 -> 0.1053885 | F42: ='Step B - Weight by Scl Impact'!F43*'Step C weights'!F$40 -> 0.32365985 | G42: ='Step B - Weight by Scl Impact'!G43*'Step C weights'!G$40 -> 0.068327004 | I42: =A42 -> HLO 8.5: Policy-related information for sustainable farming systems | J42: ='Step B - Weight by Scl Impact'!J43*'Step C weights'!B$40 -> 0.046692401 | K42: ='Step B - Weight by Scl Impact'!K43*'Step C weights'!C$40 -> 0.029496148 | L42: ='Step B - Weight by Scl Impact'!L43*'Step C weights'!D$40 -> 0.50245971 | M42: ='Step B - Weight by Scl Impact'!M43*'Step C weights'!E$40 -> 0.16970513 | N42: ='Step B - Weight by Scl Impact'!N43*'Step C weights'!F$40 -> 0.19990403 | O42: ='Step B - Weight by Scl Impact'!O43*'Step C weights'!G$40 -> 0.0089063912 | Q42: =I42 -> HLO 8.5: Policy-related information for sustainable farming systems | R42: ='Step B - Weight by Scl Impact'!R43*'Step C weights'!B$40 -> 0.14239413 | S42: ='Step B - Weight by Scl Impact'!S43*'Step C weights'!C$40 -> 0.13987004 | T42: ='Step B - Weight by Scl Impact'!T43*'Step C weights'!D$40 -> 0.36215974 | U42: ='Step B - Weight by Scl Impact'!U43*'Step C weights'!E$40 -> 0.26832412 | V42: ='Step B - Weight by Scl Impact'!V43*'Step C weights'!F$40 -> 0.24113776 | W42: ='Step B - Weight by Scl Impact'!W43*'Step C weights'!G$40 -> 0.098360218 | Y42: =Q42 -> HLO 8.5: Policy-related information for sustainable farming systems | Z42: ='Step B - Weight by Scl Impact'!Z43*'Step C weights'!B$40 -> 0.11126884 | AA42: ='Step B - Weight by Scl Impact'!AA43*'Step C weights'!C$40 -> 0.026564286 | AB42: ='Step B - Weight by Scl Impact'!AB43*'Step C weights'!D$40 -> 0.063219022 | AC42: ='Step B - Weight by Scl Impact'!AC43*'Step C weights'!E$40 -> 0.057076975 | AD42: ='Step B - Weight by Scl Impact'!AD43*'Step C weights'!F$40 -> 0.12183738 | AE42: ='Step B - Weight by Scl Impact'!AE43*'Step C weights'!G$40 -> 0.25985954 | AG42: =A42 -> HLO 8.5: Policy-related information for sustainable farming systems | AH42: ='Step B - Weight by Scl Impact'!AH43*'Step C weights'!B$40 -> 0.22253769 | AI42: ='Step B - Weight by Scl Impact'!AI43*'Step C weights'!C$40 -> 0.053128572 | AJ42: ='Step B - Weight by Scl Impact'!AJ43*'Step C weights'!D$40 -> 0.094828532 | AK42: ='Step B - Weight by Scl Impact'!AK43*'Step C weights'!E$40 -> 0.17123093 | AL42: ='Step B - Weight by Scl Impact'!AL43*'Step C weights'!F$40 -> 0.24367475 | AM42: ='Step B - Weight by Scl Impact'!AM43*'Step C weights'!G$40 -> 0.38978932

Sheet Phase 2 - Final decisions
A1: Deviations from Scores - In this tab, you should higlight, for the HLOs (and regions), where, based on Phase 2 of the methodology, your Program/Accelerator team has decided to deviate from the scores shown in Phase 1. Here you will justify your decisions - this analysis will inform the content of your Inception Report, Section 5.2.
A4: HLO (Region + Impact Area, if relevant) | B4: Other factors considered | C4: How they were considered | D4: Final decisions and justifications on the priority of this HLO
A5: E.g. 1. ASSESS "Assessing and cataloging subsidies in the agriculture sector" (LAC and SEA, all IAs) -- DELETE THIS ROW AFTER FINALISING YOUR ANALYSIS. | B5: E.g., NARES and private sector actors (AgroSavia, EMBRAPA; APAARI); Comparative advantage analysis; Research papers X, Y, Z (provide links)-- DELETE THIS ROW AFTER FINALISING YOUR ANALYSIS. | C5: E.g., Stakeholder engagement; anlaysis of CA results -- DELETE THIS ROW AFTER FINALISING YOUR ANALYSIS. | D5: E.g., The final Step A score was high (5) -- However, stakeholders note that this type of analysis is not impactful at the moment as their priorities align with developing new sustainable farming technologies (e.g., our HLO "TECHDEV"). There was some compromise, as CGIAR believes it important to get the foundations of this analysis (which will be done in 2025) and moving forward to 2030, less funding will be put into ASSESS as the foundational information and anlaysis are gathered and developed (meaning only annual updates are required) -- DELETE THIS ROW AFTER FINALISING YOUR ANALYSIS.
